Workbook

Sheet Instrucciones
A1: INSPECCIÓN FÍSICA DE EQUIPO — SERIE HORIBA AP-370
A2: APMA-370 (CO) · APSA-370 (SO2) · APOA-370 (O3) · APNA-370 (NOx)
A3: Ambientalia — Servicio Técnico · v5.0 · Estructura derivada del prototipo GRIMM EDM180 v1.2
A5: Novedades de la v5.0 — comentario de falla para el informe
A6: Columna N, «Comentario de falla (informe al cliente)»: el texto que describe el hallazgo cuando
A7: ese ítem no cumple, redactado para que se pueda pegar tal cual en el informe de servicio. Está
A8: escrito en tercera persona, sin jerga interna y sin códigos de tarjeta, nombrando el componente
A9: en términos que el cliente reconoce. Es texto fijo del catálogo: se edita una vez y sirve para
A10: todas las visitas.
A12: Columna Z, «Comentario para el informe (automático)»: arma el párrafo final por sí sola. Queda
A13: en blanco mientras el ítem esté Conforme, No aplica o Pendiente, y solo se redacta cuando hay
A14: hallazgo. Encadena cuatro piezas:
... A247: modelo (clic derecho → Mover o copiar → Crear una copia) antes de diligenciar las columnas U a Y.

Sheet APMA-370 (CO)
A1: FASE 1 — INSPECCIÓN FÍSICA DEL EQUIPO · APMA-370 (CO) (catálogo + captura)
A3: Cliente: | D3: Principio de medición: | E3: NDIR con modulación de flujo cruzado
A4: NIT: | D4: Fecha de inspección:
A5: Equipo / Modelo: | B5: Analizador de monóxido de carbono HORIBA APMA-370 | D5: Técnico responsable:
A6: Número de serie: | D6: N.º de informe (MT):
A8: ID | B8: Nivel macro (N1) | C8: Subnivel (N2) | D8: Ítem (N3) | E8: Qué se verifica | F8: Cómo se realiza la inspección | G8: Tipo de dato | H8: Unidad | I8: Criterio de aceptación | J8: Criterio de falla | K8: Si NO OK → causa probable | L8: Si NO OK → verificar (ID) | M8: Si NO OK → acción | N8: Comentario de falla (informe al cliente) | O8: Límite inferior | P8: Límite superior | Q8: Obligatorio | R8: Evidencia fotográfica requerida | S8: Repuesto / parte asociada (catálogo Zoho Books) | T8: Fuente documental | U8: Resultado | V8: Valor medido | W8: Verificación de rango | X8: Foto adjunta | Y8: Observación | Z8: Comentario para el informe (automático)
A9: 1.1.1 | B9: 1. Verificación funcional inicial | C9: 1.1 Encendido y LEDs frontales | D9: LED de encendido (Power LED) | E9: Color del LED indicador de encendido en el panel frontal | F9: Con el equipo energizado, observar el LED de la esquina inferior del panel frontal y registrar su color. No requiere abrir el equipo. | G9: OK / No OK | I9: Debe iluminarse en verde fijo (operación normal). Rojo indica alarma activa | J9: Alerta | K9: LED en rojo: hay al menos una alarma activa en el equipo | L9: 1.1.2 | M9: Registrar el color y pasar al listado de alarmas antes de continuar | N9: El indicador de encendido del panel frontal no muestra el estado normal de operación, lo que señala una condición de alarma activa en el analizador. | Q9: Sí | R9: Sí | T9: P-ST-018-MAN OPER APMA 370 V2 | U9: Pendiente | W9: =IF($G9<>"Numérico","",IF($V9="","Sin dato",IF(AND(OR(NOT(ISNUMBER($O9)),$V9>=$O9),OR(NOT(ISNUMBER($P9)),$V9<=$P9)),"Dentro de rango","Fuera de rango"))) | Z9: =IF(OR($U9="",$U9="Conforme",$U9="No aplica",$U9="Pendiente"),"",$N9&IF($W9="Fuera de rango"," Valor medido: "&TEXT($V9,"0.####")&IF($H9="",""," "&$H9)&IF(AND(ISNUMBER($O9),$V9<$O9),", por debajo del límite inferior de "&TEXT($O9,"0.####")&IF($H9="",""," "&$H9),"")&IF(AND(ISNUMBER($P9),$V9>$P9),", por encima del límite superior de "&TEXT($P9,"0.####")&IF($H9="",""," "&$H9),"")&".","")&IF($Y9="",""," "&$Y9&IF(RIGHT($Y9,1)=".","","."))&" Acción recomendada: "&$M9&IF(RIGHT($M9,1)=".","",".")&IF($J9="Bloqueante"," El equipo no se libera hasta resolver este hallazgo.",IF($J9="Cobrable"," Se incluye en la cotización de repuestos y consumibles."," Se deja registrado como observación.")))
A10: 1.1.2 | B10: 1. Verificación funcional inicial | C10: 1.1 Encendido y LEDs frontales | D10: LED de alarma (Alarm LED) | E10: Estado de alarma activa verificado mediante el color del indicador frontal | F10: Observar el LED de alarma en el panel frontal. Si está en rojo, entrar a MENU / ALARM y anotar el código de alarma activo antes de continuar. | G10: Sí/No | I10: El LED de alarma debe permanecer apagado. Si cambia a rojo indica fallo de hardware o de parámetro | J10: Bloqueante | K10: Alarma activa de proceso, de calibración o de tarjeta | L10: 3.1.1 ; 5.1.1 ; 5.1.2 ; 9.1.1 | M10: Anotar el código en MENU/ALARM y entrar por la rama que corresponda | N10: El analizador presenta al menos una alarma activa al momento de la inspección. | Q10: Sí | R10: No | T10: P-ST-018-MAN OPER APMA 370 V2 | U10: Pendiente | W10: =IF($G10<>"Numérico","",IF($V10="","Sin dato",IF(AND(OR(NOT(ISNUMBER($O10)),$V10>=$O10),OR(NOT(ISNUMBER($P10)),$V10<=$P10)),"Dentro de rango","Fuera de rango"))) | Z10: =IF(OR($U10="",$U10="Conforme",$U10="No aplica",$U10="Pendiente"),"",$N10&IF($W10="Fuera de rango"," Valor medido: "&TEXT($V10,"0.####")&IF($H10="",""," "&$H10)&IF(AND(ISNUMBER($O10),$V10<$O10),", por debajo del límite inferior de "&TEXT($O10,"0.####")&IF($H10="",""," "&$H10),"")&IF(AND(ISNUMBER($P10),$V10>$P10),", por encima del límite superior de "&TEXT($P10,"0.####")&IF($H10="",""," "&$H10),"")&".","")&IF($Y10="",""," "&$Y10&IF(RIGHT($Y10,1)=".","","."))&" Acción recomendada: "&$M10&IF(RIGHT($M10,1)=".","",".")&IF($J10="Bloqueante"," El equipo no se libera hasta resolver este hallazgo.",IF($J10="Cobrable"," Se incluye en la cotización de repuestos y consumibles."," Se deja registrado como observación.")))
A11: 1.1.3 | B11: 1. Verificación funcional inicial | C11: 1.1 Encendido y LEDs frontales | D11: Inicialización del display (TFT LCD) | E11: Arranque correcto y despliegue del menú MEAS. sin bloqueos ni líneas muertas | F11: Encender el equipo y observar la secuencia de arranque completa hasta que aparezca la pantalla MEAS. Presionar tres o cuatro botones de menú para confirmar que no hay zonas muertas ni bloqueos. | G11: OK / No OK | I11: La pantalla LCD TFT debe encender de forma estable y permitir navegación táctil | J11: Cobrable | K11: Cinta flex del LCD agrietada o suelta; panel táctil o unidad LCD averiados | L11: 7.3.1 ; 7.3.2 ; 7.4.1 | M11: Prueba cruzada con cinta y CPU de servicio; reemplazar la unidad LCD si el fallo sigue en la pantalla | N11: La pantalla del analizador no arranca correctamente: presenta bloqueos, zonas sin imagen o no despliega el menú de medición. | Q11: Sí | R11: Sí | S11: LCD Plate (3200595501) · LCD Unit (Apen LCD + Touch Panel) (3014035613) · LCD Unit / AP-370 is composed of CPU-02 (printed circuit board), chassis, and LCD. (3200627065) · LCD Unit chassis, and LCD. (3200618696) | T11: AP-370 LCD replacement / MT_191TE0NC_APMA370_241226 | U11: Pendiente | W11: =IF($G11<>"Numérico","",IF($V11="","Sin dato",IF(AND(OR(NOT(ISNUMBER($O11)),$V11>=$O11),OR(NOT(ISNUMBER($P11)),$V11<=$P11)),"Dentro de rango","Fuera de rango"))) | Z11: =IF(OR($U11="",$U11="Conforme",$U11="No aplica",$U11="Pendiente"),"",$N11&IF($W11="Fuera de rango"," Valor medido: "&TEXT($V11,"0.####")&IF($H11="",""," "&$H11)&IF(AND(ISNUMBER($O11),$V11<$O11),", por debajo del límite inferior de "&TEXT($O11,"0.####")&IF($H11="",""," "&$H11),"")&IF(AND(ISNUMBER($P11),$V11>$P11),", por encima del límite superior de "&TEXT($P11,"0.####")&IF($H11="",""," "&$H11),"")&".","")&IF($Y11="",""," "&$Y11&IF(RIGHT($Y11,1)=".","","."))&" Acción recomendada: "&$M11&IF(RIGHT($M11,1)=".","",".")&IF($J11="Bloqueante"," El equipo no se libera hasta resolver este hallazgo.",IF($J11="Cobrable"," Se incluye en la cotización de repuestos y consumibles."," Se deja registrado como observación.")))
A12: 1.2.1 | B12: 1. Verificación funcional inicial | C12: 1.2 Autodiagnóstico de software | D12: Versión de programa (firmware) | E12: Lectura de la versión de programa en la pantalla de información de software | F12: En la pantalla táctil ir a MENU / SYSTEM / INFORMATION y leer el número de programa. Anotarlo textualmente y contrastarlo con el estándar de fábrica. | G12: Texto | I12: Debe coincidir con la versión homologada de fábrica (estándar AP: P1000878001) | J12: Alerta | K12: Programa no homologado, o CPU sustituida sin recargar la configuración de fábrica | L12: 7.1.1 | M12: Confirmar el HGS con fábrica y recargar la configuración desde la CF antes de calibrar | N12: La versión de programa instalada no corresponde a la versión homologada de fábrica para este analizador. | Q12: Sí | R12: No | T12: 1 - LCD design change AP EN | U12: Pendiente | W12: =IF($G12<>"Numérico","",IF($V12="","Sin dato",IF(AND(OR(NOT(ISNUMBER($O12)),$V12>=$O12),OR(NOT(ISNUMBER($P12)),$V12<=$P12)),"Dentro de rango","Fuera de rango"))) | Z12: =IF(OR($U12="",$U12="Conforme",$U12="No aplica",$U12="Pendiente"),"",$N12&IF($W12="Fuera de rango"," Valor medido: "&TEXT($V12,"0.####")&IF($H12="",""," "&$H12)&IF(AND(ISNUMBER($O12),$V12<$O12),", por debajo del límite inferior de "&TEXT($O12,"0.####")&IF($H12="",""," "&$H12),"")&IF(AND(ISNUMBER($P12),$V12>$P12),", por encima del límite superior de "&TEXT($P12,"0.####")&IF($H12="",""," "&$H12),"")&".","")&IF($Y12="",""," "&$Y12&IF(RIGHT($Y12,1)=".","","."))&" Acción recomendada: "&$M12&IF(RIGHT($M12,1)=".","",".")&IF($J12="Bloqueante"," El equipo no se libera hasta resolver este hallazgo.",IF($J12="Cobrable"," Se incluye en la cotización de repuestos y consumibles."," Se deja registrado como observación.")))
A13: 1.3.1 | B13: 1. Verificación funcional inicial | C13: 1.3 Estabilización térmica | D13: Tiempo de calentamiento inicial (warm-up) | E13: Tiempo transcurrido desde el encendido en frío hasta la estabilización | F13: Anotar la hora de encendido del equipo y calcular las horas transcurridas hasta el momento de la inspección o de la calibración. Si el equipo llevaba operando, registrar que ya estaba estabilizado. | G13: Numérico | H13: horas | I13: Mínimo 3 h de calentamiento para estabilizar banco óptico y catalizador antes de medir. Límite superior PENDIENTE DE VALIDAR | J13: Alerta | K13: Equipo encendido hace menos de 3 h: banco óptico y catalizador aún inestables | L13: 9.1.1 ; 9.1.2 | M13: Esperar a completar el calentamiento; no calibrar ni juzgar derivas hasta entonces | N13: El analizador no ha completado el tiempo mínimo de calentamiento, por lo que sus lecturas aún no son representativas. | O13: 3 | Q13: Sí | R13: No | T13: GZ0000117746B SM E APXX-370 (Service Manual) | U13: Pendiente | W13: =IF($G13<>"Numérico","",IF($V13="","Sin dato",IF(AND(OR(NOT(ISNUMBER($O13)),$V13>=$O13),OR(NOT(ISNUMBER($P13)),$V13<=$P13)),"Dentro de rango","Fuera de rango"))) | Z13: =IF(OR($U13="",$U13="Conforme",$U13="No aplica",$U13="Pendiente"),"",$N13&IF($W13="Fuera de rango"," Valor medido: "&TEXT($V13,"0.####")&IF($H13="",""," "&$H13)&IF(AND(ISNUMBER($O13),$V13<$O13),", por debajo del límite inferior de "&TEXT($O13,"0.####")&IF($H13="",""," "&$H13),"")&IF(AND(ISNUMBER($P13),$V13>$P13),", por encima del límite superior de "&TEXT($P13,"0.####")&IF($H13="",""," "&$H13),"")&".","")&IF($Y13="",""," "&$Y13&IF(RIGHT($Y13,1)=".","","."))&" Acción recomendada: "&$M13&IF(RIGHT($M13,1)=".","",".")&IF($J13="Bloqueante"," El equipo no se libera hasta resolver este hallazgo.",IF($J13="Cobrable"," Se incluye en la cotización de repuestos y consumibles."," Se deja registrado como observación.")))
A14: 2.1.1 | B14: 2. Identificación y trazabilidad | C14: 2.1 Placas e identificación física | D14: Placa de número de serie frontal | E14: Presencia y legibilidad del número de serie en el panel frontal inferior | F14: Localizar la placa serigrafiada en la parte inferior del panel frontal, leerla y fotografiarla. Contrastar con la orden de servicio y la hoja de vida del equipo. | G14: Texto | I14: Debe ser legible y coincidir con el registro y la hoja de vida de la estación | J14: Alerta | K14: Placa ilegible, despegada, o equipo distinto al de la orden de servicio | L14: 2.1.2 | M14: Registrar el serial real, fotografiarlo y corregir la hoja de vida | N14: La placa de identificación frontal no es legible o no coincide con el equipo registrado en la orden de servicio. | Q14: Sí | R14: No | T14: MT_U7D80D0J_APMA370_260116 | U14: Pendiente | W14: =IF($G14<>"Numérico","",IF($V14="","Sin dato",IF(AND(OR(NOT(ISNUMBER($O14)),$V14>=$O14),OR(NOT(ISNUMBER($P14)),$V14<=$P14)),"Dentro de rango","Fuera de rango"))) | Z14: =IF(OR($U14="",$U14="Conforme",$U14="No aplica",$U14="Pendiente"),"",$N14&IF($W14="Fuera de rango"," Valor medido: "&TEXT($V14,"0.####")&IF($H14="",""," "&$H14)&IF(AND(ISNUMBER($O14),$V14<$O14),", por debajo del límite inferior de "&TEXT($O14,"0.####")&IF($H14="",""," "&$H14),"")&IF(AND(ISNUMBER($P14),$V14>$P14),", por encima del límite superior de "&TEXT($P14,"0.####")&IF($H14="",""," "&$H14),"")&".","")&IF($Y14="",""," "&$Y14&IF(RIGHT($Y14,1)=".","","."))&" Acción recomendada: "&$M14&IF(RIGHT($M14,1)=".","",".")&IF($J14="Bloqueante"," El equipo no se libera hasta resolver este hallazgo.",IF($J14="Cobrable"," Se incluye en la cotización de repuestos y consumibles."," Se deja registrado como observación.")))
A15: 2.1.2 | B15: 2. Identificación y trazabilidad | C15: 2.1 Placas e identificación física | D15: Placa de número de serie posterior | E15: Presencia y legibilidad de la placa de datos metálica HORIBA en el panel trasero | F15: Retirar el equipo del rack lo suficiente para ver el panel trasero, o usar espejo de inspección, y leer la placa metálica de datos HORIBA. Verificar que coincida con el serial frontal. | G15: Texto | I15: Debe ser legible y coincidir con el serial frontal y la etiqueta de la cabina | J15: Alerta | K15: Placa ilegible o no coincide con la frontal | L15: 2.1.1 | M15: Verificar contra la documentación de fábrica y reportar la discrepancia antes de intervenir | N15: La placa de datos del fabricante en el panel posterior no es legible o no coincide con la identificación frontal del equipo. | Q15: Sí | R15: No | T15: MT_U7D80D0J_APMA370_260116 | U15: Pendiente | W15: =IF($G15<>"Numérico","",IF($V15="","Sin dato",IF(AND(OR(NOT(ISNUMBER($O15)),$V15>=$O15),OR(NOT(ISNUMBER($P15)),$V15<=$P15)),"Dentro de rango","Fuera de rango"))) | Z15: =IF(OR($U15="",$U15="Conforme",$U15="No aplica",$U15="Pendiente"),"",$N15&IF($W15="Fuera de rango"," Valor medido: "&TEXT($V15,"0.####")&IF($H15="",""," "&$H15)&IF(AND(ISNUMBER($O15),$V15<$O15),", por debajo del límite inferior de "&TEXT($O15,"0.####")&IF($H15="",""," "&$H15),"")&IF(AND(ISNUMBER($P15),$V15>$P15),", por encima del límite superior de "&TEXT($P15,"0.####")&IF($H15="",""," "&$H15),"")&".","")&IF($Y15="",""," "&$Y15&IF(RIGHT($Y15,1)=".","","."))&" Acción recomendada: "&$M15&IF(RIGHT($M15,1)=".","",".")&IF($J15="Bloqueante"," El equipo no se libera hasta resolver este hallazgo.",IF($J15="Cobrable"," Se incluye en la cotización de repuestos y consumibles."," Se deja registrado como observación.")))
A16: 2.2.1 | B16: 2. Identificación y trazabilidad | C16: 2.2 Identificación lógica | D16: ID del equipo (Machine ID) | E16: Configuración del código ID del analizador para identificación en red | F16: Ir a MENU / SYSTEM / MACHINE ID y leer el valor configurado. Contrastarlo con el mapa de direcciones del sistema de adquisición de la estación. | G16: Numérico | I16: El ID configurado en el menú SYSTEM debe coincidir con el asignado por el sistema de adquisición | J16: Alerta | K16: ID distinto al asignado en el sistema de adquisición | L16: 7.5.1 | M16: Corregir el ID en MENU/SYSTEM y confirmar la llegada del dato al datalogger | N16: El identificador del analizador no coincide con el asignado en el sistema de adquisición de datos de la estación. | O16: 0 | P16: 255 | Q16: Sí | R16: No | T16: P-ST-018-MAN OPER APMA 370 V2 | U16: Pendiente | W16: =IF($G16<>"Numérico","",IF($V16="","Sin dato",IF(AND(OR(NOT(ISNUMBER($O16)),$V16>=$O16),OR(NOT(ISNUMBER($P16)),$V16<=$P16)),"Dentro de rango","Fuera de rango"))) | Z16: =IF(OR($U16="",$U16="Conforme",$U16="No aplica",$U16="Pendiente"),"",$N16&IF($W16="Fuera de rango"," Valor medido: "&TEXT($V16,"0.####")&IF($H16="",""," "&$H16)&IF(AND(ISNUMBER($O16),$V16<$O16),", por debajo del límite inferior de "&TEXT($O16,"0.####")&IF($H16="",""," "&$H16),"")&IF(AND(ISNUMBER($P16),$V16>$P16),", por encima del límite superior de "&TEXT($P16,"0.####")&IF($H16="",""," "&$H16),"")&".","")&IF($Y16="",""," "&$Y16&IF(RIGHT($Y16,1)=".","","."))&" Acción recomendada: "&$M16&IF(RIGHT($M16,1)=".","",".")&IF($J16="Bloqueante"," El equipo no se libera hasta resolver este hallazgo.",IF($J16="Cobrable"," Se incluye en la cotización de repuestos y consumibles."," Se deja registrado como observación.")))
A17: 2.3.1 | B17: 2. Identificación y trazabilidad | C17: 2.3 Etiquetas de seguridad | D17: Señalización de choque eléctrico | E17: Etiquetas de advertencia de alto voltaje en cubiertas de placas y transformadores | F17: Con el equipo apagado y desconectado, retirar la cubierta superior y verificar visualmente la presencia y legibilidad de las etiquetas de advertencia sobre cubiertas de tarjetas y transformador. | G17: Presente / Ausente | I17: Deben estar adheridas y legibles las advertencias Choque eléctrico 1, 2 y 3 | J17: Alerta | K17: Etiqueta desprendida o ilegible por limpieza con solventes | L17: Nodo terminal — actuar directamente | M17: Reponer la etiqueta de seguridad y dejar constancia del faltante | N17: Faltan o no son legibles las etiquetas de advertencia de riesgo eléctrico en el interior del analizador. | Q17: Sí | R17: Sí | T17: P-ST-019-MAN MTTO APMA370 V2 | U17: Pendiente | W17: =IF($G17<>"Numérico","",IF($V17="","Sin dato",IF(AND(OR(NOT(ISNUMBER($O17)),$V17>=$O17),OR(NOT(ISNUMBER($P17)),$V17<=$P17)),"Dentro de rango","Fuera de rango"))) | Z17: =IF(OR($U17="",$U17="Conforme",$U17="No aplica",$U17="Pendiente"),"",$N17&IF($W17="Fuera de rango"," Valor medido: "&TEXT($V17,"0.####")&IF($H17="",""," "&$H17)&IF(AND(ISNUMBER($O17),$V17<$O17),", por debajo del límite inferior de "&TEXT($O17,"0.####")&IF($H17="",""," "&$H17),"")&IF(AND(ISNUMBER($P17),$V17>$P17),", por encima del límite superior de "&TEXT($P17,"0.####")&IF($H17="",""," "&$H17),"")&".","")&IF($Y17="",""," "&$Y17&IF(RIGHT($Y17,1)=".","","."))&" Acción recomendada: "&$M17&IF(RIGHT($M17,1)=".","",".")&IF($J17="Bloqueante"," El equipo no se libera hasta resolver este hallazgo.",IF($J17="Cobrable"," Se incluye en la cotización de repuestos y consumibles."," Se deja registrado como observación.")))
A18: 2.3.2 | B18: 2. Identificación y trazabilidad | C18: 2.3 Etiquetas de seguridad | D18: Señalización de componentes calientes | E18: Etiquetas adhesivas amarillas de advertencia térmica en zonas de alta temperatura | F18: Con el equipo frío y desconectado, retirar la cubierta superior y verificar la presencia de las etiquetas amarillas de advertencia térmica sobre la carcasa del catalizador y de la bomba. | G18: Presente / Ausente | I18: Deben estar adheridas las etiquetas de calor sobre la carcasa del catalizador y de la bomba | J18: Alerta | K18: Etiqueta desprendida por el calor del catalizador o de la bomba | L18: Nodo terminal — actuar directamente | M18: Reponer la etiqueta de advertencia térmica | N18: Faltan o no son legibles las etiquetas de advertencia de superficies calientes sobre el catalizador y la bomba. | Q18: Sí | R18: Sí | T18: P-ST-019-MAN MTTO APMA370 V2 | U18: Pendiente | W18: =IF($G18<>"Numérico","",IF($V18="","Sin dato",IF(AND(OR(NOT(ISNUMBER($O18)),$V18>=$O18),OR(NOT(ISNUMBER($P18)),$V18<=$P18)),"Dentro de rango","Fuera de rango"))) | Z18: =IF(OR($U18="",$U18="Conforme",$U18="No aplica",$U18="Pendiente"),"",$N18&IF($W18="Fuera de rango"," Valor medido: "&TEXT($V18,"0.####")&IF($H18="",""," "&$H18)&IF(AND(ISNUMBER($O18),$V18<$O18),", por debajo del límite inferior de "&TEXT($O18,"0.####")&IF($H18="",""," "&$H18),"")&IF(AND(ISNUMBER($P18),$V18>$P18),", por encima del límite superior de "&TEXT($P18,"0.####")&IF($H18="",""," "&$H18),"")&".","")&IF($Y18="",""," "&$Y18&IF(RIGHT($Y18,1)=".","","."))&" Acción recomendada: "&$M18&IF(RIGHT($M18,1)=".","",".")&IF($J18="Bloqueante"," El equipo no se libera hasta resolver este hallazgo.",IF($J18="Cobrable"," Se incluye en la cotización de repuestos y consumibles."," Se deja registrado como observación.")))
A19: 3.1.1 | B19: 3. Estado de calibración | C19: 3.1 Coeficientes de calibración | D19: Coeficiente de calibración de cero | E19: Factor de corrección de cero almacenado tras el último ajuste manual o AIC | F19: Ir a MENU / CAL. y leer el valor del coeficiente ZERO en pantalla. Anotarlo antes de realizar cualquier calibración; si parpadea, indica alarma de cero. | G19: Numérico | H19: counts | I19: Debe estar dentro del rango operativo; fuera de él parpadea la alarma ZERO | J19: Bloqueante | K19: Aire cero contaminado, calentamiento insuficiente, catalizador CAT-1 agotado o humedad en la línea de referencia | L19: 1.3.1 ; 6.4.1 ; 4.3.1 ; 5.3.2 ; 3.2.1 | M19: Inyectar aire cero de cilindro certificado para descartar el generador; si persiste, seguir la rama de catalizador y humedad | N19: El coeficiente de calibración de cero se encuentra fuera del rango admisible, por lo que la calibración del punto cero no es válida. | O19: -3500 | P19: 3500 | Q19: Sí | R19: No | T19: P-ST-018-MAN OPER APMA 370 V2 | U19: Pendiente | W19: =IF($G19<>"Numérico","",IF($V19="","Sin dato",IF(AND(OR(NOT(ISNUMBER($O19)),$V19>=$O19),OR(NOT(ISNUMBER($P19)),$V19<=$P19)),"Dentro de rango","Fuera de rango"))) | Z19: =IF(OR($U19="",$U19="Conforme",$U19="No aplica",$U19="Pendiente"),"",$N19&IF($W19="Fuera de rango"," Valor medido: "&TEXT($V19,"0.####")&IF($H19="",""," "&$H19)&IF(AND(ISNUMBER($O19),$V19<$O19),", por debajo del límite inferior de "&TEXT($O19,"0.####")&IF($H19="",""," "&$H19),"")&IF(AND(ISNUMBER($P19),$V19>$P19),", por encima del límite superior de "&TEXT($P19,"0.####")&IF($H19="",""," "&$H19),"")&".","")&IF($Y19="",""," "&$Y19&IF(RIGHT($Y19,1)=".","","."))&" Acción recomendada: "&$M19&IF(RIGHT($M19,1)=".","",".")&IF($J19="Bloqueante"," El equipo no se libera hasta resolver este hallazgo.",IF($J19="Cobrable"," Se incluye en la cotización de repuestos y consumibles."," Se deja registrado como observación.")))
A20: 3.1.2 | B20: 3. Estado de calibración | C20: 3.1 Coeficientes de calibración | D20: Coeficiente de calibración de span | E20: Ganancia del detector de CO calibrada con gas patrón y almacenada en memoria | F20: Ir a MENU / CAL. y leer el valor del coeficiente SPAN en pantalla. Anotarlo antes de calibrar; si parpadea, indica alarma de span. | G20: Numérico | I20: Debe estar dentro de los límites de amplificación admitidos; fuera de él parpadea la alarma SPAN | J20: Bloqueante | K20: Concentración del patrón mal configurada, caudal de exceso insuficiente, o pérdida de intensidad óptica | L20: 3.2.1 ; 3.2.2 ; 6.1.1 ; 6.2.2 ; 6.2.1 | M20: Confirmar SPAN CONC. contra el certificado del cilindro y volver a calibrar | N20: El coeficiente de calibración de span se encuentra fuera del rango admisible, por lo que la calibración de sensibilidad no es válida. | O20: 0.5 | P20: 2 | Q20: Sí | R20: No | T20: P-ST-018-MAN OPER APMA 370 V2 | U20: Pendiente | W20: =IF($G20<>"Numérico","",IF($V20="","Sin dato",IF(AND(OR(NOT(ISNUMBER($O20)),$V20>=$O20),OR(NOT(ISNUMBER($P20)),$V20<=$P20)),"Dentro de rango","Fuera de rango"))) | Z20: =IF(OR($U20="",$U20="Conforme",$U20="No aplica",$U20="Pendiente"),"",$N20&IF($W20="Fuera de rango"," Valor medido: "&TEXT($V20,"0.####")&IF($H20="",""," "&$H20)&IF(AND(ISNUMBER($O20),$V20<$O20),", por debajo del límite inferior de "&TEXT($O20,"0.####")&IF($H20="",""," "&$H20),"")&IF(AND(ISNUMBER($P20),$V20>$P20),", por encima del límite superior de "&TEXT($P20,"0.####")&IF($H20="",""," "&$H20),"")&".","")&IF($Y20="",""," "&$Y20&IF(RIGHT($Y20,1)=".","","."))&" Acción recomendada: "&$M20&IF(RIGHT($M20,1)=".","",".")&IF($J20="Bloqueante"," El equipo no se libera hasta resolver este hallazgo.",IF($J20="Cobrable"," Se incluye en la cotización de repuestos y consumibles."," Se deja registrado como observación.")))
A21: 3.2.1 | B21: 3. Estado de calibración | C21: 3.2 Suministro de gases patrón | D21: Presión de entrada de gas patrón | E21: Presión de entrega de gases de referencia (cero y span) en las entradas traseras | F21: Conectar un manómetro de baja presión en la línea de gas patrón, aguas arriba de la entrada CAL GAS INLET, y leer la presión con el gas fluyendo. Ajustar en el regulador del cilindro. | G21: Numérico | H21: kPa | I21: Deben entregarse ligeramente por encima de la presión atmosférica para generar overflow | J21: Bloqueante | K21: Regulador del cilindro mal ajustado o cilindro despresurizado | L21: 3.2.2 | M21: Reajustar el regulador de doble etapa hasta lograr overflow estable | N21: La presión de entrega del gas patrón no es la adecuada, lo que compromete la validez de la calibración. | O21: 0 | P21: 0.5 | Q21: Sí | R21: No | T21: P-ST-018-MAN OPER APMA 370 V2 | U21: Pendiente | W21: =IF($G21<>"Numérico","",IF($V21="","Sin dato",IF(AND(OR(NOT(ISNUMBER($O21)),$V21>=$O21),OR(NOT(ISNUMBER($P21)),$V21<=$P21)),"Dentro de rango","Fuera de rango"))) | Z21: =IF(OR($U21="",$U21="Conforme",$U21="No aplica",$U21="Pendiente"),"",$N21&IF($W21="Fuera de rango"," Valor medido: "&TEXT($V21,"0.####")&IF($H21="",""," "&$H21)&IF(AND(ISNUMBER($O21),$V21<$O21),", por debajo del límite inferior de "&TEXT($O21,"0.####")&IF($H21="",""," "&$H21),"")&IF(AND(ISNUMBER($P21),$V21>$P21),", por encima del límite superior de "&TEXT($P21,"0.####")&IF($H21="",""," "&$H21),"")&".","")&IF($Y21="",""," "&$Y21&IF(RIGHT($Y21,1)=".","","."))&" Acción recomendada: "&$M21&IF(RIGHT($M21,1)=".","",".")&IF($J21="Bloqueante"," El equipo no se libera hasta resolver este hallazgo.",IF($J21="Cobrable"," Se incluye en la cotización de repuestos y consumibles."," Se deja registrado como observación.")))
A22: 3.2.2 | B22: 3. Estado de calibración | C22: 3.2 Suministro de gases patrón | D22: Caudal de exceso de gas de calibración (OVER FLOW) | E22: Caudal excedente medido por el sensor de flujo opcional de calibración | F22: Con el gas patrón fluyendo, leer el caudal de exceso en MENU / MAINTENANCE / ANALOG INPUT, o medirlo con flujómetro de burbuja en la salida de venteo del arreglo de calibración. | G22: Numérico | H22: L/min | I22: Caudal mínimo 1,2 L/min para que el analizador absorba gas patrón sin aspirar aire ambiente. Límite superior PENDIENTE DE VALIDAR | J22: Bloqueante | K22: Caudal insuficiente: el analizador aspira aire ambiente mezclado con el patrón | L22: 3.2.1 ; 5.3.2 | M22: Subir el caudal por encima de 1,2 L/min y repetir la calibración | N22: El caudal de exceso del gas de calibración es insuficiente: el analizador aspira aire ambiente mezclado con el gas patrón. | O22: 1.2 | Q22: Sí | R22: No | T22: P-ST-018-MAN OPER APMA 370 V2 | U22: Pendiente | W22: =IF($G22<>"Numérico","",IF($V22="","Sin dato",IF(AND(OR(NOT(ISNUMBER($O22)),$V22>=$O22),OR(NOT(ISNUMBER($P22)),$V22<=$P22)),"Dentro de rango","Fuera de rango"))) | Z22: =IF(OR($U22="",$U22="Conforme",$U22="No aplica",$U22="Pendiente"),"",$N22&IF($W22="Fuera de rango"," Valor medido: "&TEXT($V22,"0.####")&IF($H22="",""," "&$H22)&IF(AND(ISNUMBER($O22),$V22<$O22),", por debajo del límite inferior de "&TEXT($O22,"0.####")&IF($H22="",""," "&$H22),"")&IF(AND(ISNUMBER($P22),$V22>$P22),", por encima del límite superior de "&TEXT($P22,"0.####")&IF($H22="",""," "&$H22),"")&".","")&IF($Y22="",""," "&$Y22&IF(RIGHT($Y22,1)=".","","."))&" Acción recomendada: "&$M22&IF(RIGHT($M22,1)=".","",".")&IF($J22="Bloqueante"," El equipo no se libera hasta resolver este hallazgo.",IF($J22="Cobrable"," Se incluye en la cotización de repuestos y consumibles."," Se deja registrado como observación.")))
A23: 3.3.1 | B23: 3. Estado de calibración | C23: 3.3 Secuencia de autocalibración (AIC) | D23: Tiempo de espera (WAIT) en AIC | E23: Tiempo configurado para purgar la celda y estabilizar lecturas tras conmutar la línea de gas | F23: Ir a MENU / MAINTENANCE / AIC y leer el tiempo WAIT configurado. Anotarlo y compararlo con el mínimo recomendado por el fabricante. | G23: Numérico | H23: minutos | I23: Tiempo mínimo de retardo tras conmutar la línea de gas; el fabricante recomienda 3 min o más | J23: Alerta | K23: Tiempo insuficiente para purgar la línea de calibración | L23: Nodo terminal — actuar directamente | M23: Subir el WAIT a 3 min o más, según la longitud de la línea instalada | N23: El tiempo de espera de la secuencia de autocalibración es insuficiente para purgar la línea antes de tomar la lectura. | O23: 3 | P23: 999 | Q23: Sí | R23: No | T23: P-ST-018-MAN OPER APMA 370 V2 | U23: Pendiente | W23: =IF($G23<>"Numérico","",IF($V23="","Sin dato",IF(AND(OR(NOT(ISNUMBER($O23)),$V23>=$O23),OR(NOT(ISNUMBER($P23)),$V23<=$P23)),"Dentro de rango","Fuera de rango"))) | Z23: =IF(OR($U23="",$U23="Conforme",$U23="No aplica",$U23="Pendiente"),"",$N23&IF($W23="Fuera de rango"," Valor medido: "&TEXT($V23,"0.####")&IF($H23="",""," "&$H23)&IF(AND(ISNUMBER($O23),$V23<$O23),", por debajo del límite inferior de "&TEXT($O23,"0.####")&IF($H23="",""," "&$H23),"")&IF(AND(ISNUMBER($P23),$V23>$P23),", por encima del límite superior de "&TEXT($P23,"0.####")&IF($H23="",""," "&$H23),"")&".","")&IF($Y23="",""," "&$Y23&IF(RIGHT($Y23,1)=".","","."))&" Acción recomendada: "&$M23&IF(RIGHT($M23,1)=".","",".")&IF($J23="Bloqueante"," El equipo no se libera hasta resolver este hallazgo.",IF($J23="Cobrable"," Se incluye en la cotización de repuestos y consumibles."," Se deja registrado como observación.")))
A24: 3.3.2 | B24: 3. Estado de calibración | C24: 3.3 Secuencia de autocalibración (AIC) | D24: Tiempo de sostenimiento (HOLD) en AIC | E24: Tiempo de retención y chequeo de lecturas de salida al finalizar el AIC | F24: Ir a MENU / MAINTENANCE / AIC y leer el tiempo HOLD configurado. Anotarlo junto con el resto de parámetros de la secuencia. | G24: Numérico | H24: minutos | I24: Tiempo de validación posterior a la calibración física de las señales analógicas | J24: Alerta | K24: Parámetro distinto al acordado con la red de monitoreo | L24: Nodo terminal — actuar directamente | M24: Ajustar el HOLD al valor definido por el operador de la red | N24: El tiempo de sostenimiento de la secuencia de autocalibración no corresponde al definido para la red de monitoreo. | O24: 0 | P24: 999 | Q24: Sí | R24: No | T24: P-ST-018-MAN OPER APMA 370 V2 | U24: Pendiente | W24: =IF($G24<>"Numérico","",IF($V24="","Sin dato",IF(AND(OR(NOT(ISNUMBER($O24)),$V24>=$O24),OR(NOT(ISNUMBER($P24)),$V24<=$P24)),"Dentro de rango","Fuera de rango"))) | Z24: =IF(OR($U24="",$U24="Conforme",$U24="No aplica",$U24="Pendiente"),"",$N24&IF($W24="Fuera de rango"," Valor medido: "&TEXT($V24,"0.####")&IF($H24="",""," "&$H24)&IF(AND(ISNUMBER($O24),$V24<$O24),", por debajo del límite inferior de "&TEXT($O24,"0.####")&IF($H24="",""," "&$H24),"")&IF(AND(ISNUMBER($P24),$V24>$P24),", por encima del límite superior de "&TEXT($P24,"0.####")&IF($H24="",""," "&$H24),"")&".","")&IF($Y24="",""," "&$Y24&IF(RIGHT($Y24,1)=".","","."))&" Acción recomendada: "&$M24&IF(RIGHT($M24,1)=".","",".")&IF($J24="Bloqueante"," El equipo no se libera hasta resolver este hallazgo.",IF($J24="Cobrable"," Se incluye en la cotización de repuestos y consumibles."," Se deja registrado como observación.")))
A25: 3.3.3 | B25: 3. Estado de calibración | C25: 3.3 Secuencia de autocalibración (AIC) | D25: Activación de calibración (CAL) en AIC | E25: Selección de la corrección física del factor cero/span durante el AIC | F25: Ir a MENU / MAINTENANCE / AIC y leer el ajuste CAL (YES / NO). Confirmar con el responsable de la red si la política es corregir factores o solo verificar. | G25: Sí/No | I25: Define si se corrigen factores (YES) o solo se realiza lectura de verificación (NO) | J25: Alerta | K25: Ajuste incoherente con la política de la red (corregir factores vs. solo verificar) | L25: Nodo terminal — actuar directamente | M25: Definirlo con el responsable de la red y dejarlo documentado | N25: La opción de corrección automática de la secuencia de autocalibración no corresponde a la política definida para la estación. | Q25: Sí | R25: No | T25: P-ST-018-MAN OPER APMA 370 V2 | U25: Pendiente | W25: =IF($G25<>"Numérico","",IF($V25="","Sin dato",IF(AND(OR(NOT(ISNUMBER($O25)),$V25>=$O25),OR(NOT(ISNUMBER($P25)),$V25<=$P25)),"Dentro de rango","Fuera de rango"))) | Z25: =IF(OR($U25="",$U25="Conforme",$U25="No aplica",$U25="Pendiente"),"",$N25&IF($W25="Fuera de rango"," Valor medido: "&TEXT($V25,"0.####")&IF($H25="",""," "&$H25)&IF(AND(ISNUMBER($O25),$V25<$O25),", por debajo del límite inferior de "&TEXT($O25,"0.####")&IF($H25="",""," "&$H25),"")&IF(AND(ISNUMBER($P25),$V25>$P25),", por encima del límite superior de "&TEXT($P25,"0.####")&IF($H25="",""," "&$H25),"")&".","")&IF($Y25="",""," "&$Y25&IF(RIGHT($Y25,1)=".","","."))&" Acción recomendada: "&$M25&IF(RIGHT($M25,1)=".","",".")&IF($J25="Bloqueante"," El equipo no se libera hasta resolver este hallazgo.",IF($J25="Cobrable"," Se incluye en la cotización de repuestos y consumibles."," Se deja registrado como observación.")))
A26: 4.1.1 | B26: 4. Línea de muestreo y acondicionamiento | C26: 4.1 Conectores neumáticos traseros | D26: Férula de Sample Inlet (Sleeve) | E26: Presencia del casquillo de teflón de sellado interno en la entrada de muestra | F26: Aflojar la tuerca del puerto SAMPLE INLET en el panel trasero, extraer la manguera y verificar que la férula de teflón esté montada sobre el tubo. Volver a montar sin sobreapretar. | G26: Presente / Ausente | I26: Debe estar montada la férula para asegurar acople hermético libre de aire falso | J26: Bloqueante | K26: Férula ausente o mal montada: ingreso de aire falso por la entrada de muestra | L26: 5.3.2 ; 5.1.1 ; 3.1.1 | M26: Instalar la férula, reapretar y repetir la prueba de estanqueidad antes de calibrar | N26: Falta la férula de sellado en la entrada de muestra, lo que permite el ingreso de aire ambiente y altera la medición. | Q26: Sí | R26: Sí | S26: Sleeve / SO2001-6 (3030021777) | T26: MT_P4B4CK60_APMA370_220511 | U26: Pendiente | W26: =IF($G26<>"Numérico","",IF($V26="","Sin dato",IF(AND(OR(NOT(ISNUMBER($O26)),$V26>=$O26),OR(NOT(ISNUMBER($P26)),$V26<=$P26)),"Dentro de rango","Fuera de rango"))) | Z26: =IF(OR($U26="",$U26="Conforme",$U26="No aplica",$U26="Pendiente"),"",$N26&IF($W26="Fuera de rango"," Valor medido: "&TEXT($V26,"0.####")&IF($H26="",""," "&$H26)&IF(AND(ISNUMBER($O26),$V26<$O26),", por debajo del límite inferior de "&TEXT($O26,"0.####")&IF($H26="",""," "&$H26),"")&IF(AND(ISNUMBER($P26),$V26>$P26),", por encima del límite superior de "&TEXT($P26,"0.####")&IF($H26="",""," "&$H26),"")&".","")&IF($Y26="",""," "&$Y26&IF(RIGHT($Y26,1)=".","","."))&" Acción recomendada: "&$M26&IF(RIGHT($M26,1)=".","",".")&IF($J26="Bloqueante"," El equipo no se libera hasta resolver este hallazgo.",IF($J26="Cobrable"," Se incluye en la cotización de repuestos y consumibles."," Se deja registrado como observación.")))
A27: 4.1.2 | B27: 4. Línea de muestreo y acondicionamiento | C27: 4.1 Conectores neumáticos traseros | D27: Tuerca de Sample Inlet (Cap Nut) | E27: Presencia de la tuerca plástica de rosca fina en la entrada de muestra | F27: Inspeccionar visualmente el puerto SAMPLE INLET y comprobar que la tuerca de PVDF esté presente y roscada. Verificar el apriete manualmente, sin herramienta. | G27: Presente / Ausente | I27: Debe estar presente y roscada firmemente la tuerca PVDF para sellar la tubería | J27: Bloqueante | K27: Tuerca ausente, fisurada o floja | L27: 5.3.2 ; 4.1.1 | M27: Reponer la tuerca de PVDF y repetir la prueba de estanqueidad | N27: La tuerca de sellado de la entrada de muestra está ausente, fisurada o floja, con riesgo de fuga. | Q27: Sí | R27: Sí | S27: Cap Nut / S020020-6PVDF (3030021779) | T27: MT_P4B4CK60_APMA370_220511 | U27: Pendiente | W27: =IF($G27<>"Numérico","",IF($V27="","Sin dato",IF(AND(OR(NOT(ISNUMBER($O27)),$V27>=$O27),OR(NOT(ISNUMBER($P27)),$V27<=$P27)),"Dentro de rango","Fuera de rango"))) | Z27: =IF(OR($U27="",$U27="Conforme",$U27="No aplica",$U27="Pendiente"),"",$N27&IF($W27="Fuera de rango"," Valor medido: "&TEXT($V27,"0.####")&IF($H27="",""," "&$H27)&IF(AND(ISNUMBER($O27),$V27<$O27),", por debajo del límite inferior de "&TEXT($O27,"0.####")&IF($H27="",""," "&$H27),"")&IF(AND(ISNUMBER($P27),$V27>$P27),", por encima del límite superior de "&TEXT($P27,"0.####")&IF($H27="",""," "&$H27),"")&".","")&IF($Y27="",""," "&$Y27&IF(RIGHT($Y27,1)=".","","."))&" Acción recomendada: "&$M27&IF(RIGHT($M27,1)=".","",".")&IF($J27="Bloqueante"," El equipo no se libera hasta resolver este hallazgo.",IF($J27="Cobrable"," Se incluye en la cotización de repuestos y consumibles."," Se deja registrado como observación.")))
A28: 4.1.3 | B28: 4. Línea de muestreo y acondicionamiento | C28: 4.1 Conectores neumáticos traseros | D28: Férula de Exhaust (Sleeve) | E28: Presencia del casquillo de teflón de sellado interno en la salida de escape | F28: Aflojar la tuerca del puerto EXHAUST, extraer la manguera y verificar que la férula de teflón esté montada sobre el tubo. Volver a montar sin sobreapretar. | G28: Presente / Ausente | I28: Debe estar montada la férula para evitar fugas de gases de escape hacia la cabina | J28: Bloqueante | K28: Férula ausente: fuga de gases de escape hacia la cabina | L28: 5.3.2 | M28: Instalar la férula y verificar que el escape quede canalizado | N28: Falta la férula de sellado en la salida de escape, lo que permite la fuga de los gases de descarga hacia la cabina. | Q28: Sí | R28: Sí | S28: Sleeve / SO2001-6 (3030021777) | T28: MT_P4B4CK60_APMA370_220511 | U28: Pendiente | W28: =IF($G28<>"Numérico","",IF($V28="","Sin dato",IF(AND(OR(NOT(ISNUMBER($O28)),$V28>=$O28),OR(NOT(ISNUMBER($P28)),$V28<=$P28)),"Dentro de rango","Fuera de rango"))) | Z28: =IF(OR($U28="",$U28="Conforme",$U28="No aplica",$U28="Pendiente"),"",$N28&IF($W28="Fuera de rango"," Valor medido: "&TEXT($V28,"0.####")&IF($H28="",""," "&$H28)&IF(AND(ISNUMBER($O28),$V28<$O28),", por debajo del límite inferior de "&TEXT($O28,"0.####")&IF($H28="",""," "&$H28),"")&IF(AND(ISNUMBER($P28),$V28>$P28),", por encima del límite superior de "&TEXT($P28,"0.####")&IF($H28="",""," "&$H28),"")&".","")&IF($Y28="",""," "&$Y28&IF(RIGHT($Y28,1)=".","","."))&" Acción recomendada: "&$M28&IF(RIGHT($M28,1)=".","",".")&IF($J28="Bloqueante"," El equipo no se libera hasta resolver este hallazgo.",IF($J28="Cobrable"," Se incluye en la cotización de repuestos y consumibles."," Se deja registrado como observación.")))
A29: 4.1.4 | B29: 4. Línea de muestreo y acondicionamiento | C29: 4.1 Conectores neumáticos traseros | D29: Tuerca de Exhaust (Cap Nut) | E29: Presencia de la tuerca plástica de rosca fina en la salida de escape | F29: Inspeccionar visualmente el puerto EXHAUST y comprobar que la tuerca de PVDF esté presente y roscada. Verificar el apriete manualmente, sin herramienta. | G29: Presente / Ausente | I29: Debe estar presente y roscada firmemente la tuerca PVDF para canalizar el escape | J29: Bloqueante | K29: Tuerca ausente o floja en la salida de escape | L29: 5.3.2 ; 4.1.3 | M29: Reponer la tuerca de PVDF y reapretar | N29: La tuerca de sellado de la salida de escape está ausente, fisurada o floja. | Q29: Sí | R29: Sí | S29: Cap Nut / S020020-6PVDF (3030021779) | T29: MT_P4B4CK60_APMA370_220511 | U29: Pendiente | W29: =IF($G29<>"Numérico","",IF($V29="","Sin dato",IF(AND(OR(NOT(ISNUMBER($O29)),$V29>=$O29),OR(NOT(ISNUMBER($P29)),$V29<=$P29)),"Dentro de rango","Fuera de rango"))) | Z29: =IF(OR($U29="",$U29="Conforme",$U29="No aplica",$U29="Pendiente"),"",$N29&IF($W29="Fuera de rango"," Valor medido: "&TEXT($V29,"0.####")&IF($H29="",""," "&$H29)&IF(AND(ISNUMBER($O29),$V29<$O29),", por debajo del límite inferior de "&TEXT($O29,"0.####")&IF($H29="",""," "&$H29),"")&IF(AND(ISNUMBER($P29),$V29>$P29),", por encima del límite superior de "&TEXT($P29,"0.####")&IF($H29="",""," "&$H29),"")&".","")&IF($Y29="",""," "&$Y29&IF(RIGHT($Y29,1)=".","","."))&" Acción recomendada: "&$M29&IF(RIGHT($M29,1)=".","",".")&IF($J29="Bloqueante"," El equipo no se libera hasta resolver este hallazgo.",IF($J29="Cobrable"," Se incluye en la cotización de repuestos y consumibles."," Se deja registrado como observación.")))
A30: 4.1.5 | B30: 4. Línea de muestreo y acondicionamiento | C30: 4.1 Conectores neumáticos traseros | D30: Panel Mount Union (SO21521-6 PVDF) | E30: Estado físico e integridad del racor plástico de montaje de panel | F30: Con las mangueras retiradas, inspeccionar el racor pasamuros del panel trasero buscando fisuras en la rosca, deformación o material fatigado. Iluminar con linterna. | G30: OK / No OK | I30: Racor libre de fisuras en su rosca o fatiga de material por sobreajuste | J30: Bloqueante | K30: Racor fisurado por sobreapriete o fatiga del plástico | L30: 5.3.2 | M30: Reemplazar el racor pasamuros y repetir la prueba de estanqueidad | N30: El racor de montaje del panel posterior presenta fisuras o fatiga del material, con riesgo de fuga. | Q30: Sí | R30: Sí | S30: Panel mount union SO21521- 6(PVDF)SP SW1=14 (3030021548) | T30: MT_191TE0NC_APMA370_241226 | U30: Pendiente | W30: =IF($G30<>"Numérico","",IF($V30="","Sin dato",IF(AND(OR(NOT(ISNUMBER($O30)),$V30>=$O30),OR(NOT(ISNUMBER($P30)),$V30<=$P30)),"Dentro de rango","Fuera de rango"))) | Z30: =IF(OR($U30="",$U30="Conforme",$U30="No aplica",$U30="Pendiente"),"",$N30&IF($W30="Fuera de rango"," Valor medido: "&TEXT($V30,"0.####")&IF($H30="",""," "&$H30)&IF(AND(ISNUMBER($O30),$V30<$O30),", por debajo del límite inferior de "&TEXT($O30,"0.####")&IF($H30="",""," "&$H30),"")&IF(AND(ISNUMBER($P30),$V30>$P30),", por encima del límite superior de "&TEXT($P30,"0.####")&IF($H30="",""," "&$H30),"")&".","")&IF($Y30="",""," "&$Y30&IF(RIGHT($Y30,1)=".","","."))&" Acción recomendada: "&$M30&IF(RIGHT($M30,1)=".","",".")&IF($J30="Bloqueante"," El equipo no se libera hasta resolver este hallazgo.",IF($J30="Cobrable"," Se incluye en la cotización de repuestos y consumibles."," Se deja registrado como observación.")))
A31: 4.2.1 | B31: 4. Línea de muestreo y acondicionamiento | C31: 4.2 Portafiltros frontal | D31: Colmatación del filtro de partículas PA-10L | E31: Nivel de colmatación, hollín, polvo o humedad en el filtro frontal de teflón de 54 mm | F31: Abrir la puerta frontal, desenroscar el vaso del portafiltros, extraer el elemento y compararlo contra un filtro nuevo sobre fondo blanco. Fotografiar antes de reemplazar. | G31: OK / No OK | I31: Filtro de teflón blanco uniforme, sin partículas ni manchas oscuras que estrangulen el caudal | J31: Cobrable | K31: Filtro saturado de material particulado, hollín o humedad | L31: 5.1.2 ; 5.1.1 ; 8.1.1 | M31: Reemplazar el elemento filtrante y reiniciar su horómetro | N31: El filtro de partículas se encuentra colmatado, lo que restringe el caudal de muestra. | Q31: Sí | R31: Sí | S31: Filter Element PA-10L diámetro 54*0.5t (24pc/set) (3200043947; alt. 3200043947-1PC) | T31: MT_56X1BA8G_APMA370_260109 | U31: Pendiente | W31: =IF($G31<>"Numérico","",IF($V31="","Sin dato",IF(AND(OR(NOT(ISNUMBER($O31)),$V31>=$O31),OR(NOT(ISNUMBER($P31)),$V31<=$P31)),"Dentro de rango","Fuera de rango"))) | Z31: =IF(OR($U31="",$U31="Conforme",$U31="No aplica",$U31="Pendiente"),"",$N31&IF($W31="Fuera de rango"," Valor medido: "&TEXT($V31,"0.####")&IF($H31="",""," "&$H31)&IF(AND(ISNUMBER($O31),$V31<$O31),", por debajo del límite inferior de "&TEXT($O31,"0.####")&IF($H31="",""," "&$H31),"")&IF(AND(ISNUMBER($P31),$V31>$P31),", por encima del límite superior de "&TEXT($P31,"0.####")&IF($H31="",""," "&$H31),"")&".","")&IF($Y31="",""," "&$Y31&IF(RIGHT($Y31,1)=".","","."))&" Acción recomendada: "&$M31&IF(RIGHT($M31,1)=".","",".")&IF($J31="Bloqueante"," El equipo no se libera hasta resolver este hallazgo.",IF($J31="Cobrable"," Se incluye en la cotización de repuestos y consumibles."," Se deja registrado como observación.")))
A32: 4.2.2 | B32: 4. Línea de muestreo y acondicionamiento | C32: 4.2 Portafiltros frontal | D32: Empaque del filtro frontal (PA-10L) | E32: Flexibilidad y ausencia de grietas en la junta elástica plana del portafiltros | F32: Con el portafiltros abierto, retirar el empaque plano, flexionarlo entre los dedos y buscar grietas, aplastamiento permanente o pérdida de elasticidad. | G32: OK / No OK | I32: Empaque blando, sin aplastamientos ni deformaciones permanentes que provoquen fugas | J32: Cobrable | K32: Empaque endurecido o aplastado: fuga en el portafiltros | L32: 5.3.2 | M32: Reemplazar el empaque y repetir la prueba de estanqueidad | N32: El empaque del portafiltros ha perdido elasticidad y no garantiza el sello del alojamiento del filtro. | Q32: Sí | R32: Sí | S32: F-Packing FPM (3200044273) | T32: P-ST-019-MAN MTTO APMA370 V2 | U32: Pendiente | W32: =IF($G32<>"Numérico","",IF($V32="","Sin dato",IF(AND(OR(NOT(ISNUMBER($O32)),$V32>=$O32),OR(NOT(ISNUMBER($P32)),$V32<=$P32)),"Dentro de rango","Fuera de rango"))) | Z32: =IF(OR($U32="",$U32="Conforme",$U32="No aplica",$U32="Pendiente"),"",$N32&IF($W32="Fuera de rango"," Valor medido: "&TEXT($V32,"0.####")&IF($H32="",""," "&$H32)&IF(AND(ISNUMBER($O32),$V32<$O32),", por debajo del límite inferior de "&TEXT($O32,"0.####")&IF($H32="",""," "&$H32),"")&IF(AND(ISNUMBER($P32),$V32>$P32),", por encima del límite superior de "&TEXT($P32,"0.####")&IF($H32="",""," "&$H32),"")&".","")&IF($Y32="",""," "&$Y32&IF(RIGHT($Y32,1)=".","","."))&" Acción recomendada: "&$M32&IF(RIGHT($M32,1)=".","",".")&IF($J32="Bloqueante"," El equipo no se libera hasta resolver este hallazgo.",IF($J32="Cobrable"," Se incluye en la cotización de repuestos y consumibles."," Se deja registrado como observación.")))
A33: 4.2.3 | B33: 4. Línea de muestreo y acondicionamiento | C33: 4.2 Portafiltros frontal | D33: Junta tórica del portafiltros (O-Ring) | E33: Resequedad, microfisuras o deformación de la junta tórica de la tapa del filtro | F33: Retirar la junta tórica de la tapa del portafiltros, limpiarla y examinarla estirándola suavemente contra la luz, buscando microfisuras, resequedad o deformación. | G33: OK / No OK | I33: Junta de vitón elástica y ligeramente lubricada para garantizar hermetismo de la tapa | J33: Cobrable | K33: Junta reseca o con microfisuras: fuga en la tapa | L33: 5.3.2 | M33: Reemplazar la junta tórica y lubricarla levemente al montar | N33: La junta tórica de la tapa del portafiltros presenta resequedad o microfisuras y no garantiza la hermeticidad. | Q33: Sí | R33: Sí | S33: O-Ring JISB2401 G70 (3200043785) | T33: P-ST-019-MAN MTTO APMA370 V2 | U33: Pendiente | W33: =IF($G33<>"Numérico","",IF($V33="","Sin dato",IF(AND(OR(NOT(ISNUMBER($O33)),$V33>=$O33),OR(NOT(ISNUMBER($P33)),$V33<=$P33)),"Dentro de rango","Fuera de rango"))) | Z33: =IF(OR($U33="",$U33="Conforme",$U33="No aplica",$U33="Pendiente"),"",$N33&IF($W33="Fuera de rango"," Valor medido: "&TEXT($V33,"0.####")&IF($H33="",""," "&$H33)&IF(AND(ISNUMBER($O33),$V33<$O33),", por debajo del límite inferior de "&TEXT($O33,"0.####")&IF($H33="",""," "&$H33),"")&IF(AND(ISNUMBER($P33),$V33>$P33),", por encima del límite superior de "&TEXT($P33,"0.####")&IF($H33="",""," "&$H33),"")&".","")&IF($Y33="",""," "&$Y33&IF(RIGHT($Y33,1)=".","","."))&" Acción recomendada: "&$M33&IF(RIGHT($M33,1)=".","",".")&IF($J33="Bloqueante"," El equipo no se libera hasta resolver este hallazgo.",IF($J33="Cobrable"," Se incluye en la cotización de repuestos y consumibles."," Se deja registrado como observación.")))
A34: 4.3.1 | B34: 4. Línea de muestreo y acondicionamiento | C34: 4.3 Acondicionamiento de la muestra | D34: Trampa de humedad (Mist Catcher BAA) | E34: Acumulación de agua condensada y saturación del depurador de humedad | F34: Con el equipo apagado, retirar la cubierta superior, desmontar la trampa Mist Catcher y verificar si hay agua acumulada en el depósito y el estado del relleno. Vaciar y secar si aplica. | G34: OK / No OK | I34: El depósito debe estar libre de condensados y el relleno sin saturación física | J34: Cobrable | K34: Condensado acumulado por línea de muestreo sin trampa, o shelter con oscilación térmica | L34: 4.3.2 ; 3.1.1 ; 10.4.1 | M34: Vaciar y secar la trampa, purgar el circuito con aire seco y corregir el origen del condensado | N34: La trampa de humedad presenta acumulación de condensado, con riesgo de arrastre de agua hacia el sistema de medición. | Q34: Sí | R34: Sí | S34: Sin artículo en el catálogo (Mist Catcher MC-1) — PENDIENTE DE CREAR EN ZOHO | T34: MT_V440EL8D_APMA370_260430 | U34: Pendiente | W34: =IF($G34<>"Numérico","",IF($V34="","Sin dato",IF(AND(OR(NOT(ISNUMBER($O34)),$V34>=$O34),OR(NOT(ISNUMBER($P34)),$V34<=$P34)),"Dentro de rango","Fuera de rango"))) | Z34: =IF(OR($U34="",$U34="Conforme",$U34="No aplica",$U34="Pendiente"),"",$N34&IF($W34="Fuera de rango"," Valor medido: "&TEXT($V34,"0.####")&IF($H34="",""," "&$H34)&IF(AND(ISNUMBER($O34),$V34<$O34),", por debajo del límite inferior de "&TEXT($O34,"0.####")&IF($H34="",""," "&$H34),"")&IF(AND(ISNUMBER($P34),$V34>$P34),", por encima del límite superior de "&TEXT($P34,"0.####")&IF($H34="",""," "&$H34),"")&".","")&IF($Y34="",""," "&$Y34&IF(RIGHT($Y34,1)=".","","."))&" Acción recomendada: "&$M34&IF(RIGHT($M34,1)=".","",".")&IF($J34="Bloqueante"," El equipo no se libera hasta resolver este hallazgo.",IF($J34="Cobrable"," Se incluye en la cotización de repuestos y consumibles."," Se deja registrado como observación.")))
A35: 4.3.2 | B35: 4. Línea de muestreo y acondicionamiento | C35: 4.3 Acondicionamiento de la muestra | D35: Líneas de teflón internas | E35: Estrangulamientos, dobleces agudos o acumulación de suciedad en mangueras neumáticas | F35: Con la cubierta superior retirada, recorrer visualmente cada tramo de manguera interna buscando dobleces agudos, aplastamientos, decoloración o suciedad. Verificar el asiento de cada racor. | G35: OK / No OK | I35: Tuberías de teflón translúcidas, firmes en sus racores y sin dobleces que restrinjan el flujo | J35: Cobrable | K35: Manguera doblada, aplastada o con suciedad interna | L35: 5.1.1 ; 5.1.2 | M35: Rectificar el trazado o reemplazar el tramo afectado | N35: Las líneas neumáticas internas presentan dobleces, aplastamientos o suciedad que restringen el paso del gas de muestra. | Q35: Sí | R35: Sí | T35: MT_U403C0JJ_APMA370_21033001 | U35: Pendiente | W35: =IF($G35<>"Numérico","",IF($V35="","Sin dato",IF(AND(OR(NOT(ISNUMBER($O35)),$V35>=$O35),OR(NOT(ISNUMBER($P35)),$V35<=$P35)),"Dentro de rango","Fuera de rango"))) | Z35: =IF(OR($U35="",$U35="Conforme",$U35="No aplica",$U35="Pendiente"),"",$N35&IF($W35="Fuera de rango"," Valor medido: "&TEXT($V35,"0.####")&IF($H35="",""," "&$H35)&IF(AND(ISNUMBER($O35),$V35<$O35),", por debajo del límite inferior de "&TEXT($O35,"0.####")&IF($H35="",""," "&$H35),"")&IF(AND(ISNUMBER($P35),$V35>$P35),", por encima del límite superior de "&TEXT($P35,"0.####")&IF($H35="",""," "&$H35),"")&".","")&IF($Y35="",""," "&$Y35&IF(RIGHT($Y35,1)=".","","."))&" Acción recomendada: "&$M35&IF(RIGHT($M35,1)=".","",".")&IF($J35="Bloqueante"," El equipo no se libera hasta resolver este hallazgo.",IF($J35="Cobrable"," Se incluye en la cotización de repuestos y consumibles."," Se deja registrado como observación.")))
A36: 5.1.1 | B36: 5. Sistema neumático | C36: 5.1 Caudal y presión de muestra | D36: Caudal volumétrico de muestra (SAMPLE) | E36: Caudal de gas de muestra a través de la celda de medida en ANALOG INPUT | F36: Leer el valor SAMPLE en MENU / MAINTENANCE / ANALOG INPUT. Para verificación independiente, medir con flujómetro de burbuja en el puerto SAMPLE INLET con la línea desconectada. | G36: Numérico | H36: L/min | I36: Caudal nominal de muestreo; fuera de 1,0 a 2,0 L/min se activa la alarma FLOW 1 | J36: Bloqueante | K36: Filtro colmatado, fuga en el circuito, o diafragma de bomba desgastado | L36: 4.2.1 ; 5.1.2 ; 5.2.2 ; 5.3.2 | M36: Medir el caudal real con flujómetro de burbuja en SAMPLE INLET y recorrer la rama en ese orden | N36: El caudal de muestra se encuentra fuera del rango de operación especificado por el fabricante. | O36: 1 | P36: 2 | Q36: Sí | R36: No | T36: P-ST-018-MAN OPER APMA 370 V2 | U36: Pendiente | W36: =IF($G36<>"Numérico","",IF($V36="","Sin dato",IF(AND(OR(NOT(ISNUMBER($O36)),$V36>=$O36),OR(NOT(ISNUMBER($P36)),$V36<=$P36)),"Dentro de rango","Fuera de rango"))) | Z36: =IF(OR($U36="",$U36="Conforme",$U36="No aplica",$U36="Pendiente"),"",$N36&IF($W36="Fuera de rango"," Valor medido: "&TEXT($V36,"0.####")&IF($H36="",""," "&$H36)&IF(AND(ISNUMBER($O36),$V36<$O36),", por debajo del límite inferior de "&TEXT($O36,"0.####")&IF($H36="",""," "&$H36),"")&IF(AND(ISNUMBER($P36),$V36>$P36),", por encima del límite superior de "&TEXT($P36,"0.####")&IF($H36="",""," "&$H36),"")&".","")&IF($Y36="",""," "&$Y36&IF(RIGHT($Y36,1)=".","","."))&" Acción recomendada: "&$M36&IF(RIGHT($M36,1)=".","",".")&IF($J36="Bloqueante"," El equipo no se libera hasta resolver este hallazgo.",IF($J36="Cobrable"," Se incluye en la cotización de repuestos y consumibles."," Se deja registrado como observación.")))
A37: 5.1.2 | B37: 5. Sistema neumático | C37: 5.1 Caudal y presión de muestra | D37: Presión de succión de la bomba (PUMP) | E37: Presión de succión generada por la bomba de muestreo en la celda óptica | F37: Leer el valor PUMP en MENU / MAINTENANCE / ANALOG INPUT con el equipo en operación normal y la línea de muestra conectada. Anotar el valor estabilizado. | G37: Numérico | H37: kPa | I37: Lectura en ANALOG INPUT; un valor mayor o igual a 65 kPa activa la alarma PRE1 | J37: Bloqueante | K37: Vacío alto: obstrucción aguas arriba. Vacío bajo: fuga o diafragma roto | L37: 4.2.1 ; 4.3.2 ; 5.2.2 ; 5.3.2 | M37: Desconectar la línea en SAMPLE INLET: si la presión cae, la obstrucción está aguas arriba; si no, está dentro del equipo | N37: La presión de succión de la bomba está fuera del rango de operación, lo que indica una obstrucción o una fuga en el circuito neumático. | O37: 0 | P37: 65 | Q37: Sí | R37: No | T37: P-ST-018-MAN OPER APMA 370 V2 | U37: Pendiente | W37: =IF($G37<>"Numérico","",IF($V37="","Sin dato",IF(AND(OR(NOT(ISNUMBER($O37)),$V37>=$O37),OR(NOT(ISNUMBER($P37)),$V37<=$P37)),"Dentro de rango","Fuera de rango"))) | Z37: =IF(OR($U37="",$U37="Conforme",$U37="No aplica",$U37="Pendiente"),"",$N37&IF($W37="Fuera de rango"," Valor medido: "&TEXT($V37,"0.####")&IF($H37="",""," "&$H37)&IF(AND(ISNUMBER($O37),$V37<$O37),", por debajo del límite inferior de "&TEXT($O37,"0.####")&IF($H37="",""," "&$H37),"")&IF(AND(ISNUMBER($P37),$V37>$P37),", por encima del límite superior de "&TEXT($P37,"0.####")&IF($H37="",""," "&$H37),"")&".","")&IF($Y37="",""," "&$Y37&IF(RIGHT($Y37,1)=".","","."))&" Acción recomendada: "&$M37&IF(RIGHT($M37,1)=".","",".")&IF($J37="Bloqueante"," El equipo no se libera hasta resolver este hallazgo.",IF($J37="Cobrable"," Se incluye en la cotización de repuestos y consumibles."," Se deja registrado como observación.")))
A38: 5.2.1 | B38: 5. Sistema neumático | C38: 5.2 Bomba de muestreo | D38: Vibración y ruido mecánico de la bomba (P-1-B) | E38: Estabilidad del motor y rodamientos de la bomba de muestreo (verificación auditiva y táctil) | F38: Con el equipo en marcha y la cubierta retirada, escuchar la bomba y apoyar la mano sobre su carcasa para detectar vibración anormal, golpeteo metálico u oscilación excesiva. | G38: OK / No OK | I38: Operación continua y estable, sin golpes metálicos ni oscilación mecánica excesiva | J38: Cobrable | K38: Diafragma roto (siseo de aire) o rodamiento y motor dañados (golpeteo metálico) | L38: 5.2.2 ; 5.2.3 ; 5.1.2 | M38: Discriminar por el tipo de ruido y reemplazar diafragmas o la unidad de bomba completa | N38: La bomba de muestreo presenta ruido o vibración anormal, señal de desgaste mecánico interno. | Q38: Sí | R38: Sí | S38: Pump GD-6EH-100 (100～120V) APMA / APNA / APSA / APHA (3014059459) | T38: P-ST-019-MAN MTTO APMA370 V2 | U38: Pendiente | W38: =IF($G38<>"Numérico","",IF($V38="","Sin dato",IF(AND(OR(NOT(ISNUMBER($O38)),$V38>=$O38),OR(NOT(ISNUMBER($P38)),$V38<=$P38)),"Dentro de rango","Fuera de rango"))) | Z38: =IF(OR($U38="",$U38="Conforme",$U38="No aplica",$U38="Pendiente"),"",$N38&IF($W38="Fuera de rango"," Valor medido: "&TEXT($V38,"0.####")&IF($H38="",""," "&$H38)&IF(AND(ISNUMBER($O38),$V38<$O38),", por debajo del límite inferior de "&TEXT($O38,"0.####")&IF($H38="",""," "&$H38),"")&IF(AND(ISNUMBER($P38),$V38>$P38),", por encima del límite superior de "&TEXT($P38,"0.####")&IF($H38="",""," "&$H38),"")&".","")&IF($Y38="",""," "&$Y38&IF(RIGHT($Y38,1)=".","","."))&" Acción recomendada: "&$M38&IF(RIGHT($M38,1)=".","",".")&IF($J38="Bloqueante"," El equipo no se libera hasta resolver este hallazgo.",IF($J38="Cobrable"," Se incluye en la cotización de repuestos y consumibles."," Se deja registrado como observación.")))
A39: 5.2.2 | B39: 5. Sistema neumático | C39: 5.2 Bomba de muestreo | D39: Desgaste de diafragmas de la bomba (P-1-D) | E39: Resequedad, porosidad o fisuras de los dos diafragmas de EPDM de la bomba | F39: Apagar el equipo, desmontar los dos cabezales de la bomba y extraer los diafragmas. Examinarlos contra la luz buscando porosidades, fisuras radiales o endurecimiento del EPDM. | G39: OK / No OK | I39: Diafragmas de EPDM elásticos y sin fisuras, para evitar caídas de vacío y de caudal | J39: Cobrable | K39: Fatiga del EPDM por horas de servicio, o arrastre de condensado hacia el cabezal | L39: 8.1.2 ; 4.3.1 | M39: Reemplazar el juego de diafragmas, reiniciar el horómetro y corregir el origen del condensado | N39: Los diafragmas de la bomba de muestreo presentan desgaste, fisuras o pérdida de elasticidad. | Q39: Sí | R39: Sí | S39: Diaphragm Assy GS, GD series EPDM - APMA / APOA / APHA (3200044033) · Diaphragm Assy GS, Gdseries EPDM (3200602390) | T39: MT_2V0CY0DC_APMA370_250930 | U39: Pendiente | W39: =IF($G39<>"Numérico","",IF($V39="","Sin dato",IF(AND(OR(NOT(ISNUMBER($O39)),$V39>=$O39),OR(NOT(ISNUMBER($P39)),$V39<=$P39)),"Dentro de rango","Fuera de rango"))) | Z39: =IF(OR($U39="",$U39="Conforme",$U39="No aplica",$U39="Pendiente"),"",$N39&IF($W39="Fuera de rango"," Valor medido: "&TEXT($V39,"0.####")&IF($H39="",""," "&$H39)&IF(AND(ISNUMBER($O39),$V39<$O39),", por debajo del límite inferior de "&TEXT($O39,"0.####")&IF($H39="",""," "&$H39),"")&IF(AND(ISNUMBER($P39),$V39>$P39),", por encima del límite superior de "&TEXT($P39,"0.####")&IF($H39="",""," "&$H39),"")&".","")&IF($Y39="",""," "&$Y39&IF(RIGHT($Y39,1)=".","","."))&" Acción recomendada: "&$M39&IF(RIGHT($M39,1)=".","",".")&IF($J39="Bloqueante"," El equipo no se libera hasta resolver este hallazgo.",IF($J39="Cobrable"," Se incluye en la cotización de repuestos y consumibles."," Se deja registrado como observación.")))
A40: 5.2.3 | B40: 5. Sistema neumático | C40: 5.2 Bomba de muestreo | D40: Limpieza de cabezales y válvulas de la bomba | E40: Acumulación de depósitos, residuos o polvo negro en las válvulas planas de teflón | F40: Con los cabezales desmontados, limpiar las cámaras y las charnelas de válvula con paño libre de pelusa y verificar que las válvulas planas asienten sin residuos ni deformación. | G40: OK / No OK | I40: Cámaras del cabezal y charnelas de válvula limpias para garantizar sellado hermético | J40: Cobrable | K40: Depósitos de polvo negro por filtro colmatado o por operación sin filtro | L40: 4.2.1 | M40: Limpiar cámaras y válvulas planas, y corregir la causa aguas arriba | N40: Los cabezales y las válvulas de la bomba presentan acumulación de depósitos que afectan su sellado. | Q40: Sí | R40: Sí | S40: Sin artículo propio; se atiende con el kit de diafragma de la bomba | T40: MT_U403C0JJ_APMA370_21033001 | U40: Pendiente | W40: =IF($G40<>"Numérico","",IF($V40="","Sin dato",IF(AND(OR(NOT(ISNUMBER($O40)),$V40>=$O40),OR(NOT(ISNUMBER($P40)),$V40<=$P40)),"Dentro de rango","Fuera de rango"))) | Z40: =IF(OR($U40="",$U40="Conforme",$U40="No aplica",$U40="Pendiente"),"",$N40&IF($W40="Fuera de rango"," Valor medido: "&TEXT($V40,"0.####")&IF($H40="",""," "&$H40)&IF(AND(ISNUMBER($O40),$V40<$O40),", por debajo del límite inferior de "&TEXT($O40,"0.####")&IF($H40="",""," "&$H40),"")&IF(AND(ISNUMBER($P40),$V40>$P40),", por encima del límite superior de "&TEXT($P40,"0.####")&IF($H40="",""," "&$H40),"")&".","")&IF($Y40="",""," "&$Y40&IF(RIGHT($Y40,1)=".","","."))&" Acción recomendada: "&$M40&IF(RIGHT($M40,1)=".","",".")&IF($J40="Bloqueante"," El equipo no se libera hasta resolver este hallazgo.",IF($J40="Cobrable"," Se incluye en la cotización de repuestos y consumibles."," Se deja registrado como observación.")))
A41: 5.3.1 | B41: 5. Sistema neumático | C41: 5.3 Válvulas y estanqueidad | D41: Conmutación de la válvula de modulación (SV-2) | E41: Conmutación cíclica entre gas de muestra y aire de referencia | F41: Con el equipo en operación y la cubierta retirada, escuchar y palpar la electroválvula SV-2 para confirmar la conmutación cíclica constante. Verificar que no se detenga ni suene irregular. | G41: OK / No OK | I41: Debe conmutar neumáticamente de forma cíclica a una frecuencia constante de 1 Hz | J41: Bloqueante | K41: Bobina quemada, vástago atascado o fuga interna en la válvula | L41: 6.1.1 ; 6.1.2 ; 9.3.1 | M41: Reemplazar la unidad de electroválvula y verificar que la modulación vuelva a ser rítmica | N41: La electroválvula de modulación no conmuta de forma constante, lo que invalida la medición diferencial del analizador. | Q41: Sí | R41: Sí | S41: SV Unit WTB-3K-N1F-3 APMA / APOA (3014034340) | T41: P-ST-019-MAN MTTO APMA370 V2 | U41: Pendiente | W41: =IF($G41<>"Numérico","",IF($V41="","Sin dato",IF(AND(OR(NOT(ISNUMBER($O41)),$V41>=$O41),OR(NOT(ISNUMBER($P41)),$V41<=$P41)),"Dentro de rango","Fuera de rango"))) | Z41: =IF(OR($U41="",$U41="Conforme",$U41="No aplica",$U41="Pendiente"),"",$N41&IF($W41="Fuera de rango"," Valor medido: "&TEXT($V41,"0.####")&IF($H41="",""," "&$H41)&IF(AND(ISNUMBER($O41),$V41<$O41),", por debajo del límite inferior de "&TEXT($O41,"0.####")&IF($H41="",""," "&$H41),"")&IF(AND(ISNUMBER($P41),$V41>$P41),", por encima del límite superior de "&TEXT($P41,"0.####")&IF($H41="",""," "&$H41),"")&".","")&IF($Y41="",""," "&$Y41&IF(RIGHT($Y41,1)=".","","."))&" Acción recomendada: "&$M41&IF(RIGHT($M41,1)=".","",".")&IF($J41="Bloqueante"," El equipo no se libera hasta resolver este hallazgo.",IF($J41="Cobrable"," Se incluye en la cotización de repuestos y consumibles."," Se deja registrado como observación.")))
A42: 5.3.2 | B42: 5. Sistema neumático | C42: 5.3 Válvulas y estanqueidad | D42: Prueba de estanqueidad (Leak Test) | E42: Mantenimiento del vacío sellando el puerto de entrada para detectar fugas | F42: Sellar el puerto SAMPLE INLET con un tapón, dejar la bomba en marcha y observar en ANALOG INPUT que la lectura de presión se estabilice y se mantenga sin fluctuaciones. Restituir la línea al terminar. | G42: OK / No OK | I42: El circuito neumático debe mantener el vacío estable sin fluctuaciones tras aislar la succión | J42: Bloqueante | K42: Fuga en conexiones traseras, portafiltros o mangueras internas | L42: 4.1.1 ; 4.1.2 ; 4.2.3 ; 4.2.2 ; 4.3.2 | M42: Recorrer los puntos de sello en ese orden hasta ubicar la fuga y repetir la prueba | N42: El circuito neumático no mantiene el vacío durante la prueba de estanqueidad: existe una fuga que permite el ingreso de aire ambiente. | Q42: Sí | R42: Sí | T42: GZ0000117746B SM E APXX-370 (Service Manual) | U42: Pendiente | W42: =IF($G42<>"Numérico","",IF($V42="","Sin dato",IF(AND(OR(NOT(ISNUMBER($O42)),$V42>=$O42),OR(NOT(ISNUMBER($P42)),$V42<=$P42)),"Dentro de rango","Fuera de rango"))) | Z42: =IF(OR($U42="",$U42="Conforme",$U42="No aplica",$U42="Pendiente"),"",$N42&IF($W42="Fuera de rango"," Valor medido: "&TEXT($V42,"0.####")&IF($H42="",""," "&$H42)&IF(AND(ISNUMBER($O42),$V42<$O42),", por debajo del límite inferior de "&TEXT($O42,"0.####")&IF($H42="",""," "&$H42),"")&IF(AND(ISNUMBER($P42),$V42>$P42),", por encima del límite superior de "&TEXT($P42,"0.####")&IF($H42="",""," "&$H42),"")&".","")&IF($Y42="",""," "&$Y42&IF(RIGHT($Y42,1)=".","","."))&" Acción recomendada: "&$M42&IF(RIGHT($M42,1)=".","",".")&IF($J42="Bloqueante"," El equipo no se libera hasta resolver este hallazgo.",IF($J42="Cobrable"," Se incluye en la cotización de repuestos y consumibles."," Se deja registrado como observación.")))
A43: 6.1.1 | B43: 6. Banco de medición y óptica | C43: 6.1 Señales del banco NDIR (modulación de flujo cruzado) | D43: Tensión de señal principal (SIGNAL MAIN) | E43: Tensión analógica del canal de medición de CO en ANALOG INPUT | F43: Ir a MENU / MAINTENANCE / ANALOG INPUT, ubicar SIGNAL (MAIN) y anotar el valor con el equipo midiendo aire ambiente estabilizado. | G43: Numérico | H43: mV | I43: Representa la energía infrarroja del detector para el monóxido de carbono | J43: Bloqueante | K43: Suspensión del banco óptico desmontada, humedad en la celda, o lámpara IR degradada | L43: 6.3.1 ; 6.2.2 ; 6.2.1 ; 4.3.1 | M43: Verificar primero que el bloque óptico flote libre; después óptica y lámpara | N43: La señal del canal de medición se encuentra fuera de su nivel de operación o presenta inestabilidad. | O43: 0 | P43: 3000 | Q43: Sí | R43: No | T43: P-ST-018-MAN OPER APMA 370 V2 | U43: Pendiente | W43: =IF($G43<>"Numérico","",IF($V43="","Sin dato",IF(AND(OR(NOT(ISNUMBER($O43)),$V43>=$O43),OR(NOT(ISNUMBER($P43)),$V43<=$P43)),"Dentro de rango","Fuera de rango"))) | Z43: =IF(OR($U43="",$U43="Conforme",$U43="No aplica",$U43="Pendiente"),"",$N43&IF($W43="Fuera de rango"," Valor medido: "&TEXT($V43,"0.####")&IF($H43="",""," "&$H43)&IF(AND(ISNUMBER($O43),$V43<$O43),", por debajo del límite inferior de "&TEXT($O43,"0.####")&IF($H43="",""," "&$H43),"")&IF(AND(ISNUMBER($P43),$V43>$P43),", por encima del límite superior de "&TEXT($P43,"0.####")&IF($H43="",""," "&$H43),"")&".","")&IF($Y43="",""," "&$Y43&IF(RIGHT($Y43,1)=".","","."))&" Acción recomendada: "&$M43&IF(RIGHT($M43,1)=".","",".")&IF($J43="Bloqueante"," El equipo no se libera hasta resolver este hallazgo.",IF($J43="Cobrable"," Se incluye en la cotización de repuestos y consumibles."," Se deja registrado como observación.")))
A44: 6.1.2 | B44: 6. Banco de medición y óptica | C44: 6.1 Señales del banco NDIR (modulación de flujo cruzado) | D44: Tensión de señal de compensación (SIGNAL COMP) | E44: Tensión analógica del canal de referencia para corregir interferentes | F44: En la misma pantalla ANALOG INPUT, ubicar SIGNAL (COMP) y anotar el valor con el equipo estabilizado. Registrar ambos valores en la misma lectura. | G44: Numérico | H44: mV | I44: Empleada por el firmware para corregir el efecto de otros componentes de la muestra | J44: Bloqueante | K44: Contaminación del canal de compensación o desfase de la tarjeta ADC | L44: 6.2.2 ; 6.3.1 ; 7.1.2 | M44: Limpiar la óptica; si persiste, recalibrar fase y atenuador del canal COMP en modo servicio | N44: La señal del canal de compensación se encuentra fuera de su nivel de operación o presenta inestabilidad. | O44: 0 | P44: 3000 | Q44: Sí | R44: No | T44: P-ST-018-MAN OPER APMA 370 V2 | U44: Pendiente | W44: =IF($G44<>"Numérico","",IF($V44="","Sin dato",IF(AND(OR(NOT(ISNUMBER($O44)),$V44>=$O44),OR(NOT(ISNUMBER($P44)),$V44<=$P44)),"Dentro de rango","Fuera de rango"))) | Z44: =IF(OR($U44="",$U44="Conforme",$U44="No aplica",$U44="Pendiente"),"",$N44&IF($W44="Fuera de rango"," Valor medido: "&TEXT($V44,"0.####")&IF($H44="",""," "&$H44)&IF(AND(ISNUMBER($O44),$V44<$O44),", por debajo del límite inferior de "&TEXT($O44,"0.####")&IF($H44="",""," "&$H44),"")&IF(AND(ISNUMBER($P44),$V44>$P44),", por encima del límite superior de "&TEXT($P44,"0.####")&IF($H44="",""," "&$H44),"")&".","")&IF($Y44="",""," "&$Y44&IF(RIGHT($Y44,1)=".","","."))&" Acción recomendada: "&$M44&IF(RIGHT($M44,1)=".","",".")&IF($J44="Bloqueante"," El equipo no se libera hasta resolver este hallazgo.",IF($J44="Cobrable"," Se incluye en la cotización de repuestos y consumibles."," Se deja registrado como observación.")))
A45: 6.2.1 | B45: 6. Banco de medición y óptica | C45: 6.2 Fuente infrarroja y celda óptica | D45: Lámpara infrarroja (IR Lamp) | E45: Desgaste térmico, estabilidad del haz e integridad del filamento de la fuente IR | F45: Con el equipo apagado y frío, retirar la cubierta y examinar la ampolla de la lámpara IR contra la luz buscando ennegrecimiento interno o filamento deformado. No tocar el vidrio con los dedos. | G45: OK / No OK | I45: Filamento activo de forma continua y ampolla libre de manchas severas (indican desgaste) | J45: Bloqueante | K45: Filamento con microfisuras o ampolla ennegrecida por horas de servicio | L45: 6.1.1 ; 3.1.2 | M45: Reemplazar la lámpara IR y recalibrar cero y span | N45: La lámpara infrarroja del banco de medición presenta desgaste, lo que reduce la energía disponible para la medición. | Q45: Sí | R45: Sí | S45: Sin artículo en el catálogo (lámpara IR del APMA) — PENDIENTE DE CREAR EN ZOHO | T45: MT_2V0CY0DC_APMA370_250930 / Service Manual | U45: Pendiente | W45: =IF($G45<>"Numérico","",IF($V45="","Sin dato",IF(AND(OR(NOT(ISNUMBER($O45)),$V45>=$O45),OR(NOT(ISNUMBER($P45)),$V45<=$P45)),"Dentro de rango","Fuera de rango"))) | Z45: =IF(OR($U45="",$U45="Conforme",$U45="No aplica",$U45="Pendiente"),"",$N45&IF($W45="Fuera de rango"," Valor medido: "&TEXT($V45,"0.####")&IF($H45="",""," "&$H45)&IF(AND(ISNUMBER($O45),$V45<$O45),", por debajo del límite inferior de "&TEXT($O45,"0.####")&IF($H45="",""," "&$H45),"")&IF(AND(ISNUMBER($P45),$V45>$P45),", por encima del límite superior de "&TEXT($P45,"0.####")&IF($H45="",""," "&$H45),"")&".","")&IF($Y45="",""," "&$Y45&IF(RIGHT($Y45,1)=".","","."))&" Acción recomendada: "&$M45&IF(RIGHT($M45,1)=".","",".")&IF($J45="Bloqueante"," El equipo no se libera hasta resolver este hallazgo.",IF($J45="Cobrable"," Se incluye en la cotización de repuestos y consumibles."," Se deja registrado como observación.")))
A46: 6.2.2 | B46: 6. Banco de medición y óptica | C46: 6.2 Fuente infrarroja y celda óptica | D46: Limpieza de ventanas ópticas y lentes de la celda | E46: Suciedad, hollín o humedad en las caras translúcidas del tubo de absorción óptica | F46: Con el equipo apagado y frío, acceder a la celda óptica y examinar las ventanas con linterna, buscando películas, hollín o condensación. Limpiar solo con los materiales indicados en el manual de mantenimiento. | G46: OK / No OK | I46: Ventanas limpias y translúcidas para garantizar el paso libre del haz infrarrojo | J46: Cobrable | K46: Depósitos de hollín, o condensación por humedad en la línea de muestra | L46: 4.3.1 ; 6.1.1 | M46: Limpiar las ventanas con material óptico apropiado y eliminar el origen de la humedad | N46: Las ventanas ópticas de la celda de medida presentan depósitos o condensación que atenúan la señal. | Q46: Sí | R46: Sí | T46: MT_2V0CY0DC_APMA370_250930 | U46: Pendiente | W46: =IF($G46<>"Numérico","",IF($V46="","Sin dato",IF(AND(OR(NOT(ISNUMBER($O46)),$V46>=$O46),OR(NOT(ISNUMBER($P46)),$V46<=$P46)),"Dentro de rango","Fuera de rango"))) | Z46: =IF(OR($U46="",$U46="Conforme",$U46="No aplica",$U46="Pendiente"),"",$N46&IF($W46="Fuera de rango"," Valor medido: "&TEXT($V46,"0.####")&IF($H46="",""," "&$H46)&IF(AND(ISNUMBER($O46),$V46<$O46),", por debajo del límite inferior de "&TEXT($O46,"0.####")&IF($H46="",""," "&$H46),"")&IF(AND(ISNUMBER($P46),$V46>$P46),", por encima del límite superior de "&TEXT($P46,"0.####")&IF($H46="",""," "&$H46),"")&".","")&IF($Y46="",""," "&$Y46&IF(RIGHT($Y46,1)=".","","."))&" Acción recomendada: "&$M46&IF(RIGHT($M46,1)=".","",".")&IF($J46="Bloqueante"," El equipo no se libera hasta resolver este hallazgo.",IF($J46="Cobrable"," Se incluye en la cotización de repuestos y consumibles."," Se deja registrado como observación.")))
A47: 6.3.1 | B47: 6. Banco de medición y óptica | C47: 6.3 Suspensión mecánica del banco óptico | D47: Resortes de amortiguación del banco óptico | E47: Presencia y tensión de los 3 resortes que suspenden la celda de medida | F47: Con la cubierta retirada, verificar que los 3 resortes de suspensión del banco óptico estén enganchados en ambos extremos y comparar su longitud libre entre sí para detectar estiramiento. | G47: OK / No OK | I47: Los 3 resortes deben estar enganchados y libres de estiramientos o deformaciones | J47: Cobrable | K47: Resorte desenganchado o estirado tras un transporte o una intervención | L47: 6.1.1 ; 6.3.2 ; 5.2.1 | M47: Reponer los tres resortes y comprobar que la celda no toque el chasis | N47: El sistema de suspensión del banco óptico está incompleto o deformado, lo que transmite la vibración de la bomba a la medición. | Q47: Sí | R47: Sí | S47: Spring //=001= L=64 K=0.59 (3012161550) | T47: MT_191TE0NC_APMA370_241226 / MT_U7D80D0J_APMA370_260116 | U47: Pendiente | W47: =IF($G47<>"Numérico","",IF($V47="","Sin dato",IF(AND(OR(NOT(ISNUMBER($O47)),$V47>=$O47),OR(NOT(ISNUMBER($P47)),$V47<=$P47)),"Dentro de rango","Fuera de rango"))) | Z47: =IF(OR($U47="",$U47="Conforme",$U47="No aplica",$U47="Pendiente"),"",$N47&IF($W47="Fuera de rango"," Valor medido: "&TEXT($V47,"0.####")&IF($H47="",""," "&$H47)&IF(AND(ISNUMBER($O47),$V47<$O47),", por debajo del límite inferior de "&TEXT($O47,"0.####")&IF($H47="",""," "&$H47),"")&IF(AND(ISNUMBER($P47),$V47>$P47),", por encima del límite superior de "&TEXT($P47,"0.####")&IF($H47="",""," "&$H47),"")&".","")&IF($Y47="",""," "&$Y47&IF(RIGHT($Y47,1)=".","","."))&" Acción recomendada: "&$M47&IF(RIGHT($M47,1)=".","",".")&IF($J47="Bloqueante"," El equipo no se libera hasta resolver este hallazgo.",IF($J47="Cobrable"," Se incluye en la cotización de repuestos y consumibles."," Se deja registrado como observación.")))
A48: 6.3.2 | B48: 6. Banco de medición y óptica | C48: 6.3 Suspensión mecánica del banco óptico | D48: Topes amortiguadores (Stoppers) | E48: Estado físico y flexibilidad de los soportes elásticos que limitan la oscilación de la celda | F48: Inspeccionar los topes de goma en sus zócalos, presionarlos con el dedo para comprobar que conservan elasticidad y verificar que no estén desprendidos ni endurecidos. | G48: OK / No OK | I48: Stoppers de goma flexibles en su zócalo, para absorber la vibración inducida por la bomba | J48: Cobrable | K48: Goma endurecida o desprendida de su zócalo | L48: 6.3.1 ; 6.1.1 | M48: Reemplazar los topes y recentrar el bloque óptico | N48: Los topes amortiguadores del banco óptico están endurecidos o desprendidos de su alojamiento. | Q48: Sí | R48: Sí | S48: Stopper, Spring //For AIA-1X0 (3012165197) | T48: MT_191TE0NC_APMA370_241226 / MT_U7D80D0J_APMA370_260116 | U48: Pendiente | W48: =IF($G48<>"Numérico","",IF($V48="","Sin dato",IF(AND(OR(NOT(ISNUMBER($O48)),$V48>=$O48),OR(NOT(ISNUMBER($P48)),$V48<=$P48)),"Dentro de rango","Fuera de rango"))) | Z48: =IF(OR($U48="",$U48="Conforme",$U48="No aplica",$U48="Pendiente"),"",$N48&IF($W48="Fuera de rango"," Valor medido: "&TEXT($V48,"0.####")&IF($H48="",""," "&$H48)&IF(AND(ISNUMBER($O48),$V48<$O48),", por debajo del límite inferior de "&TEXT($O48,"0.####")&IF($H48="",""," "&$H48),"")&IF(AND(ISNUMBER($P48),$V48>$P48),", por encima del límite superior de "&TEXT($P48,"0.####")&IF($H48="",""," "&$H48),"")&".","")&IF($Y48="",""," "&$Y48&IF(RIGHT($Y48,1)=".","","."))&" Acción recomendada: "&$M48&IF(RIGHT($M48,1)=".","",".")&IF($J48="Bloqueante"," El equipo no se libera hasta resolver este hallazgo.",IF($J48="Cobrable"," Se incluye en la cotización de repuestos y consumibles."," Se deja registrado como observación.")))
A49: 6.3.3 | B49: 6. Banco de medición y óptica | C49: 6.3 Suspensión mecánica del banco óptico | D49: Tornillos de tope (Screw Stopper) | E49: Presencia e integridad de los tornillos M5x20 que limitan el desplazamiento elástico | F49: Verificar visualmente la presencia de los tornillos M5x20 en los anclajes del chasis y comprobar con destornillador que estén roscados a su posición de ajuste. | G49: Presente / Ausente | I49: Deben estar presentes y roscados firmemente los tornillos M5x20 en los anclajes del chasis | J49: Cobrable | K49: Tornillo ausente o desajustado por vibración continua | L49: 6.3.4 ; 6.3.1 | M49: Reponer y ajustar los tornillos M5x20 a su posición de tope | N49: Faltan o están desajustados los tornillos de tope de la suspensión del banco óptico. | Q49: Sí | R49: Sí | S49: Screw, Stopper //=002=M5X20 For Spring (3012155051) | T49: MT_U6RF8092_APMA-370_240311 / MT_U7D80D0J_APMA370_260116 | U49: Pendiente | W49: =IF($G49<>"Numérico","",IF($V49="","Sin dato",IF(AND(OR(NOT(ISNUMBER($O49)),$V49>=$O49),OR(NOT(ISNUMBER($P49)),$V49<=$P49)),"Dentro de rango","Fuera de rango"))) | Z49: =IF(OR($U49="",$U49="Conforme",$U49="No aplica",$U49="Pendiente"),"",$N49&IF($W49="Fuera de rango"," Valor medido: "&TEXT($V49,"0.####")&IF($H49="",""," "&$H49)&IF(AND(ISNUMBER($O49),$V49<$O49),", por debajo del límite inferior de "&TEXT($O49,"0.####")&IF($H49="",""," "&$H49),"")&IF(AND(ISNUMBER($P49),$V49>$P49),", por encima del límite superior de "&TEXT($P49,"0.####")&IF($H49="",""," "&$H49),"")&".","")&IF($Y49="",""," "&$Y49&IF(RIGHT($Y49,1)=".","","."))&" Acción recomendada: "&$M49&IF(RIGHT($M49,1)=".","",".")&IF($J49="Bloqueante"," El equipo no se libera hasta resolver este hallazgo.",IF($J49="Cobrable"," Se incluye en la cotización de repuestos y consumibles."," Se deja registrado como observación.")))
A50: 6.3.4 | B50: 6. Banco de medición y óptica | C50: 6.3 Suspensión mecánica del banco óptico | D50: Tuercas hexagonales de fijación | E50: Ajuste y torque de las tuercas M5 en los tornillos de los zócalos amortiguadores | F50: Comprobar con llave del tamaño correspondiente que las tuercas M5 de los zócalos amortiguadores estén ajustadas, sin apretar en exceso para no rigidizar la suspensión. | G50: OK / No OK | I50: Tuercas M5 ajustadas firmemente para evitar desprendimiento del bloque óptico | J50: Cobrable | K50: Tuerca floja por la vibración de la bomba | L50: 6.3.3 | M50: Reapretar sin llegar a rigidizar la suspensión | N50: Las tuercas de fijación de la suspensión del banco óptico se encuentran flojas. | Q50: Sí | R50: Sí | S50: Hexagon Nut // JISB1181(TYP1) M05 (S-ZN3) ROHS (3011000121) | T50: MT_U6RF8092_APMA-370_240311 / MT_U7D80D0J_APMA370_260116 | U50: Pendiente | W50: =IF($G50<>"Numérico","",IF($V50="","Sin dato",IF(AND(OR(NOT(ISNUMBER($O50)),$V50>=$O50),OR(NOT(ISNUMBER($P50)),$V50<=$P50)),"Dentro de rango","Fuera de rango"))) | Z50: =IF(OR($U50="",$U50="Conforme",$U50="No aplica",$U50="Pendiente"),"",$N50&IF($W50="Fuera de rango"," Valor medido: "&TEXT($V50,"0.####")&IF($H50="",""," "&$H50)&IF(AND(ISNUMBER($O50),$V50<$O50),", por debajo del límite inferior de "&TEXT($O50,"0.####")&IF($H50="",""," "&$H50),"")&IF(AND(ISNUMBER($P50),$V50>$P50),", por encima del límite superior de "&TEXT($P50,"0.####")&IF($H50="",""," "&$H50),"")&".","")&IF($Y50="",""," "&$Y50&IF(RIGHT($Y50,1)=".","","."))&" Acción recomendada: "&$M50&IF(RIGHT($M50,1)=".","",".")&IF($J50="Bloqueante"," El equipo no se libera hasta resolver este hallazgo.",IF($J50="Cobrable"," Se incluye en la cotización de repuestos y consumibles."," Se deja registrado como observación.")))
A51: 6.4.1 | B51: 6. Banco de medición y óptica | C51: 6.4 Purificación de la línea de referencia | D51: Eficiencia del relleno catalítico de CO (CAT-1) | E51: Estado y capacidad de conversión del óxido metálico del catalizador interno de CO | F51: Verificar en el horómetro las horas acumuladas del CAT-1 y comprobar en ANALOG INPUT que la temperatura del catalizador sea estable. Una deriva sostenida del cero sugiere agotamiento del relleno. | G51: OK / No OK | I51: El catalizador debe asegurar la oxidación del CO en la línea de referencia y evitar derivas del cero | J51: Bloqueante | K51: Relleno de óxido metálico agotado o humedecido | L51: 8.1.3 ; 9.1.2 ; 3.1.1 ; 6.4.2 | M51: Reemplazar el relleno del CAT-1, reiniciar el horómetro y recalibrar el cero | N51: El catalizador de la línea de referencia ha perdido eficiencia, lo que produce deriva del punto cero. | Q51: Sí | R51: Sí | S51: Catalyzer Tube HP-10D2 APMA / APSA (3014059457) | T51: P-ST-019-MAN MTTO APMA370 V2 | U51: Pendiente | W51: =IF($G51<>"Numérico","",IF($V51="","Sin dato",IF(AND(OR(NOT(ISNUMBER($O51)),$V51>=$O51),OR(NOT(ISNUMBER($P51)),$V51<=$P51)),"Dentro de rango","Fuera de rango"))) | Z51: =IF(OR($U51="",$U51="Conforme",$U51="No aplica",$U51="Pendiente"),"",$N51&IF($W51="Fuera de rango"," Valor medido: "&TEXT($V51,"0.####")&IF($H51="",""," "&$H51)&IF(AND(ISNUMBER($O51),$V51<$O51),", por debajo del límite inferior de "&TEXT($O51,"0.####")&IF($H51="",""," "&$H51),"")&IF(AND(ISNUMBER($P51),$V51>$P51),", por encima del límite superior de "&TEXT($P51,"0.####")&IF($H51="",""," "&$H51),"")&".","")&IF($Y51="",""," "&$Y51&IF(RIGHT($Y51,1)=".","","."))&" Acción recomendada: "&$M51&IF(RIGHT($M51,1)=".","",".")&IF($J51="Bloqueante"," El equipo no se libera hasta resolver este hallazgo.",IF($J51="Cobrable"," Se incluye en la cotización de repuestos y consumibles."," Se deja registrado como observación.")))
A52: 6.4.2 | B52: 6. Banco de medición y óptica | C52: 6.4 Purificación de la línea de referencia | D52: Filtro coalescente interno (DFU9900-05-BK) | E52: Nivel de colmatación o presencia de aceite en el filtro de microfibra Balston de referencia | F52: Con el equipo apagado, desmontar el filtro coalescente en línea y examinar el elemento de microfibra contra la luz, buscando oscurecimiento, colmatación o presencia de aceite. | G52: OK / No OK | I52: Elemento de microfibra limpio, para proteger el catalizador de contaminantes finos | J52: Cobrable | K52: Elemento colmatado o con aceite: restringe la línea de referencia | L52: 6.4.1 ; 3.1.1 | M52: Reemplazar el elemento en línea y recalibrar el cero | N52: El filtro coalescente de la línea de referencia se encuentra colmatado o contaminado. | Q52: Sí | R52: Sí | S52: Filter Element DFU9900-05-BK APMA / APHA (3200043957) | T52: P-ST-019-MAN MTTO APMA370 V2 | U52: Pendiente | W52: =IF($G52<>"Numérico","",IF($V52="","Sin dato",IF(AND(OR(NOT(ISNUMBER($O52)),$V52>=$O52),OR(NOT(ISNUMBER($P52)),$V52<=$P52)),"Dentro de rango","Fuera de rango"))) | Z52: =IF(OR($U52="",$U52="Conforme",$U52="No aplica",$U52="Pendiente"),"",$N52&IF($W52="Fuera de rango"," Valor medido: "&TEXT($V52,"0.####")&IF($H52="",""," "&$H52)&IF(AND(ISNUMBER($O52),$V52<$O52),", por debajo del límite inferior de "&TEXT($O52,"0.####")&IF($H52="",""," "&$H52),"")&IF(AND(ISNUMBER($P52),$V52>$P52),", por encima del límite superior de "&TEXT($P52,"0.####")&IF($H52="",""," "&$H52),"")&".","")&IF($Y52="",""," "&$Y52&IF(RIGHT($Y52,1)=".","","."))&" Acción recomendada: "&$M52&IF(RIGHT($M52,1)=".","",".")&IF($J52="Bloqueante"," El equipo no se libera hasta resolver este hallazgo.",IF($J52="Cobrable"," Se incluye en la cotización de repuestos y consumibles."," Se deja registrado como observación.")))
A53: 7.1.1 | B53: 7. Electrónica y control | C53: 7.1 Tarjetas electrónicas | D53: Estado de la tarjeta principal CPU (AP-CPU-02) | E53: Limpieza, sujeción y ausencia de corrosión en integrados y zócalos de la placa CPU | F53: Con el equipo apagado y desconectado, retirar la cubierta y examinar la tarjeta CPU con linterna, buscando polvo, sulfatación en zócalos, marcas de calor o condensadores abombados. | G53: OK / No OK | I53: Tarjeta lógica limpia, libre de polvo conductivo o rastros de sobrecalentamiento | J53: Bloqueante | K53: Polvo conductivo, sulfatación en zócalos o daño térmico | L53: 7.1.5 ; 9.3.2 ; 7.3.1 | M53: Limpiar y reasentar conectores; si se reemplaza la CPU, inicializarla y recargar la configuración desde CF | N53: La tarjeta principal de control presenta suciedad, sulfatación o indicios de daño térmico. | Q53: Sí | R53: Sí | S53: Printed Board Inst. AP-CPU-02 (AP-370) (3200629662) | T53: 1 - LCD design change AP EN / MT_85HHP0N0_APMA370_20022603 | U53: Pendiente | W53: =IF($G53<>"Numérico","",IF($V53="","Sin dato",IF(AND(OR(NOT(ISNUMBER($O53)),$V53>=$O53),OR(NOT(ISNUMBER($P53)),$V53<=$P53)),"Dentro de rango","Fuera de rango"))) | Z53: =IF(OR($U53="",$U53="Conforme",$U53="No aplica",$U53="Pendiente"),"",$N53&IF($W53="Fuera de rango"," Valor medido: "&TEXT($V53,"0.####")&IF($H53="",""," "&$H53)&IF(AND(ISNUMBER($O53),$V53<$O53),", por debajo del límite inferior de "&TEXT($O53,"0.####")&IF($H53="",""," "&$H53),"")&IF(AND(ISNUMBER($P53),$V53>$P53),", por encima del límite superior de "&TEXT($P53,"0.####")&IF($H53="",""," "&$H53),"")&".","")&IF($Y53="",""," "&$Y53&IF(RIGHT($Y53,1)=".","","."))&" Acción recomendada: "&$M53&IF(RIGHT($M53,1)=".","",".")&IF($J53="Bloqueante"," El equipo no se libera hasta resolver este hallazgo.",IF($J53="Cobrable"," Se incluye en la cotización de repuestos y consumibles."," Se deja registrado como observación.")))
A54: 7.1.2 | B54: 7. Electrónica y control | C54: 7.1 Tarjetas electrónicas | D54: Configuración del DIP switch SW2 en AP-ADC-05 | E54: Configuración física del DIP switch SW2 de modelo en la tarjeta de conversión analógica | F54: Con el equipo apagado, ubicar el DIP switch SW2 en la tarjeta AP-ADC-05 y leer la posición de cada bit. Fotografiar la configuración antes de modificar cualquier posición. | G54: OK / No OK | I54: Para el modelo: BIT0 y BIT1 en ON, BIT2 y BIT3 en OFF | J54: Bloqueante | K54: Configuración de modelo alterada tras cambiar la tarjeta | L54: 7.1.3 ; 6.1.1 | M54: Restituir los bits del modelo y verificar que las lecturas vuelvan a ser coherentes | N54: La configuración de la tarjeta de conversión analógica no corresponde a este modelo de analizador. | Q54: Sí | R54: Sí | S54: AP-ADC-05 (tarjeta; sin artículo en el catálogo) | T54: GZ0000117746B SM E APXX-370 (Service Manual) | U54: Pendiente | W54: =IF($G54<>"Numérico","",IF($V54="","Sin dato",IF(AND(OR(NOT(ISNUMBER($O54)),$V54>=$O54),OR(NOT(ISNUMBER($P54)),$V54<=$P54)),"Dentro de rango","Fuera de rango"))) | Z54: =IF(OR($U54="",$U54="Conforme",$U54="No aplica",$U54="Pendiente"),"",$N54&IF($W54="Fuera de rango"," Valor medido: "&TEXT($V54,"0.####")&IF($H54="",""," "&$H54)&IF(AND(ISNUMBER($O54),$V54<$O54),", por debajo del límite inferior de "&TEXT($O54,"0.####")&IF($H54="",""," "&$H54),"")&IF(AND(ISNUMBER($P54),$V54>$P54),", por encima del límite superior de "&TEXT($P54,"0.####")&IF($H54="",""," "&$H54),"")&".","")&IF($Y54="",""," "&$Y54&IF(RIGHT($Y54,1)=".","","."))&" Acción recomendada: "&$M54&IF(RIGHT($M54,1)=".","",".")&IF($J54="Bloqueante"," El equipo no se libera hasta resolver este hallazgo.",IF($J54="Cobrable"," Se incluye en la cotización de repuestos y consumibles."," Se deja registrado como observación.")))
A55: 7.1.3 | B55: 7. Electrónica y control | C55: 7.1 Tarjetas electrónicas | D55: Indicadores LED de la tarjeta ADC (+24V, +5V) | E55: Iluminación de los LED indicadores de fuentes secundarias en la tarjeta ADC-05 | F55: Con el equipo energizado y la cubierta retirada, observar los LED de +24 V y +5 V en la tarjeta AP-ADC-05 y confirmar que ambos estén encendidos de forma fija. | G55: OK / No OK | I55: Los LED de +24 V y +5 V deben iluminarse en verde fijo | J55: Bloqueante | K55: Falta una de las tensiones de alimentación de la tarjeta | L55: 9.3.1 ; 9.3.2 ; 7.4.1 | M55: Seguir la rama de alimentación hasta la fuente antes de sospechar de la tarjeta | N55: La tarjeta de conversión analógica no recibe alguna de sus tensiones de alimentación. | Q55: Sí | R55: Sí | S55: AP-ADC-05 (tarjeta; sin artículo en el catálogo) | T55: GZ0000117746B SM E APXX-370 (Service Manual) | U55: Pendiente | W55: =IF($G55<>"Numérico","",IF($V55="","Sin dato",IF(AND(OR(NOT(ISNUMBER($O55)),$V55>=$O55),OR(NOT(ISNUMBER($P55)),$V55<=$P55)),"Dentro de rango","Fuera de rango"))) | Z55: =IF(OR($U55="",$U55="Conforme",$U55="No aplica",$U55="Pendiente"),"",$N55&IF($W55="Fuera de rango"," Valor medido: "&TEXT($V55,"0.####")&IF($H55="",""," "&$H55)&IF(AND(ISNUMBER($O55),$V55<$O55),", por debajo del límite inferior de "&TEXT($O55,"0.####")&IF($H55="",""," "&$H55),"")&IF(AND(ISNUMBER($P55),$V55>$P55),", por encima del límite superior de "&TEXT($P55,"0.####")&IF($H55="",""," "&$H55),"")&".","")&IF($Y55="",""," "&$Y55&IF(RIGHT($Y55,1)=".","","."))&" Acción recomendada: "&$M55&IF(RIGHT($M55,1)=".","",".")&IF($J55="Bloqueante"," El equipo no se libera hasta resolver este hallazgo.",IF($J55="Cobrable"," Se incluye en la cotización de repuestos y consumibles."," Se deja registrado como observación.")))
A56: 7.1.4 | B56: 7. Electrónica y control | C56: 7.1 Tarjetas electrónicas | D56: Estado físico de la tarjeta de relés (AP-RPL-02A) | E56: Sobrecalentamientos o quemaduras en relés y transistores de control de la placa RPL | F56: Con el equipo apagado, examinar la tarjeta de relés buscando decoloración por calor, relés con carcasa deformada, soldaduras agrietadas o marcas de arco en las pistas. | G56: OK / No OK | I56: Componentes sin daños por sobrecarga; soldaduras intactas sin marcas de cortocircuito | J56: Bloqueante | K56: Relé o transistor quemado por sobrecarga en una salida de contacto | L56: 7.1.5 ; 7.1.6 | M56: Reemplazar la tarjeta RPL y revisar la carga conectada a los contactos de alarma | N56: La tarjeta de relés presenta componentes con daño térmico o marcas de sobrecarga. | Q56: Sí | R56: Sí | S56: AP-RPL-02 / AP-RPL-02A (tarjeta; sin artículo en el catálogo) | T56: MT_191TE0NC_APMA370_241226 / Service Manual | U56: Pendiente | W56: =IF($G56<>"Numérico","",IF($V56="","Sin dato",IF(AND(OR(NOT(ISNUMBER($O56)),$V56>=$O56),OR(NOT(ISNUMBER($P56)),$V56<=$P56)),"Dentro de rango","Fuera de rango"))) | Z56: =IF(OR($U56="",$U56="Conforme",$U56="No aplica",$U56="Pendiente"),"",$N56&IF($W56="Fuera de rango"," Valor medido: "&TEXT($V56,"0.####")&IF($H56="",""," "&$H56)&IF(AND(ISNUMBER($O56),$V56<$O56),", por debajo del límite inferior de "&TEXT($O56,"0.####")&IF($H56="",""," "&$H56),"")&IF(AND(ISNUMBER($P56),$V56>$P56),", por encima del límite superior de "&TEXT($P56,"0.####")&IF($H56="",""," "&$H56),"")&".","")&IF($Y56="",""," "&$Y56&IF(RIGHT($Y56,1)=".","","."))&" Acción recomendada: "&$M56&IF(RIGHT($M56,1)=".","",".")&IF($J56="Bloqueante"," El equipo no se libera hasta resolver este hallazgo.",IF($J56="Cobrable"," Se incluye en la cotización de repuestos y consumibles."," Se deja registrado como observación.")))
A57: 7.1.5 | B57: 7. Electrónica y control | C57: 7.1 Tarjetas electrónicas | D57: LED de comunicación ST0 y ST1 en tarjeta RPL | E57: Frecuencia de parpadeo de los indicadores LED de diagnóstico de la tarjeta de relés | F57: Con el equipo energizado, observar durante al menos 30 segundos los LED ST0 y ST1 de la tarjeta RPL y registrar si parpadean, quedan fijos o apagados. | G57: OK / No OK | I57: ST1 debe parpadear (H8 activo) y ST0 titilar rápido (I2C activo); luz fija o apagada indica falla | J57: Bloqueante | K57: Cinta plana I2C floja, o microprocesador H8 bloqueado | L57: 7.3.1 ; 7.1.1 ; 7.1.4 | M57: Reasentar la cinta I2C; si ST1 sigue fijo, ejecutar el memory scan y considerar cambiar la RPL | N57: La comunicación interna entre la tarjeta de control y la tarjeta de relés se encuentra interrumpida. | Q57: Sí | R57: Sí | S57: AP-RPL-02 / AP-RPL-02A (tarjeta; sin artículo en el catálogo) | T57: GZ0000117746B SM E APXX-370 (Service Manual) | U57: Pendiente | W57: =IF($G57<>"Numérico","",IF($V57="","Sin dato",IF(AND(OR(NOT(ISNUMBER($O57)),$V57>=$O57),OR(NOT(ISNUMBER($P57)),$V57<=$P57)),"Dentro de rango","Fuera de rango"))) | Z57: =IF(OR($U57="",$U57="Conforme",$U57="No aplica",$U57="Pendiente"),"",$N57&IF($W57="Fuera de rango"," Valor medido: "&TEXT($V57,"0.####")&IF($H57="",""," "&$H57)&IF(AND(ISNUMBER($O57),$V57<$O57),", por debajo del límite inferior de "&TEXT($O57,"0.####")&IF($H57="",""," "&$H57),"")&IF(AND(ISNUMBER($P57),$V57>$P57),", por encima del límite superior de "&TEXT($P57,"0.####")&IF($H57="",""," "&$H57),"")&".","")&IF($Y57="",""," "&$Y57&IF(RIGHT($Y57,1)=".","","."))&" Acción recomendada: "&$M57&IF(RIGHT($M57,1)=".","",".")&IF($J57="Bloqueante"," El equipo no se libera hasta resolver este hallazgo.",IF($J57="Cobrable"," Se incluye en la cotización de repuestos y consumibles."," Se deja registrado como observación.")))
A58: 7.1.6 | B58: 7. Electrónica y control | C58: 7.1 Tarjetas electrónicas | D58: LED de tensión +5 V en tarjeta RPL | E58: LED indicador de alimentación interna de 5 V en la tarjeta de relés periféricos | F58: Con el equipo energizado, observar el LED de +5 V de la tarjeta RPL y confirmar que esté encendido de forma continua. | G58: OK / No OK | I58: Debe permanecer encendido continuo en verde, indicando que el regulador lógico local opera | J58: Bloqueante | K58: Regulador local sin alimentación o dañado | L58: 9.3.2 ; 7.4.1 | M58: Verificar la llegada de 5 V a la tarjeta antes de reemplazarla | N58: La tarjeta de relés no recibe su tensión de alimentación lógica. | Q58: Sí | R58: Sí | S58: AP-RPL-02 / AP-RPL-02A (tarjeta; sin artículo en el catálogo) | T58: GZ0000117746B SM E APXX-370 (Service Manual) | U58: Pendiente | W58: =IF($G58<>"Numérico","",IF($V58="","Sin dato",IF(AND(OR(NOT(ISNUMBER($O58)),$V58>=$O58),OR(NOT(ISNUMBER($P58)),$V58<=$P58)),"Dentro de rango","Fuera de rango"))) | Z58: =IF(OR($U58="",$U58="Conforme",$U58="No aplica",$U58="Pendiente"),"",$N58&IF($W58="Fuera de rango"," Valor medido: "&TEXT($V58,"0.####")&IF($H58="",""," "&$H58)&IF(AND(ISNUMBER($O58),$V58<$O58),", por debajo del límite inferior de "&TEXT($O58,"0.####")&IF($H58="",""," "&$H58),"")&IF(AND(ISNUMBER($P58),$V58>$P58),", por encima del límite superior de "&TEXT($P58,"0.####")&IF($H58="",""," "&$H58),"")&".","")&IF($Y58="",""," "&$Y58&IF(RIGHT($Y58,1)=".","","."))&" Acción recomendada: "&$M58&IF(RIGHT($M58,1)=".","",".")&IF($J58="Bloqueante"," El equipo no se libera hasta resolver este hallazgo.",IF($J58="Cobrable"," Se incluye en la cotización de repuestos y consumibles."," Se deja registrado como observación.")))
A59: 7.1.7 | B59: 7. Electrónica y control | C59: 7.1 Tarjetas electrónicas | D59: Switch de selección de alarma general (SW1/SW2 en RPL) | E59: Ajuste de interruptores de asociación de alarma que definen el contacto general | F59: Con el equipo apagado, leer la posición de los microinterruptores de alarma en la tarjeta RPL y contrastarla con el esquema de alarmas acordado con la estación. Fotografiar la configuración. | G59: OK / No OK | I59: Posiciones de los microinterruptores en concordancia con el esquema de alarmas de la estación | J59: Alerta | K59: Configuración de alarma distinta a la acordada con la estación | L59: 7.1.4 | M59: Ajustar los microinterruptores al esquema de telemetría y documentarlo | N59: La configuración de las alarmas de salida no corresponde al esquema acordado con la estación. | Q59: Sí | R59: Sí | S59: AP-RPL-02 / AP-RPL-02A (tarjeta; sin artículo en el catálogo) | T59: GZ0000117746B SM E APXX-370 (Service Manual) | U59: Pendiente | W59: =IF($G59<>"Numérico","",IF($V59="","Sin dato",IF(AND(OR(NOT(ISNUMBER($O59)),$V59>=$O59),OR(NOT(ISNUMBER($P59)),$V59<=$P59)),"Dentro de rango","Fuera de rango"))) | Z59: =IF(OR($U59="",$U59="Conforme",$U59="No aplica",$U59="Pendiente"),"",$N59&IF($W59="Fuera de rango"," Valor medido: "&TEXT($V59,"0.####")&IF($H59="",""," "&$H59)&IF(AND(ISNUMBER($O59),$V59<$O59),", por debajo del límite inferior de "&TEXT($O59,"0.####")&IF($H59="",""," "&$H59),"")&IF(AND(ISNUMBER($P59),$V59>$P59),", por encima del límite superior de "&TEXT($P59,"0.####")&IF($H59="",""," "&$H59),"")&".","")&IF($Y59="",""," "&$Y59&IF(RIGHT($Y59,1)=".","","."))&" Acción recomendada: "&$M59&IF(RIGHT($M59,1)=".","",".")&IF($J59="Bloqueante"," El equipo no se libera hasta resolver este hallazgo.",IF($J59="Cobrable"," Se incluye en la cotización de repuestos y consumibles."," Se deja registrado como observación.")))
A60: 7.2.1 | B60: 7. Electrónica y control | C60: 7.2 Respaldo de reloj y memoria | D60: Batería de litio del reloj de tiempo real (BATT1 / CR2032) | E60: Voltaje DC de la pila de litio de respaldo de hora y secuencia de autocalibración | F60: Con el equipo apagado, extraer la pila del portapilas de la CPU y medir su tensión en vacío con multímetro. Anotar el valor y reinstalarla o reemplazarla según corresponda. | G60: Numérico | H60: V | I60: Un voltaje inferior a 2,5 V activa la alarma BATT | J60: Cobrable | K60: Pila al final de su vida útil (unos 3 años de servicio) | L60: Nodo terminal — actuar directamente | M60: Reemplazar la CR2032 y reprogramar fecha, hora y secuencia AIC | N60: La batería de respaldo del reloj está agotada: el analizador pierde fecha, hora y programación al desconectarse. | O60: 2.5 | P60: 3.3 | Q60: Sí | R60: No | S60: Batería CR2032 para Horiba AP Series (3200043671) | T60: P-ST-019-MAN MTTO APMA370 V2 | U60: Pendiente | W60: =IF($G60<>"Numérico","",IF($V60="","Sin dato",IF(AND(OR(NOT(ISNUMBER($O60)),$V60>=$O60),OR(NOT(ISNUMBER($P60)),$V60<=$P60)),"Dentro de rango","Fuera de rango"))) | Z60: =IF(OR($U60="",$U60="Conforme",$U60="No aplica",$U60="Pendiente"),"",$N60&IF($W60="Fuera de rango"," Valor medido: "&TEXT($V60,"0.####")&IF($H60="",""," "&$H60)&IF(AND(ISNUMBER($O60),$V60<$O60),", por debajo del límite inferior de "&TEXT($O60,"0.####")&IF($H60="",""," "&$H60),"")&IF(AND(ISNUMBER($P60),$V60>$P60),", por encima del límite superior de "&TEXT($P60,"0.####")&IF($H60="",""," "&$H60),"")&".","")&IF($Y60="",""," "&$Y60&IF(RIGHT($Y60,1)=".","","."))&" Acción recomendada: "&$M60&IF(RIGHT($M60,1)=".","",".")&IF($J60="Bloqueante"," El equipo no se libera hasta resolver este hallazgo.",IF($J60="Cobrable"," Se incluye en la cotización de repuestos y consumibles."," Se deja registrado como observación.")))
A61: 7.3.1 | B61: 7. Electrónica y control | C61: 7.3 Display y cableado interno | D61: Cintas flex de la pantalla táctil LCD (Tape Wire) | E61: Arrugas, microfisuras o sulfatación en las terminales de los dos buses flex planos | F61: Con el equipo apagado, examinar las dos cintas flex del LCD en toda su longitud y en sus terminales, buscando dobleces marcados, microfisuras o sulfatación en los contactos. | G61: OK / No OK | I61: Cables flexibles intactos y firmemente enchufados a la placa CPU, para evitar fallos del panel | J61: Cobrable | K61: Cinta agrietada o terminal sulfatado por humedad del shelter | L61: 1.1.3 ; 7.3.2 | M61: Reemplazar la cinta flex y corregir la humedad del shelter | N61: Las cintas de datos de la pantalla presentan deterioro o falso contacto. | Q61: Sí | R61: Sí | S61: Tape Wire (3010040355) | T61: AP-370 LCD replacement / MT_191TE0NC_APMA370_241226 | U61: Pendiente | W61: =IF($G61<>"Numérico","",IF($V61="","Sin dato",IF(AND(OR(NOT(ISNUMBER($O61)),$V61>=$O61),OR(NOT(ISNUMBER($P61)),$V61<=$P61)),"Dentro de rango","Fuera de rango"))) | Z61: =IF(OR($U61="",$U61="Conforme",$U61="No aplica",$U61="Pendiente"),"",$N61&IF($W61="Fuera de rango"," Valor medido: "&TEXT($V61,"0.####")&IF($H61="",""," "&$H61)&IF(AND(ISNUMBER($O61),$V61<$O61),", por debajo del límite inferior de "&TEXT($O61,"0.####")&IF($H61="",""," "&$H61),"")&IF(AND(ISNUMBER($P61),$V61>$P61),", por encima del límite superior de "&TEXT($P61,"0.####")&IF($H61="",""," "&$H61),"")&".","")&IF($Y61="",""," "&$Y61&IF(RIGHT($Y61,1)=".","","."))&" Acción recomendada: "&$M61&IF(RIGHT($M61,1)=".","",".")&IF($J61="Bloqueante"," El equipo no se libera hasta resolver este hallazgo.",IF($J61="Cobrable"," Se incluye en la cotización de repuestos y consumibles."," Se deja registrado como observación.")))
A62: 7.3.2 | B62: 7. Electrónica y control | C62: 7.3 Display y cableado interno | D62: Respuesta táctil de la pantalla (Touch Panel) | E62: Sensibilidad del panel resistivo al presionar y seleccionar opciones del display | F62: Recorrer los menús de la pantalla presionando botones en las cuatro esquinas y en el centro, y verificar que la selección responda en el punto exacto donde se presiona. | G62: OK / No OK | I62: Desplazamiento ágil y preciso entre menús, sin derivas táctiles ni zonas inoperantes | J62: Cobrable | K62: Delaminación del panel resistivo por humedad, o desgaste por uso con objetos punzantes | L62: 7.3.1 ; 10.4.2 | M62: Recalibrar el panel; si no responde, reemplazarlo y controlar la humedad de la cabina | N62: El panel táctil no responde con precisión al tacto o presenta zonas inoperantes. | Q62: Sí | R62: Sí | S62: Touch Panel (TP-AP370) | T62: MT_1JS71VM3_APMA370_21061101 / MT_85HHP0N0_APMA370_220822 | U62: Pendiente | W62: =IF($G62<>"Numérico","",IF($V62="","Sin dato",IF(AND(OR(NOT(ISNUMBER($O62)),$V62>=$O62),OR(NOT(ISNUMBER($P62)),$V62<=$P62)),"Dentro de rango","Fuera de rango"))) | Z62: =IF(OR($U62="",$U62="Conforme",$U62="No aplica",$U62="Pendiente"),"",$N62&IF($W62="Fuera de rango"," Valor medido: "&TEXT($V62,"0.####")&IF($H62="",""," "&$H62)&IF(AND(ISNUMBER($O62),$V62<$O62),", por debajo del límite inferior de "&TEXT($O62,"0.####")&IF($H62="",""," "&$H62),"")&IF(AND(ISNUMBER($P62),$V62>$P62),", por encima del límite superior de "&TEXT($P62,"0.####")&IF($H62="",""," "&$H62),"")&".","")&IF($Y62="",""," "&$Y62&IF(RIGHT($Y62,1)=".","","."))&" Acción recomendada: "&$M62&IF(RIGHT($M62,1)=".","",".")&IF($J62="Bloqueante"," El equipo no se libera hasta resolver este hallazgo.",IF($J62="Cobrable"," Se incluye en la cotización de repuestos y consumibles."," Se deja registrado como observación.")))
A63: 7.4.1 | B63: 7. Electrónica y control | C63: 7.4 Alimentación eléctrica | D63: Tensiones secundarias de la fuente de poder principal | E63: Estabilidad de voltajes e integridad física de condensadores en la fuente principal | F63: Con el equipo apagado, inspeccionar la fuente buscando condensadores abombados o con fuga. Con el equipo energizado, verificar en ANALOG INPUT la estabilidad de los rieles de 24 V y 5 V. | G63: OK / No OK | I63: Condensadores sin abombamientos y voltajes secundarios libres de rizado eléctrico | J63: Bloqueante | K63: Condensadores degradados o fuente al final de su vida útil | L63: 9.3.1 ; 9.3.2 ; 10.5.1 | M63: Reemplazar la fuente y verificar la calidad de la red que alimenta el equipo | N63: La fuente de poder principal presenta deterioro o no entrega sus tensiones dentro de tolerancia. | Q63: Sí | R63: Sí | S63: Power Supply Assy (3200637752) · Power Supply Assy (3200637753) | T63: MT_191TE0NC_APMA370_241226 | U63: Pendiente | W63: =IF($G63<>"Numérico","",IF($V63="","Sin dato",IF(AND(OR(NOT(ISNUMBER($O63)),$V63>=$O63),OR(NOT(ISNUMBER($P63)),$V63<=$P63)),"Dentro de rango","Fuera de rango"))) | Z63: =IF(OR($U63="",$U63="Conforme",$U63="No aplica",$U63="Pendiente"),"",$N63&IF($W63="Fuera de rango"," Valor medido: "&TEXT($V63,"0.####")&IF($H63="",""," "&$H63)&IF(AND(ISNUMBER($O63),$V63<$O63),", por debajo del límite inferior de "&TEXT($O63,"0.####")&IF($H63="",""," "&$H63),"")&IF(AND(ISNUMBER($P63),$V63>$P63),", por encima del límite superior de "&TEXT($P63,"0.####")&IF($H63="",""," "&$H63),"")&".","")&IF($Y63="",""," "&$Y63&IF(RIGHT($Y63,1)=".","","."))&" Acción recomendada: "&$M63&IF(RIGHT($M63,1)=".","",".")&IF($J63="Bloqueante"," El equipo no se libera hasta resolver este hallazgo.",IF($J63="Cobrable"," Se incluye en la cotización de repuestos y consumibles."," Se deja registrado como observación.")))
A64: 7.4.2 | B64: 7. Electrónica y control | C64: 7.4 Alimentación eléctrica | D64: Transformador de la bomba de muestreo | E64: Tensión AC de salida en el secundario del transformador de aislamiento de la bomba | F64: Con el equipo energizado y las debidas precauciones de alto voltaje, medir con multímetro en modo VAC la tensión en el secundario del transformador de la bomba. | G64: Numérico | H64: V | I64: Transformador de aislamiento de 42 VA; debe suministrar tensión estable a la bobina del motor | J64: Bloqueante | K64: Devanado abierto, o transformador no original instalado | L64: 5.2.1 ; 10.5.1 | M64: Reponer el transformador original de 42 VA | N64: El transformador de alimentación de la bomba no entrega la tensión especificada. | O64: 100 | P64: 120 | Q64: Sí | R64: No | S64: Power Transformer APXX-360/370 PUMP:42VA (3200488656) | T64: MT_191TE0NC_APMA370_241226 | U64: Pendiente | W64: =IF($G64<>"Numérico","",IF($V64="","Sin dato",IF(AND(OR(NOT(ISNUMBER($O64)),$V64>=$O64),OR(NOT(ISNUMBER($P64)),$V64<=$P64)),"Dentro de rango","Fuera de rango"))) | Z64: =IF(OR($U64="",$U64="Conforme",$U64="No aplica",$U64="Pendiente"),"",$N64&IF($W64="Fuera de rango"," Valor medido: "&TEXT($V64,"0.####")&IF($H64="",""," "&$H64)&IF(AND(ISNUMBER($O64),$V64<$O64),", por debajo del límite inferior de "&TEXT($O64,"0.####")&IF($H64="",""," "&$H64),"")&IF(AND(ISNUMBER($P64),$V64>$P64),", por encima del límite superior de "&TEXT($P64,"0.####")&IF($H64="",""," "&$H64),"")&".","")&IF($Y64="",""," "&$Y64&IF(RIGHT($Y64,1)=".","","."))&" Acción recomendada: "&$M64&IF(RIGHT($M64,1)=".","",".")&IF($J64="Bloqueante"," El equipo no se libera hasta resolver este hallazgo.",IF($J64="Cobrable"," Se incluye en la cotización de repuestos y consumibles."," Se deja registrado como observación.")))
A65: 7.5.1 | B65: 7. Electrónica y control | C65: 7.5 Comunicaciones | D65: Conector del cable serial RS-232C | E65: Soldaduras, continuidad y asignación de pines del conector trasero DB9 de datos | F65: Con el equipo apagado, inspeccionar el conector DB9 trasero buscando pines doblados o soldaduras frías, y verificar la continuidad del cable con multímetro según el esquema de pines. | G65: OK / No OK | I65: Pines 2 y 3 cruzados, pin 5 a tierra y pines 7-8 puenteados para habilitar el enlace serial | J65: Alerta | K65: Cable recto en lugar de cruzado, o pines sin el puente 7-8 | L65: 7.5.2 ; 2.2.1 | M65: Usar cable cruzado con puente local 7-8 y verificar la descarga de datos | N65: El puerto de comunicación serial presenta daño, o el cableado no corresponde al esquema requerido para la descarga de datos. | Q65: Sí | R65: Sí | S65: Cable assembly RS-232C (3200216747) | T65: I.X.X.X-X Instructivo Descarga de Datos Horiba AP | U65: Pendiente | W65: =IF($G65<>"Numérico","",IF($V65="","Sin dato",IF(AND(OR(NOT(ISNUMBER($O65)),$V65>=$O65),OR(NOT(ISNUMBER($P65)),$V65<=$P65)),"Dentro de rango","Fuera de rango"))) | Z65: =IF(OR($U65="",$U65="Conforme",$U65="No aplica",$U65="Pendiente"),"",$N65&IF($W65="Fuera de rango"," Valor medido: "&TEXT($V65,"0.####")&IF($H65="",""," "&$H65)&IF(AND(ISNUMBER($O65),$V65<$O65),", por debajo del límite inferior de "&TEXT($O65,"0.####")&IF($H65="",""," "&$H65),"")&IF(AND(ISNUMBER($P65),$V65>$P65),", por encima del límite superior de "&TEXT($P65,"0.####")&IF($H65="",""," "&$H65),"")&".","")&IF($Y65="",""," "&$Y65&IF(RIGHT($Y65,1)=".","","."))&" Acción recomendada: "&$M65&IF(RIGHT($M65,1)=".","",".")&IF($J65="Bloqueante"," El equipo no se libera hasta resolver este hallazgo.",IF($J65="Cobrable"," Se incluye en la cotización de repuestos y consumibles."," Se deja registrado como observación.")))
A66: 7.5.2 | B66: 7. Electrónica y control | C66: 7.5 Comunicaciones | D66: Tarjeta serial opcional (AP-SIO-04) | E66: Presencia e integración de la placa serial dedicada en el conector CN2 | F66: Retirar la placa ciega trasera y verificar visualmente si la tarjeta AP-SIO-04 está instalada y conectada al conector CN2 de la CPU mediante su cable. | G66: Presente / Ausente | I66: Tarjeta SIO acoplada firmemente en el conector CN2 de la CPU si se implementa descarga remota | J66: Alerta | K66: Tarjeta ausente o cable CN2 desconectado | L66: 7.5.1 | M66: Instalar o reasentar la tarjeta SIO y verificar el enlace a 19200 bps | N66: La tarjeta de comunicación serial no está instalada o no está correctamente conectada. | Q66: Sí | R66: Sí | S66: RS-232C (For Horiba AP Series) (3014036951) | T66: Procedimiento Integración Tarjeta RS232 | U66: Pendiente | W66: =IF($G66<>"Numérico","",IF($V66="","Sin dato",IF(AND(OR(NOT(ISNUMBER($O66)),$V66>=$O66),OR(NOT(ISNUMBER($P66)),$V66<=$P66)),"Dentro de rango","Fuera de rango"))) | Z66: =IF(OR($U66="",$U66="Conforme",$U66="No aplica",$U66="Pendiente"),"",$N66&IF($W66="Fuera de rango"," Valor medido: "&TEXT($V66,"0.####")&IF($H66="",""," "&$H66)&IF(AND(ISNUMBER($O66),$V66<$O66),", por debajo del límite inferior de "&TEXT($O66,"0.####")&IF($H66="",""," "&$H66),"")&IF(AND(ISNUMBER($P66),$V66>$P66),", por encima del límite superior de "&TEXT($P66,"0.####")&IF($H66="",""," "&$H66),"")&".","")&IF($Y66="",""," "&$Y66&IF(RIGHT($Y66,1)=".","","."))&" Acción recomendada: "&$M66&IF(RIGHT($M66,1)=".","",".")&IF($J66="Bloqueante"," El equipo no se libera hasta resolver este hallazgo.",IF($J66="Cobrable"," Se incluye en la cotización de repuestos y consumibles."," Se deja registrado como observación.")))
A67: 8.1.1 | B67: 8. Filtros y consumibles | C67: 8.1 Horómetros de consumibles | D67: Horas acumuladas del filtro de partículas PA-10L | E67: Horas de uso acumuladas del filtro frontal en la pantalla HOUR METER | F67: Ir a MENU / MAINTENANCE / HOUR METER y leer las horas acumuladas del filtro de partículas. Reiniciar el contador únicamente si se reemplaza el elemento. | G67: Numérico | H67: horas | I67: Cambio preventivo recomendado cada 2 semanas de uso (336 h) | J67: Cobrable | K67: Horómetro por encima del intervalo de dos semanas | L67: 4.2.1 | M67: Reemplazar el elemento y reiniciar el contador | N67: El filtro de partículas superó el intervalo de reemplazo recomendado por el fabricante. | O67: 0 | P67: 336 | Q67: Sí | R67: No | S67: Filter Element PA-10L diámetro 54*0.5t (24pc/set) (3200043947; alt. 3200043947-1PC) | T67: P-ST-019-MAN MTTO APMA370 V2 | U67: Pendiente | W67: =IF($G67<>"Numérico","",IF($V67="","Sin dato",IF(AND(OR(NOT(ISNUMBER($O67)),$V67>=$O67),OR(NOT(ISNUMBER($P67)),$V67<=$P67)),"Dentro de rango","Fuera de rango"))) | Z67: =IF(OR($U67="",$U67="Conforme",$U67="No aplica",$U67="Pendiente"),"",$N67&IF($W67="Fuera de rango"," Valor medido: "&TEXT($V67,"0.####")&IF($H67="",""," "&$H67)&IF(AND(ISNUMBER($O67),$V67<$O67),", por debajo del límite inferior de "&TEXT($O67,"0.####")&IF($H67="",""," "&$H67),"")&IF(AND(ISNUMBER($P67),$V67>$P67),", por encima del límite superior de "&TEXT($P67,"0.####")&IF($H67="",""," "&$H67),"")&".","")&IF($Y67="",""," "&$Y67&IF(RIGHT($Y67,1)=".","","."))&" Acción recomendada: "&$M67&IF(RIGHT($M67,1)=".","",".")&IF($J67="Bloqueante"," El equipo no se libera hasta resolver este hallazgo.",IF($J67="Cobrable"," Se incluye en la cotización de repuestos y consumibles."," Se deja registrado como observación.")))
A68: 8.1.2 | B68: 8. Filtros y consumibles | C68: 8.1 Horómetros de consumibles | D68: Horas acumuladas de diafragmas de la bomba (P-1-D) | E68: Horas acumuladas de operación de los diafragmas en la pantalla HOUR METER | F68: En la pantalla HOUR METER, leer las horas acumuladas del diafragma de bomba (P-1-D). Reiniciar el contador únicamente si se reemplazan los diafragmas. | G68: Numérico | H68: horas | I68: Contador para planificar el reemplazo anual de las membranas elásticas de la bomba | J68: Cobrable | K68: Horómetro por encima del intervalo anual | L68: 5.2.2 | M68: Reemplazar los diafragmas y reiniciar el contador | N68: Los diafragmas de la bomba superaron el intervalo de reemplazo recomendado por el fabricante. | O68: 0 | P68: 8760 | Q68: Sí | R68: No | S68: Diaphragm Assy GS, GD series EPDM - APMA / APOA / APHA (3200044033) | T68: P-ST-019-MAN MTTO APMA370 V2 | U68: Pendiente | W68: =IF($G68<>"Numérico","",IF($V68="","Sin dato",IF(AND(OR(NOT(ISNUMBER($O68)),$V68>=$O68),OR(NOT(ISNUMBER($P68)),$V68<=$P68)),"Dentro de rango","Fuera de rango"))) | Z68: =IF(OR($U68="",$U68="Conforme",$U68="No aplica",$U68="Pendiente"),"",$N68&IF($W68="Fuera de rango"," Valor medido: "&TEXT($V68,"0.####")&IF($H68="",""," "&$H68)&IF(AND(ISNUMBER($O68),$V68<$O68),", por debajo del límite inferior de "&TEXT($O68,"0.####")&IF($H68="",""," "&$H68),"")&IF(AND(ISNUMBER($P68),$V68>$P68),", por encima del límite superior de "&TEXT($P68,"0.####")&IF($H68="",""," "&$H68),"")&".","")&IF($Y68="",""," "&$Y68&IF(RIGHT($Y68,1)=".","","."))&" Acción recomendada: "&$M68&IF(RIGHT($M68,1)=".","",".")&IF($J68="Bloqueante"," El equipo no se libera hasta resolver este hallazgo.",IF($J68="Cobrable"," Se incluye en la cotización de repuestos y consumibles."," Se deja registrado como observación.")))
A69: 8.1.3 | B69: 8. Filtros y consumibles | C69: 8.1 Horómetros de consumibles | D69: Horas acumuladas del catalizador de CO (CAT-1) | E69: Horas de operación acumuladas del catalizador oxidante de CO en HOUR METER | F69: En la pantalla HOUR METER, leer las horas acumuladas del catalizador de CO (CAT-1). Reiniciar el contador únicamente si se reemplaza el relleno. | G69: Numérico | H69: horas | I69: Contador para programar el reemplazo del relleno del catalizador cada 2 años | J69: Cobrable | K69: Horómetro por encima del intervalo de dos años | L69: 6.4.1 | M69: Reemplazar el relleno y reiniciar el contador | N69: El catalizador de la línea de referencia superó el intervalo de reemplazo recomendado por el fabricante. | O69: 0 | P69: 17520 | Q69: Sí | R69: No | S69: Catalyzer Tube HP-10D2 APMA / APSA (3014059457) | T69: P-ST-019-MAN MTTO APMA370 V2 | U69: Pendiente | W69: =IF($G69<>"Numérico","",IF($V69="","Sin dato",IF(AND(OR(NOT(ISNUMBER($O69)),$V69>=$O69),OR(NOT(ISNUMBER($P69)),$V69<=$P69)),"Dentro de rango","Fuera de rango"))) | Z69: =IF(OR($U69="",$U69="Conforme",$U69="No aplica",$U69="Pendiente"),"",$N69&IF($W69="Fuera de rango"," Valor medido: "&TEXT($V69,"0.####")&IF($H69="",""," "&$H69)&IF(AND(ISNUMBER($O69),$V69<$O69),", por debajo del límite inferior de "&TEXT($O69,"0.####")&IF($H69="",""," "&$H69),"")&IF(AND(ISNUMBER($P69),$V69>$P69),", por encima del límite superior de "&TEXT($P69,"0.####")&IF($H69="",""," "&$H69),"")&".","")&IF($Y69="",""," "&$Y69&IF(RIGHT($Y69,1)=".","","."))&" Acción recomendada: "&$M69&IF(RIGHT($M69,1)=".","",".")&IF($J69="Bloqueante"," El equipo no se libera hasta resolver este hallazgo.",IF($J69="Cobrable"," Se incluye en la cotización de repuestos y consumibles."," Se deja registrado como observación.")))
A70: 8.1.4 | B70: 8. Filtros y consumibles | C70: 8.1 Horómetros de consumibles | D70: Horas acumuladas de la trampa Mist Catcher (MC-1) | E70: Horas de uso acumuladas de la trampa secadora de humedad en HOUR METER | F70: En la pantalla HOUR METER, leer las horas acumuladas de la trampa Mist Catcher (MC-1). Reiniciar el contador únicamente si se reemplaza la trampa. | G70: Numérico | H70: horas | I70: Contador para planificar la sustitución anual de la trampa Mist Catcher MC-1 | J70: Cobrable | K70: Horómetro por encima del intervalo anual | L70: 4.3.1 | M70: Reemplazar la trampa y reiniciar el contador | N70: La trampa de humedad superó el intervalo de reemplazo recomendado por el fabricante. | O70: 0 | P70: 8760 | Q70: Sí | R70: No | S70: Sin artículo en el catálogo (Mist Catcher MC-1) — PENDIENTE DE CREAR EN ZOHO | T70: P-ST-019-MAN MTTO APMA370 V2 | U70: Pendiente | W70: =IF($G70<>"Numérico","",IF($V70="","Sin dato",IF(AND(OR(NOT(ISNUMBER($O70)),$V70>=$O70),OR(NOT(ISNUMBER($P70)),$V70<=$P70)),"Dentro de rango","Fuera de rango"))) | Z70: =IF(OR($U70="",$U70="Conforme",$U70="No aplica",$U70="Pendiente"),"",$N70&IF($W70="Fuera de rango"," Valor medido: "&TEXT($V70,"0.####")&IF($H70="",""," "&$H70)&IF(AND(ISNUMBER($O70),$V70<$O70),", por debajo del límite inferior de "&TEXT($O70,"0.####")&IF($H70="",""," "&$H70),"")&IF(AND(ISNUMBER($P70),$V70>$P70),", por encima del límite superior de "&TEXT($P70,"0.####")&IF($H70="",""," "&$H70),"")&".","")&IF($Y70="",""," "&$Y70&IF(RIGHT($Y70,1)=".","","."))&" Acción recomendada: "&$M70&IF(RIGHT($M70,1)=".","",".")&IF($J70="Bloqueante"," El equipo no se libera hasta resolver este hallazgo.",IF($J70="Cobrable"," Se incluye en la cotización de repuestos y consumibles."," Se deja registrado como observación.")))
A71: 8.1.5 | B71: 8. Filtros y consumibles | C71: 8.1 Horómetros de consumibles | D71: Horas acumuladas de la bomba completa (P-1-B) | E71: Horas de funcionamiento de la unidad de bomba electromecánica completa en HOUR METER | F71: En la pantalla HOUR METER, leer las horas acumuladas de la unidad de bomba (P-1-B). Reiniciar el contador únicamente si se reemplaza la bomba. | G71: Numérico | H71: horas | I71: Contador para programar el reemplazo o reconstrucción del motor de bomba cada 2 años | J71: Cobrable | K71: Horómetro por encima del intervalo de dos años | L71: 5.2.1 | M71: Programar el reemplazo de la unidad de bomba y reiniciar el contador | N71: La bomba de muestreo superó el intervalo de reemplazo recomendado por el fabricante. | O71: 0 | P71: 17520 | Q71: Sí | R71: No | S71: Pump GD-6EH-100 (100～120V) APMA / APNA / APSA / APHA (3014059459) | T71: P-ST-019-MAN MTTO APMA370 V2 | U71: Pendiente | W71: =IF($G71<>"Numérico","",IF($V71="","Sin dato",IF(AND(OR(NOT(ISNUMBER($O71)),$V71>=$O71),OR(NOT(ISNUMBER($P71)),$V71<=$P71)),"Dentro de rango","Fuera de rango"))) | Z71: =IF(OR($U71="",$U71="Conforme",$U71="No aplica",$U71="Pendiente"),"",$N71&IF($W71="Fuera de rango"," Valor medido: "&TEXT($V71,"0.####")&IF($H71="",""," "&$H71)&IF(AND(ISNUMBER($O71),$V71<$O71),", por debajo del límite inferior de "&TEXT($O71,"0.####")&IF($H71="",""," "&$H71),"")&IF(AND(ISNUMBER($P71),$V71>$P71),", por encima del límite superior de "&TEXT($P71,"0.####")&IF($H71="",""," "&$H71),"")&".","")&IF($Y71="",""," "&$Y71&IF(RIGHT($Y71,1)=".","","."))&" Acción recomendada: "&$M71&IF(RIGHT($M71,1)=".","",".")&IF($J71="Bloqueante"," El equipo no se libera hasta resolver este hallazgo.",IF($J71="Cobrable"," Se incluye en la cotización de repuestos y consumibles."," Se deja registrado como observación.")))
A72: 8.2.1 | B72: 8. Filtros y consumibles | C72: 8.2 Filtros de chasis | D72: Obstrucción de esponjas disipadoras (Filter Sponge) | E72: Acumulación de polvo e integridad física de los filtros de esponja superiores del chasis | F72: Retirar las esponjas de la cubierta y del ventilador, examinarlas a contraluz y comprobar el paso de aire. Lavarlas con agua y dejarlas secar completamente antes de reinstalar. | G72: OK / No OK | I72: Esponjas de poliuretano limpias y permeables al aire, para mantener la refrigeración interna | J72: Cobrable | K72: Polvo del shelter acumulado: reduce el aire de enfriamiento | L72: 10.2.1 ; 9.1.1 | M72: Lavar o reemplazar las esponjas y revisar el nivel de polvo de la cabina | N72: Los filtros de ventilación del chasis se encuentran obstruidos por polvo, lo que reduce la refrigeración del analizador. | Q72: Sí | R72: Sí | S72: Filter Sponge (3012299939) | T72: MT_191TE0NC_APMA370_241226 / MT_U7D80D0J_APMA370_260116 | U72: Pendiente | W72: =IF($G72<>"Numérico","",IF($V72="","Sin dato",IF(AND(OR(NOT(ISNUMBER($O72)),$V72>=$O72),OR(NOT(ISNUMBER($P72)),$V72<=$P72)),"Dentro de rango","Fuera de rango"))) | Z72: =IF(OR($U72="",$U72="Conforme",$U72="No aplica",$U72="Pendiente"),"",$N72&IF($W72="Fuera de rango"," Valor medido: "&TEXT($V72,"0.####")&IF($H72="",""," "&$H72)&IF(AND(ISNUMBER($O72),$V72<$O72),", por debajo del límite inferior de "&TEXT($O72,"0.####")&IF($H72="",""," "&$H72),"")&IF(AND(ISNUMBER($P72),$V72>$P72),", por encima del límite superior de "&TEXT($P72,"0.####")&IF($H72="",""," "&$H72),"")&".","")&IF($Y72="",""," "&$Y72&IF(RIGHT($Y72,1)=".","","."))&" Acción recomendada: "&$M72&IF(RIGHT($M72,1)=".","",".")&IF($J72="Bloqueante"," El equipo no se libera hasta resolver este hallazgo.",IF($J72="Cobrable"," Se incluye en la cotización de repuestos y consumibles."," Se deja registrado como observación.")))
A73: 9.1.1 | B73: 9. Sensores auxiliares | C73: 9.1 Temperatura | D73: Temperatura de la celda de medida (CELL) | E73: Temperatura del compartimiento calentado de la celda óptica en ANALOG INPUT | F73: Leer el valor CELL en MENU / MAINTENANCE / ANALOG INPUT y, en paralelo, medir la temperatura ambiente de la sala. Verificar que la diferencia esté dentro de lo especificado. | G73: Numérico | H73: °C | I73: Valor estándar: temperatura ambiente + 5 a 15 °C (rango típico 30 a 55 °C) | J73: Bloqueante | K73: Temperatura de sala fuera de rango, termistor dañado, o lazo de calentamiento inoperante | L73: 10.4.1 ; 7.1.3 ; 8.2.1 | M73: Descartar primero la sala; una lectura absurda (muy alta o negativa) apunta al termistor | N73: La temperatura de la celda de medida se encuentra fuera del rango de operación especificado. | O73: 30 | P73: 55 | Q73: Sí | R73: No | T73: P-ST-018-MAN OPER APMA 370 V2 | U73: Pendiente | W73: =IF($G73<>"Numérico","",IF($V73="","Sin dato",IF(AND(OR(NOT(ISNUMBER($O73)),$V73>=$O73),OR(NOT(ISNUMBER($P73)),$V73<=$P73)),"Dentro de rango","Fuera de rango"))) | Z73: =IF(OR($U73="",$U73="Conforme",$U73="No aplica",$U73="Pendiente"),"",$N73&IF($W73="Fuera de rango"," Valor medido: "&TEXT($V73,"0.####")&IF($H73="",""," "&$H73)&IF(AND(ISNUMBER($O73),$V73<$O73),", por debajo del límite inferior de "&TEXT($O73,"0.####")&IF($H73="",""," "&$H73),"")&IF(AND(ISNUMBER($P73),$V73>$P73),", por encima del límite superior de "&TEXT($P73,"0.####")&IF($H73="",""," "&$H73),"")&".","")&IF($Y73="",""," "&$Y73&IF(RIGHT($Y73,1)=".","","."))&" Acción recomendada: "&$M73&IF(RIGHT($M73,1)=".","",".")&IF($J73="Bloqueante"," El equipo no se libera hasta resolver este hallazgo.",IF($J73="Cobrable"," Se incluye en la cotización de repuestos y consumibles."," Se deja registrado como observación.")))
A74: 9.1.2 | B74: 9. Sensores auxiliares | C74: 9.1 Temperatura | D74: Sensor de temperatura del catalizador de CO (CAT) | E74: Lazo térmico de temperatura del catalizador de CO para oxidación de la referencia | F74: Verificar en ANALOG INPUT que no haya alarma de temperatura de catalizador, y confirmar por tacto con el debido cuidado que la carcasa del CAT-1 esté caliente. | G74: OK / No OK | I74: Temperatura del horno catalítico estable; su descenso drástico dispara la alarma CAT | J74: Bloqueante | K74: Calentamiento incompleto, resistencia abierta o termocupla dañada | L74: 1.3.1 ; 6.4.1 ; 7.1.4 | M74: Esperar 1 h de calentamiento; si la alarma persiste, medir continuidad de resistencia y termocupla | N74: El lazo de control de temperatura del catalizador no alcanza o no mantiene su valor de operación. | Q74: Sí | R74: Sí | S74: Heat Insulator (3012168489) | T74: P-ST-018-MAN OPER APMA 370 V2 | U74: Pendiente | W74: =IF($G74<>"Numérico","",IF($V74="","Sin dato",IF(AND(OR(NOT(ISNUMBER($O74)),$V74>=$O74),OR(NOT(ISNUMBER($P74)),$V74<=$P74)),"Dentro de rango","Fuera de rango"))) | Z74: =IF(OR($U74="",$U74="Conforme",$U74="No aplica",$U74="Pendiente"),"",$N74&IF($W74="Fuera de rango"," Valor medido: "&TEXT($V74,"0.####")&IF($H74="",""," "&$H74)&IF(AND(ISNUMBER($O74),$V74<$O74),", por debajo del límite inferior de "&TEXT($O74,"0.####")&IF($H74="",""," "&$H74),"")&IF(AND(ISNUMBER($P74),$V74>$P74),", por encima del límite superior de "&TEXT($P74,"0.####")&IF($H74="",""," "&$H74),"")&".","")&IF($Y74="",""," "&$Y74&IF(RIGHT($Y74,1)=".","","."))&" Acción recomendada: "&$M74&IF(RIGHT($M74,1)=".","",".")&IF($J74="Bloqueante"," El equipo no se libera hasta resolver este hallazgo.",IF($J74="Cobrable"," Se incluye en la cotización de repuestos y consumibles."," Se deja registrado como observación.")))
A75: 9.2.1 | B75: 9. Sensores auxiliares | C75: 9.2 Presión | D75: Presión barométrica ambiental (AMBIENT) | E75: Presión barométrica registrada por el transductor piezoeléctrico en ANALOG INPUT | F75: Leer el valor AMBIENT en MENU / MAINTENANCE / ANALOG INPUT y compararlo con la presión barométrica de referencia del sitio. | G75: Numérico | H75: kPa | I75: Presión ambiental del sitio; usada para corregir la densidad del gas según la altitud | J75: Bloqueante | K75: Sensor descalibrado por la altitud del sitio, o transductor dañado | L75: 9.2.2 | M75: Compensar el intercepto con PRESS ADJUSTMENT; si no responde, reemplazar la tarjeta que integra el sensor | N75: La lectura de presión barométrica del analizador no corresponde a la presión real del sitio. | O75: 50 | P75: 115 | Q75: Sí | R75: No | T75: P-ST-018-MAN OPER APMA 370 V2 / Procedimiento Ajuste de Presión Ambiente | U75: Pendiente | W75: =IF($G75<>"Numérico","",IF($V75="","Sin dato",IF(AND(OR(NOT(ISNUMBER($O75)),$V75>=$O75),OR(NOT(ISNUMBER($P75)),$V75<=$P75)),"Dentro de rango","Fuera de rango"))) | Z75: =IF(OR($U75="",$U75="Conforme",$U75="No aplica",$U75="Pendiente"),"",$N75&IF($W75="Fuera de rango"," Valor medido: "&TEXT($V75,"0.####")&IF($H75="",""," "&$H75)&IF(AND(ISNUMBER($O75),$V75<$O75),", por debajo del límite inferior de "&TEXT($O75,"0.####")&IF($H75="",""," "&$H75),"")&IF(AND(ISNUMBER($P75),$V75>$P75),", por encima del límite superior de "&TEXT($P75,"0.####")&IF($H75="",""," "&$H75),"")&".","")&IF($Y75="",""," "&$Y75&IF(RIGHT($Y75,1)=".","","."))&" Acción recomendada: "&$M75&IF(RIGHT($M75,1)=".","",".")&IF($J75="Bloqueante"," El equipo no se libera hasta resolver este hallazgo.",IF($J75="Cobrable"," Se incluye en la cotización de repuestos y consumibles."," Se deja registrado como observación.")))
A76: 9.2.2 | B76: 9. Sensores auxiliares | C76: 9.2 Presión | D76: Desviación de los sensores de presión | E76: Desvío entre las lecturas internas de presión y los barómetros de referencia | F76: Con un barómetro patrón calibrado junto al equipo, comparar su lectura contra el valor AMBIENT en pantalla y calcular la desviación porcentual. | G76: Numérico | H76: % | I76: La desviación entre el patrón externo y el valor en pantalla debe ser menor al 2 % | J76: Bloqueante | K76: Corrimiento de offset del transductor respecto al barómetro patrón | L76: 9.2.1 ; 5.1.2 | M76: Ajustar el offset por software y volver a comparar contra el patrón | N76: Los sensores de presión del analizador presentan una desviación superior a la tolerancia frente al patrón de referencia. | O76: 0 | P76: 2 | Q76: Sí | R76: No | T76: P-ST-018-MAN OPER APMA 370 V2 / Service Manual | U76: Pendiente | W76: =IF($G76<>"Numérico","",IF($V76="","Sin dato",IF(AND(OR(NOT(ISNUMBER($O76)),$V76>=$O76),OR(NOT(ISNUMBER($P76)),$V76<=$P76)),"Dentro de rango","Fuera de rango"))) | Z76: =IF(OR($U76="",$U76="Conforme",$U76="No aplica",$U76="Pendiente"),"",$N76&IF($W76="Fuera de rango"," Valor medido: "&TEXT($V76,"0.####")&IF($H76="",""," "&$H76)&IF(AND(ISNUMBER($O76),$V76<$O76),", por debajo del límite inferior de "&TEXT($O76,"0.####")&IF($H76="",""," "&$H76),"")&IF(AND(ISNUMBER($P76),$V76>$P76),", por encima del límite superior de "&TEXT($P76,"0.####")&IF($H76="",""," "&$H76),"")&".","")&IF($Y76="",""," "&$Y76&IF(RIGHT($Y76,1)=".","","."))&" Acción recomendada: "&$M76&IF(RIGHT($M76,1)=".","",".")&IF($J76="Bloqueante"," El equipo no se libera hasta resolver este hallazgo.",IF($J76="Cobrable"," Se incluye en la cotización de repuestos y consumibles."," Se deja registrado como observación.")))
A77: 9.3.1 | B77: 9. Sensores auxiliares | C77: 9.3 Tensiones internas | D77: Tensión interna del riel DC 24 V | E77: Tensión del bus DC secundario de alimentación de periféricos en ANALOG INPUT | F77: Leer el valor DC 24V en la segunda página de ANALOG INPUT. Para verificación independiente, medir con multímetro en el punto de prueba de 24 V de la tarjeta ADC. | G77: Numérico | H77: V | I77: Debe estar dentro de la tolerancia de 24 V ± 0,5 V | J77: Bloqueante | K77: Fuente degradada o carga excesiva sobre el riel | L77: 7.4.1 ; 10.5.1 | M77: Medir en el punto de prueba de la tarjeta; si la fuente no regula, reemplazarla | N77: La tensión interna de 24 V del analizador se encuentra fuera de tolerancia. | O77: 23.5 | P77: 24.5 | Q77: Sí | R77: No | T77: P-ST-018-MAN OPER APMA 370 V2 / Service Manual | U77: Pendiente | W77: =IF($G77<>"Numérico","",IF($V77="","Sin dato",IF(AND(OR(NOT(ISNUMBER($O77)),$V77>=$O77),OR(NOT(ISNUMBER($P77)),$V77<=$P77)),"Dentro de rango","Fuera de rango"))) | Z77: =IF(OR($U77="",$U77="Conforme",$U77="No aplica",$U77="Pendiente"),"",$N77&IF($W77="Fuera de rango"," Valor medido: "&TEXT($V77,"0.####")&IF($H77="",""," "&$H77)&IF(AND(ISNUMBER($O77),$V77<$O77),", por debajo del límite inferior de "&TEXT($O77,"0.####")&IF($H77="",""," "&$H77),"")&IF(AND(ISNUMBER($P77),$V77>$P77),", por encima del límite superior de "&TEXT($P77,"0.####")&IF($H77="",""," "&$H77),"")&".","")&IF($Y77="",""," "&$Y77&IF(RIGHT($Y77,1)=".","","."))&" Acción recomendada: "&$M77&IF(RIGHT($M77,1)=".","",".")&IF($J77="Bloqueante"," El equipo no se libera hasta resolver este hallazgo.",IF($J77="Cobrable"," Se incluye en la cotización de repuestos y consumibles."," Se deja registrado como observación.")))
A78: 9.3.2 | B78: 9. Sensores auxiliares | C78: 9.3 Tensiones internas | D78: Tensión interna del riel DC 5 V | E78: Tensión de alimentación regulada del microcontrolador lógico en ANALOG INPUT | F78: Leer el valor DC 5V en la segunda página de ANALOG INPUT. Para verificación independiente, medir con multímetro en el punto de prueba de 5 V de la tarjeta ADC. | G78: Numérico | H78: V | I78: Debe estar dentro de la tolerancia de 5 V ± 0,5 V | J78: Bloqueante | K78: Regulador de la fuente fuera de tolerancia | L78: 7.4.1 ; 10.5.1 | M78: Medir en el punto de prueba; si está fuera de ±0,5 V, reemplazar la fuente | N78: La tensión interna de 5 V del analizador se encuentra fuera de tolerancia. | O78: 4.5 | P78: 5.5 | Q78: Sí | R78: No | T78: P-ST-018-MAN OPER APMA 370 V2 / Service Manual | U78: Pendiente | W78: =IF($G78<>"Numérico","",IF($V78="","Sin dato",IF(AND(OR(NOT(ISNUMBER($O78)),$V78>=$O78),OR(NOT(ISNUMBER($P78)),$V78<=$P78)),"Dentro de rango","Fuera de rango"))) | Z78: =IF(OR($U78="",$U78="Conforme",$U78="No aplica",$U78="Pendiente"),"",$N78&IF($W78="Fuera de rango"," Valor medido: "&TEXT($V78,"0.####")&IF($H78="",""," "&$H78)&IF(AND(ISNUMBER($O78),$V78<$O78),", por debajo del límite inferior de "&TEXT($O78,"0.####")&IF($H78="",""," "&$H78),"")&IF(AND(ISNUMBER($P78),$V78>$P78),", por encima del límite superior de "&TEXT($P78,"0.####")&IF($H78="",""," "&$H78),"")&".","")&IF($Y78="",""," "&$Y78&IF(RIGHT($Y78,1)=".","","."))&" Acción recomendada: "&$M78&IF(RIGHT($M78,1)=".","",".")&IF($J78="Bloqueante"," El equipo no se libera hasta resolver este hallazgo.",IF($J78="Cobrable"," Se incluye en la cotización de repuestos y consumibles."," Se deja registrado como observación.")))
A79: 10.1.1 | B79: 10. Gabinete, montaje e instalación | C79: 10.1 Chasis y puerta frontal | D79: Ajuste y fijación de la puerta frontal | E79: Alineación e integridad física de la puerta del panel frontal del gabinete | F79: Abrir y cerrar la puerta frontal varias veces, verificar que encaje sin forzar y que quede a ras del chasis, y comprobar que la pantalla se pueda presionar sin que la puerta ceda. | G79: OK / No OK | I79: Puerta encajada firmemente, sin desniveles que impidan presionar adecuadamente la pantalla | J79: Cobrable | K79: Bisagra descolgada o casquillo desgastado | L79: 10.1.2 ; 10.1.3 | M79: Reponer casquillos y eje, y realinear la puerta | N79: La puerta frontal del analizador no cierra alineada, lo que dificulta la operación de la pantalla. | Q79: Sí | R79: Sí | S79: Door (3012298155) · Latch, Mini, Screw Type, TL-297-7, NO.1 (3011017097) · Panel, Lock 60 °C 12H F022711600 (3014059988) | T79: MT_56X1BA8G_APMA370_260109 / MT_2V0CY0DC_APMA370_20060501 | U79: Pendiente | W79: =IF($G79<>"Numérico","",IF($V79="","Sin dato",IF(AND(OR(NOT(ISNUMBER($O79)),$V79>=$O79),OR(NOT(ISNUMBER($P79)),$V79<=$P79)),"Dentro de rango","Fuera de rango"))) | Z79: =IF(OR($U79="",$U79="Conforme",$U79="No aplica",$U79="Pendiente"),"",$N79&IF($W79="Fuera de rango"," Valor medido: "&TEXT($V79,"0.####")&IF($H79="",""," "&$H79)&IF(AND(ISNUMBER($O79),$V79<$O79),", por debajo del límite inferior de "&TEXT($O79,"0.####")&IF($H79="",""," "&$H79),"")&IF(AND(ISNUMBER($P79),$V79>$P79),", por encima del límite superior de "&TEXT($P79,"0.####")&IF($H79="",""," "&$H79),"")&".","")&IF($Y79="",""," "&$Y79&IF(RIGHT($Y79,1)=".","","."))&" Acción recomendada: "&$M79&IF(RIGHT($M79,1)=".","",".")&IF($J79="Bloqueante"," El equipo no se libera hasta resolver este hallazgo.",IF($J79="Cobrable"," Se incluye en la cotización de repuestos y consumibles."," Se deja registrado como observación.")))
A80: 10.1.2 | B80: 10. Gabinete, montaje e instalación | C80: 10.1 Chasis y puerta frontal | D80: Casquillos de bisagra de la puerta frontal | E80: Presencia de los casquillos en los puntos de pivote del panel frontal basculante | F80: Con la puerta abierta, inspeccionar los puntos de pivote superior e inferior y verificar la presencia de los casquillos plásticos. Comprobar que no haya holgura lateral. | G80: Presente / Ausente | I80: Casquillos plásticos de nylon en buen estado, para alinear simétricamente la apertura | J80: Cobrable | K80: Casquillo de nylon desgastado o ausente | L80: 10.1.1 | M80: Reemplazar los casquillos de bisagra | N80: Los casquillos de bisagra de la puerta frontal están desgastados o ausentes. | Q80: Sí | R80: Sí | S80: Door Hinge (3012304034) · Hinji Bush (3012304035) | T80: MT_P4B4CK60_APMA370_220511 | U80: Pendiente | W80: =IF($G80<>"Numérico","",IF($V80="","Sin dato",IF(AND(OR(NOT(ISNUMBER($O80)),$V80>=$O80),OR(NOT(ISNUMBER($P80)),$V80<=$P80)),"Dentro de rango","Fuera de rango"))) | Z80: =IF(OR($U80="",$U80="Conforme",$U80="No aplica",$U80="Pendiente"),"",$N80&IF($W80="Fuera de rango"," Valor medido: "&TEXT($V80,"0.####")&IF($H80="",""," "&$H80)&IF(AND(ISNUMBER($O80),$V80<$O80),", por debajo del límite inferior de "&TEXT($O80,"0.####")&IF($H80="",""," "&$H80),"")&IF(AND(ISNUMBER($P80),$V80>$P80),", por encima del límite superior de "&TEXT($P80,"0.####")&IF($H80="",""," "&$H80),"")&".","")&IF($Y80="",""," "&$Y80&IF(RIGHT($Y80,1)=".","","."))&" Acción recomendada: "&$M80&IF(RIGHT($M80,1)=".","",".")&IF($J80="Bloqueante"," El equipo no se libera hasta resolver este hallazgo.",IF($J80="Cobrable"," Se incluye en la cotización de repuestos y consumibles."," Se deja registrado como observación.")))
A81: 10.1.3 | B81: 10. Gabinete, montaje e instalación | C81: 10.1 Chasis y puerta frontal | D81: Eje de bisagra de la puerta frontal | E81: Presencia de los pasadores cilíndricos metálicos de rotación de la bisagra | F81: Con la puerta abierta, verificar que los pasadores metálicos de la bisagra estén introducidos a tope y no sobresalgan ni estén desplazados. | G81: Presente / Ausente | I81: Pasadores metálicos introducidos a tope, para articular con seguridad la compuerta | J81: Cobrable | K81: Pasador desplazado o ausente | L81: 10.1.1 | M81: Reponer el pasador a tope | N81: El eje de la bisagra de la puerta frontal está desplazado o ausente. | Q81: Sí | R81: Sí | S81: Door Hinge (3012304034) · Hinge-Shaft (3012297312) | T81: MT_P4B4CK60_APMA370_220511 | U81: Pendiente | W81: =IF($G81<>"Numérico","",IF($V81="","Sin dato",IF(AND(OR(NOT(ISNUMBER($O81)),$V81>=$O81),OR(NOT(ISNUMBER($P81)),$V81<=$P81)),"Dentro de rango","Fuera de rango"))) | Z81: =IF(OR($U81="",$U81="Conforme",$U81="No aplica",$U81="Pendiente"),"",$N81&IF($W81="Fuera de rango"," Valor medido: "&TEXT($V81,"0.####")&IF($H81="",""," "&$H81)&IF(AND(ISNUMBER($O81),$V81<$O81),", por debajo del límite inferior de "&TEXT($O81,"0.####")&IF($H81="",""," "&$H81),"")&IF(AND(ISNUMBER($P81),$V81>$P81),", por encima del límite superior de "&TEXT($P81,"0.####")&IF($H81="",""," "&$H81),"")&".","")&IF($Y81="",""," "&$Y81&IF(RIGHT($Y81,1)=".","","."))&" Acción recomendada: "&$M81&IF(RIGHT($M81,1)=".","",".")&IF($J81="Bloqueante"," El equipo no se libera hasta resolver este hallazgo.",IF($J81="Cobrable"," Se incluye en la cotización de repuestos y consumibles."," Se deja registrado como observación.")))
A82: 10.2.1 | B82: 10. Gabinete, montaje e instalación | C82: 10.2 Ventilación | D82: Extractor de calor (Cooling Fan) posterior | E82: Operación del ventilador posterior de extracción activa de aire caliente | F82: Con el equipo energizado, aproximar la mano o una tira de papel a la rejilla posterior para confirmar el flujo de aire, y escuchar el ventilador buscando ruido de rodamiento. | G82: OK / No OK | I82: Ventilador girando de forma estable, sin polvo extremo ni ruidos de rodamientos desgastados | J82: Bloqueante | K82: Rodamiento desgastado o ventilador obstruido por polvo | L82: 8.2.1 ; 9.1.1 | M82: Reemplazar el ventilador; el equipo no se libera con la refrigeración comprometida | N82: El ventilador de refrigeración no opera correctamente, lo que compromete la estabilidad térmica del analizador. | Q82: Sí | R82: Sí | S82: Sin artículo en el catálogo (ventilador posterior) — PENDIENTE DE CREAR EN ZOHO | T82: MT_191TE0NC_APMA370_241226 | U82: Pendiente | W82: =IF($G82<>"Numérico","",IF($V82="","Sin dato",IF(AND(OR(NOT(ISNUMBER($O82)),$V82>=$O82),OR(NOT(ISNUMBER($P82)),$V82<=$P82)),"Dentro de rango","Fuera de rango"))) | Z82: =IF(OR($U82="",$U82="Conforme",$U82="No aplica",$U82="Pendiente"),"",$N82&IF($W82="Fuera de rango"," Valor medido: "&TEXT($V82,"0.####")&IF($H82="",""," "&$H82)&IF(AND(ISNUMBER($O82),$V82<$O82),", por debajo del límite inferior de "&TEXT($O82,"0.####")&IF($H82="",""," "&$H82),"")&IF(AND(ISNUMBER($P82),$V82>$P82),", por encima del límite superior de "&TEXT($P82,"0.####")&IF($H82="",""," "&$H82),"")&".","")&IF($Y82="",""," "&$Y82&IF(RIGHT($Y82,1)=".","","."))&" Acción recomendada: "&$M82&IF(RIGHT($M82,1)=".","",".")&IF($J82="Bloqueante"," El equipo no se libera hasta resolver este hallazgo.",IF($J82="Cobrable"," Se incluye en la cotización de repuestos y consumibles."," Se deja registrado como observación.")))
A83: 10.3.1 | B83: 10. Gabinete, montaje e instalación | C83: 10.3 Montaje en rack | D83: Rieles o bandeja de base en rack de 19 pulgadas | E83: Presencia de guías de soporte o bandeja base para montaje del analizador en gabinete | F83: Inspeccionar visualmente por debajo del equipo si está apoyado sobre bandeja o rieles, y comprobar presionando el frente del chasis que no haya flexión ni juego. | G83: OK / No OK | I83: Base metálica firme para sostener el analizador (16 kg) y evitar la flexión frontal | J83: Alerta | K83: Equipo apoyado solo por el frente: flexión del chasis | L83: Nodo terminal — actuar directamente | M83: Instalar bandeja o rieles de soporte antes de cerrar el servicio | N83: El analizador no cuenta con bandeja o rieles de soporte y queda apoyado únicamente por su frente. | Q83: Sí | R83: Sí | T83: P-ST-018-MAN OPER APMA 370 V2 | U83: Pendiente | W83: =IF($G83<>"Numérico","",IF($V83="","Sin dato",IF(AND(OR(NOT(ISNUMBER($O83)),$V83>=$O83),OR(NOT(ISNUMBER($P83)),$V83<=$P83)),"Dentro de rango","Fuera de rango"))) | Z83: =IF(OR($U83="",$U83="Conforme",$U83="No aplica",$U83="Pendiente"),"",$N83&IF($W83="Fuera de rango"," Valor medido: "&TEXT($V83,"0.####")&IF($H83="",""," "&$H83)&IF(AND(ISNUMBER($O83),$V83<$O83),", por debajo del límite inferior de "&TEXT($O83,"0.####")&IF($H83="",""," "&$H83),"")&IF(AND(ISNUMBER($P83),$V83>$P83),", por encima del límite superior de "&TEXT($P83,"0.####")&IF($H83="",""," "&$H83),"")&".","")&IF($Y83="",""," "&$Y83&IF(RIGHT($Y83,1)=".","","."))&" Acción recomendada: "&$M83&IF(RIGHT($M83,1)=".","",".")&IF($J83="Bloqueante"," El equipo no se libera hasta resolver este hallazgo.",IF($J83="Cobrable"," Se incluye en la cotización de repuestos y consumibles."," Se deja registrado como observación.")))
A84: 10.3.2 | B84: 10. Gabinete, montaje e instalación | C84: 10.3 Montaje en rack | D84: Holgura con el fondo del rack | E84: Separación libre entre el chasis posterior y la cubierta o puerta del rack | F84: Medir con flexómetro la distancia entre el panel trasero del equipo y la puerta o pared posterior del rack, con las mangueras y cables ya instalados. | G84: Numérico | H84: mm | I84: Mínimo 150 mm en la parte trasera para mangueras neumáticas y ventilación. Límite superior PENDIENTE DE VALIDAR | J84: Alerta | K84: Espacio insuficiente: mangueras dobladas y ventilación restringida | L84: 4.3.2 ; 10.2.1 | M84: Reubicar el equipo para dejar al menos 150 mm libres detrás | N84: El espacio libre detrás del analizador es insuficiente para el trazado de mangueras y para su ventilación. | O84: 150 | Q84: Sí | R84: No | T84: P-ST-018-MAN OPER APMA 370 V2 | U84: Pendiente | W84: =IF($G84<>"Numérico","",IF($V84="","Sin dato",IF(AND(OR(NOT(ISNUMBER($O84)),$V84>=$O84),OR(NOT(ISNUMBER($P84)),$V84<=$P84)),"Dentro de rango","Fuera de rango"))) | Z84: =IF(OR($U84="",$U84="Conforme",$U84="No aplica",$U84="Pendiente"),"",$N84&IF($W84="Fuera de rango"," Valor medido: "&TEXT($V84,"0.####")&IF($H84="",""," "&$H84)&IF(AND(ISNUMBER($O84),$V84<$O84),", por debajo del límite inferior de "&TEXT($O84,"0.####")&IF($H84="",""," "&$H84),"")&IF(AND(ISNUMBER($P84),$V84>$P84),", por encima del límite superior de "&TEXT($P84,"0.####")&IF($H84="",""," "&$H84),"")&".","")&IF($Y84="",""," "&$Y84&IF(RIGHT($Y84,1)=".","","."))&" Acción recomendada: "&$M84&IF(RIGHT($M84,1)=".","",".")&IF($J84="Bloqueante"," El equipo no se libera hasta resolver este hallazgo.",IF($J84="Cobrable"," Se incluye en la cotización de repuestos y consumibles."," Se deja registrado como observación.")))
A85: 10.4.1 | B85: 10. Gabinete, montaje e instalación | C85: 10.4 Condiciones ambientales del sitio | D85: Temperatura ambiental de operación de la sala | E85: Temperatura controlada del shelter para asegurar condiciones termoestables | F85: Medir la temperatura de la sala con termohigrómetro calibrado, a la altura del equipo y alejado de la descarga del aire acondicionado. Registrar también el valor máximo del día si hay datalogger. | G85: Numérico | H85: °C | I85: Rango de operación del analizador para mantener estabilidad óptica y química | J85: Alerta | K85: Aire acondicionado insuficiente o en falla | L85: 9.1.1 ; 10.4.2 | M85: Corregir la climatización del shelter; la deriva no se juzga hasta estabilizar la sala | N85: La temperatura de la cabina de monitoreo se encuentra fuera del rango de operación especificado para el analizador. | O85: 5 | P85: 40 | Q85: Sí | R85: No | T85: P-ST-018-MAN OPER APMA 370 V2 | U85: Pendiente | W85: =IF($G85<>"Numérico","",IF($V85="","Sin dato",IF(AND(OR(NOT(ISNUMBER($O85)),$V85>=$O85),OR(NOT(ISNUMBER($P85)),$V85<=$P85)),"Dentro de rango","Fuera de rango"))) | Z85: =IF(OR($U85="",$U85="Conforme",$U85="No aplica",$U85="Pendiente"),"",$N85&IF($W85="Fuera de rango"," Valor medido: "&TEXT($V85,"0.####")&IF($H85="",""," "&$H85)&IF(AND(ISNUMBER($O85),$V85<$O85),", por debajo del límite inferior de "&TEXT($O85,"0.####")&IF($H85="",""," "&$H85),"")&IF(AND(ISNUMBER($P85),$V85>$P85),", por encima del límite superior de "&TEXT($P85,"0.####")&IF($H85="",""," "&$H85),"")&".","")&IF($Y85="",""," "&$Y85&IF(RIGHT($Y85,1)=".","","."))&" Acción recomendada: "&$M85&IF(RIGHT($M85,1)=".","",".")&IF($J85="Bloqueante"," El equipo no se libera hasta resolver este hallazgo.",IF($J85="Cobrable"," Se incluye en la cotización de repuestos y consumibles."," Se deja registrado como observación.")))
A86: 10.4.2 | B86: 10. Gabinete, montaje e instalación | C86: 10.4 Condiciones ambientales del sitio | D86: Humedad relativa con temperatura menor a 31 °C | E86: Límite higrométrico del aire ambiente en el shelter para temperaturas menores a 31 °C | F86: Medir la humedad relativa con termohigrómetro calibrado junto al equipo y registrarla junto con la temperatura medida en el mismo instante. | G86: Numérico | H86: %HR | I86: Humedad relativa máxima 80 % para evitar condensaciones ópticas internas | J86: Alerta | K86: Humedad alta: riesgo de condensación óptica y de sulfatación del panel | L86: 4.3.1 ; 7.3.2 | M86: Deshumidificar la cabina y revisar la línea de muestreo | N86: La humedad relativa de la cabina supera el límite admisible, con riesgo de condensación en el analizador. | O86: 0 | P86: 80 | Q86: Sí | R86: No | T86: P-ST-018-MAN OPER APMA 370 V2 | U86: Pendiente | W86: =IF($G86<>"Numérico","",IF($V86="","Sin dato",IF(AND(OR(NOT(ISNUMBER($O86)),$V86>=$O86),OR(NOT(ISNUMBER($P86)),$V86<=$P86)),"Dentro de rango","Fuera de rango"))) | Z86: =IF(OR($U86="",$U86="Conforme",$U86="No aplica",$U86="Pendiente"),"",$N86&IF($W86="Fuera de rango"," Valor medido: "&TEXT($V86,"0.####")&IF($H86="",""," "&$H86)&IF(AND(ISNUMBER($O86),$V86<$O86),", por debajo del límite inferior de "&TEXT($O86,"0.####")&IF($H86="",""," "&$H86),"")&IF(AND(ISNUMBER($P86),$V86>$P86),", por encima del límite superior de "&TEXT($P86,"0.####")&IF($H86="",""," "&$H86),"")&".","")&IF($Y86="",""," "&$Y86&IF(RIGHT($Y86,1)=".","","."))&" Acción recomendada: "&$M86&IF(RIGHT($M86,1)=".","",".")&IF($J86="Bloqueante"," El equipo no se libera hasta resolver este hallazgo.",IF($J86="Cobrable"," Se incluye en la cotización de repuestos y consumibles."," Se deja registrado como observación.")))
A87: 10.4.3 | B87: 10. Gabinete, montaje e instalación | C87: 10.4 Condiciones ambientales del sitio | D87: Humedad relativa con temperatura entre 31 y 40 °C | E87: Límite higrométrico descendente conforme aumenta la temperatura entre 31 y 40 °C | F87: Con la temperatura de sala medida entre 31 y 40 °C, calcular el límite de humedad interpolando linealmente entre 80 % a 31 °C y 50 % a 40 °C, y comparar con la humedad medida. | G87: Numérico | H87: %HR | I87: Humedad máxima controlada linealmente entre 80 % (31 °C) y 50 % (40 °C) | J87: Alerta | K87: Humedad por encima del límite interpolado para esa temperatura | L87: 10.4.1 ; 10.4.2 | M87: Bajar temperatura o humedad hasta entrar en la curva admisible | N87: La humedad relativa de la cabina supera el límite admisible para la temperatura registrada en el sitio. | O87: 0 | P87: 50 | Q87: Sí | R87: No | T87: P-ST-018-MAN OPER APMA 370 V2 | U87: Pendiente | W87: =IF($G87<>"Numérico","",IF($V87="","Sin dato",IF(AND(OR(NOT(ISNUMBER($O87)),$V87>=$O87),OR(NOT(ISNUMBER($P87)),$V87<=$P87)),"Dentro de rango","Fuera de rango"))) | Z87: =IF(OR($U87="",$U87="Conforme",$U87="No aplica",$U87="Pendiente"),"",$N87&IF($W87="Fuera de rango"," Valor medido: "&TEXT($V87,"0.####")&IF($H87="",""," "&$H87)&IF(AND(ISNUMBER($O87),$V87<$O87),", por debajo del límite inferior de "&TEXT($O87,"0.####")&IF($H87="",""," "&$H87),"")&IF(AND(ISNUMBER($P87),$V87>$P87),", por encima del límite superior de "&TEXT($P87,"0.####")&IF($H87="",""," "&$H87),"")&".","")&IF($Y87="",""," "&$Y87&IF(RIGHT($Y87,1)=".","","."))&" Acción recomendada: "&$M87&IF(RIGHT($M87,1)=".","",".")&IF($J87="Bloqueante"," El equipo no se libera hasta resolver este hallazgo.",IF($J87="Cobrable"," Se incluye en la cotización de repuestos y consumibles."," Se deja registrado como observación.")))
A88: 10.5.1 | B88: 10. Gabinete, montaje e instalación | C88: 10.5 Suministro eléctrico | D88: Variación de tensión nominal AC | E88: Variación de tensión de la red eléctrica AC en la toma de corriente del analizador | F88: Medir con multímetro en modo VAC la tensión en la toma de corriente que alimenta el equipo, en operación normal. Repetir la medición si la estación tiene planta o UPS conmutando. | G88: Numérico | H88: V | I88: Rango tolerado por la fuente interna para operación óptima (nominal 220 V AC) | J88: Bloqueante | K88: Red inestable, o planta y UPS conmutando fuera de rango | L88: 7.4.1 | M88: Estabilizar la alimentación antes de juzgar cualquier lectura eléctrica del equipo | N88: La tensión de la red eléctrica que alimenta el analizador se encuentra fuera del rango admisible. | O88: 198 | P88: 264 | Q88: Sí | R88: No | T88: P-ST-018-MAN OPER APMA 370 V2 | U88: Pendiente | W88: =IF($G88<>"Numérico","",IF($V88="","Sin dato",IF(AND(OR(NOT(ISNUMBER($O88)),$V88>=$O88),OR(NOT(ISNUMBER($P88)),$V88<=$P88)),"Dentro de rango","Fuera de rango"))) | Z88: =IF(OR($U88="",$U88="Conforme",$U88="No aplica",$U88="Pendiente"),"",$N88&IF($W88="Fuera de rango"," Valor medido: "&TEXT($V88,"0.####")&IF($H88="",""," "&$H88)&IF(AND(ISNUMBER($O88),$V88<$O88),", por debajo del límite inferior de "&TEXT($O88,"0.####")&IF($H88="",""," "&$H88),"")&IF(AND(ISNUMBER($P88),$V88>$P88),", por encima del límite superior de "&TEXT($P88,"0.####")&IF($H88="",""," "&$H88),"")&".","")&IF($Y88="",""," "&$Y88&IF(RIGHT($Y88,1)=".","","."))&" Acción recomendada: "&$M88&IF(RIGHT($M88,1)=".","",".")&IF($J88="Bloqueante"," El equipo no se libera hasta resolver este hallazgo.",IF($J88="Cobrable"," Se incluye en la cotización de repuestos y consumibles."," Se deja registrado como observación.")))

Sheet APSA-370 (SO2)
A1: FASE 1 — INSPECCIÓN FÍSICA DEL EQUIPO · APSA-370 (SO2) (catálogo + captura)
A3: Cliente: | D3: Principio de medición: | E3: Fluorescencia ultravioleta (UVF)
A4: NIT: | D4: Fecha de inspección:
A5: Equipo / Modelo: | B5: Analizador de dióxido de azufre HORIBA APSA-370 | D5: Técnico responsable:
A6: Número de serie: | D6: N.º de informe (MT):
A8: ID | B8: Nivel macro (N1) | C8: Subnivel (N2) | D8: Ítem (N3) | E8: Qué se verifica | F8: Cómo se realiza la inspección | G8: Tipo de dato | H8: Unidad | I8: Criterio de aceptación | J8: Criterio de falla | K8: Si NO OK → causa probable | L8: Si NO OK → verificar (ID) | M8: Si NO OK → acción | N8: Comentario de falla (informe al cliente) | O8: Límite inferior | P8: Límite superior | Q8: Obligatorio | R8: Evidencia fotográfica requerida | S8: Repuesto / parte asociada (catálogo Zoho Books) | T8: Fuente documental | U8: Resultado | V8: Valor medido | W8: Verificación de rango | X8: Foto adjunta | Y8: Observación | Z8: Comentario para el informe (automático)
A9: 1.1.1 | B9: 1. Verificación funcional inicial | C9: 1.1 Encendido y LEDs frontales | D9: LED de encendido del panel frontal | E9: Estado de iluminación del LED de encendido con el analizador energizado | F9: Con el equipo energizado, observar el LED de encendido del panel frontal y registrar su color. No requiere abrir el equipo. | G9: OK / No OK | I9: Debe iluminarse en verde en operación normal; cambia a rojo si existe alarma activa | J9: Alerta | K9: LED en rojo: hay al menos una alarma activa en el equipo | L9: 1.2.2 | M9: Registrar el color y pasar al listado de alarmas antes de continuar | N9: El indicador de encendido del panel frontal no muestra el estado normal de operación, lo que señala una condición de alarma activa en el analizador. | Q9: Sí | R9: Sí | T9: P-ST-030-MAN OPER APSA 370 V2 | U9: Pendiente | W9: =IF($G9<>"Numérico","",IF($V9="","Sin dato",IF(AND(OR(NOT(ISNUMBER($O9)),$V9>=$O9),OR(NOT(ISNUMBER($P9)),$V9<=$P9)),"Dentro de rango","Fuera de rango"))) | Z9: =IF(OR($U9="",$U9="Conforme",$U9="No aplica",$U9="Pendiente"),"",$N9&IF($W9="Fuera de rango"," Valor medido: "&TEXT($V9,"0.####")&IF($H9="",""," "&$H9)&IF(AND(ISNUMBER($O9),$V9<$O9),", por debajo del límite inferior de "&TEXT($O9,"0.####")&IF($H9="",""," "&$H9),"")&IF(AND(ISNUMBER($P9),$V9>$P9),", por encima del límite superior de "&TEXT($P9,"0.####")&IF($H9="",""," "&$H9),"")&".","")&IF($Y9="",""," "&$Y9&IF(RIGHT($Y9,1)=".","","."))&" Acción recomendada: "&$M9&IF(RIGHT($M9,1)=".","",".")&IF($J9="Bloqueante"," El equipo no se libera hasta resolver este hallazgo.",IF($J9="Cobrable"," Se incluye en la cotización de repuestos y consumibles."," Se deja registrado como observación.")))
A10: 1.2.1 | B10: 1. Verificación funcional inicial | C10: 1.2 Autodiagnóstico de software | D10: Inicialización de parámetros en SRAM | E10: Carga de datos lógicos y ausencia de errores de inicialización al arrancar la CPU | F10: Encender el equipo y observar la secuencia de arranque completa, verificando que no aparezcan mensajes de error de memoria y que cargue automáticamente la pantalla MEAS. | G10: OK / No OK | I10: Arranque limpio sin errores de memoria y con la pantalla MEAS cargada automáticamente | J10: Bloqueante | K10: Batería de respaldo agotada o memoria corrompida por picos de tensión | L10: 7.2.1 ; 7.1.9 | M10: Reemplazar la batería y reconfigurar; si persiste, inicializar la CPU y recargar la configuración desde CF | N10: El analizador no completa correctamente su secuencia de arranque: presenta errores de memoria o pierde la configuración almacenada. | Q10: Sí | R10: Sí | T10: P-ST-030-MAN OPER APSA 370 V2 | U10: Pendiente | W10: =IF($G10<>"Numérico","",IF($V10="","Sin dato",IF(AND(OR(NOT(ISNUMBER($O10)),$V10>=$O10),OR(NOT(ISNUMBER($P10)),$V10<=$P10)),"Dentro de rango","Fuera de rango"))) | Z10: =IF(OR($U10="",$U10="Conforme",$U10="No aplica",$U10="Pendiente"),"",$N10&IF($W10="Fuera de rango"," Valor medido: "&TEXT($V10,"0.####")&IF($H10="",""," "&$H10)&IF(AND(ISNUMBER($O10),$V10<$O10),", por debajo del límite inferior de "&TEXT($O10,"0.####")&IF($H10="",""," "&$H10),"")&IF(AND(ISNUMBER($P10),$V10>$P10),", por encima del límite superior de "&TEXT($P10,"0.####")&IF($H10="",""," "&$H10),"")&".","")&IF($Y10="",""," "&$Y10&IF(RIGHT($Y10,1)=".","","."))&" Acción recomendada: "&$M10&IF(RIGHT($M10,1)=".","",".")&IF($J10="Bloqueante"," El equipo no se libera hasta resolver este hallazgo.",IF($J10="Cobrable"," Se incluye en la cotización de repuestos y consumibles."," Se deja registrado como observación.")))
A11: 1.2.2 | B11: 1. Verificación funcional inicial | C11: 1.2 Autodiagnóstico de software | D11: Indicador de alarmas activas en pantalla | E11: Presencia del botón ALARM en la esquina inferior derecha de la pantalla principal | F11: Observar la esquina inferior derecha de la pantalla MEAS. Si aparece el botón ALARM, presionarlo y anotar todos los códigos activos antes de continuar. | G11: Sí/No | I11: El botón de alarma no debe estar visible en la pantalla MEAS en condiciones normales | J11: Bloqueante | K11: Alarma activa de proceso, de calibración o de tarjeta | L11: 6.1.1 ; 5.1.1 ; 5.1.2 ; 9.1.1 | M11: Anotar el código en MENU/ALARM y entrar por la rama que corresponda | N11: El analizador presenta al menos una alarma activa al momento de la inspección. | Q11: Sí | R11: No | T11: P-ST-030-MAN OPER APSA 370 V2 | U11: Pendiente | W11: =IF($G11<>"Numérico","",IF($V11="","Sin dato",IF(AND(OR(NOT(ISNUMBER($O11)),$V11>=$O11),OR(NOT(ISNUMBER($P11)),$V11<=$P11)),"Dentro de rango","Fuera de rango"))) | Z11: =IF(OR($U11="",$U11="Conforme",$U11="No aplica",$U11="Pendiente"),"",$N11&IF($W11="Fuera de rango"," Valor medido: "&TEXT($V11,"0.####")&IF($H11="",""," "&$H11)&IF(AND(ISNUMBER($O11),$V11<$O11),", por debajo del límite inferior de "&TEXT($O11,"0.####")&IF($H11="",""," "&$H11),"")&IF(AND(ISNUMBER($P11),$V11>$P11),", por encima del límite superior de "&TEXT($P11,"0.####")&IF($H11="",""," "&$H11),"")&".","")&IF($Y11="",""," "&$Y11&IF(RIGHT($Y11,1)=".","","."))&" Acción recomendada: "&$M11&IF(RIGHT($M11,1)=".","",".")&IF($J11="Bloqueante"," El equipo no se libera hasta resolver este hallazgo.",IF($J11="Cobrable"," Se incluye en la cotización de repuestos y consumibles."," Se deja registrado como observación.")))
A12: 1.2.3 | B12: 1. Verificación funcional inicial | C12: 1.2 Autodiagnóstico de software | D12: Identificación del programa en menú | E12: Versión y número de programa en la pantalla de información del sistema | F12: Ir a MENU / SYSTEM / INFORMATION y leer el número de programa en pantalla. Anotarlo textualmente y contrastarlo con el estándar de fábrica. | G12: Texto | I12: Debe mostrar el código de programa estándar de fábrica (AP: P1000878001 / EN: P1000877001) | J12: Alerta | K12: Programa no homologado, o CPU sustituida sin recargar la configuración de fábrica | L12: 7.1.9 | M12: Confirmar el HGS con fábrica y recargar la configuración desde la CF antes de calibrar | N12: La versión de programa instalada no corresponde a la versión homologada de fábrica para este analizador. | Q12: Sí | R12: No | T12: 1 - LCD design change AP EN | U12: Pendiente | W12: =IF($G12<>"Numérico","",IF($V12="","Sin dato",IF(AND(OR(NOT(ISNUMBER($O12)),$V12>=$O12),OR(NOT(ISNUMBER($P12)),$V12<=$P12)),"Dentro de rango","Fuera de rango"))) | Z12: =IF(OR($U12="",$U12="Conforme",$U12="No aplica",$U12="Pendiente"),"",$N12&IF($W12="Fuera de rango"," Valor medido: "&TEXT($V12,"0.####")&IF($H12="",""," "&$H12)&IF(AND(ISNUMBER($O12),$V12<$O12),", por debajo del límite inferior de "&TEXT($O12,"0.####")&IF($H12="",""," "&$H12),"")&IF(AND(ISNUMBER($P12),$V12>$P12),", por encima del límite superior de "&TEXT($P12,"0.####")&IF($H12="",""," "&$H12),"")&".","")&IF($Y12="",""," "&$Y12&IF(RIGHT($Y12,1)=".","","."))&" Acción recomendada: "&$M12&IF(RIGHT($M12,1)=".","",".")&IF($J12="Bloqueante"," El equipo no se libera hasta resolver este hallazgo.",IF($J12="Cobrable"," Se incluye en la cotización de repuestos y consumibles."," Se deja registrado como observación.")))
A13: 1.3.1 | B13: 1. Verificación funcional inicial | C13: 1.3 Estabilización térmica | D13: Tiempo de calentamiento y estabilización | E13: Tiempo transcurrido desde el encendido hasta la calibración o la medición en campo | F13: Anotar la hora de encendido del equipo y calcular las horas transcurridas hasta la inspección o la calibración. Si el equipo llevaba operando, registrar que ya estaba estabilizado. | G13: Numérico | H13: horas | I13: Mínimo 3 h de estabilización; se recomienda 24 a 48 h para mediciones de campo estables | J13: Alerta | K13: Equipo encendido hace menos de 3 h: lámpara y HC Cutter aún inestables | L13: 6.1.1 ; 9.1.1 ; 6.3.1 | M13: Esperar el calentamiento completo (24 h tras un arranque en frío) antes de calibrar | N13: El analizador no ha completado el tiempo mínimo de calentamiento, por lo que sus lecturas aún no son representativas. | O13: 3 | P13: 48 | Q13: Sí | R13: No | T13: P-ST-030-MAN OPER APSA 370 V2 | U13: Pendiente | W13: =IF($G13<>"Numérico","",IF($V13="","Sin dato",IF(AND(OR(NOT(ISNUMBER($O13)),$V13>=$O13),OR(NOT(ISNUMBER($P13)),$V13<=$P13)),"Dentro de rango","Fuera de rango"))) | Z13: =IF(OR($U13="",$U13="Conforme",$U13="No aplica",$U13="Pendiente"),"",$N13&IF($W13="Fuera de rango"," Valor medido: "&TEXT($V13,"0.####")&IF($H13="",""," "&$H13)&IF(AND(ISNUMBER($O13),$V13<$O13),", por debajo del límite inferior de "&TEXT($O13,"0.####")&IF($H13="",""," "&$H13),"")&IF(AND(ISNUMBER($P13),$V13>$P13),", por encima del límite superior de "&TEXT($P13,"0.####")&IF($H13="",""," "&$H13),"")&".","")&IF($Y13="",""," "&$Y13&IF(RIGHT($Y13,1)=".","","."))&" Acción recomendada: "&$M13&IF(RIGHT($M13,1)=".","",".")&IF($J13="Bloqueante"," El equipo no se libera hasta resolver este hallazgo.",IF($J13="Cobrable"," Se incluye en la cotización de repuestos y consumibles."," Se deja registrado como observación.")))
A14: 1.3.2 | B14: 1. Verificación funcional inicial | C14: 1.3 Estabilización térmica | D14: Ajuste del minuto de reset de integración | E14: Minuto del reloj en el que se ejecuta el reset de integración (RESET TIME) | F14: Ir a MENU / SYSTEM / RESET TIME y leer el minuto configurado. Contrastarlo con el requerimiento del sistema de adquisición de la estación. | G14: Numérico | H14: minutos | I14: Debe estar ajustado a 00 o 30 min según los requerimientos del sistema de adquisición | J14: Alerta | K14: Parámetro distinto al requerido por el sistema de adquisición | L14: Nodo terminal — actuar directamente | M14: Ajustar RESET TIME al valor acordado con el operador de la red | N14: El minuto de reset de integración no corresponde al requerido por el sistema de adquisición de datos de la estación. | O14: 0 | P14: 30 | Q14: Sí | R14: No | T14: P-ST-030-MAN OPER APSA 370 V2 | U14: Pendiente | W14: =IF($G14<>"Numérico","",IF($V14="","Sin dato",IF(AND(OR(NOT(ISNUMBER($O14)),$V14>=$O14),OR(NOT(ISNUMBER($P14)),$V14<=$P14)),"Dentro de rango","Fuera de rango"))) | Z14: =IF(OR($U14="",$U14="Conforme",$U14="No aplica",$U14="Pendiente"),"",$N14&IF($W14="Fuera de rango"," Valor medido: "&TEXT($V14,"0.####")&IF($H14="",""," "&$H14)&IF(AND(ISNUMBER($O14),$V14<$O14),", por debajo del límite inferior de "&TEXT($O14,"0.####")&IF($H14="",""," "&$H14),"")&IF(AND(ISNUMBER($P14),$V14>$P14),", por encima del límite superior de "&TEXT($P14,"0.####")&IF($H14="",""," "&$H14),"")&".","")&IF($Y14="",""," "&$Y14&IF(RIGHT($Y14,1)=".","","."))&" Acción recomendada: "&$M14&IF(RIGHT($M14,1)=".","",".")&IF($J14="Bloqueante"," El equipo no se libera hasta resolver este hallazgo.",IF($J14="Cobrable"," Se incluye en la cotización de repuestos y consumibles."," Se deja registrado como observación.")))
A15: 2.1.1 | B15: 2. Identificación y trazabilidad | C15: 2.1 Placas e identificación física | D15: Número de serie del analizador | E15: Legibilidad e integridad del serial del fabricante en la placa posterior metálica | F15: Retirar el equipo del rack lo suficiente para ver el panel trasero, o usar espejo de inspección, y leer la placa metálica de datos HORIBA. Fotografiarla y anotarla en la hoja de campo. | G15: Texto | I15: Debe ser legible y registrarse en la hoja de campo | J15: Alerta | K15: Placa ilegible, o equipo distinto al de la orden de servicio | L15: 2.1.2 | M15: Registrar el serial real, fotografiarlo y corregir la hoja de vida | N15: La placa de identificación del fabricante no es legible o no coincide con el equipo registrado en la orden de servicio. | Q15: Sí | R15: No | T15: MT_829WE09R_APSA370_221102 | U15: Pendiente | W15: =IF($G15<>"Numérico","",IF($V15="","Sin dato",IF(AND(OR(NOT(ISNUMBER($O15)),$V15>=$O15),OR(NOT(ISNUMBER($P15)),$V15<=$P15)),"Dentro de rango","Fuera de rango"))) | Z15: =IF(OR($U15="",$U15="Conforme",$U15="No aplica",$U15="Pendiente"),"",$N15&IF($W15="Fuera de rango"," Valor medido: "&TEXT($V15,"0.####")&IF($H15="",""," "&$H15)&IF(AND(ISNUMBER($O15),$V15<$O15),", por debajo del límite inferior de "&TEXT($O15,"0.####")&IF($H15="",""," "&$H15),"")&IF(AND(ISNUMBER($P15),$V15>$P15),", por encima del límite superior de "&TEXT($P15,"0.####")&IF($H15="",""," "&$H15),"")&".","")&IF($Y15="",""," "&$Y15&IF(RIGHT($Y15,1)=".","","."))&" Acción recomendada: "&$M15&IF(RIGHT($M15,1)=".","",".")&IF($J15="Bloqueante"," El equipo no se libera hasta resolver este hallazgo.",IF($J15="Cobrable"," Se incluye en la cotización de repuestos y consumibles."," Se deja registrado como observación.")))
A16: 2.1.2 | B16: 2. Identificación y trazabilidad | C16: 2.1 Placas e identificación física | D16: Número HGS del analizador | E16: Identificación del número HGS del analizador y del sistema para trazabilidad de repuestos | F16: Buscar el número HGS en la placa del equipo o en la documentación de entrega de fábrica y anotarlo. Es el dato que permite pedir repuestos con la configuración correcta. | G16: Texto | I16: El número HGS debe estar identificado en la placa del equipo o en la documentación de fábrica | J16: Alerta | K16: HGS no documentado: impide pedir repuestos con la configuración correcta | L16: 2.1.1 | M16: Solicitar el HGS a fábrica y registrarlo en la hoja de vida | N16: El número HGS del analizador no está documentado, lo que impide solicitar repuestos con la configuración correcta. | Q16: Sí | R16: No | T16: 1 - LCD design change AP EN | U16: Pendiente | W16: =IF($G16<>"Numérico","",IF($V16="","Sin dato",IF(AND(OR(NOT(ISNUMBER($O16)),$V16>=$O16),OR(NOT(ISNUMBER($P16)),$V16<=$P16)),"Dentro de rango","Fuera de rango"))) | Z16: =IF(OR($U16="",$U16="Conforme",$U16="No aplica",$U16="Pendiente"),"",$N16&IF($W16="Fuera de rango"," Valor medido: "&TEXT($V16,"0.####")&IF($H16="",""," "&$H16)&IF(AND(ISNUMBER($O16),$V16<$O16),", por debajo del límite inferior de "&TEXT($O16,"0.####")&IF($H16="",""," "&$H16),"")&IF(AND(ISNUMBER($P16),$V16>$P16),", por encima del límite superior de "&TEXT($P16,"0.####")&IF($H16="",""," "&$H16),"")&".","")&IF($Y16="",""," "&$Y16&IF(RIGHT($Y16,1)=".","","."))&" Acción recomendada: "&$M16&IF(RIGHT($M16,1)=".","",".")&IF($J16="Bloqueante"," El equipo no se libera hasta resolver este hallazgo.",IF($J16="Cobrable"," Se incluye en la cotización de repuestos y consumibles."," Se deja registrado como observación.")))
A17: 2.2.1 | B17: 2. Identificación y trazabilidad | C17: 2.2 Etiquetas de seguridad | D17: Etiqueta de advertencia de alto voltaje (lámpara) | E17: Presencia y legibilidad de la etiqueta de peligro de choque eléctrico cerca de la lámpara | F17: Con el equipo apagado, desconectado y frío, retirar la cubierta superior y verificar la presencia y legibilidad de la etiqueta de choque eléctrico junto al bloque óptico de la lámpara. | G17: Presente / Ausente | I17: La etiqueta Choque Eléctrico 1 debe estar adherida y legible cerca del bloque óptico | J17: Alerta | K17: Etiqueta desprendida o ilegible | L17: Nodo terminal — actuar directamente | M17: Reponer la etiqueta de seguridad y dejar constancia del faltante | N17: Falta o no es legible la etiqueta de advertencia de riesgo eléctrico junto al bloque óptico. | Q17: Sí | R17: Sí | T17: P-ST-029-MAN MTTO APSA370 V2 | U17: Pendiente | W17: =IF($G17<>"Numérico","",IF($V17="","Sin dato",IF(AND(OR(NOT(ISNUMBER($O17)),$V17>=$O17),OR(NOT(ISNUMBER($P17)),$V17<=$P17)),"Dentro de rango","Fuera de rango"))) | Z17: =IF(OR($U17="",$U17="Conforme",$U17="No aplica",$U17="Pendiente"),"",$N17&IF($W17="Fuera de rango"," Valor medido: "&TEXT($V17,"0.####")&IF($H17="",""," "&$H17)&IF(AND(ISNUMBER($O17),$V17<$O17),", por debajo del límite inferior de "&TEXT($O17,"0.####")&IF($H17="",""," "&$H17),"")&IF(AND(ISNUMBER($P17),$V17>$P17),", por encima del límite superior de "&TEXT($P17,"0.####")&IF($H17="",""," "&$H17),"")&".","")&IF($Y17="",""," "&$Y17&IF(RIGHT($Y17,1)=".","","."))&" Acción recomendada: "&$M17&IF(RIGHT($M17,1)=".","",".")&IF($J17="Bloqueante"," El equipo no se libera hasta resolver este hallazgo.",IF($J17="Cobrable"," Se incluye en la cotización de repuestos y consumibles."," Se deja registrado como observación.")))
A18: 2.2.2 | B18: 2. Identificación y trazabilidad | C18: 2.2 Etiquetas de seguridad | D18: Etiqueta de advertencia de alta temperatura | E18: Etiqueta de peligro de quemadura térmica en componentes que acumulan calor | F18: Con el equipo apagado y frío, retirar la cubierta superior y verificar la presencia de las etiquetas de componente caliente sobre la carcasa de la bomba y del HC Cutter. | G18: Presente / Ausente | I18: La etiqueta de componente caliente debe estar visible en la bomba y en el HC Cutter | J18: Alerta | K18: Etiqueta desprendida por el calor de la bomba o del HC Cutter | L18: Nodo terminal — actuar directamente | M18: Reponer la etiqueta de advertencia térmica | N18: Faltan o no son legibles las etiquetas de advertencia de superficies calientes sobre la bomba y el eliminador de hidrocarburos. | Q18: Sí | R18: Sí | T18: P-ST-029-MAN MTTO APSA370 V2 | U18: Pendiente | W18: =IF($G18<>"Numérico","",IF($V18="","Sin dato",IF(AND(OR(NOT(ISNUMBER($O18)),$V18>=$O18),OR(NOT(ISNUMBER($P18)),$V18<=$P18)),"Dentro de rango","Fuera de rango"))) | Z18: =IF(OR($U18="",$U18="Conforme",$U18="No aplica",$U18="Pendiente"),"",$N18&IF($W18="Fuera de rango"," Valor medido: "&TEXT($V18,"0.####")&IF($H18="",""," "&$H18)&IF(AND(ISNUMBER($O18),$V18<$O18),", por debajo del límite inferior de "&TEXT($O18,"0.####")&IF($H18="",""," "&$H18),"")&IF(AND(ISNUMBER($P18),$V18>$P18),", por encima del límite superior de "&TEXT($P18,"0.####")&IF($H18="",""," "&$H18),"")&".","")&IF($Y18="",""," "&$Y18&IF(RIGHT($Y18,1)=".","","."))&" Acción recomendada: "&$M18&IF(RIGHT($M18,1)=".","",".")&IF($J18="Bloqueante"," El equipo no se libera hasta resolver este hallazgo.",IF($J18="Cobrable"," Se incluye en la cotización de repuestos y consumibles."," Se deja registrado como observación.")))
A19: 3.1.1 | B19: 3. Estado de calibración | C19: 3.1 Coeficientes de calibración | D19: Coeficiente de calibración de cero (ZERO ADJUST) | E19: Coeficiente almacenado en el menú de calibración para el ajuste de cero | F19: Ir a MENU / CAL. y leer el valor del coeficiente ZERO en pantalla. Anotarlo antes de realizar cualquier calibración. | G19: Numérico | H19: counts | I19: Debe encontrarse dentro de los límites de tolerancia lógicos definidos por firmware | J19: Bloqueante | K19: Aire cero contaminado, calentamiento insuficiente, scrubber agotado o fuga neumática | L19: 1.3.1 ; 6.3.2 ; 5.1.5 ; 4.1.3 ; 5.3.1 | M19: Inyectar aire cero de cilindro certificado para descartar el generador; si persiste, seguir la rama de scrubber y fugas | N19: El coeficiente de calibración de cero se encuentra fuera del rango admisible, por lo que la calibración del punto cero no es válida. | O19: -3500 | P19: 3500 | Q19: Sí | R19: No | T19: P-ST-030-MAN OPER APSA 370 V2 | U19: Pendiente | W19: =IF($G19<>"Numérico","",IF($V19="","Sin dato",IF(AND(OR(NOT(ISNUMBER($O19)),$V19>=$O19),OR(NOT(ISNUMBER($P19)),$V19<=$P19)),"Dentro de rango","Fuera de rango"))) | Z19: =IF(OR($U19="",$U19="Conforme",$U19="No aplica",$U19="Pendiente"),"",$N19&IF($W19="Fuera de rango"," Valor medido: "&TEXT($V19,"0.####")&IF($H19="",""," "&$H19)&IF(AND(ISNUMBER($O19),$V19<$O19),", por debajo del límite inferior de "&TEXT($O19,"0.####")&IF($H19="",""," "&$H19),"")&IF(AND(ISNUMBER($P19),$V19>$P19),", por encima del límite superior de "&TEXT($P19,"0.####")&IF($H19="",""," "&$H19),"")&".","")&IF($Y19="",""," "&$Y19&IF(RIGHT($Y19,1)=".","","."))&" Acción recomendada: "&$M19&IF(RIGHT($M19,1)=".","",".")&IF($J19="Bloqueante"," El equipo no se libera hasta resolver este hallazgo.",IF($J19="Cobrable"," Se incluye en la cotización de repuestos y consumibles."," Se deja registrado como observación.")))
A20: 3.1.2 | B20: 3. Estado de calibración | C20: 3.1 Coeficientes de calibración | D20: Coeficiente de calibración de span (SPAN ADJUST) | E20: Coeficiente de ganancia de pendiente almacenado tras la calibración de span | F20: Ir a MENU / CAL. y leer el valor del coeficiente SPAN en pantalla. Anotarlo antes de calibrar y compararlo con el registrado en el servicio anterior. | G20: Numérico | I20: Dentro de la tolerancia de ganancia de software; en campo se ubica típicamente entre 0,9 y 1,3 | J20: Bloqueante | K20: Concentración del patrón mal configurada, lámpara degradada, o electroválvula con fuga | L20: 3.1.3 ; 6.1.1 ; 5.3.2 ; 3.2.1 | M20: Confirmar SPAN CONC. contra el certificado del cilindro y volver a calibrar | N20: El coeficiente de calibración de span se encuentra fuera del rango admisible, por lo que la calibración de sensibilidad no es válida. | O20: 0.5 | P20: 2 | Q20: Sí | R20: No | T20: P-ST-030-MAN OPER APSA 370 V2 | U20: Pendiente | W20: =IF($G20<>"Numérico","",IF($V20="","Sin dato",IF(AND(OR(NOT(ISNUMBER($O20)),$V20>=$O20),OR(NOT(ISNUMBER($P20)),$V20<=$P20)),"Dentro de rango","Fuera de rango"))) | Z20: =IF(OR($U20="",$U20="Conforme",$U20="No aplica",$U20="Pendiente"),"",$N20&IF($W20="Fuera de rango"," Valor medido: "&TEXT($V20,"0.####")&IF($H20="",""," "&$H20)&IF(AND(ISNUMBER($O20),$V20<$O20),", por debajo del límite inferior de "&TEXT($O20,"0.####")&IF($H20="",""," "&$H20),"")&IF(AND(ISNUMBER($P20),$V20>$P20),", por encima del límite superior de "&TEXT($P20,"0.####")&IF($H20="",""," "&$H20),"")&".","")&IF($Y20="",""," "&$Y20&IF(RIGHT($Y20,1)=".","","."))&" Acción recomendada: "&$M20&IF(RIGHT($M20,1)=".","",".")&IF($J20="Bloqueante"," El equipo no se libera hasta resolver este hallazgo.",IF($J20="Cobrable"," Se incluye en la cotización de repuestos y consumibles."," Se deja registrado como observación.")))
A21: 3.1.3 | B21: 3. Estado de calibración | C21: 3.1 Coeficientes de calibración | D21: Concentración de gas de span configurada (SPAN CONC) | E21: Ajuste de la concentración de gas patrón en la pantalla de edición de span | F21: Ir a MENU / CAL. / SPAN CONC. y leer el valor configurado. Contrastarlo contra el certificado del cilindro de gas patrón que se va a utilizar. | G21: Numérico | H21: ppm | I21: Debe configurarse el valor nominal exacto del cilindro de gas patrón de SO2 a utilizar | J21: Bloqueante | K21: Valor no coincide con el certificado del cilindro en uso | L21: 3.1.2 | M21: Corregir el valor en el menú y repetir la calibración de span | N21: La concentración de gas patrón configurada en el analizador no coincide con la del cilindro certificado en uso. | O21: 1e-05 | P21: 99999 | Q21: Sí | R21: No | T21: P-ST-030-MAN OPER APSA 370 V2 | U21: Pendiente | W21: =IF($G21<>"Numérico","",IF($V21="","Sin dato",IF(AND(OR(NOT(ISNUMBER($O21)),$V21>=$O21),OR(NOT(ISNUMBER($P21)),$V21<=$P21)),"Dentro de rango","Fuera de rango"))) | Z21: =IF(OR($U21="",$U21="Conforme",$U21="No aplica",$U21="Pendiente"),"",$N21&IF($W21="Fuera de rango"," Valor medido: "&TEXT($V21,"0.####")&IF($H21="",""," "&$H21)&IF(AND(ISNUMBER($O21),$V21<$O21),", por debajo del límite inferior de "&TEXT($O21,"0.####")&IF($H21="",""," "&$H21),"")&IF(AND(ISNUMBER($P21),$V21>$P21),", por encima del límite superior de "&TEXT($P21,"0.####")&IF($H21="",""," "&$H21),"")&".","")&IF($Y21="",""," "&$Y21&IF(RIGHT($Y21,1)=".","","."))&" Acción recomendada: "&$M21&IF(RIGHT($M21,1)=".","",".")&IF($J21="Bloqueante"," El equipo no se libera hasta resolver este hallazgo.",IF($J21="Cobrable"," Se incluye en la cotización de repuestos y consumibles."," Se deja registrado como observación.")))
A22: 3.2.1 | B22: 3. Estado de calibración | C22: 3.2 Suministro de gases patrón | D22: Presión del gas en el puerto posterior de calibración | E22: Estabilidad de la presión de suministro en la entrada de gas de calibración | F22: Conectar un manómetro de baja presión en la línea de gas de calibración, aguas arriba del puerto CAL GAS INLET, y leer la presión con el gas fluyendo. | G22: Numérico | H22: Pa | I22: La presión del gas de calibración debe mantenerse regulada para asegurar estabilidad neumática | J22: Bloqueante | K22: Regulador del cilindro mal ajustado o cilindro despresurizado | L22: 3.1.2 | M22: Reajustar el regulador de doble etapa y repetir la calibración | N22: La presión de entrega del gas de calibración no es estable, lo que compromete la validez de la calibración. | O22: -500 | P22: 500 | Q22: Sí | R22: No | T22: P-ST-030-MAN OPER APSA 370 V2 | U22: Pendiente | W22: =IF($G22<>"Numérico","",IF($V22="","Sin dato",IF(AND(OR(NOT(ISNUMBER($O22)),$V22>=$O22),OR(NOT(ISNUMBER($P22)),$V22<=$P22)),"Dentro de rango","Fuera de rango"))) | Z22: =IF(OR($U22="",$U22="Conforme",$U22="No aplica",$U22="Pendiente"),"",$N22&IF($W22="Fuera de rango"," Valor medido: "&TEXT($V22,"0.####")&IF($H22="",""," "&$H22)&IF(AND(ISNUMBER($O22),$V22<$O22),", por debajo del límite inferior de "&TEXT($O22,"0.####")&IF($H22="",""," "&$H22),"")&IF(AND(ISNUMBER($P22),$V22>$P22),", por encima del límite superior de "&TEXT($P22,"0.####")&IF($H22="",""," "&$H22),"")&".","")&IF($Y22="",""," "&$Y22&IF(RIGHT($Y22,1)=".","","."))&" Acción recomendada: "&$M22&IF(RIGHT($M22,1)=".","",".")&IF($J22="Bloqueante"," El equipo no se libera hasta resolver este hallazgo.",IF($J22="Cobrable"," Se incluye en la cotización de repuestos y consumibles."," Se deja registrado como observación.")))
A23: 3.3.1 | B23: 3. Estado de calibración | C23: 3.3 Secuencia de autocalibración (AIC) | D23: Tiempo de espera para estabilización en AIC (WAIT) | E23: Tiempo de estabilización tras la conmutación de líneas de gas en calibración automática | F23: Ir a MENU / MAINTENANCE / AIC y leer el tiempo WAIT configurado. Anotarlo y verificar que dé margen suficiente de purga para la línea instalada. | G23: Numérico | H23: minutos | I23: Ajuste de tiempo para garantizar purga y estabilización completa de las lecturas | J23: Alerta | K23: Tiempo insuficiente para purgar la línea de calibración | L23: Nodo terminal — actuar directamente | M23: Subir el WAIT a 20 min o más, según la longitud de la línea instalada | N23: El tiempo de espera de la secuencia de autocalibración es insuficiente para purgar la línea antes de tomar la lectura. | O23: 20 | P23: 999 | Q23: Sí | R23: No | T23: P-ST-030-MAN OPER APSA 370 V2 | U23: Pendiente | W23: =IF($G23<>"Numérico","",IF($V23="","Sin dato",IF(AND(OR(NOT(ISNUMBER($O23)),$V23>=$O23),OR(NOT(ISNUMBER($P23)),$V23<=$P23)),"Dentro de rango","Fuera de rango"))) | Z23: =IF(OR($U23="",$U23="Conforme",$U23="No aplica",$U23="Pendiente"),"",$N23&IF($W23="Fuera de rango"," Valor medido: "&TEXT($V23,"0.####")&IF($H23="",""," "&$H23)&IF(AND(ISNUMBER($O23),$V23<$O23),", por debajo del límite inferior de "&TEXT($O23,"0.####")&IF($H23="",""," "&$H23),"")&IF(AND(ISNUMBER($P23),$V23>$P23),", por encima del límite superior de "&TEXT($P23,"0.####")&IF($H23="",""," "&$H23),"")&".","")&IF($Y23="",""," "&$Y23&IF(RIGHT($Y23,1)=".","","."))&" Acción recomendada: "&$M23&IF(RIGHT($M23,1)=".","",".")&IF($J23="Bloqueante"," El equipo no se libera hasta resolver este hallazgo.",IF($J23="Cobrable"," Se incluye en la cotización de repuestos y consumibles."," Se deja registrado como observación.")))
A24: 3.3.2 | B24: 3. Estado de calibración | C24: 3.3 Secuencia de autocalibración (AIC) | D24: Tiempo de retención en AIC (HOLD) | E24: Tiempo de validación para registrar y verificar lecturas tras volver a MEAS | F24: Ir a MENU / MAINTENANCE / AIC y leer el tiempo HOLD configurado. Anotarlo junto con el resto de parámetros de la secuencia. | G24: Numérico | H24: minutos | I24: Tiempo configurado para la verificación posterior a la calibración | J24: Alerta | K24: Parámetro distinto al acordado con la red de monitoreo | L24: Nodo terminal — actuar directamente | M24: Ajustar el HOLD al valor definido por el operador de la red | N24: El tiempo de sostenimiento de la secuencia de autocalibración no corresponde al definido para la red de monitoreo. | O24: 0 | P24: 999 | Q24: Sí | R24: No | T24: P-ST-030-MAN OPER APSA 370 V2 | U24: Pendiente | W24: =IF($G24<>"Numérico","",IF($V24="","Sin dato",IF(AND(OR(NOT(ISNUMBER($O24)),$V24>=$O24),OR(NOT(ISNUMBER($P24)),$V24<=$P24)),"Dentro de rango","Fuera de rango"))) | Z24: =IF(OR($U24="",$U24="Conforme",$U24="No aplica",$U24="Pendiente"),"",$N24&IF($W24="Fuera de rango"," Valor medido: "&TEXT($V24,"0.####")&IF($H24="",""," "&$H24)&IF(AND(ISNUMBER($O24),$V24<$O24),", por debajo del límite inferior de "&TEXT($O24,"0.####")&IF($H24="",""," "&$H24),"")&IF(AND(ISNUMBER($P24),$V24>$P24),", por encima del límite superior de "&TEXT($P24,"0.####")&IF($H24="",""," "&$H24),"")&".","")&IF($Y24="",""," "&$Y24&IF(RIGHT($Y24,1)=".","","."))&" Acción recomendada: "&$M24&IF(RIGHT($M24,1)=".","",".")&IF($J24="Bloqueante"," El equipo no se libera hasta resolver este hallazgo.",IF($J24="Cobrable"," Se incluye en la cotización de repuestos y consumibles."," Se deja registrado como observación.")))
A25: 3.3.3 | B25: 3. Estado de calibración | C25: 3.3 Secuencia de autocalibración (AIC) | D25: Habilitación de calibración en AIC (CAL YES/NO) | E25: Especificación de si se permite actualizar los coeficientes tras el AIC | F25: Ir a MENU / MAINTENANCE / AIC y leer el ajuste CAL (YES / NO). Confirmar con el responsable de la red si la política es corregir factores o solo verificar. | G25: Sí/No | I25: YES actualiza automáticamente los coeficientes; NO solo calcula las derivas sin alterarlos | J25: Alerta | K25: Ajuste incoherente con la política de la red | L25: Nodo terminal — actuar directamente | M25: Definirlo con el responsable de la red y dejarlo documentado | N25: La opción de corrección automática de la secuencia de autocalibración no corresponde a la política definida para la estación. | Q25: Sí | R25: No | T25: P-ST-030-MAN OPER APSA 370 V2 | U25: Pendiente | W25: =IF($G25<>"Numérico","",IF($V25="","Sin dato",IF(AND(OR(NOT(ISNUMBER($O25)),$V25>=$O25),OR(NOT(ISNUMBER($P25)),$V25<=$P25)),"Dentro de rango","Fuera de rango"))) | Z25: =IF(OR($U25="",$U25="Conforme",$U25="No aplica",$U25="Pendiente"),"",$N25&IF($W25="Fuera de rango"," Valor medido: "&TEXT($V25,"0.####")&IF($H25="",""," "&$H25)&IF(AND(ISNUMBER($O25),$V25<$O25),", por debajo del límite inferior de "&TEXT($O25,"0.####")&IF($H25="",""," "&$H25),"")&IF(AND(ISNUMBER($P25),$V25>$P25),", por encima del límite superior de "&TEXT($P25,"0.####")&IF($H25="",""," "&$H25),"")&".","")&IF($Y25="",""," "&$Y25&IF(RIGHT($Y25,1)=".","","."))&" Acción recomendada: "&$M25&IF(RIGHT($M25,1)=".","",".")&IF($J25="Bloqueante"," El equipo no se libera hasta resolver este hallazgo.",IF($J25="Cobrable"," Se incluye en la cotización de repuestos y consumibles."," Se deja registrado como observación.")))
A26: 3.4.1 | B26: 3. Estado de calibración | C26: 3.4 Deriva de cero (Zero Drift) | D26: Deriva diaria de cero en rangos bajos (rango menor o igual a 0,2 ppm) | E26: Deriva diaria de cero máxima permitida en rangos menores o iguales a 0,2 ppm | F26: Introducir gas cero y dejar estabilizar; anotar la lectura, repetir la medición 24 h después en las mismas condiciones y calcular la diferencia. | G26: Numérico | H26: ppb/día | I26: Desviación máxima diaria de la lectura del cero en rangos bajos | J26: Bloqueante | K26: Scrubber de referencia agotado, microfuga, o inestabilidad térmica de la sala | L26: 6.3.2 ; 5.1.5 ; 10.1.1 | M26: Corregir la causa antes de recalibrar; recalibrar sin corregir solo enmascara la deriva | N26: La deriva diaria del punto cero en rangos bajos supera la tolerancia especificada por el fabricante. | O26: -1 | P26: 1 | Q26: Sí | R26: No | T26: P-ST-030-MAN OPER APSA 370 V2 | U26: Pendiente | W26: =IF($G26<>"Numérico","",IF($V26="","Sin dato",IF(AND(OR(NOT(ISNUMBER($O26)),$V26>=$O26),OR(NOT(ISNUMBER($P26)),$V26<=$P26)),"Dentro de rango","Fuera de rango"))) | Z26: =IF(OR($U26="",$U26="Conforme",$U26="No aplica",$U26="Pendiente"),"",$N26&IF($W26="Fuera de rango"," Valor medido: "&TEXT($V26,"0.####")&IF($H26="",""," "&$H26)&IF(AND(ISNUMBER($O26),$V26<$O26),", por debajo del límite inferior de "&TEXT($O26,"0.####")&IF($H26="",""," "&$H26),"")&IF(AND(ISNUMBER($P26),$V26>$P26),", por encima del límite superior de "&TEXT($P26,"0.####")&IF($H26="",""," "&$H26),"")&".","")&IF($Y26="",""," "&$Y26&IF(RIGHT($Y26,1)=".","","."))&" Acción recomendada: "&$M26&IF(RIGHT($M26,1)=".","",".")&IF($J26="Bloqueante"," El equipo no se libera hasta resolver este hallazgo.",IF($J26="Cobrable"," Se incluye en la cotización de repuestos y consumibles."," Se deja registrado como observación.")))
A27: 3.4.2 | B27: 3. Estado de calibración | C27: 3.4 Deriva de cero (Zero Drift) | D27: Deriva semanal de cero en rangos bajos (rango menor o igual a 0,2 ppm) | E27: Deriva semanal de cero máxima permitida en rangos menores o iguales a 0,2 ppm | F27: Introducir gas cero y anotar la lectura; repetir la medición una semana después en las mismas condiciones y calcular la diferencia. | G27: Numérico | H27: ppb/semana | I27: Desviación máxima semanal de la lectura del cero en rangos bajos | J27: Bloqueante | K27: Degradación progresiva del scrubber o del HC Cutter | L27: 6.3.2 ; 6.3.1 ; 8.1.2 | M27: Reemplazar el consumible agotado y repetir el seguimiento semanal | N27: La deriva semanal del punto cero en rangos bajos supera la tolerancia especificada por el fabricante. | O27: -1 | P27: 1 | Q27: Sí | R27: No | T27: P-ST-030-MAN OPER APSA 370 V2 | U27: Pendiente | W27: =IF($G27<>"Numérico","",IF($V27="","Sin dato",IF(AND(OR(NOT(ISNUMBER($O27)),$V27>=$O27),OR(NOT(ISNUMBER($P27)),$V27<=$P27)),"Dentro de rango","Fuera de rango"))) | Z27: =IF(OR($U27="",$U27="Conforme",$U27="No aplica",$U27="Pendiente"),"",$N27&IF($W27="Fuera de rango"," Valor medido: "&TEXT($V27,"0.####")&IF($H27="",""," "&$H27)&IF(AND(ISNUMBER($O27),$V27<$O27),", por debajo del límite inferior de "&TEXT($O27,"0.####")&IF($H27="",""," "&$H27),"")&IF(AND(ISNUMBER($P27),$V27>$P27),", por encima del límite superior de "&TEXT($P27,"0.####")&IF($H27="",""," "&$H27),"")&".","")&IF($Y27="",""," "&$Y27&IF(RIGHT($Y27,1)=".","","."))&" Acción recomendada: "&$M27&IF(RIGHT($M27,1)=".","",".")&IF($J27="Bloqueante"," El equipo no se libera hasta resolver este hallazgo.",IF($J27="Cobrable"," Se incluye en la cotización de repuestos y consumibles."," Se deja registrado como observación.")))
A28: 3.4.3 | B28: 3. Estado de calibración | C28: 3.4 Deriva de cero (Zero Drift) | D28: Deriva diaria de cero en rangos altos (rango mayor a 0,2 ppm) | E28: Deriva diaria de cero máxima permitida en rangos superiores a 0,2 ppm | F28: Introducir gas cero en el rango alto de trabajo y anotar la lectura; repetir 24 h después y expresar la diferencia como porcentaje del fondo de escala. | G28: Numérico | H28: % F.S. | I28: Desviación máxima diaria del cero respecto al fondo de escala, en rangos altos | J28: Bloqueante | K28: Fuga neumática o contaminación del aire cero | L28: 5.1.5 ; 4.3.1 ; 6.3.2 | M28: Ubicar la fuga o cambiar el aire cero y repetir la medición a 24 h | N28: La deriva diaria del punto cero en rangos altos supera la tolerancia especificada por el fabricante. | O28: -1 | P28: 1 | Q28: Sí | R28: No | T28: P-ST-030-MAN OPER APSA 370 V2 | U28: Pendiente | W28: =IF($G28<>"Numérico","",IF($V28="","Sin dato",IF(AND(OR(NOT(ISNUMBER($O28)),$V28>=$O28),OR(NOT(ISNUMBER($P28)),$V28<=$P28)),"Dentro de rango","Fuera de rango"))) | Z28: =IF(OR($U28="",$U28="Conforme",$U28="No aplica",$U28="Pendiente"),"",$N28&IF($W28="Fuera de rango"," Valor medido: "&TEXT($V28,"0.####")&IF($H28="",""," "&$H28)&IF(AND(ISNUMBER($O28),$V28<$O28),", por debajo del límite inferior de "&TEXT($O28,"0.####")&IF($H28="",""," "&$H28),"")&IF(AND(ISNUMBER($P28),$V28>$P28),", por encima del límite superior de "&TEXT($P28,"0.####")&IF($H28="",""," "&$H28),"")&".","")&IF($Y28="",""," "&$Y28&IF(RIGHT($Y28,1)=".","","."))&" Acción recomendada: "&$M28&IF(RIGHT($M28,1)=".","",".")&IF($J28="Bloqueante"," El equipo no se libera hasta resolver este hallazgo.",IF($J28="Cobrable"," Se incluye en la cotización de repuestos y consumibles."," Se deja registrado como observación.")))
A29: 3.4.4 | B29: 3. Estado de calibración | C29: 3.4 Deriva de cero (Zero Drift) | D29: Deriva semanal de cero en rangos altos (rango mayor a 0,2 ppm) | E29: Deriva semanal de cero máxima permitida en rangos superiores a 0,2 ppm | F29: Introducir gas cero en el rango alto de trabajo y anotar la lectura; repetir una semana después y expresar la diferencia como porcentaje del fondo de escala. | G29: Numérico | H29: % F.S. | I29: Desviación máxima semanal del cero respecto al fondo de escala, en rangos altos | J29: Bloqueante | K29: Degradación de consumibles de referencia o del sellado neumático | L29: 6.3.2 ; 5.1.5 | M29: Reemplazar los consumibles vencidos y repetir el seguimiento semanal | N29: La deriva semanal del punto cero en rangos altos supera la tolerancia especificada por el fabricante. | O29: -2 | P29: 2 | Q29: Sí | R29: No | T29: P-ST-030-MAN OPER APSA 370 V2 | U29: Pendiente | W29: =IF($G29<>"Numérico","",IF($V29="","Sin dato",IF(AND(OR(NOT(ISNUMBER($O29)),$V29>=$O29),OR(NOT(ISNUMBER($P29)),$V29<=$P29)),"Dentro de rango","Fuera de rango"))) | Z29: =IF(OR($U29="",$U29="Conforme",$U29="No aplica",$U29="Pendiente"),"",$N29&IF($W29="Fuera de rango"," Valor medido: "&TEXT($V29,"0.####")&IF($H29="",""," "&$H29)&IF(AND(ISNUMBER($O29),$V29<$O29),", por debajo del límite inferior de "&TEXT($O29,"0.####")&IF($H29="",""," "&$H29),"")&IF(AND(ISNUMBER($P29),$V29>$P29),", por encima del límite superior de "&TEXT($P29,"0.####")&IF($H29="",""," "&$H29),"")&".","")&IF($Y29="",""," "&$Y29&IF(RIGHT($Y29,1)=".","","."))&" Acción recomendada: "&$M29&IF(RIGHT($M29,1)=".","",".")&IF($J29="Bloqueante"," El equipo no se libera hasta resolver este hallazgo.",IF($J29="Cobrable"," Se incluye en la cotización de repuestos y consumibles."," Se deja registrado como observación.")))
A30: 3.5.1 | B30: 3. Estado de calibración | C30: 3.5 Deriva de span (Span Drift) | D30: Deriva diaria de span (todos los rangos) | E30: Deriva diaria de span máxima permitida con variación térmica dentro de 5 °C | F30: Introducir gas patrón de span y anotar la lectura estabilizada; repetir 24 h después con el mismo cilindro y expresar la diferencia como porcentaje del fondo de escala. | G30: Numérico | H30: % F.S. | I30: Desviación diaria máxima tolerada de la lectura de span | J30: Bloqueante | K30: Pérdida de intensidad de la lámpara, óptica sucia, o caudal inestable | L30: 6.1.1 ; 6.2.4 ; 5.1.1 | M30: Recorrer la rama óptica y neumática antes de reajustar el span | N30: La deriva diaria del punto de span supera la tolerancia especificada por el fabricante. | O30: -1 | P30: 1 | Q30: Sí | R30: No | T30: P-ST-030-MAN OPER APSA 370 V2 | U30: Pendiente | W30: =IF($G30<>"Numérico","",IF($V30="","Sin dato",IF(AND(OR(NOT(ISNUMBER($O30)),$V30>=$O30),OR(NOT(ISNUMBER($P30)),$V30<=$P30)),"Dentro de rango","Fuera de rango"))) | Z30: =IF(OR($U30="",$U30="Conforme",$U30="No aplica",$U30="Pendiente"),"",$N30&IF($W30="Fuera de rango"," Valor medido: "&TEXT($V30,"0.####")&IF($H30="",""," "&$H30)&IF(AND(ISNUMBER($O30),$V30<$O30),", por debajo del límite inferior de "&TEXT($O30,"0.####")&IF($H30="",""," "&$H30),"")&IF(AND(ISNUMBER($P30),$V30>$P30),", por encima del límite superior de "&TEXT($P30,"0.####")&IF($H30="",""," "&$H30),"")&".","")&IF($Y30="",""," "&$Y30&IF(RIGHT($Y30,1)=".","","."))&" Acción recomendada: "&$M30&IF(RIGHT($M30,1)=".","",".")&IF($J30="Bloqueante"," El equipo no se libera hasta resolver este hallazgo.",IF($J30="Cobrable"," Se incluye en la cotización de repuestos y consumibles."," Se deja registrado como observación.")))
A31: 3.5.2 | B31: 3. Estado de calibración | C31: 3.5 Deriva de span (Span Drift) | D31: Deriva semanal de span (todos los rangos) | E31: Deriva semanal de span máxima permitida con variación térmica dentro de 5 °C | F31: Introducir gas patrón de span y anotar la lectura estabilizada; repetir una semana después con el mismo cilindro y expresar la diferencia como porcentaje del fondo de escala. | G31: Numérico | H31: % F.S. | I31: Desviación semanal máxima tolerada de la lectura de span | J31: Bloqueante | K31: Envejecimiento de la lámpara de xenón o ensuciamiento progresivo de la óptica | L31: 8.1.5 ; 6.1.1 ; 6.2.5 | M31: Programar el cambio de lámpara y la limpieza óptica | N31: La deriva semanal del punto de span supera la tolerancia especificada por el fabricante. | O31: -2 | P31: 2 | Q31: Sí | R31: No | T31: P-ST-030-MAN OPER APSA 370 V2 | U31: Pendiente | W31: =IF($G31<>"Numérico","",IF($V31="","Sin dato",IF(AND(OR(NOT(ISNUMBER($O31)),$V31>=$O31),OR(NOT(ISNUMBER($P31)),$V31<=$P31)),"Dentro de rango","Fuera de rango"))) | Z31: =IF(OR($U31="",$U31="Conforme",$U31="No aplica",$U31="Pendiente"),"",$N31&IF($W31="Fuera de rango"," Valor medido: "&TEXT($V31,"0.####")&IF($H31="",""," "&$H31)&IF(AND(ISNUMBER($O31),$V31<$O31),", por debajo del límite inferior de "&TEXT($O31,"0.####")&IF($H31="",""," "&$H31),"")&IF(AND(ISNUMBER($P31),$V31>$P31),", por encima del límite superior de "&TEXT($P31,"0.####")&IF($H31="",""," "&$H31),"")&".","")&IF($Y31="",""," "&$Y31&IF(RIGHT($Y31,1)=".","","."))&" Acción recomendada: "&$M31&IF(RIGHT($M31,1)=".","",".")&IF($J31="Bloqueante"," El equipo no se libera hasta resolver este hallazgo.",IF($J31="Cobrable"," Se incluye en la cotización de repuestos y consumibles."," Se deja registrado como observación.")))
A32: 3.6.1 | B32: 3. Estado de calibración | C32: 3.6 Linealidad | D32: Criterio de linealidad de calibración (diferencia de mejor ajuste) | E32: Desviación máxima de cada punto de una calibración multipunto respecto a la recta de regresión | F32: Realizar una calibración multipunto con dilutor, ajustar la recta de regresión y calcular para cada punto la diferencia respecto a la línea de mejor ajuste, en porcentaje del fondo de escala. | G32: Numérico | H32: % F.S. | I32: Diferencia máxima respecto a la línea de mejor ajuste, conforme a la normativa de calibración | J32: Bloqueante | K32: Dilutor descalibrado, fuga en la línea de calibración, o no linealidad del detector | L32: 3.2.1 ; 5.1.5 ; 6.2.6 | M32: Verificar el dilutor con patrón externo antes de atribuir la no linealidad al equipo | N32: La calibración multipunto presenta una desviación respecto a la recta de mejor ajuste superior a la tolerancia admisible. | O32: -2 | P32: 2 | Q32: Sí | R32: No | T32: P-ST-030-MAN OPER APSA 370 V2 | U32: Pendiente | W32: =IF($G32<>"Numérico","",IF($V32="","Sin dato",IF(AND(OR(NOT(ISNUMBER($O32)),$V32>=$O32),OR(NOT(ISNUMBER($P32)),$V32<=$P32)),"Dentro de rango","Fuera de rango"))) | Z32: =IF(OR($U32="",$U32="Conforme",$U32="No aplica",$U32="Pendiente"),"",$N32&IF($W32="Fuera de rango"," Valor medido: "&TEXT($V32,"0.####")&IF($H32="",""," "&$H32)&IF(AND(ISNUMBER($O32),$V32<$O32),", por debajo del límite inferior de "&TEXT($O32,"0.####")&IF($H32="",""," "&$H32),"")&IF(AND(ISNUMBER($P32),$V32>$P32),", por encima del límite superior de "&TEXT($P32,"0.####")&IF($H32="",""," "&$H32),"")&".","")&IF($Y32="",""," "&$Y32&IF(RIGHT($Y32,1)=".","","."))&" Acción recomendada: "&$M32&IF(RIGHT($M32,1)=".","",".")&IF($J32="Bloqueante"," El equipo no se libera hasta resolver este hallazgo.",IF($J32="Cobrable"," Se incluye en la cotización de repuestos y consumibles."," Se deja registrado como observación.")))
A33: 4.1.1 | B33: 4. Línea de muestreo y acondicionamiento | C33: 4.1 Portafiltros frontal | D33: Estado del elemento filtrante PA-10L | E33: Grado de saturación y oscurecimiento del filtro de teflón de 54 mm del panel frontal | F33: Abrir la puerta frontal, desenroscar el vaso del portafiltros, extraer el elemento y compararlo contra un filtro nuevo sobre fondo blanco. Fotografiar antes de reemplazar. | G33: OK / No OK | I33: Debe verse limpio, sin hollín ni decoloración marrón; reemplazar cada 2 semanas | J33: Cobrable | K33: Filtro saturado de material particulado, hollín o humedad | L33: 5.1.2 ; 5.1.1 ; 8.1.1 | M33: Reemplazar el elemento filtrante y reiniciar su horómetro | N33: El filtro de partículas se encuentra colmatado, lo que restringe el caudal de muestra. | Q33: Sí | R33: Sí | S33: Filter Element PA-10L diámetro 54*0.5t (24pc/set) (3200043947; alt. 3200043947-1PC) | T33: P-ST-029-MAN MTTO APSA370 V2 | U33: Pendiente | W33: =IF($G33<>"Numérico","",IF($V33="","Sin dato",IF(AND(OR(NOT(ISNUMBER($O33)),$V33>=$O33),OR(NOT(ISNUMBER($P33)),$V33<=$P33)),"Dentro de rango","Fuera de rango"))) | Z33: =IF(OR($U33="",$U33="Conforme",$U33="No aplica",$U33="Pendiente"),"",$N33&IF($W33="Fuera de rango"," Valor medido: "&TEXT($V33,"0.####")&IF($H33="",""," "&$H33)&IF(AND(ISNUMBER($O33),$V33<$O33),", por debajo del límite inferior de "&TEXT($O33,"0.####")&IF($H33="",""," "&$H33),"")&IF(AND(ISNUMBER($P33),$V33>$P33),", por encima del límite superior de "&TEXT($P33,"0.####")&IF($H33="",""," "&$H33),"")&".","")&IF($Y33="",""," "&$Y33&IF(RIGHT($Y33,1)=".","","."))&" Acción recomendada: "&$M33&IF(RIGHT($M33,1)=".","",".")&IF($J33="Bloqueante"," El equipo no se libera hasta resolver este hallazgo.",IF($J33="Cobrable"," Se incluye en la cotización de repuestos y consumibles."," Se deja registrado como observación.")))
A34: 4.1.2 | B34: 4. Línea de muestreo y acondicionamiento | C34: 4.1 Portafiltros frontal | D34: Junta tórica del portafiltros (O-Ring) | E34: Elasticidad y sellado del O-ring de la tapa del portafiltros frontal | F34: Retirar la junta tórica de la tapa del portafiltros, limpiarla y examinarla estirándola suavemente contra la luz, buscando microfisuras, resequedad o aplastamiento permanente. | G34: OK / No OK | I34: Sin resequedad, fisuras ni deformación por aplastamiento; reemplazar cada 1 año | J34: Cobrable | K34: Junta reseca o aplastada: fuga en la tapa del portafiltros | L34: 5.1.5 | M34: Reemplazar la junta tórica y repetir la prueba de hermeticidad | N34: La junta tórica de la tapa del portafiltros presenta resequedad, fisuras o aplastamiento y no garantiza la hermeticidad. | Q34: Sí | R34: Sí | S34: O-Ring 160ﾟC12H drawing vacuum APSA / APOA (3014059499) | T34: P-ST-029-MAN MTTO APSA370 V2 | U34: Pendiente | W34: =IF($G34<>"Numérico","",IF($V34="","Sin dato",IF(AND(OR(NOT(ISNUMBER($O34)),$V34>=$O34),OR(NOT(ISNUMBER($P34)),$V34<=$P34)),"Dentro de rango","Fuera de rango"))) | Z34: =IF(OR($U34="",$U34="Conforme",$U34="No aplica",$U34="Pendiente"),"",$N34&IF($W34="Fuera de rango"," Valor medido: "&TEXT($V34,"0.####")&IF($H34="",""," "&$H34)&IF(AND(ISNUMBER($O34),$V34<$O34),", por debajo del límite inferior de "&TEXT($O34,"0.####")&IF($H34="",""," "&$H34),"")&IF(AND(ISNUMBER($P34),$V34>$P34),", por encima del límite superior de "&TEXT($P34,"0.####")&IF($H34="",""," "&$H34),"")&".","")&IF($Y34="",""," "&$Y34&IF(RIGHT($Y34,1)=".","","."))&" Acción recomendada: "&$M34&IF(RIGHT($M34,1)=".","",".")&IF($J34="Bloqueante"," El equipo no se libera hasta resolver este hallazgo.",IF($J34="Cobrable"," Se incluye en la cotización de repuestos y consumibles."," Se deja registrado como observación.")))
A35: 4.1.3 | B35: 4. Línea de muestreo y acondicionamiento | C35: 4.1 Portafiltros frontal | D35: Humedad en el portafiltros | E35: Presencia de condensación de agua líquida en la caja del portafiltros frontal | F35: Con el portafiltros abierto, pasar un paño limpio por el interior del vaso y verificar si sale húmedo. Revisar también la manguera aguas arriba en busca de gotas. | G35: Sí/No | I35: Debe estar completamente seco; la presencia de agua indica falla en trampas de condensado previas | J35: Bloqueante | K35: Ingreso de agua por la sonda, o condensación por oscilación térmica del shelter | L35: 4.2.1 ; 4.2.2 ; 10.1.1 ; 5.1.3 | M35: Apagar la bomba, secar y purgar el circuito con aire seco, y corregir el origen del agua antes de volver a medir | N35: Se encontró agua condensada en el portafiltros, con riesgo de daño del sistema óptico y de la bomba. | Q35: Sí | R35: No | T35: MT_B8RUT7HE_APSA370_20111702 | U35: Pendiente | W35: =IF($G35<>"Numérico","",IF($V35="","Sin dato",IF(AND(OR(NOT(ISNUMBER($O35)),$V35>=$O35),OR(NOT(ISNUMBER($P35)),$V35<=$P35)),"Dentro de rango","Fuera de rango"))) | Z35: =IF(OR($U35="",$U35="Conforme",$U35="No aplica",$U35="Pendiente"),"",$N35&IF($W35="Fuera de rango"," Valor medido: "&TEXT($V35,"0.####")&IF($H35="",""," "&$H35)&IF(AND(ISNUMBER($O35),$V35<$O35),", por debajo del límite inferior de "&TEXT($O35,"0.####")&IF($H35="",""," "&$H35),"")&IF(AND(ISNUMBER($P35),$V35>$P35),", por encima del límite superior de "&TEXT($P35,"0.####")&IF($H35="",""," "&$H35),"")&".","")&IF($Y35="",""," "&$Y35&IF(RIGHT($Y35,1)=".","","."))&" Acción recomendada: "&$M35&IF(RIGHT($M35,1)=".","",".")&IF($J35="Bloqueante"," El equipo no se libera hasta resolver este hallazgo.",IF($J35="Cobrable"," Se incluye en la cotización de repuestos y consumibles."," Se deja registrado como observación.")))
A36: 4.2.1 | B36: 4. Línea de muestreo y acondicionamiento | C36: 4.2 Sonda y líneas de muestreo | D36: Integridad de la línea de teflón | E36: Estrangulamientos, fisuras o fugas físicas en la tubería de muestreo | F36: Recorrer la línea de muestreo desde la sonda hasta el equipo buscando dobleces agudos, aplastamientos, empalmes improvisados o tramos vencidos. Verificar el apriete de cada racor. | G36: OK / No OK | I36: Tubería de teflón de 6 mm OD libre de dobleces agudos y bien ajustada | J36: Cobrable | K36: Manguera doblada, fisurada o con empalmes improvisados | L36: 5.1.1 ; 4.1.3 | M36: Reemplazar el tramo afectado y rehacer la conexión | N36: La línea de muestreo presenta dobleces, fisuras o empalmes que comprometen la integridad de la muestra. | Q36: Sí | R36: Sí | T36: P-ST-030-MAN OPER APSA 370 V2 | U36: Pendiente | W36: =IF($G36<>"Numérico","",IF($V36="","Sin dato",IF(AND(OR(NOT(ISNUMBER($O36)),$V36>=$O36),OR(NOT(ISNUMBER($P36)),$V36<=$P36)),"Dentro de rango","Fuera de rango"))) | Z36: =IF(OR($U36="",$U36="Conforme",$U36="No aplica",$U36="Pendiente"),"",$N36&IF($W36="Fuera de rango"," Valor medido: "&TEXT($V36,"0.####")&IF($H36="",""," "&$H36)&IF(AND(ISNUMBER($O36),$V36<$O36),", por debajo del límite inferior de "&TEXT($O36,"0.####")&IF($H36="",""," "&$H36),"")&IF(AND(ISNUMBER($P36),$V36>$P36),", por encima del límite superior de "&TEXT($P36,"0.####")&IF($H36="",""," "&$H36),"")&".","")&IF($Y36="",""," "&$Y36&IF(RIGHT($Y36,1)=".","","."))&" Acción recomendada: "&$M36&IF(RIGHT($M36,1)=".","",".")&IF($J36="Bloqueante"," El equipo no se libera hasta resolver este hallazgo.",IF($J36="Cobrable"," Se incluye en la cotización de repuestos y consumibles."," Se deja registrado como observación.")))
