Workbook

Sheet Instrucciones
A1: Desk 2.0 — Plan de fases y tandas de desarrollo · Revisión Man on the Loop (R01.1, 07/09/2026)
A3: Qué es este libro
A4: Propuesta de troceo del desarrollo de Desk 2.0 con Claude Code (Spec-Driven Development sobre Gentle-AI + Engram), derivada del Documento Maestro R08.1 y del acta del 03/09/2026. Acompaña al documento «Desk2.0_Plan_Fases_y_Tandas_ClaudeCode_R01». El objetivo de este libro es que Gerencia y el equipo técnico revisen si cada fase, épica y tanda tiene sentido para Ambientalia antes de arrancar.
A6: Cómo revisarlo
A7: 1. Hoja «Fases»: lea el orden y el alcance de las seis fases. Anote en las columnas amarillas.
A8: 2. Hoja «Épicas»: los bloques dentro de cada fase. Anote en las columnas amarillas.
A9: 3. Hoja «Tandas»: la unidad de trabajo que se le pide a Claude Code (un cambio OpenSpec cada una). Para cada fila responda «¿Tiene sentido?» (Sí / No / Con cambios / Duda), añada comentario, prioridad revisada (Sube / Se mantiene / Baja / Fuera) y, si aplica, la decisión de negocio que la condiciona. Las celdas amarillas son las únicas que se editan; el resto es la propuesta.
A10: 4. Hoja «Gates»: decisiones que abren tandas. Registre la decisión tomada, quién y cuándo. Cuando una decisión se cierra, la tanda pasa de «escrita» a «ejecutable».
A11: 5. Hoja «Calendario»: contraste de la Fase 1 con la meta del 31/12/2026. Las semanas con * en Tandas son estimadas y dependen de la decisión.
A12: 6. Hoja «Resumen»: se calcula sola a partir de sus respuestas (cuántas tandas revisadas, cuántas con objeción por épica).
A14: Convenciones
A15: ID de tanda: F<fase><épica>-<nn>. Tamaño: XS < medio día · S un día · M dos o tres días · L cuatro o cinco días (se parte si no cabe en tres). Semana: número de semana de calendario de 2026 (S37 = 07/09). Fuente: apartado del Documento Maestro R08.1 (Mx.y, Cn = corrección, Pnn = punto abierto del Anexo D, ítem n = backlog §3.2) o acta.
... A18: Regla de la sesión (convocatoria 03/09): cada bloque sale con una decisión escrita, o con un responsable y una fecha. Lo que no salga con ninguna de las dos vuelve al Anexo D y bloquea su tanda.

Sheet Fases
A1: Fase | B1: Nombre | C1: Horizonte | D1: Duración | E1: Alcance | F1: Condición de entrada | G1: ¿Tiene sentido? | H1: Comentario del revisor | I1: Prioridad revisada | J1: Revisado por | K1: Fecha
A2: F0 | B2: Cimientos SDD | C2: S37–S38 (07–18/09/2026) | D2: 1,5 semanas | E2: Traducir el as-built a specs OpenSpec; CLAUDE.md; Engram; pruebas del motor; staging y CI. | F2: Ninguna decisión pendiente
A3: F1 | B3: Réplica del Desk 1.0 + diagnóstico protocolizado + informes (MVP) | C3: S38–S53 (14/09–31/12/2026) | D3: 15 semanas | E3: Paridad con Zoho Desk; correcciones C1–C12; motor de checklist dinámico con catálogo importado; módulo de informes; puesta en producción. | F3: Gates de §4.5 del plan (sesiones de los viernes)
A4: F2 | B4: Operación interna completa | C4: 2027 · T1 | D4: — | E4: Kanban y KPIs (OTD, bodegajes), descuento de repuestos, comentarios predefinidos, app móvil responsive sin offline, migración documental. | F4: Datos limpios de la F1
A5: F3 | B5: Área de cliente nivel básico y seguridad | C5: 2027 · T2 | D5: — | E5: C8, ítem 26 (hoja de vida reducida y aprobación en un clic), identidad registrada, nueve puntos de seguridad. | F5: Etapa independiente (27/08)
A6: F4 | B6: Eficiencia, capacidad y conocimiento | C6: 2027 · S2 | D6: — | E6: Inventario transaccional, parámetro de carga y citas, dashboards por rol, capa RAG/KB, firmware, offline, QR/NFC. | F6: Parámetro de carga antes que agendamiento
A7: F5 | B7: Promesa, predicción y ecosistema | C7: 2028 | D7: — | E7: CTP, predicción de carga, agente conversacional, IoT, servicio premium, sustitución total de Zoho Desk. | F7: MVP con dato estructurado

Sheet Épicas
A1: Fase | B1: Épica | C1: Nombre | D1: Semanas | E1: Contenido | F1: Nº tandas | G1: ¿Tiene sentido? | H1: Comentario del revisor | I1: Prioridad revisada | J1: Revisado por | K1: Fecha
A2: F0 | B2: F0 | C2: Cimientos SDD | D2: S37–S38 | E2: Auditoría del as-built, specs as-built, Engram, pruebas, staging | F2: =COUNTIF(Tandas!$B:$B,B2) -> 5
A3: F1 | B3: F1A | C3: Correcciones sin decisión pendiente | D3: S38 | E3: C1, C11, C12, C9 (parte técnica), auditoría | F3: =COUNTIF(Tandas!$B:$B,B3) -> 5
A4: F1 | B4: F1B | C4: Paridad funcional con el Desk 1.0 | D4: S39–S44 | E4: Ítems 1, 2, 4–10, 17, 19, 20, 22; flujos equipo nuevo y soporte remoto | F4: =COUNTIF(Tandas!$B:$B,B4) -> 9
A5: F1 | B5: F1C | C5: Correcciones que cambian el proceso | D5: S40–S48 (según decisiones) | E5: C2, C3, C4, C5, C6, C7+C9, C10, rutas abreviadas | F5: =COUNTIF(Tandas!$B:$B,B5) -> 8
A6: F1 | B6: F1D | C6: Diagnóstico protocolizado con checklist dinámico | D6: S42–S47 | E6: Modelo del catálogo, importador Excel, macro-fases, validación por macro, encadenamiento No OK, criterio de falla, falla nueva, Horiba | F6: =COUNTIF(Tandas!$B:$B,B6) -> 9
A7: F1 | B7: F1E | C7: Módulo de informes | D7: S46–S50 | E7: Informe de diagnóstico y de salida derivados del checklist; validación por dos personas | F7: =COUNTIF(Tandas!$B:$B,B7) -> 5
A8: F1 | B8: F1F | C8: Puesta en producción | D8: S50–S53 | E8: Migración de tickets abiertos, respaldo, aceptación, formación, Zoho a solo lectura | F8: =COUNTIF(Tandas!$B:$B,B8) -> 4
A9: F2 | B9: F2 | C9: Operación interna completa | D9: 2027 T1 | E9: Ítems 13, 14, 15, 18 (sin offline), 30, 32, 37; comentarios predefinidos; P8/P54 | F9: =COUNTIF(Tandas!$B:$B,B9) -> 8
A10: F3 | B10: F3 | C10: Área de cliente y seguridad | D10: 2027 T2 | E10: C8, 26, 29, 52; seguridad | F10: =COUNTIF(Tandas!$B:$B,B10) -> 3
A11: F4 | B11: F4 | C11: Eficiencia, capacidad y conocimiento | D11: 2027 S2 | E11: Ítems 27, 28, 31–60 reordenados | F11: =COUNTIF(Tandas!$B:$B,B11) -> 5
A12: F5 | B12: F5 | C12: Promesa, predicción y ecosistema | D12: 2028 | E12: Ítems 61–76 | F12: =COUNTIF(Tandas!$B:$B,B12) -> 2

Sheet Tandas
A1: Fase | B1: Épica | C1: ID tanda | D1: Nombre | E1: Contenido | F1: Capacidad (spec) | G1: Fuente | H1: Gate (decisión necesaria) | I1: Tamaño | J1: Semana | K1: ¿Tiene sentido? | L1: Comentario del revisor | M1: Prioridad revisada | N1: Decisión / condición | O1: Revisado por | P1: Fecha
A2: F0 | B2: F0 | C2: F0-00 | D2: Auditoría del as-built | E2: Tanda sin código. sdd-explore con un sub-agente por frente: motor de flujo (34 transiciones/21 estados, hallazgos R04), esquema de datos vs Anexo G y diseños de docs/superpowers, sincronización Zoho, UI (qué replica ya Zoho Desk), pruebas y build (96 ficheros vitest, typecheck, lint), deuda (reclasificar debt.md). Veredicto conservar / refactorizar / rehacer por frente; baseline a Engram. | F2: todas las as-built | G2: Anexo H · debt.md · docs/superpowers | H2: — | I2: M | J2: S37
A3: F0 | B3: F0 | C3: F0-01 | D3: Init SDD, config, CLAUDE.md y export .md del documento maestro | E3: sdd-init sobre el repo; openspec/config.yaml (contexto, strict_tdd: true, reglas por fase); CLAUDE.md con las 12 reglas invariables y el mapa documental (§4.7); exportación docs/Manifesto/…_R08.1.md; decidir qué skills de .claude/.agent se conservan. | F3: — | G3: Plan §4.4, §4.7 | H3: — | I3: S | J3: S37
A4: F0 | B4: F0 | C4: F0-02 | D4: Specs as-built de las capacidades existentes | E4: A partir del inventario de F0-00 y de docs/superpowers/specs: specs de transitions-st, permissions, remisiones, zoho-sync, derivacion-avisos, trazas, tickets-core tal como están, con los hallazgos R04 marcados «a corregir en Cx». Superpowers queda como histórico. | F4: todas las as-built | G4: M1.3, M1.9, Anexo G · docs/superpowers | H4: F0-00 | I4: L | J4: S38
A5: F0 | B5: F0 | C5: F0-03 | D5: Proyecto Engram y carga de decisiones | E5: Proyecto Engram; decisiones cerradas (§1.8 y acta 03/09) como observaciones decision/*; convención de topic_key; evaluar Git Sync. | F5: — | G5: §1.8, acta 03/09 | H5: — | I5: S | J5: S37
A6: F0 | B6: F0 | C6: F0-04 | D6: Pruebas del motor, staging y CI | E6: Pruebas mínimas del motor de transiciones (origen/destino declarados; Finalizado único terminal); staging en VPS Hostinger con PostgreSQL; CI. | F6: transitions-st | G6: M11.5 | H6: — | I6: M | J6: S38
A7: F1 | B7: F1A | C7: F1A-01 | D7: C1 · Guarda del checkbox obligatorio | E7: buildTransitionPlan: error cuando el campo es obligatorio y no llega marcado (debt.md M-2). | F7: transitions-st | G7: M1.7 · M11.7 · P33 | H7: Ninguno | I7: XS | J7: S38
A8: F1 | B8: F1A | C8: F1A-02 | D8: C11 · SLA de un día sobre Notificado | E8: SLA existente en Zoho; ampliado con correo redundante al cambiar de área y escalado al superior. | F8: transitions-st, derivacion-avisos | G8: M1.7 · P40 · acta 03/09 | H8: Ninguno | I8: S | J8: S38
A9: F1 | B9: F1A | C9: F1A-03 | D9: C12 · Salidas de Verificación (equipo nuevo) | E9: Transiciones aprobada/rechazada desde Verificación antes de construir la rama. | F9: transitions-equipo-nuevo | G9: M1.4 · P38 | H9: Ninguno | I9: S | J9: S38
A10: F1 | B10: F1A | C10: F1A-04 | D10: C9 · Bodegajes contra Ingreso a Servicio | E10: Recalcular bodegaje de entrada, inicio de servicio y diagnóstico contra la marca de tiempo de la transición; campo «fecha de aviso al cliente». | F10: trazas, kpis | G10: M1.10 · P41 | H10: Definición ya resuelta en R08 | I10: S | J10: S38
A11: F1 | B11: F1A | C11: F1A-05 | D11: audit-F1A | E11: Auditoría de blueprint con IA tras las correcciones; hallazgos al Anexo D. | F11: — | G11: M11.6 | H11: — | I11: S | J11: S38
A12: F1 | B12: F1B | C12: F1B-01 | D12: Serial único y autocompletado | E12: Código único de ticket por serial; serial obligatorio en la remisión; autocompletado de cliente, modelo y OV activas. | F12: tickets-core, zoho-sync | G12: Ítems 1, 19 · §1.8 (14/08, 20/08) | H12: Ninguno | I12: M | J12: S39
A13: F1 | B13: F1B | C13: F1B-02 | D13: Hoja de vida: cuatro campos y enlace a Drive | E13: Alta por Comercial; fecha de adquisición, fecha de factura, fin de garantía, código interno del cliente (identificador secundario); botón de enlace a la carpeta de Drive (fase 0 de migración). | F13: hojas-vida | G13: Ítem 9 · P8 · 27/08 | H13: decision/p8-p54-drive · quién carga los campos | I13: M | J13: S39
... A64: F5 | B64: F5 | C64: F5-02 | D64: Agente conversacional, IoT, premium | E64: Agente sobre KB Externa; telemetría; servicio premium; sustitución total de Zoho Desk. | F64: portal, conocimiento | G64: Ítems 66, 70, 71, 76 | H64: — | I64: L | J64: 2028
A66: * Semana estimada: la tanda se ejecuta cuando la decisión del gate esté escrita (hoja Gates). Fuente de todas las filas: Documento Maestro R08.1 y acta del 03/09/2026; propuesta de Gerencia con apoyo de Claude, 07/09/2026.

Sheet Gates
A1: Clave Engram | B1: Decisión necesaria | C1: Tanda(s) que abre | D1: Sesión prevista | E1: Estado | F1: Decisión tomada | G1: Decidido por | H1: Fecha de decisión | I1: Comentario
A2: decision/p21-ingreso-sin-ov | B2: OV obligatoria desde el inicio o estado provisional | C2: F1B-03 | D2: 11/09/2026 | E2: Pendiente
A3: decision/p8-p54-drive | B3: Botón de enlace a Drive como fase 0; convivencia con Drive | C3: F1B-02 | D3: 11/09/2026 | E3: Pendiente
A4: decision/p45-macro-fases | B4: Juego de macro-fases común a todas las marcas | C4: F1D-03 | D4: 11/09/2026 (Johny) | E4: Pendiente
A5: decision/flujos-comercial-posible-cliente | B5: Alcance de M1.11 y M1.12 en Desk 2.0 | C5: F1B-06 | D5: 11/09/2026 | E5: Pendiente
A6: decision/top5-prioridad | B6: Si los Top 5 entran en la prioridad automática | C6: F1B-07 | D6: 11/09/2026 | E6: Pendiente
A7: decision/p14-remisiones-entrada | B7: Quién escribe remisiones_entrada | C7: F1E-01 | D7: 11/09/2026 | E7: Pendiente
A8: decision/c2-anulado | B8: Estado Anulado; tratamiento del histórico | C8: F1C-01 (protege F1E-03) | D8: 11/09 o 18/09/2026 | E8: Pendiente
A9: decision/c4-dos-ramas | B9: Dos ramas; si Facturado es estado | C9: F1C-02 | D9: 18/09/2026 | E9: Pendiente
A10: decision/c3-salida-esperas | B10: Destino y caducidad de las cuatro esperas | C10: F1C-03 | D10: 18/09/2026 | E10: Pendiente
A11: decision/c5-tipo-evento | B11: Desambiguar «Creación de informe» | C11: F1C-04 | D11: 18/09/2026 | E11: Pendiente
A12: decision/c10-permisos-cargo | B12: Matriz cargo × transición | C12: F1C-05 | D12: 25/09/2026 | E12: Pendiente
A13: decision/c7-reloj-sla | B13: Estados que paran el reloj | C13: F1C-06 | D13: 25/09/2026 | E13: Pendiente
... A20: decision/fecha-corte | B20: Desde cuándo los tickets nacen en la app | C20: F1F-01 | D20: Noviembre 2026 | E20: Pendiente

Sheet Calendario
A1: Semana | B1: Lunes | C1: F0 + 1A | D1: 1B Paridad | E1: 1C Correcciones (según decisión) | F1: 1D Diagnóstico | G1: 1E Informes | H1: 1F Producción | I1: Observación del revisor
A2: S37 | B2: 07/09 | C2: F0-00 · F0-01 · F0-03
A3: S38 | B3: 14/09 | C3: F0-02 · F0-04 · F1A-01…05
A4: S39 | B4: 21/09 | D4: F1B-01 · F1B-02
A5: S40 | B5: 28/09 | D5: F1B-03 · F1B-04 | E5: C2 (si decidido)
A6: S41 | B6: 05/10 | D6: F1B-05 | E6: C4
A7: S42 | B7: 12/10 | D7: F1B-06 | F7: F1D-01
A8: S43 | B8: 19/10 | D8: F1B-07 | E8: C3 | F8: F1D-02
A9: S44 | B9: 26/10 | D9: F1B-08 · F1B-09 | E9: C5 · C10 | F9: F1D-03
A10: S45 | B10: 02/11 | F10: F1D-04
A11: S46 | B11: 09/11 | E11: C7+C9 | F11: F1D-05 · F1D-06 | G11: F1E-01
A12: S47 | B12: 16/11 | E12: C6 | F12: F1D-07 · F1D-08 · F1D-09 | G12: F1E-02
A13: S48 | B13: 23/11 | E13: Rutas abreviadas | G13: F1E-03
A14: S49 | B14: 30/11 | G14: F1E-04
A15: S50 | B15: 07/12 | G15: F1E-05 | H15: F1F-01
A16: S51 | B16: 14/12 | H16: F1F-02 · F1F-03
A17: S52 | B17: 21/12 | H17: F1F-03 · F1F-04
A18: S53 | B18: 28/12 | H18: Margen · meta 31/12
A20: Lectura: cabe, sin holgura. 1C fuera de la ruta crítica salvo C2 (conviene antes de F1E-03). 1D y 1E se solapan porque el modelo del informe sólo necesita el modelo del catálogo. F1B-06 es recortable a un flujo y F1D-08 (Horiba) diferible a enero si hay que ganar una semana. Fuera del 31/12: área de cliente, app móvil con offline, OCR/QR/NFC, comentarios predefinidos.

Sheet Resumen
A1: Épica | B1: Nombre | C1: Tandas propuestas | D1: Revisadas | E1: Sí | F1: Con cambios / Duda | G1: No | H1: Sube | I1: Baja / Fuera | J1: % revisado
A2: F0 | B2: Cimientos SDD | C2: =COUNTIF(Tandas!$B:$B,A2) -> 5 | D2: =COUNTIFS(Tandas!$B:$B,A2,Tandas!$K:$K,"<>") -> 0 | E2: =COUNTIFS(Tandas!$B:$B,A2,Tandas!$K:$K,"Sí") -> 0 | F2: =COUNTIFS(Tandas!$B:$B,A2,Tandas!$K:$K,"Con cambios")+COUNTIFS(Tandas!$B:$B,A2,Tandas!$K:$K,"Duda") -> 0 | G2: =COUNTIFS(Tandas!$B:$B,A2,Tandas!$K:$K,"No") -> 0 | H2: =COUNTIFS(Tandas!$B:$B,A2,Tandas!$M:$M,"Sube") -> 0 | I2: =COUNTIFS(Tandas!$B:$B,A2,Tandas!$M:$M,"Baja")+COUNTIFS(Tandas!$B:$B,A2,Tandas!$M:$M,"Fuera") -> 0 | J2: =IF(C2=0,0,D2/C2) -> 0
A3: F1A | B3: Correcciones sin decisión pendiente | C3: =COUNTIF(Tandas!$B:$B,A3) -> 5 | D3: =COUNTIFS(Tandas!$B:$B,A3,Tandas!$K:$K,"<>") -> 0 | E3: =COUNTIFS(Tandas!$B:$B,A3,Tandas!$K:$K,"Sí") -> 0 | F3: =COUNTIFS(Tandas!$B:$B,A3,Tandas!$K:$K,"Con cambios")+COUNTIFS(Tandas!$B:$B,A3,Tandas!$K:$K,"Duda") -> 0 | G3: =COUNTIFS(Tandas!$B:$B,A3,Tandas!$K:$K,"No") -> 0 | H3: =COUNTIFS(Tandas!$B:$B,A3,Tandas!$M:$M,"Sube") -> 0 | I3: =COUNTIFS(Tandas!$B:$B,A3,Tandas!$M:$M,"Baja")+COUNTIFS(Tandas!$B:$B,A3,Tandas!$M:$M,"Fuera") -> 0 | J3: =IF(C3=0,0,D3/C3) -> 0
A4: F1B | B4: Paridad funcional con el Desk 1.0 | C4: =COUNTIF(Tandas!$B:$B,A4) -> 9 | D4: =COUNTIFS(Tandas!$B:$B,A4,Tandas!$K:$K,"<>") -> 0 | E4: =COUNTIFS(Tandas!$B:$B,A4,Tandas!$K:$K,"Sí") -> 0 | F4: =COUNTIFS(Tandas!$B:$B,A4,Tandas!$K:$K,"Con cambios")+COUNTIFS(Tandas!$B:$B,A4,Tandas!$K:$K,"Duda") -> 0 | G4: =COUNTIFS(Tandas!$B:$B,A4,Tandas!$K:$K,"No") -> 0 | H4: =COUNTIFS(Tandas!$B:$B,A4,Tandas!$M:$M,"Sube") -> 0 | I4: =COUNTIFS(Tandas!$B:$B,A4,Tandas!$M:$M,"Baja")+COUNTIFS(Tandas!$B:$B,A4,Tandas!$M:$M,"Fuera") -> 0 | J4: =IF(C4=0,0,D4/C4) -> 0
A5: F1C | B5: Correcciones que cambian el proceso | C5: =COUNTIF(Tandas!$B:$B,A5) -> 8 | D5: =COUNTIFS(Tandas!$B:$B,A5,Tandas!$K:$K,"<>") -> 0 | E5: =COUNTIFS(Tandas!$B:$B,A5,Tandas!$K:$K,"Sí") -> 0 | F5: =COUNTIFS(Tandas!$B:$B,A5,Tandas!$K:$K,"Con cambios")+COUNTIFS(Tandas!$B:$B,A5,Tandas!$K:$K,"Duda") -> 0 | G5: =COUNTIFS(Tandas!$B:$B,A5,Tandas!$K:$K,"No") -> 0 | H5: =COUNTIFS(Tandas!$B:$B,A5,Tandas!$M:$M,"Sube") -> 0 | I5: =COUNTIFS(Tandas!$B:$B,A5,Tandas!$M:$M,"Baja")+COUNTIFS(Tandas!$B:$B,A5,Tandas!$M:$M,"Fuera") -> 0 | J5: =IF(C5=0,0,D5/C5) -> 0
A6: F1D | B6: Diagnóstico protocolizado con checklist dinámico | C6: =COUNTIF(Tandas!$B:$B,A6) -> 9 | D6: =COUNTIFS(Tandas!$B:$B,A6,Tandas!$K:$K,"<>") -> 0 | E6: =COUNTIFS(Tandas!$B:$B,A6,Tandas!$K:$K,"Sí") -> 0 | F6: =COUNTIFS(Tandas!$B:$B,A6,Tandas!$K:$K,"Con cambios")+COUNTIFS(Tandas!$B:$B,A6,Tandas!$K:$K,"Duda") -> 0 | G6: =COUNTIFS(Tandas!$B:$B,A6,Tandas!$K:$K,"No") -> 0 | H6: =COUNTIFS(Tandas!$B:$B,A6,Tandas!$M:$M,"Sube") -> 0 | I6: =COUNTIFS(Tandas!$B:$B,A6,Tandas!$M:$M,"Baja")+COUNTIFS(Tandas!$B:$B,A6,Tandas!$M:$M,"Fuera") -> 0 | J6: =IF(C6=0,0,D6/C6) -> 0
A7: F1E | B7: Módulo de informes | C7: =COUNTIF(Tandas!$B:$B,A7) -> 5 | D7: =COUNTIFS(Tandas!$B:$B,A7,Tandas!$K:$K,"<>") -> 0 | E7: =COUNTIFS(Tandas!$B:$B,A7,Tandas!$K:$K,"Sí") -> 0 | F7: =COUNTIFS(Tandas!$B:$B,A7,Tandas!$K:$K,"Con cambios")+COUNTIFS(Tandas!$B:$B,A7,Tandas!$K:$K,"Duda") -> 0 | G7: =COUNTIFS(Tandas!$B:$B,A7,Tandas!$K:$K,"No") -> 0 | H7: =COUNTIFS(Tandas!$B:$B,A7,Tandas!$M:$M,"Sube") -> 0 | I7: =COUNTIFS(Tandas!$B:$B,A7,Tandas!$M:$M,"Baja")+COUNTIFS(Tandas!$B:$B,A7,Tandas!$M:$M,"Fuera") -> 0 | J7: =IF(C7=0,0,D7/C7) -> 0
A8: F1F | B8: Puesta en producción | C8: =COUNTIF(Tandas!$B:$B,A8) -> 4 | D8: =COUNTIFS(Tandas!$B:$B,A8,Tandas!$K:$K,"<>") -> 0 | E8: =COUNTIFS(Tandas!$B:$B,A8,Tandas!$K:$K,"Sí") -> 0 | F8: =COUNTIFS(Tandas!$B:$B,A8,Tandas!$K:$K,"Con cambios")+COUNTIFS(Tandas!$B:$B,A8,Tandas!$K:$K,"Duda") -> 0 | G8: =COUNTIFS(Tandas!$B:$B,A8,Tandas!$K:$K,"No") -> 0 | H8: =COUNTIFS(Tandas!$B:$B,A8,Tandas!$M:$M,"Sube") -> 0 | I8: =COUNTIFS(Tandas!$B:$B,A8,Tandas!$M:$M,"Baja")+COUNTIFS(Tandas!$B:$B,A8,Tandas!$M:$M,"Fuera") -> 0 | J8: =IF(C8=0,0,D8/C8) -> 0
A9: F2 | B9: Operación interna completa | C9: =COUNTIF(Tandas!$B:$B,A9) -> 8 | D9: =COUNTIFS(Tandas!$B:$B,A9,Tandas!$K:$K,"<>") -> 0 | E9: =COUNTIFS(Tandas!$B:$B,A9,Tandas!$K:$K,"Sí") -> 0 | F9: =COUNTIFS(Tandas!$B:$B,A9,Tandas!$K:$K,"Con cambios")+COUNTIFS(Tandas!$B:$B,A9,Tandas!$K:$K,"Duda") -> 0 | G9: =COUNTIFS(Tandas!$B:$B,A9,Tandas!$K:$K,"No") -> 0 | H9: =COUNTIFS(Tandas!$B:$B,A9,Tandas!$M:$M,"Sube") -> 0 | I9: =COUNTIFS(Tandas!$B:$B,A9,Tandas!$M:$M,"Baja")+COUNTIFS(Tandas!$B:$B,A9,Tandas!$M:$M,"Fuera") -> 0 | J9: =IF(C9=0,0,D9/C9) -> 0
A10: F3 | B10: Área de cliente y seguridad | C10: =COUNTIF(Tandas!$B:$B,A10) -> 3 | D10: =COUNTIFS(Tandas!$B:$B,A10,Tandas!$K:$K,"<>") -> 0 | E10: =COUNTIFS(Tandas!$B:$B,A10,Tandas!$K:$K,"Sí") -> 0 | F10: =COUNTIFS(Tandas!$B:$B,A10,Tandas!$K:$K,"Con cambios")+COUNTIFS(Tandas!$B:$B,A10,Tandas!$K:$K,"Duda") -> 0 | G10: =COUNTIFS(Tandas!$B:$B,A10,Tandas!$K:$K,"No") -> 0 | H10: =COUNTIFS(Tandas!$B:$B,A10,Tandas!$M:$M,"Sube") -> 0 | I10: =COUNTIFS(Tandas!$B:$B,A10,Tandas!$M:$M,"Baja")+COUNTIFS(Tandas!$B:$B,A10,Tandas!$M:$M,"Fuera") -> 0 | J10: =IF(C10=0,0,D10/C10) -> 0
A11: F4 | B11: Eficiencia, capacidad y conocimiento | C11: =COUNTIF(Tandas!$B:$B,A11) -> 5 | D11: =COUNTIFS(Tandas!$B:$B,A11,Tandas!$K:$K,"<>") -> 0 | E11: =COUNTIFS(Tandas!$B:$B,A11,Tandas!$K:$K,"Sí") -> 0 | F11: =COUNTIFS(Tandas!$B:$B,A11,Tandas!$K:$K,"Con cambios")+COUNTIFS(Tandas!$B:$B,A11,Tandas!$K:$K,"Duda") -> 0 | G11: =COUNTIFS(Tandas!$B:$B,A11,Tandas!$K:$K,"No") -> 0 | H11: =COUNTIFS(Tandas!$B:$B,A11,Tandas!$M:$M,"Sube") -> 0 | I11: =COUNTIFS(Tandas!$B:$B,A11,Tandas!$M:$M,"Baja")+COUNTIFS(Tandas!$B:$B,A11,Tandas!$M:$M,"Fuera") -> 0 | J11: =IF(C11=0,0,D11/C11) -> 0
A12: F5 | B12: Promesa, predicción y ecosistema | C12: =COUNTIF(Tandas!$B:$B,A12) -> 2 | D12: =COUNTIFS(Tandas!$B:$B,A12,Tandas!$K:$K,"<>") -> 0 | E12: =COUNTIFS(Tandas!$B:$B,A12,Tandas!$K:$K,"Sí") -> 0 | F12: =COUNTIFS(Tandas!$B:$B,A12,Tandas!$K:$K,"Con cambios")+COUNTIFS(Tandas!$B:$B,A12,Tandas!$K:$K,"Duda") -> 0 | G12: =COUNTIFS(Tandas!$B:$B,A12,Tandas!$K:$K,"No") -> 0 | H12: =COUNTIFS(Tandas!$B:$B,A12,Tandas!$M:$M,"Sube") -> 0 | I12: =COUNTIFS(Tandas!$B:$B,A12,Tandas!$M:$M,"Baja")+COUNTIFS(Tandas!$B:$B,A12,Tandas!$M:$M,"Fuera") -> 0 | J12: =IF(C12=0,0,D12/C12) -> 0
A13: Total | C13: =SUM(C2:C12) -> 63 | D13: =SUM(D2:D12) -> 0 | E13: =SUM(E2:E12) -> 0 | F13: =SUM(F2:F12) -> 0 | G13: =SUM(G2:G12) -> 0 | H13: =SUM(H2:H12) -> 0 | I13: =SUM(I2:I12) -> 0 | J13: =IF(C13=0,0,D13/C13) -> 0
A15: Gates decididos | B15: decididos / total | C15: =COUNTIF(Gates!$E:$E,"Decidida") -> 0 | D15: =COUNTA(Gates!$A:$A)-1 -> 19
A16: Se calcula solo a partir de las columnas amarillas de Tandas y Gates.
