Workbook

Sheet Instrucciones
A1: INSPECCIÓN FÍSICA DEL EQUIPO — GRIMM EDM180 (C/D)
A2: Prototipo de estructura jerárquica en Excel · Ambientalia — Servicio Técnico · v9
A4: Novedades de la v9
A5: Se añadió la hoja «Flujo No OK 2»: la misma información de encadenamiento condicional (columnas
A6: N-O de Inspección y hoja «Flujo No OK»), reorganizada en tabla plana de un renglón por enlace
A7: origen→destino — misma filosofía que la referencia que compartió el usuario para los Horiba
A8: APxA-370 (columnas Modelo, ID origen, Ítem, Criterio de falla, Causa probable, Orden, ID destino,
A9: Verificación siguiente, Acción si se confirma, Resultado del origen y Rama activa). «Resultado del
A10: origen» y «Rama activa» son fórmulas en vivo contra la hoja Inspección: si el ítem de origen queda
A11: marcado No conforme/Requiere reemplazo en la visita, la fila se enciende sola. Filtre por «Rama
A12: activa = SÍ» para ver solo lo que la visita de hoy disparó. ID origen e ID destino son hipervínculos
A13: a la fila del ítem en Inspección. 84 enlaces sobre los mismos ~40 ítems con secuencia documentada
... A128: no uno publicado por GRIMM; se deja igual, pero sin fuente oficial confirmada.
A129: ID | B129: Ítem | C129: Resultado | D129: Valor medido | E129: Foto | F129: Observación
A130: 3.1.1 | B130: Flujo de la bomba de secado | C130: Requiere reemplazo | D130: 2.45 | E130: Sí | F130: Flujo cercano al límite de reemplazo; desgaste en el empaque del pistón.

Sheet Listas
A1: Resultado | B1: Foto adjunta | C1: Obligatorio | D1: Criterio de falla
A2: Conforme | B2: Sí | C2: Sí | D2: Alerta
A3: No conforme | B3: No | C3: No | D3: Cobrable
A4: Requiere reemplazo | B4: No aplica | D4: Bloqueante
A5: No aplica
A6: Pendiente

Sheet Inspección
A1: FASE 1 — INSPECCIÓN FÍSICA DEL EQUIPO (catálogo + captura)
A3: Cliente: | D3: Serie del espectrómetro:
A4: NIT: | D4: Fecha de inspección:
A5: Equipo / Modelo: | B5: Monitor de partículas GRIMM EDM180 | D5: Técnico responsable:
A6: Número de serie: | D6: N.º de informe (MT):
A8: ID | B8: Nivel macro (N1) | C8: Subnivel (N2) | D8: Ítem (N3) | E8: Qué se verifica | F8: Cómo se verifica (método) | G8: Tipo de dato | H8: Unidad | I8: Criterio de aceptación | J8: Límite inferior | K8: Límite superior | L8: Obligatorio | M8: Criterio de falla | N8: Acción si sale No OK | O8: Ítem(s) relacionado(s) | P8: Comentario de falla (informe al cliente) | Q8: Evidencia fotográfica requerida | R8: Repuesto / parte asociada | S8: Informe de referencia | T8: Resultado | U8: Valor medido | V8: Verificación de rango | W8: Foto adjunta | X8: Observación
A9: 1.1.1 | B9: 1. Verificación funcional inicial | C9: 1.1 Encendido y autodiagnóstico | D9: Ciclo self-test | E9: El equipo enciende y supera el ciclo self test | F9: Encender el equipo desde el panel frontal y observar en pantalla que complete el ciclo de autodiagnóstico (self-test) sin quedar detenido ni mostrar código de error. | G9: Sí/No | I9: Debe superar el self test | L9: Sí | M9: Bloqueante | N9: Revisar el código específico mostrado en pantalla (SER-MAN cap. 2.1). Si es “New Self Test”, limpiar la entrada de aire de muestra (2.1.3) y reintentar; si el código persiste, el equipo requiere servicio técnico calificado. Ver Cadena 1 en hoja Flujo No OK. | O9: 2.1.3 · 5.3.2 · 7.1.1 | P9: El equipo no completa el ciclo de autodiagnóstico (self-test) al encender. | Q9: No | S9: MT_18A12051_260811 | T9: Pendiente | V9: =IF($G9<>"Numérico","",IF($U9="","Sin dato",IF(AND(OR(NOT(ISNUMBER($J9)),$U9>=$J9),OR(NOT(ISNUMBER($K9)),$U9<=$K9)),"Dentro de rango","Fuera de rango")))
A10: 1.1.2 | B10: 1. Verificación funcional inicial | C10: 1.1 Encendido y autodiagnóstico | D10: Inicio de medición | E10: El equipo comienza a medir tras el self test | F10: Verificar en pantalla o en el software Diagnosis GRIMM que, al finalizar el self-test, el equipo pase automáticamente a modo de medición y comience a reportar conteos. | G10: Sí/No | I10: Debe iniciar medición | L10: Sí | M10: Bloqueante | N10: Si el equipo completa el self-test pero no pasa a medición, revisar los mismos códigos de la Cadena 1 (self-test) — causa probablemente común con 1.1.1. | O10: 1.1.1 | P10: El equipo supera el self-test pero no inicia la medición automáticamente. | Q10: No | S10: MT_18A12051_260811 | T10: Pendiente | V10: =IF($G10<>"Numérico","",IF($U10="","Sin dato",IF(AND(OR(NOT(ISNUMBER($J10)),$U10>=$J10),OR(NOT(ISNUMBER($K10)),$U10<=$K10)),"Dentro de rango","Fuera de rango")))
A11: 1.1.3 | B11: 1. Verificación funcional inicial | C11: 1.1 Encendido y autodiagnóstico | D11: Alarmas activas | E11: Alarmas o avisos en pantalla al arranque (p. ej. alerta "Dryer") | F11: Revisar la pantalla del equipo al arranque y anotar cualquier alarma o aviso visible (p. ej. "Dryer"); confirmar en el software de diagnóstico si hay alarmas adicionales no visibles en pantalla. | G11: Texto | I11: Sin alarmas activas | L11: Sí | M11: Alerta | N11: Si la alarma es “Dryer”: revisar el manómetro de vacío tras la tapa del panel frontal (3.2.1) y la presión de vacío (3.2.2). Ver Cadena 2 en hoja Flujo No OK. | O11: 3.2.1 · 3.2.2 · 2.4.1 | P11: Se observa una alarma o aviso activo en pantalla al arranque del equipo (p. ej. «Dryer»). | Q11: Sí | S11: MT_18A21062_260227 | T11: Pendiente | V11: =IF($G11<>"Numérico","",IF($U11="","Sin dato",IF(AND(OR(NOT(ISNUMBER($J11)),$U11>=$J11),OR(NOT(ISNUMBER($K11)),$U11<=$K11)),"Dentro de rango","Fuera de rango")))
A12: 1.2.1 | B12: 1. Verificación funcional inicial | C12: 1.2 Identificación y trazabilidad | D12: Serial del monitor | E12: El serial del monitor coincide con la placa y con la orden de servicio | F12: Comparar el número de serie impreso en la placa/etiqueta del equipo con el registrado en la orden de servicio. | G12: Sí/No | I12: Debe coincidir | L12: Sí | M12: Bloqueante | N12: No liberar el equipo hasta resolver. Reparar/reemplazar el componente asociado (ver Repuesto/parte asociada); si no se resuelve en sitio, escalar a soporte GRIMM/DURAG. | P12: El número de serie del equipo no coincide con el registrado en la orden de servicio. | Q12: Sí | S12: MT_18A19035_260727 | T12: Pendiente | V12: =IF($G12<>"Numérico","",IF($U12="","Sin dato",IF(AND(OR(NOT(ISNUMBER($J12)),$U12>=$J12),OR(NOT(ISNUMBER($K12)),$U12<=$K12)),"Dentro de rango","Fuera de rango")))
A13: 1.2.2 | B13: 1. Verificación funcional inicial | C13: 1.2 Identificación y trazabilidad | D13: Serial del espectrómetro | E13: El espectrómetro instalado corresponde al del equipo (no de otro monitor) | F13: Ingresar al software Diagnosis GRIMM y leer el serial del espectrómetro instalado; contrastarlo con el serial de fábrica asociado a ese monitor. | G13: Sí/No | I13: Debe corresponder | L13: Sí | M13: Bloqueante | N13: No liberar el equipo hasta resolver. Reparar/reemplazar el componente asociado (ver Repuesto/parte asociada); si no se resuelve en sitio, escalar a soporte GRIMM/DURAG. | P13: El espectrómetro instalado no corresponde al registrado para este equipo; podría tratarse de un componente de otro monitor. | Q13: Sí | S13: MT_18A19035_260727 | T13: Pendiente | V13: =IF($G13<>"Numérico","",IF($U13="","Sin dato",IF(AND(OR(NOT(ISNUMBER($J13)),$U13>=$J13),OR(NOT(ISNUMBER($K13)),$U13<=$K13)),"Dentro de rango","Fuera de rango")))
A14: 1.2.3 | B14: 1. Verificación funcional inicial | C14: 1.2 Identificación y trazabilidad | D14: Accesorios recibidos | E14: Inventario de accesorios: tubo de muestra, cabezal TSP, sensor T/HR, cables | F14: Hacer inventario visual de los accesorios entregados junto al equipo (tubo de muestra, cabezal TSP, sensor T/HR, cables) y contrastarlo contra la lista estándar de accesorios. | G14: Texto | I14: Inventario completo | L14: Sí | M14: Cobrable | N14: Reemplazar o reparar el componente indicado en Repuesto/parte asociada; incluir en la cotización al cliente. | P14: El inventario de accesorios entregados con el equipo está incompleto (tubo de muestra, cabezal TSP, sensor T/HR o cables). | Q14: Sí | S14: MT_18A19035_260727 | T14: Pendiente | V14: =IF($G14<>"Numérico","",IF($U14="","Sin dato",IF(AND(OR(NOT(ISNUMBER($J14)),$U14>=$J14),OR(NOT(ISNUMBER($K14)),$U14<=$K14)),"Dentro de rango","Fuera de rango")))
A15: 1.2.4 | B15: 1. Verificación funcional inicial | C15: 1.2 Identificación y trazabilidad | D15: Etiquetas físicas (Type Label / etiqueta de calibración) | E15: Presencia y legibilidad de la etiqueta de tipo y de la etiqueta de calibración vigente | F15: Inspección visual: verificar que la etiqueta de tipo (Type Label) y la etiqueta de calibración estén adheridas, legibles y con fecha vigente. | G15: OK / No OK | I15: Presentes y legibles | L15: No | M15: Alerta | N15: Registrar el hallazgo en Observación y dar seguimiento; no requiere acción inmediata. | P15: La etiqueta de tipo o la etiqueta de calibración no están presentes, no son legibles o están vencidas. | Q15: Sí | S15: Service Training NEW v0.8 | T15: Pendiente | V15: =IF($G15<>"Numérico","",IF($U15="","Sin dato",IF(AND(OR(NOT(ISNUMBER($J15)),$U15>=$J15),OR(NOT(ISNUMBER($K15)),$U15<=$K15)),"Dentro de rango","Fuera de rango")))
A16: 1.3.1 | B16: 1. Verificación funcional inicial | C16: 1.3 Estado de calibración | D16: Vigencia de calibración en Torre GRIMM | E16: Fecha de la última calibración en torre patrón | F16: Revisar la fecha de la última calibración en la torre patrón GRIMM (registro interno AMB-STCALENVIRO-01) y calcular si han transcurrido menos de 12 meses. | G16: Fecha | I16: Vigencia máxima 12 meses | L16: Sí | M16: Bloqueante | N16: No liberar el equipo hasta resolver. Reparar/reemplazar el componente asociado (ver Repuesto/parte asociada); si no se resuelve en sitio, escalar a soporte GRIMM/DURAG. | P16: La última calibración en torre patrón tiene más de 12 meses de vigencia. | Q16: No | R16: AMB-STCALENVIRO-01 | S16: MT_18A12051_260811 | T16: Pendiente | V16: =IF($G16<>"Numérico","",IF($U16="","Sin dato",IF(AND(OR(NOT(ISNUMBER($J16)),$U16>=$J16),OR(NOT(ISNUMBER($K16)),$U16<=$K16)),"Dentro de rango","Fuera de rango")))
A17: 1.3.2 | B17: 1. Verificación funcional inicial | C17: 1.3 Estado de calibración | D17: Certificado disponible | E17: Existe certificado de la última calibración | F17: Solicitar/consultar el archivo del certificado de calibración correspondiente a la última fecha registrada. | G17: Sí/No | I17: Debe existir | L17: No | M17: Alerta | N17: Registrar el hallazgo en Observación y dar seguimiento; no requiere acción inmediata. | P17: No se cuenta con el certificado de la última calibración del equipo. | Q17: No | S17: MT_18A19035_260727 | T17: Pendiente | V17: =IF($G17<>"Numérico","",IF($U17="","Sin dato",IF(AND(OR(NOT(ISNUMBER($J17)),$U17>=$J17),OR(NOT(ISNUMBER($K17)),$U17<=$K17)),"Dentro de rango","Fuera de rango")))
A18: 1.3.3 | B18: 1. Verificación funcional inicial | C18: 1.3 Estado de calibración | D18: Desviación relativa de masa (verificación con aire ambiente) | E18: Diferencia entre el candidato y el espectrómetro de referencia al verificar con aire ambiente tras la calibración en torre | F18: Con el equipo ya calibrado en torre, realizar una medición simultánea con aire ambiente frente al espectrómetro de referencia y calcular la diferencia porcentual o en µg/m³ entre ambos. | G18: Numérico | H18: % o µg/m³ | I18: Criterio de fábrica: ±3% o ±2µg/m³. Criterio para cliente/campo: ±5% o ±2µg/m³ (correo GRIMM 25-nov-2021) | J18: -5 | K18: 5 | L18: Sí | M18: Bloqueante | N18: Si la desviación de masa queda fuera de criterio tras calibrar en torre, el Service Training documenta el ciclo completo: pre-comparación, calibración de preamplificador/láser/flujo/umbrales, prueba de 48 h, verificación final. Ver Cadena 13. | O18: 5.2.1 · 4.3.3 | P18: La desviación de masa frente al equipo de referencia supera el criterio aceptado tras la calibración en torre. | Q18: Sí | S18: Correo EDM180C Calibration desviación (nov-2021) | T18: Pendiente | V18: =IF($G18<>"Numérico","",IF($U18="","Sin dato",IF(AND(OR(NOT(ISNUMBER($J18)),$U18>=$J18),OR(NOT(ISNUMBER($K18)),$U18<=$K18)),"Dentro de rango","Fuera de rango"))) -> Sin dato
A19: 2.1.1 | B19: 2. Línea de muestreo y cabezal | C19: 2.1 Cabezal TSP | D19: Estado físico del cabezal | E19: Golpes, deformación, corrosión del cabezal TSP | F19: Inspección visual del cabezal TSP buscando golpes, deformación o corrosión. | G19: OK / No OK | I19: Sin deformación ni corrosión | L19: Sí | M19: Cobrable | N19: Reemplazar o reparar el componente indicado en Repuesto/parte asociada; incluir en la cotización al cliente. | P19: El cabezal TSP presenta golpes, deformación o corrosión. | Q19: Sí | R19: 1205317 / X180TSP (cabezal TSP completo) / GRM-CTSP-01 (tubo capilar de la sonda) | S19: MT_18A20087_260512 | T19: Pendiente | V19: =IF($G19<>"Numérico","",IF($U19="","Sin dato",IF(AND(OR(NOT(ISNUMBER($J19)),$U19>=$J19),OR(NOT(ISNUMBER($K19)),$U19<=$K19)),"Dentro de rango","Fuera de rango")))
A20: 2.1.2 | B20: 2. Línea de muestreo y cabezal | C20: 2.1 Cabezal TSP | D20: Tornillo de seguridad del cabezal | E20: Presencia y estado del tornillo de seguridad del cabezal TSP | F20: Inspección visual y manual: confirmar presencia y ajuste del tornillo de seguridad del cabezal. | G20: Presente / Ausente | I20: Debe estar presente | L20: Sí | M20: Cobrable | N20: Reemplazar o reparar el componente indicado en Repuesto/parte asociada; incluir en la cotización al cliente. | P20: Falta el tornillo de seguridad del cabezal TSP o no está correctamente ajustado. | Q20: Sí | R20: M02M2X4D912A4 | S20: MT_18A20087_260512 | T20: Pendiente | V20: =IF($G20<>"Numérico","",IF($U20="","Sin dato",IF(AND(OR(NOT(ISNUMBER($J20)),$U20>=$J20),OR(NOT(ISNUMBER($K20)),$U20<=$K20)),"Dentro de rango","Fuera de rango")))
A21: 2.1.3 | B21: 2. Línea de muestreo y cabezal | C21: 2.1 Cabezal TSP | D21: Limpieza interna del cabezal | E21: Acumulación de material particulado en el interior del cabezal | F21: Desmontar el cabezal y revisar visualmente el interior en busca de acumulación de material particulado; limpiar si es necesario. | G21: OK / No OK | I21: Libre de acumulación | L21: Sí | M21: Cobrable | N21: Reemplazar o reparar el componente indicado en Repuesto/parte asociada; incluir en la cotización al cliente. | P21: Se observa acumulación de material particulado en el interior del cabezal. | Q21: No | S21: MT_18A20087_260512 | T21: Pendiente | V21: =IF($G21<>"Numérico","",IF($U21="","Sin dato",IF(AND(OR(NOT(ISNUMBER($J21)),$U21>=$J21),OR(NOT(ISNUMBER($K21)),$U21<=$K21)),"Dentro de rango","Fuera de rango")))
A22: 2.1.4 | B22: 2. Línea de muestreo y cabezal | C22: 2.1 Cabezal TSP | D22: Malla fly-mesh de la sonda | E22: Estado de la malla de protección (fly-mesh) del cabezal de muestreo | F22: Inspección visual de la malla de protección del cabezal, verificando que no esté obstruida ni rota. | G22: OK / No OK | I22: Sin obstrucción ni rotura | L22: No | M22: Cobrable | N22: Reemplazar o reparar el componente indicado en Repuesto/parte asociada; incluir en la cotización al cliente. | P22: La malla de protección (fly-mesh) del cabezal está obstruida o rota. | Q22: No | R22: 1204089 (Screening Foil — a confirmar si corresponde a la malla fly-mesh) | S22: Service Training.pdf | T22: Pendiente | V22: =IF($G22<>"Numérico","",IF($U22="","Sin dato",IF(AND(OR(NOT(ISNUMBER($J22)),$U22>=$J22),OR(NOT(ISNUMBER($K22)),$U22<=$K22)),"Dentro de rango","Fuera de rango")))
A23: 2.1.5 | B23: 2. Línea de muestreo y cabezal | C23: 2.1 Cabezal TSP | D23: Calefactor opcional del cabezal (head heater) | E23: Presencia y funcionamiento del calefactor opcional del cabezal de muestreo, en los equipos que lo incorporen | F23: Verificar si el equipo trae instalada la opción de calefactor del cabezal; de ser así, comprobar su encendido y funcionamiento. | G23: Presente / Ausente | I23: Aplica solo si el equipo trae la opción instalada; de ser así, debe operar sin falla | L23: No | M23: Alerta | N23: Registrar el hallazgo en Observación y dar seguimiento; no requiere acción inmediata. | P23: El calefactor opcional del cabezal no enciende o no funciona correctamente. | Q23: No | S23: Service Training NEW v0.8 | T23: Pendiente | V23: =IF($G23<>"Numérico","",IF($U23="","Sin dato",IF(AND(OR(NOT(ISNUMBER($J23)),$U23>=$J23),OR(NOT(ISNUMBER($K23)),$U23<=$K23)),"Dentro de rango","Fuera de rango")))
A24: 2.2.1 | B24: 2. Línea de muestreo y cabezal | C24: 2.2 Tubo de muestra (1.5 m) | D24: Rectitud del tubo | E24: Deformación o torcedura del tubo de muestra | F24: Inspección visual a lo largo del tubo de muestra buscando deformaciones o torceduras. | G24: OK / No OK | I24: Sin deformación mecánica | L24: Sí | M24: Cobrable | N24: Reemplazar o reparar el componente indicado en Repuesto/parte asociada; incluir en la cotización al cliente. | P24: El tubo de muestra presenta deformación o torcedura. | Q24: Sí | R24: GR-TI-01 / X180120150AR (tubo 1.5 m completo con cabezal y secador Nafion) / 182-15 | S24: MT_18A12051_260811 | T24: Pendiente | V24: =IF($G24<>"Numérico","",IF($U24="","Sin dato",IF(AND(OR(NOT(ISNUMBER($J24)),$U24>=$J24),OR(NOT(ISNUMBER($K24)),$U24<=$K24)),"Dentro de rango","Fuera de rango")))
A25: 2.2.2 | B25: 2. Línea de muestreo y cabezal | C25: 2.2 Tubo de muestra (1.5 m) | D25: Fugas internas | E25: Prueba de estanqueidad del tubo de muestra | F25: Realizar prueba de estanqueidad del tubo de muestra (obturar un extremo y aplicar presión/vacío controlado, verificando que no haya caída). | G25: OK / No OK | I25: Sin fugas | L25: Sí | M25: Cobrable | N25: Reemplazar o reparar el componente indicado en Repuesto/parte asociada; incluir en la cotización al cliente. | P25: El tubo de muestra no pasa la prueba de estanqueidad (presenta fugas). | Q25: No | S25: MT_18A12051_260811 | T25: Pendiente | V25: =IF($G25<>"Numérico","",IF($U25="","Sin dato",IF(AND(OR(NOT(ISNUMBER($J25)),$U25>=$J25),OR(NOT(ISNUMBER($K25)),$U25<=$K25)),"Dentro de rango","Fuera de rango")))
A26: 2.2.3 | B26: 2. Línea de muestreo y cabezal | C26: 2.2 Tubo de muestra (1.5 m) | D26: Estructura interna de bronce | E26: Integridad de la estructura de bronce y su base respecto a las líneas neumáticas | F26: Inspección visual y manual de la estructura de bronce interna y su unión con las líneas neumáticas. | G26: OK / No OK | I26: Base unida a las líneas neumáticas | L26: Sí | M26: Cobrable | N26: Reemplazar o reparar el componente indicado en Repuesto/parte asociada; incluir en la cotización al cliente. | P26: La estructura interna de bronce del tubo de muestra está dañada o desprendida de las líneas neumáticas. | Q26: Sí | R26: GR-TI-01 | S26: MT_18A12051_260811 | T26: Pendiente | V26: =IF($G26<>"Numérico","",IF($U26="","Sin dato",IF(AND(OR(NOT(ISNUMBER($J26)),$U26>=$J26),OR(NOT(ISNUMBER($K26)),$U26<=$K26)),"Dentro de rango","Fuera de rango")))
A27: 2.2.4 | B27: 2. Línea de muestreo y cabezal | C27: 2.2 Tubo de muestra (1.5 m) | D27: Tornillería del tubo | E27: Deformación mecánica de la tornillería del tubo de muestra | F27: Inspección visual y manual de los tornillos del tubo de muestra, verificando ausencia de deformación. | G27: OK / No OK | I27: Sin deformación | L27: Sí | M27: Cobrable | N27: Reemplazar o reparar el componente indicado en Repuesto/parte asociada; incluir en la cotización al cliente. | P27: La tornillería del tubo de muestra presenta deformación mecánica. | Q27: Sí | R27: 4037489 / M00M3X3D913A2 | S27: MT_18A20087_260512 | T27: Pendiente | V27: =IF($G27<>"Numérico","",IF($U27="","Sin dato",IF(AND(OR(NOT(ISNUMBER($J27)),$U27>=$J27),OR(NOT(ISNUMBER($K27)),$U27<=$K27)),"Dentro de rango","Fuera de rango")))
A28: 2.2.5 | B28: 2. Línea de muestreo y cabezal | C28: 2.2 Tubo de muestra (1.5 m) | D28: O-Ring de la boquilla de entrada | E28: Desgaste de la junta tórica interna de la boquilla de ingreso de muestreo | F28: Desmontar la boquilla de entrada e inspeccionar visualmente el O-Ring en busca de desgaste o cortes. | G28: OK / No OK | I28: Sin desgaste que genere fuga | L28: Sí | M28: Cobrable | N28: Punto habitual de fuga documentado para la prueba de estanqueidad (Cadena 9). | O28: 3.3.1 | P28: El O-Ring de la boquilla de entrada del tubo de muestra presenta desgaste que genera fuga. | Q28: Sí | R28: C0004x1 | S28: MT_18A21062_260227 | T28: Pendiente | V28: =IF($G28<>"Numérico","",IF($U28="","Sin dato",IF(AND(OR(NOT(ISNUMBER($J28)),$U28>=$J28),OR(NOT(ISNUMBER($K28)),$U28<=$K28)),"Dentro de rango","Fuera de rango")))
A29: 2.2.6 | B29: 2. Línea de muestreo y cabezal | C29: 2.2 Tubo de muestra (1.5 m) | D29: Soporte del tubo (Sample Pipe Holder) y tornillo de fijación | E29: Presencia y estado del soporte que fija el tubo de muestra y de su tornillo de fijación | F29: Inspección visual y manual del soporte (Sample Pipe Holder) y su tornillo de fijación, verificando que sostenga el tubo con firmeza. | G29: OK / No OK | I29: Presente y firme | L29: Sí | M29: Cobrable | N29: Punto de contacto documentado en el diagnóstico del mecanismo de lift (Cadena 8) si falla el switch de fin de carrera. | O29: 8.1.5 | P29: El soporte del tubo de muestra (Sample Pipe Holder) o su tornillo de fijación no sujetan el tubo con firmeza. | Q29: Sí | R29: 1200005 (19" Inlet Probe Holder — a confirmar si es el Sample Pipe Holder) | S29: Service Training NEW v0.8 | T29: Pendiente | V29: =IF($G29<>"Numérico","",IF($U29="","Sin dato",IF(AND(OR(NOT(ISNUMBER($J29)),$U29>=$J29),OR(NOT(ISNUMBER($K29)),$U29<=$K29)),"Dentro de rango","Fuera de rango")))
A30: 2.3.1 | B30: 2. Línea de muestreo y cabezal | C30: 2.3 Protección contra intemperie | D30: Rain protector / deflector | E30: Presencia e integridad del protector de lluvia del tubo de muestra | F30: Inspección visual del protector de lluvia/deflector, verificando presencia e integridad. | G30: Presente / Ausente | I30: Presente y sin roturas | L30: Sí | M30: Cobrable | N30: Reemplazar o reparar el componente indicado en Repuesto/parte asociada; incluir en la cotización al cliente. | P30: Falta el protector de lluvia del tubo de muestra o está deteriorado. | Q30: Sí | R30: 4019827 (deflector) / 1202546 (rain protector, SKU independiente en Zoho) | S30: MT_18A20087_260512 | T30: Pendiente | V30: =IF($G30<>"Numérico","",IF($U30="","Sin dato",IF(AND(OR(NOT(ISNUMBER($J30)),$U30>=$J30),OR(NOT(ISNUMBER($K30)),$U30<=$K30)),"Dentro de rango","Fuera de rango")))
A31: 2.3.2 | B31: 2. Línea de muestreo y cabezal | C31: 2.3 Protección contra intemperie | D31: Acople de sellado tubo–shelter | E31: Acople de protección para filtrado de agua hacia el shelter | F31: Inspección visual del acople de protección contra filtración de agua hacia el shelter. | G31: OK / No OK | I31: Acople original instalado | L31: Sí | M31: Alerta | N31: Registrar el hallazgo en Observación y dar seguimiento; no requiere acción inmediata. | P31: El acople de sellado entre el tubo y el shelter no es el original o no cumple su función de protección contra agua. | Q31: Sí | S31: MT_18A20087_260512 | T31: Pendiente | V31: =IF($G31<>"Numérico","",IF($U31="","Sin dato",IF(AND(OR(NOT(ISNUMBER($J31)),$U31>=$J31),OR(NOT(ISNUMBER($K31)),$U31<=$K31)),"Dentro de rango","Fuera de rango")))
A32: 2.3.3 | B32: 2. Línea de muestreo y cabezal | C32: 2.3 Protección contra intemperie | D32: Sellados provisionales | E32: Uso de cinta u otros sellos provisionales en la conexión | F32: Inspección visual de la conexión tubo-shelter, verificando que no haya cinta u otros sellos improvisados. | G32: Sí/No | I32: No debe haber sellos provisionales | L32: Sí | M32: Alerta | N32: Registrar el hallazgo en Observación y dar seguimiento; no requiere acción inmediata. | P32: Se detectan sellos provisionales (cinta u otros) en la conexión del tubo con el shelter. | Q32: Sí | S32: MT_18A20087_260512 | T32: Pendiente | V32: =IF($G32<>"Numérico","",IF($U32="","Sin dato",IF(AND(OR(NOT(ISNUMBER($J32)),$U32>=$J32),OR(NOT(ISNUMBER($K32)),$U32<=$K32)),"Dentro de rango","Fuera de rango")))
A33: 2.3.4 | B33: 2. Línea de muestreo y cabezal | C33: 2.3 Protección contra intemperie | D33: Paso de techo (roof lead through) | E33: Estado del pasamuros/paso de techo por donde ingresa el tubo de muestra a la caseta | F33: Inspección visual del pasamuros/paso de techo por donde entra el tubo, verificando sellado y ausencia de daño. | G33: OK / No OK | I33: Sellado y sin daño | L33: Sí | M33: Alerta | N33: Registrar el hallazgo en Observación y dar seguimiento; no requiere acción inmediata. | P33: El pasamuros/paso de techo por donde ingresa el tubo de muestra no está sellado o presenta daño. | Q33: Sí | S33: Service Training NEW v0.8 | T33: Pendiente | V33: =IF($G33<>"Numérico","",IF($U33="","Sin dato",IF(AND(OR(NOT(ISNUMBER($J33)),$U33>=$J33),OR(NOT(ISNUMBER($K33)),$U33<=$K33)),"Dentro de rango","Fuera de rango")))
A34: 2.4.1 | B34: 2. Línea de muestreo y cabezal | C34: 2.4 Secador Nafion y drenaje | D34: Estado del Nafion | E34: Deterioro del secador Nafion integrado | F34: Inspección visual del secador Nafion integrado, revisando signos de deterioro. | G34: OK / No OK | I34: Sin deterioro | L34: Sí | M34: Cobrable | N34: Estado del Nafion ligado a la alarma Dryer y a “vacío no OK” (Cadena 2); revisar junto con el drenaje (2.4.2). | O34: 2.4.2 · 1.1.3 · 3.3.3 | P34: El secador Nafion integrado muestra signos de deterioro. | Q34: Sí | R34: 1205244 (Nafion sampling pipe) / X1801203A (Nafion tube assembly 0.98 m) | S34: MT_18A12051_260811 | T34: Pendiente | V34: =IF($G34<>"Numérico","",IF($U34="","Sin dato",IF(AND(OR(NOT(ISNUMBER($J34)),$U34>=$J34),OR(NOT(ISNUMBER($K34)),$U34<=$K34)),"Dentro de rango","Fuera de rango")))
A35: 2.4.2 | B35: 2. Línea de muestreo y cabezal | C35: 2.4 Secador Nafion y drenaje | D35: Water drain | E35: Drenaje de agua despejado y operativo | F35: Verificar visualmente que el drenaje de agua esté despejado, dejando salir el condensado sin obstrucción. | G35: OK / No OK | I35: Despejado | L35: Sí | M35: Cobrable | N35: Un drenaje obstruido puede contribuir a la alarma Dryer/vacío no OK (Cadena 2). | O35: 2.4.1 · 1.1.3 | P35: El drenaje de agua está obstruido. | Q35: No | R35: X180150 | S35: MT_18A12051_260811 | T35: Pendiente | V35: =IF($G35<>"Numérico","",IF($U35="","Sin dato",IF(AND(OR(NOT(ISNUMBER($J35)),$U35>=$J35),OR(NOT(ISNUMBER($K35)),$U35<=$K35)),"Dentro de rango","Fuera de rango")))
A36: 2.4.3 | B36: 2. Línea de muestreo y cabezal | C36: 2.4 Secador Nafion y drenaje | D36: Mangueras de la línea neumática | E36: Roturas, fisuras o endurecimiento de las mangueras | F36: Inspección visual y manual de las mangueras de la línea neumática, doblándolas suavemente para detectar endurecimiento o fisuras. | G36: OK / No OK | I36: Sin roturas | L36: Sí | M36: Cobrable | N36: Punto habitual de fuga/obstrucción documentado tanto en la prueba de estanqueidad (Cadena 9) como en el filtro cero (Cadena 4). | O36: 3.3.1 · 4.4.1 | P36: Las mangueras de la línea neumática presentan roturas, fisuras o endurecimiento. | Q36: Sí | R36: E003.2X6.4SILBL/GN/RT · E004.6X7.8SILBL/GN/RT (mangueras de silicona) / 1200914, 1200915 (conectores de manguera M3.2/F3.2) | S36: MT_18A12051_260811 | T36: Pendiente | V36: =IF($G36<>"Numérico","",IF($U36="","Sin dato",IF(AND(OR(NOT(ISNUMBER($J36)),$U36>=$J36),OR(NOT(ISNUMBER($K36)),$U36<=$K36)),"Dentro de rango","Fuera de rango")))
A37: 2.4.4 | B37: 2. Línea de muestreo y cabezal | C37: 2.4 Secador Nafion y drenaje | D37: Prueba de luz "First Aid" (obstrucción del tubo) | E37: Pasar una luz LED por el tubo de muestra: la luz debe atravesarlo completo, sin bloqueos ni residuos visibles; limpiar con aire comprimido si hay obstrucción | F37: Pasar una luz LED por un extremo del tubo de muestra y verificar desde el otro extremo que la luz se vea completa, sin bloqueos; si hay obstrucción, limpiar con aire comprimido. | G37: OK / No OK | I37: La luz debe pasar completa por el tubo | L37: No | M37: Alerta | N37: Registrar el hallazgo en Observación y dar seguimiento; no requiere acción inmediata. | P37: El tubo de muestra presenta obstrucción interna (no permite el paso completo de una luz LED). | Q37: Sí | S37: Correo GRIMM EDM180 TEST FIRST AID 18A12046 | T37: Pendiente | V37: =IF($G37<>"Numérico","",IF($U37="","Sin dato",IF(AND(OR(NOT(ISNUMBER($J37)),$U37>=$J37),OR(NOT(ISNUMBER($K37)),$U37<=$K37)),"Dentro de rango","Fuera de rango")))
A38: 2.4.5 | B38: 2. Línea de muestreo y cabezal | C38: 2.4 Secador Nafion y drenaje | D38: Trampa de agua y racor de salida (water trap / condensate outlet) | E38: Integridad física de la trampa de agua y del racor de salida de condensado, como componentes distintos del secador Nafion | F38: Inspección visual de la trampa de agua y del racor de salida de condensado, verificando ausencia de daño o fugas. | G38: OK / No OK | I38: Sin daño ni fugas | L38: No | M38: Cobrable | N38: Reemplazar o reparar el componente indicado en Repuesto/parte asociada; incluir en la cotización al cliente. | P38: La trampa de agua o el racor de salida de condensado presentan daño o fuga. | Q38: No | R38: 1204257 (frasco 25 mL) / 1204257OR (O-Ring 16x2 mm) | S38: Service Training NEW v0.8 | T38: Pendiente | V38: =IF($G38<>"Numérico","",IF($U38="","Sin dato",IF(AND(OR(NOT(ISNUMBER($J38)),$U38>=$J38),OR(NOT(ISNUMBER($K38)),$U38<=$K38)),"Dentro de rango","Fuera de rango")))
A39: 3.1.1 | B39: 3. Sistema neumático y etapa de secado | C39: 3.1 Bombas (vacío/secado y muestra) | D39: Flujo de la bomba de secado (vacuum flow) | E39: Medición del flujo de la bomba de secado en la salida de condensado (condensate outlet) | F39: Conectar un flujómetro en la salida de condensado (condensate outlet) de la bomba de secado y registrar la lectura en L/min con el equipo en operación normal. | G39: Numérico | H39: L/min | I39: Manual: ~1,8 L/min (válvula de aguja, equipos antiguos) o 2,0-2,2 L/min (tobera crítica, desde 2004). Service Training: 2,0 ±0,1 L/min. 2,45 L/min se registró en campo como valor cercano al límite de reemplazo | J39: 1.8 | K39: 2.3 | L39: Sí | M39: Bloqueante | N39: Tras confirmar fugas y P-Valve (Cadena 3), si aparece “Error 200” revisar el manómetro y el flujo de vacío en el pin de salida trasero (~2,1 L/min); considerar el kit de vacío/bomba. | O39: 3.1.2 · 3.2.1 · 3.4.1 | P39: El flujo de la bomba de secado, medido en la salida de condensado, está fuera del rango de referencia. | Q39: No | R39: 1205273 (kit reparación) / 1205271 o X1809001A115V (bomba completa 230V/115V) | S39: SER-MAN DUST MONITOR 180 / Service Training.pdf / MT_18A24064_260609 | T39: Requiere reemplazo | U39: 2.45 | V39: =IF($G39<>"Numérico","",IF($U39="","Sin dato",IF(AND(OR(NOT(ISNUMBER($J39)),$U39>=$J39),OR(NOT(ISNUMBER($K39)),$U39<=$K39)),"Dentro de rango","Fuera de rango"))) -> Fuera de rango | W39: Sí | X39: EJEMPLO — Flujo en el límite superior del rango; desgaste en el empaque del pistón. Borrar antes de usar el formato.
A40: 3.1.2 | B40: 3. Sistema neumático y etapa de secado | C40: 3.1 Bombas (vacío/secado y muestra) | D40: Estado del kit de la bomba (bomba de vacío/secado) | E40: Desgaste de los componentes internos del kit de la bomba de vacío | F40: Desmontar la bomba de vacío/secado e inspeccionar visualmente el desgaste de los componentes internos del kit. | G40: OK / No OK | I40: Sin desgaste significativo | L40: Sí | M40: Cobrable | N40: El kit de vacío es una causa documentada de error de flujo persistente (correo Flow Error) — reemplazarlo si el ajuste de flujo no resuelve el error. Ver Cadena 3. | O40: 3.1.1 · 3.4.1 | P40: Los componentes internos del kit de la bomba de vacío/secado presentan desgaste significativo. | Q40: Sí | R40: 1205273 / 1204472 (juego de bielas 70SH) / U0929002552 (sello Viton) | S40: MT_18A20087_260512 | T40: Pendiente | V40: =IF($G40<>"Numérico","",IF($U40="","Sin dato",IF(AND(OR(NOT(ISNUMBER($J40)),$U40>=$J40),OR(NOT(ISNUMBER($K40)),$U40<=$K40)),"Dentro de rango","Fuera de rango")))
A41: 3.1.3 | B41: 3. Sistema neumático y etapa de secado | C41: 3.1 Bombas (vacío/secado y muestra) | D41: Empaque del pistón (sealing sleeve) de la bomba de vacío/secado | E41: Desgaste del empaque del pistón de la bomba de secado | F41: Con la bomba desmontada, inspeccionar visualmente el empaque del pistón (sealing sleeve) en busca de desgaste. | G41: OK / No OK | I41: Sin desgaste | L41: Sí | M41: Cobrable | N41: Reemplazar o reparar el componente indicado en Repuesto/parte asociada; incluir en la cotización al cliente. | P41: El empaque del pistón (sealing sleeve) de la bomba de vacío/secado presenta desgaste. | Q41: Sí | R41: 1204480 | S41: MT_18A24064_260609 | T41: Pendiente | V41: =IF($G41<>"Numérico","",IF($U41="","Sin dato",IF(AND(OR(NOT(ISNUMBER($J41)),$U41>=$J41),OR(NOT(ISNUMBER($K41)),$U41<=$K41)),"Dentro de rango","Fuera de rango")))
A42: 3.1.4 | B42: 3. Sistema neumático y etapa de secado | C42: 3.1 Bombas (vacío/secado y muestra) | D42: Ruido y vibración de la bomba de vacío/secado | E42: Ruido o vibración anómala de la bomba | F42: Con el equipo en operación, escuchar y palpar la bomba de secado para detectar ruido o vibración anómala. | G42: OK / No OK | I42: Sin ruido anómalo | L42: No | M42: Alerta | N42: Registrar el hallazgo en Observación y dar seguimiento; no requiere acción inmediata. | P42: La bomba de vacío/secado presenta ruido o vibración anómala. | Q42: No | R42: M6015X8M4 / GR-VD158M4-01 (amortiguadores de vibración) | S42: Derivado | T42: Pendiente | V42: =IF($G42<>"Numérico","",IF($U42="","Sin dato",IF(AND(OR(NOT(ISNUMBER($J42)),$U42>=$J42),OR(NOT(ISNUMBER($K42)),$U42<=$K42)),"Dentro de rango","Fuera de rango")))
A43: 3.1.5 | B43: 3. Sistema neumático y etapa de secado | C43: 3.1 Bombas (vacío/secado y muestra) | D43: Bomba de muestra (Sample Pump) | E43: El equipo incorpora una bomba de muestra física, distinta de la bomba de vacío/secado (ítems 3.1.1-3.1.4); verificar presencia, fijación y funcionamiento | F43: Localizar la bomba de muestra (distinta de la bomba de vacío/secado) según el diagrama interno del equipo; verificar su fijación y, con el equipo encendido, confirmar que opera sin fugas ni ruido anómalo. | G43: OK / No OK | I43: Operativa, sin fugas ni ruido anómalo | L43: Sí | M43: Bloqueante | N43: No liberar el equipo hasta resolver. Reparar/reemplazar el componente asociado (ver Repuesto/parte asociada); si no se resuelve en sitio, escalar a soporte GRIMM/DURAG. | P43: La bomba de muestra (Sample Pump) no opera correctamente, presenta fugas o ruido anómalo. | Q43: Sí | R43: X1809002A115V / X1809002A1 (bomba tipo 203, 115V/230V) / GRM-SPK-01 (placa) / GRM-SPK-02 (sello) / 1204476 (bloque bomba 203) / 1204474 (anillo de suspensión) | S43: Service Training NEW v0.8 | T43: Pendiente | V43: =IF($G43<>"Numérico","",IF($U43="","Sin dato",IF(AND(OR(NOT(ISNUMBER($J43)),$U43>=$J43),OR(NOT(ISNUMBER($K43)),$U43<=$K43)),"Dentro de rango","Fuera de rango")))
A44: 3.1.6 | B44: 3. Sistema neumático y etapa de secado | C44: 3.1 Bombas (vacío/secado y muestra) | D44: Depósito de compensación (Compensating Reservoir) | E44: Presencia e integridad del depósito de compensación del circuito neumático | F44: Inspección visual del depósito de compensación (Compensating Reservoir) del circuito neumático, verificando presencia e integridad. | G44: Presente / Ausente | I44: Presente, sin daño | L44: No | M44: Cobrable | N44: Reemplazar o reparar el componente indicado en Repuesto/parte asociada; incluir en la cotización al cliente. | P44: Falta el depósito de compensación del circuito neumático o presenta daño. | Q44: No | R44: X18090043 (triple hole) / X18090042 (twin hole) + juntas C0620111102 / C0620111101 | S44: Service Training NEW v0.8 | T44: Pendiente | V44: =IF($G44<>"Numérico","",IF($U44="","Sin dato",IF(AND(OR(NOT(ISNUMBER($J44)),$U44>=$J44),OR(NOT(ISNUMBER($K44)),$U44<=$K44)),"Dentro de rango","Fuera de rango")))
A45: 3.2.1 | B45: 3. Sistema neumático y etapa de secado | C45: 3.2 Instrumentación de presión | D45: Manómetro de vacío | E45: El manómetro entrega lectura y no presenta falla mecánica | F45: Con el equipo en operación, leer el manómetro de vacío y verificar que entregue una lectura estable, sin daño mecánico visible en la carátula o aguja. | G45: OK / No OK | I45: Debe entregar lectura | L45: Sí | M45: Cobrable | N45: Es el primer punto de verificación cuando el LED del dryer está en rojo durante el self-test (manómetro tras la tapa del panel frontal). Ver Cadena 2. | O45: 3.2.2 · 1.1.3 · 3.3.3 | P45: El manómetro de vacío no entrega lectura o presenta daño mecánico. | Q45: Sí | R45: 1201007 | S45: MT_18A19035_260727 | T45: Pendiente | V45: =IF($G45<>"Numérico","",IF($U45="","Sin dato",IF(AND(OR(NOT(ISNUMBER($J45)),$U45>=$J45),OR(NOT(ISNUMBER($K45)),$U45<=$K45)),"Dentro de rango","Fuera de rango")))
A46: 3.2.2 | B46: 3. Sistema neumático y etapa de secado | C46: 3.2 Instrumentación de presión | D46: Presión negativa de succión (vacío) | E46: Presión negativa generada por la etapa de secado, leída en el manómetro/sensor de vacío | F46: Leer el valor de vacío en el manómetro o en el sensor de vacío del software de diagnóstico, con el equipo en operación normal. | G46: Numérico | H46: kPa | I46: -60 ±10 kPa (Service Training); rango técnico general del equipo 0 a -30 mBar | J46: -70 | K46: -50 | L46: Sí | M46: Bloqueante | N46: Si sale fuera de -70/-50 kPa, forma parte de la Cadena 3 (error de flujo): revisar tras confirmar fugas (3.3.1) y voltaje de P-Valve (3.4.2); también ligado a la Cadena 2 (dryer). | O46: 3.3.1 · 3.4.2 · 3.1.1 | P46: La presión de vacío generada por la etapa de secado está fuera del rango de referencia. | Q46: No | R46: H6DP015AZ8H / H6DSDX01D4 (sensores de presión — a confirmar cuál corresponde) | S46: Service Training.pdf | T46: Pendiente | V46: =IF($G46<>"Numérico","",IF($U46="","Sin dato",IF(AND(OR(NOT(ISNUMBER($J46)),$U46>=$J46),OR(NOT(ISNUMBER($K46)),$U46<=$K46)),"Dentro de rango","Fuera de rango"))) -> Sin dato
A47: 3.2.3 | B47: 3. Sistema neumático y etapa de secado | C47: 3.2 Instrumentación de presión | D47: Presostatos (pressure switches) | E47: Operatividad de los presostatos del circuito neumático (hasta tres, según Service Training NEW) | F47: Con el equipo en operación (y, si aplica, durante el ciclo de self-test), verificar en el software de diagnóstico que los presostatos conmuten según lo esperado. | G47: OK / No OK | I47: Deben conmutar correctamente | L47: No | M47: Cobrable | N47: Reemplazar o reparar el componente indicado en Repuesto/parte asociada; incluir en la cotización al cliente. | P47: Uno o más presostatos del circuito neumático no conmutan correctamente. | Q47: No | R47: X1809006 (presostato vacío -350 mbar) / X1809007 (presure linker -5kPa) | S47: Service Training NEW v0.8 | T47: Pendiente | V47: =IF($G47<>"Numérico","",IF($U47="","Sin dato",IF(AND(OR(NOT(ISNUMBER($J47)),$U47>=$J47),OR(NOT(ISNUMBER($K47)),$U47<=$K47)),"Dentro de rango","Fuera de rango")))
A48: 3.3.1 | B48: 3. Sistema neumático y etapa de secado | C48: 3.3 Estanqueidad | D48: Prueba de fugas del circuito (test de presión) | E48: Cargar el circuito a 80 mmHg con tensiómetro y verificar la caída de presión | F48: Cargar el circuito neumático a 80 mmHg con un tensiómetro (o equipo equivalente) y medir la caída de presión en el tiempo indicado por el manual (10-20 s). | G48: Numérico | H48: mmHg | I48: Manual: la caída no debe superar 2 mmHg en 10 s. Service Training: el sistema es estanco si tras 20 s queda por encima de 60 mmHg | J48: 60 | K48: 80 | L48: Sí | M48: Bloqueante | N48: Si tras 20 s el sistema queda por debajo de 60 mmHg: buscar la fuga con el esquema neumático (flow schematics) del equipo. Puntos habituales: O-rings del holder (3.3.2), O-ring de la boquilla de entrada (2.2.5), mangueras (2.4.3). Ver Cadena 9. | O48: 3.3.2 · 2.2.5 · 2.4.3 | P48: El circuito neumático no pasa la prueba de estanqueidad (presenta fuga). | Q48: No | R48: 1206223 / 1206225 (conjuntos de tubería, si la fuga está ahí) | S48: SER-MAN DUST MONITOR 180 / Service Training.pdf | T48: Pendiente | V48: =IF($G48<>"Numérico","",IF($U48="","Sin dato",IF(AND(OR(NOT(ISNUMBER($J48)),$U48>=$J48),OR(NOT(ISNUMBER($K48)),$U48<=$K48)),"Dentro de rango","Fuera de rango"))) -> Sin dato
A49: 3.3.2 | B49: 3. Sistema neumático y etapa de secado | C49: 3.3 Estanqueidad | D49: O-Rings y conectores del holder | E49: Estado de los O-Rings y conectores del cabezal de muestra (holder) | F49: Desmontar el cabezal de muestra (holder) e inspeccionar visualmente los O-Rings y conectores en busca de desgaste. | G49: OK / No OK | I49: Sin desgaste | L49: Sí | M49: Cobrable | N49: Punto habitual de fuga documentado para la prueba de estanqueidad (Cadena 9). | O49: 3.3.1 | P49: Los O-Rings o conectores del cabezal de muestra (holder) presentan desgaste. | Q49: Sí | R49: C0004x1.2N70 / 1201011 | S49: MT_18A12051_260811 | T49: Pendiente | V49: =IF($G49<>"Numérico","",IF($U49="","Sin dato",IF(AND(OR(NOT(ISNUMBER($J49)),$U49>=$J49),OR(NOT(ISNUMBER($K49)),$U49<=$K49)),"Dentro de rango","Fuera de rango")))
A50: 3.3.3 | B50: 3. Sistema neumático y etapa de secado | C50: 3.3 Estanqueidad | D50: Alerta "Dryer" | E50: Alerta activa de la etapa de secado en el equipo | F50: Revisar en pantalla o en el software de diagnóstico si la alerta "Dryer" está activa. | G50: Sí/No | I50: No debe estar activa | L50: Sí | M50: Bloqueante | N50: Códigos SER-MAN “VACUUM NOT OK” (revisar 3.2.1/3.2.2 y 2.4.1/2.4.2) o “VACUUM SWITCH” (presostato cerrado sin vacío suficiente — el manual indica contactar al fabricante/representante, no es resoluble en sitio). Ver Cadena 2. | O50: 3.2.1 · 3.2.2 · 2.4.1 · 2.4.2 | P50: La alerta «Dryer» está activa en el equipo. | Q50: Sí | S50: MT_18A21062_260227 | T50: Pendiente | V50: =IF($G50<>"Numérico","",IF($U50="","Sin dato",IF(AND(OR(NOT(ISNUMBER($J50)),$U50>=$J50),OR(NOT(ISNUMBER($K50)),$U50<=$K50)),"Dentro de rango","Fuera de rango")))
A51: 3.4.1 | B51: 3. Sistema neumático y etapa de secado | C51: 3.4 Flujo de muestra y válvulas | D51: Flujo de muestra (sample flow) | E51: Caudal de aire de muestreo medido en operación normal | F51: Con un flujómetro de referencia, medir el caudal de aire de muestreo en operación normal y compararlo con la lectura interna del equipo. | G51: Numérico | H51: L/min | I51: 1,2 L/min ±3% (Service Training); manual: no debe desviarse más de 0,02 L/min de 1,20 L/min | J51: 1.16 | K51: 1.24 | L51: Sí | M51: Bloqueante | N51: Orden documentado (correo Flow Error 18A12047): 1) fugas (3.3.1), 2) voltaje P-Valve (3.4.2, referencia de campo 11,47 V), 3) aislar el espectrómetro (otra carcasa/tubería externa), 4) limpiar la tarjeta análoga (5.1.2), 5) ajuste manual de flujo por Terminal (ctrl-f). Ver Cadena 3. | O51: 3.3.1 · 3.4.2 · 3.1.1 · 3.1.2 · 5.1.2 · 7.1.4 | P51: El caudal de aire de muestreo está fuera del rango de referencia. | Q51: No | S51: Service Training.pdf / SER-MAN DUST MONITOR 180 | T51: Pendiente | V51: =IF($G51<>"Numérico","",IF($U51="","Sin dato",IF(AND(OR(NOT(ISNUMBER($J51)),$U51>=$J51),OR(NOT(ISNUMBER($K51)),$U51<=$K51)),"Dentro de rango","Fuera de rango"))) -> Sin dato
A52: 3.4.2 | B52: 3. Sistema neumático y etapa de secado | C52: 3.4 Flujo de muestra y válvulas | D52: Voltaje de la válvula proporcional (P-Valve) | E52: Tensión de control de la válvula proporcional del circuito de flujo | F52: Con el equipo en operación, medir con multímetro la tensión de control de la válvula proporcional (P-Valve) en los puntos de prueba indicados en el esquema eléctrico. | G52: Numérico | H52: V | I52: Service Training: 3,7 ±0,4 V. Manual: ~6,5 V en medición (aceptable 6-7 V), ~4,5 V en arranque. Valores no reconciliados entre fuentes: verificar según generación del equipo | J52: 3.3 | K52: 7 | L52: No | M52: Cobrable | N52: Referencia de campo documentada: 11,47 V con flujo fuera de rango. Forma parte de la Cadena 3 (error de flujo) — si no se corrige, continuar con limpieza de la tarjeta análoga y ajuste por Terminal. | O52: 3.4.1 · 5.1.2 | P52: La tensión de control de la válvula proporcional (P-Valve) está fuera del rango esperado. | Q52: No | R52: X1809003 (válvula proporcional completa) | S52: Service Training.pdf / SER-MAN DUST MONITOR 180 | T52: Pendiente | V52: =IF($G52<>"Numérico","",IF($U52="","Sin dato",IF(AND(OR(NOT(ISNUMBER($J52)),$U52>=$J52),OR(NOT(ISNUMBER($K52)),$U52<=$K52)),"Dentro de rango","Fuera de rango"))) -> Sin dato
A53: 3.4.3 | B53: 3. Sistema neumático y etapa de secado | C53: 3.4 Flujo de muestra y válvulas | D53: Controlador de aire de purga (Rinsing Air Controller) | E53: Flujo del aire de purga/barrido del controlador RAC y su filtro asociado | F53: Medir con flujómetro el flujo de aire de purga/barrido en la salida del controlador RAC. | G53: Numérico | H53: L/min | I53: 0,3-0,5 L/min; chequeo anual | J53: 0.3 | K53: 0.5 | L53: No | M53: Cobrable | N53: Protocolo documentado: retirar el tubo central del RAC, conectar el flujómetro, enviar “ctrl+f” por HyperTerminal; el flujo debe quedar en 0,3-0,5 L/min. Si no, revisar el filtro RAC (3.4.6). Ver Cadena 7. | O53: 3.4.6 | P53: El flujo de aire de purga del controlador RAC está fuera del rango de referencia. | Q53: No | R53: 1206221 (filtro + controlador de aire de purga, conjunto) | S53: SER-MAN DUST MONITOR 180 / Service Training.pdf | T53: Pendiente | V53: =IF($G53<>"Numérico","",IF($U53="","Sin dato",IF(AND(OR(NOT(ISNUMBER($J53)),$U53>=$J53),OR(NOT(ISNUMBER($K53)),$U53<=$K53)),"Dentro de rango","Fuera de rango"))) -> Sin dato
A54: 3.4.4 | B54: 3. Sistema neumático y etapa de secado | C54: 3.4 Flujo de muestra y válvulas | D54: Flujo en modo self-test | E54: Flujo mostrado durante el ciclo de autodiagnóstico (self-test) del equipo | F54: Iniciar el ciclo de self-test desde el panel y leer el flujo mostrado en pantalla o en el software durante ese ciclo. | G54: Numérico | H54: L/min | I54: Debe ser 0,0 L/min (o 0,3 L/min según variante); si no, revisar estanqueidad o la válvula | J54: 0 | K54: 0.3 | L54: No | M54: Alerta | N54: Registrar el hallazgo en Observación y dar seguimiento; no requiere acción inmediata. | P54: El flujo mostrado durante el ciclo de self-test no corresponde al valor esperado. | Q54: Sí | S54: Correo GRIMM EDM180 TEST FIRST AID 18A12046 / Correo Flow Error 18A12047 | T54: Pendiente | V54: =IF($G54<>"Numérico","",IF($U54="","Sin dato",IF(AND(OR(NOT(ISNUMBER($J54)),$U54>=$J54),OR(NOT(ISNUMBER($K54)),$U54<=$K54)),"Dentro de rango","Fuera de rango"))) -> Sin dato
A55: 3.4.5 | B55: 3. Sistema neumático y etapa de secado | C55: 3.4 Flujo de muestra y válvulas | D55: Válvula de autodiagnóstico (Valve Selftest) | E55: Operatividad de la válvula dedicada al ciclo de self-test, distinta de la válvula proporcional (P-Valve) | F55: Durante el ciclo de self-test, verificar visualmente o por escucha que la válvula dedicada al autodiagnóstico abra y cierre correctamente. | G55: OK / No OK | I55: Debe abrir y cerrar correctamente durante el self-test | L55: No | M55: Cobrable | N55: Reemplazar o reparar el componente indicado en Repuesto/parte asociada; incluir en la cotización al cliente. | P55: La válvula dedicada al ciclo de self-test no abre o no cierra correctamente. | Q55: No | R55: 1206226 | S55: Service Training NEW v0.8 | T55: Pendiente | V55: =IF($G55<>"Numérico","",IF($U55="","Sin dato",IF(AND(OR(NOT(ISNUMBER($J55)),$U55>=$J55),OR(NOT(ISNUMBER($K55)),$U55<=$K55)),"Dentro de rango","Fuera de rango")))
A56: 3.4.6 | B56: 3. Sistema neumático y etapa de secado | C56: 3.4 Flujo de muestra y válvulas | D56: Filtro de aire de purga (Rinsing Air Filter) | E56: Estado y colmatación del filtro asociado al controlador de aire de purga (RAC, ítem 3.4.3) | F56: Desmontar el filtro asociado al controlador RAC e inspeccionar visualmente su grado de colmatación. | G56: OK / No OK | I56: Sin colmatación | L56: No | M56: Cobrable | N56: Filtro asociado al controlador RAC (3.4.3); revisar junto con el flujo de purga si sale fuera de rango. | O56: 3.4.3 | P56: El filtro asociado al controlador de aire de purga (RAC) está colmatado. | Q56: No | R56: J01SM16592K | S56: Service Training NEW v0.8 | T56: Pendiente | V56: =IF($G56<>"Numérico","",IF($U56="","Sin dato",IF(AND(OR(NOT(ISNUMBER($J56)),$U56>=$J56),OR(NOT(ISNUMBER($K56)),$U56<=$K56)),"Dentro de rango","Fuera de rango")))
A57: 4.1.1 | B57: 4. Espectrómetro: cámara de medida y óptica | C57: 4.1 Estado del recinto | D57: Humedad / condensación | E57: Presencia de humedad o condensación en el gabinete del espectrómetro | F57: Abrir el gabinete del espectrómetro e inspeccionar visualmente en busca de humedad o gotas de condensación. | G57: Sí/No | I57: Ausencia de humedad | L57: Sí | M57: Alerta | N57: Registrar el hallazgo en Observación y dar seguimiento; no requiere acción inmediata. | P57: Se observa humedad o condensación dentro del gabinete del espectrómetro. | Q57: Sí | S57: MT_18A18033_260108 | T57: Pendiente | V57: =IF($G57<>"Numérico","",IF($U57="","Sin dato",IF(AND(OR(NOT(ISNUMBER($J57)),$U57>=$J57),OR(NOT(ISNUMBER($K57)),$U57<=$K57)),"Dentro de rango","Fuera de rango")))
A58: 4.1.2 | B58: 4. Espectrómetro: cámara de medida y óptica | C58: 4.1 Estado del recinto | D58: Óxido y corrosión | E58: Óxido o corrosión en componentes internos por ingreso de humedad | F58: Inspección visual de los componentes internos del gabinete del espectrómetro en busca de óxido o corrosión. | G58: Sí/No | I58: Sin óxido ni corrosión | L58: Sí | M58: Cobrable | N58: Reemplazar o reparar el componente indicado en Repuesto/parte asociada; incluir en la cotización al cliente. | P58: Se observa óxido o corrosión en componentes internos del gabinete del espectrómetro. | Q58: Sí | S58: MT_18A18033_260108 | T58: Pendiente | V58: =IF($G58<>"Numérico","",IF($U58="","Sin dato",IF(AND(OR(NOT(ISNUMBER($J58)),$U58>=$J58),OR(NOT(ISNUMBER($K58)),$U58<=$K58)),"Dentro de rango","Fuera de rango")))
A59: 4.1.3 | B59: 4. Espectrómetro: cámara de medida y óptica | C59: 4.1 Estado del recinto | D59: Limpieza de la cámara de medida | E59: Necesidad de limpieza integral de la cámara de medición | F59: Inspección visual del interior de la cámara de medición para determinar si requiere limpieza integral. | G59: OK / No OK | I59: Cámara limpia | L59: Sí | M59: Cobrable | N59: Reemplazar o reparar el componente indicado en Repuesto/parte asociada; incluir en la cotización al cliente. | P59: La cámara de medición requiere limpieza integral. | Q59: Sí | R59: Si el daño de la cámara es irreparable en campo: 4037324 (unidad de medida 187 completa) o 4037324B (sin unidad láser) | S59: MT_18A24064_260609 | T59: Pendiente | V59: =IF($G59<>"Numérico","",IF($U59="","Sin dato",IF(AND(OR(NOT(ISNUMBER($J59)),$U59>=$J59),OR(NOT(ISNUMBER($K59)),$U59<=$K59)),"Dentro de rango","Fuera de rango")))
A60: 4.2.1 | B60: 4. Espectrómetro: cámara de medida y óptica | C60: 4.2 Componentes ópticos | D60: Espejo y tornillo del espejo | E60: Estado del espejo y de su O-Ring de montaje | F60: Inspección visual del espejo óptico y de su O-Ring de montaje, verificando ausencia de daño o fuga. | G60: OK / No OK | I60: Sin daño ni fuga | L60: Sí | M60: Cobrable | N60: Reemplazar o reparar el componente indicado en Repuesto/parte asociada; incluir en la cotización al cliente. | P60: El espejo óptico o su O-Ring de montaje presentan daño o fuga. | Q60: Sí | R60: GRM-MS-001 (tornillo del espejo) / C00014x2.5NBR70 y C00014x2N70 (O-Rings, dos medidas) | S60: MT_18A20087_260512 | T60: Pendiente | V60: =IF($G60<>"Numérico","",IF($U60="","Sin dato",IF(AND(OR(NOT(ISNUMBER($J60)),$U60>=$J60),OR(NOT(ISNUMBER($K60)),$U60<=$K60)),"Dentro de rango","Fuera de rango")))
A61: 4.2.2 | B61: 4. Espectrómetro: cámara de medida y óptica | C61: 4.2 Componentes ópticos | D61: Manchas en la óptica | E61: Manchas o suciedad que generen ruido electrónico en la medida | F61: Inspección visual de los componentes ópticos con luz directa, buscando manchas o suciedad que puedan generar ruido en la señal. | G61: Sí/No | I61: Óptica libre de manchas | L61: Sí | M61: Cobrable | N61: Código SER-MAN “NEW CALIBRATION” con DC-Diff demasiado alto → limpiar la óptica del láser. Ver Cadena 11. | O61: 4.3.1 · 4.3.2 | P61: Se observan manchas o suciedad en los componentes ópticos que pueden generar ruido en la medición. | Q61: Sí | S61: MT_18A20034_250703_Mantenimiento | T61: Pendiente | V61: =IF($G61<>"Numérico","",IF($U61="","Sin dato",IF(AND(OR(NOT(ISNUMBER($J61)),$U61>=$J61),OR(NOT(ISNUMBER($K61)),$U61<=$K61)),"Dentro de rango","Fuera de rango")))
A62: 4.2.3 | B62: 4. Espectrómetro: cámara de medida y óptica | C62: 4.2 Componentes ópticos | D62: Boquilla de ingreso de material particulado | E62: Estado de la boquilla y su sello neumático | F62: Inspección visual de la boquilla de ingreso y de su sello neumático. | G62: OK / No OK | I62: Sello neumático íntegro | L62: Sí | M62: Cobrable | N62: Reemplazar o reparar el componente indicado en Repuesto/parte asociada; incluir en la cotización al cliente. | P62: La boquilla de ingreso de material particulado o su sello neumático presentan daño. | Q62: Sí | R62: C0004x1 / 1203297 (boquilla de entrada 1100) | S62: MT_18A18033_260108 | T62: Pendiente | V62: =IF($G62<>"Numérico","",IF($U62="","Sin dato",IF(AND(OR(NOT(ISNUMBER($J62)),$U62>=$J62),OR(NOT(ISNUMBER($K62)),$U62<=$K62)),"Dentro de rango","Fuera de rango")))
A63: 4.3.1 | B63: 4. Espectrómetro: cámara de medida y óptica | C63: 4.3 Unidad láser | D63: Corriente de operación en alta (La_h) | E63: Corriente del diodo láser en alta según software Diagnosis GRIMM | F63: Consultar en el software Diagnosis GRIMM la lectura de corriente del diodo láser en modo alta (La_h). | G63: Numérico | H63: mA | I63: Ningún documento de referencia (manual, Service Training) da el valor máximo en mA; ver también ítem de potencia óptica (mW) como criterio alternativo | J63: PENDIENTE DE VALIDAR | K63: PENDIENTE DE VALIDAR | L63: Sí | M63: Bloqueante | N63: Código SER-MAN “NEW CALIBRATION” con DC-Diff demasiado bajo → láser apagado o dañado; revisar la tarjeta driver del láser (5.1.4). Ver Cadena 11. | O63: 4.3.2 · 5.1.4 | P63: La corriente del diodo láser en modo alta (La_h) está fuera del comportamiento esperado. | Q63: Sí | R63: X187LDRVR (unidad láser) / X187LDRVR-R (reparación) | S63: MT_18A24064_260609 — PENDIENTE DE VALIDAR | T63: Pendiente | V63: =IF($G63<>"Numérico","",IF($U63="","Sin dato",IF(AND(OR(NOT(ISNUMBER($J63)),$U63>=$J63),OR(NOT(ISNUMBER($K63)),$U63<=$K63)),"Dentro de rango","Fuera de rango"))) -> Sin dato
A64: 4.3.2 | B64: 4. Espectrómetro: cámara de medida y óptica | C64: 4.3 Unidad láser | D64: Valores K-Line: DC_h y DC_diff | E64: Lectura de DC_h y DC_diff (DC_h menos DC_d) en el diagnóstico del láser | F64: Consultar en el software Diagnosis GRIMM (menú de diagnóstico del láser) las lecturas de DC_h y calcular DC_diff (DC_h − DC_d). | G64: Numérico | H64: mV | I64: DC_h debe ser menor a 500,0 mV; DC_diff (DC_h - DC_d) debe ser menor a 100,0 mV | K64: 500 | L64: Sí | M64: Bloqueante | N64: Mismo código “NEW CALIBRATION” que 4.3.1; DC-Diff demasiado alto indica óptica del láser contaminada (limpiar, ítem 4.2.2) en vez de láser dañado. | O64: 4.3.1 · 4.2.2 | P64: Los valores DC_h/DC_diff del diagnóstico del láser exceden los límites de referencia. | Q64: Sí | R64: X187LDRVR / X187LDRVR-R / 1205047 (portaláser completo) | S64: Service Training.pdf | T64: Pendiente | V64: =IF($G64<>"Numérico","",IF($U64="","Sin dato",IF(AND(OR(NOT(ISNUMBER($J64)),$U64>=$J64),OR(NOT(ISNUMBER($K64)),$U64<=$K64)),"Dentro de rango","Fuera de rango"))) -> Sin dato
A65: 4.3.5 | B65: 4. Espectrómetro: cámara de medida y óptica | C65: 4.3 Unidad láser | D65: Potencia óptica del láser | E65: Potencia óptica medida en alta y en baja (modo dúplex) | F65: Con el medidor de potencia óptica indicado en el manual, medir la potencia del láser en modo alta y en modo baja (dúplex). | G65: Numérico | H65: mW | I65: Alta: 30 ±10 mW. Baja: 0,4 ±0,1 mW. Potencia máxima de fábrica 60 mW; clase láser 3B (máx. 500 mW, 660 nm) | J65: 20 | K65: 40 | L65: No | M65: Cobrable | N65: Si la potencia óptica está fuera de rango y no se resuelve con limpieza de óptica (4.2.2) ni ajuste, corresponde a la falla de láser documentada en el correo Flow Error (reemplazo de unidad láser completa, ref. de campo pieza 1205338 “Lasereinheit 187 komplett”). | O65: 4.2.2 · 5.1.4 | P65: La potencia óptica del láser, medida en alta o en baja, está fuera del rango de referencia. | Q65: Sí | R65: X187LDRVR / X187LDRVR-R | S65: Service Training.pdf | T65: Pendiente | V65: =IF($G65<>"Numérico","",IF($U65="","Sin dato",IF(AND(OR(NOT(ISNUMBER($J65)),$U65>=$J65),OR(NOT(ISNUMBER($K65)),$U65<=$K65)),"Dentro de rango","Fuera de rango"))) -> Sin dato
A66: 4.3.3 | B66: 4. Espectrómetro: cámara de medida y óptica | C66: 4.3 Unidad láser | D66: Respuesta a verificación con dolomita | E66: El láser reacciona durante el procedimiento de verificación con dolomita | F66: Ejecutar el procedimiento de verificación con dolomita (partícula patrón) y observar en el software que el láser reaccione con el conteo esperado. | G66: OK / No OK | I66: Debe presentar reacción | L66: Sí | M66: Bloqueante | N66: Si el láser no reacciona a la verificación con dolomita, corresponde al mismo ciclo de recalibración completo del Service Training (Cadena 13). | O66: 5.2.1 · 1.3.3 | P66: El láser no presenta la reacción esperada durante la verificación con dolomita. | Q66: No | R66: X187LDRVR / X187LDRVR-R | S66: MT_18A20087_260512 | T66: Pendiente | V66: =IF($G66<>"Numérico","",IF($U66="","Sin dato",IF(AND(OR(NOT(ISNUMBER($J66)),$U66>=$J66),OR(NOT(ISNUMBER($K66)),$U66<=$K66)),"Dentro de rango","Fuera de rango")))
A67: 4.3.4 | B67: 4. Espectrómetro: cámara de medida y óptica | C67: 4.3 Unidad láser | D67: Capacidad de ajuste de potenciómetros | E67: Los potenciómetros permiten llevar la ganancia al rango operativo | F67: Con el equipo abierto y en modo de ajuste, girar los potenciómetros de ganancia y verificar que permitan llevar la lectura al rango operativo. | G67: Sí/No | I67: Debe permitir el ajuste | L67: Sí | M67: Cobrable | N67: Reemplazar o reparar el componente indicado en Repuesto/parte asociada; incluir en la cotización al cliente. | P67: Los potenciómetros de ganancia no permiten llevar la lectura al rango operativo. | Q67: Sí | R67: X187LDRVR-R | S67: MT_18A20087_260512 | T67: Pendiente | V67: =IF($G67<>"Numérico","",IF($U67="","Sin dato",IF(AND(OR(NOT(ISNUMBER($J67)),$U67>=$J67),OR(NOT(ISNUMBER($K67)),$U67<=$K67)),"Dentro de rango","Fuera de rango")))
A68: 4.4.1 | B68: 4. Espectrómetro: cámara de medida y óptica | C68: 4.4 Pruebas funcionales del espectrómetro | D68: Prueba de filtro cero (0-Filter) | E68: Colocar filtro de partículas cero en la entrada y verificar el conteo | F68: Colocar el filtro de partículas cero en la entrada de muestreo y verificar en el software que todos los canales reporten conteo cero. | G68: OK / No OK | I68: Todos los conteos deben ser cero | L68: Sí | M68: Bloqueante | N68: Si los conteos no son cero: revisar también CO_h/CO_d (4.4.3), la estanqueidad (3.3.1), las conexiones de tubo (2.4.3), disturbios electrónicos (5.1.2/5.1.3) y la membrana del controlador de aire de purga RAC (3.4.3). Ver Cadena 4. | O68: 4.4.3 · 3.3.1 · 2.4.3 · 5.1.2 · 3.4.3 | P68: Con el filtro de partículas cero instalado, uno o más canales no reportan conteo cero. | Q68: Sí | S68: Service Training.pdf / Correo EDM180C fault (dic-2021) | T68: Pendiente | V68: =IF($G68<>"Numérico","",IF($U68="","Sin dato",IF(AND(OR(NOT(ISNUMBER($J68)),$U68>=$J68),OR(NOT(ISNUMBER($K68)),$U68<=$K68)),"Dentro de rango","Fuera de rango")))
A69: 4.4.2 | B69: 4. Espectrómetro: cámara de medida y óptica | C69: 4.4 Pruebas funcionales del espectrómetro | D69: Trampa de luz (light-trap) | E69: Limpieza y estado del vidrio especial de la trampa de luz de la cámara de medida | F69: Abrir la cámara de medida e inspeccionar visualmente el vidrio especial de la trampa de luz; limpiar con alcohol si tiene residuos. | G69: OK / No OK | I69: Limpio, sin residuos; limpiar con alcohol | L69: No | M69: Cobrable | N69: Reemplazar o reparar el componente indicado en Repuesto/parte asociada; incluir en la cotización al cliente. | P69: El vidrio de la trampa de luz de la cámara de medida presenta residuos o suciedad. | Q69: Sí | R69: 4022371 (trampa de luz) / C0005x1.5 (O-Ring) | S69: SER-MAN DUST MONITOR 180 | T69: Pendiente | V69: =IF($G69<>"Numérico","",IF($U69="","Sin dato",IF(AND(OR(NOT(ISNUMBER($J69)),$U69>=$J69),OR(NOT(ISNUMBER($K69)),$U69<=$K69)),"Dentro de rango","Fuera de rango")))
A70: 4.4.3 | B70: 4. Espectrómetro: cámara de medida y óptica | C70: 4.4 Pruebas funcionales del espectrómetro | D70: Preamplificador y fotodiodo del detector | E70: Corrosión o daño visible en el fotodiodo/preamplificador dentro de la cámara de medida | F70: Con el filtro cero puesto, revisar en el software los valores CO_h/CO_d; si están anormalmente altos, inspeccionar visualmente el fotodiodo/preamplificador en busca de corrosión (la reparación es solo en fábrica). | G70: OK / No OK | I70: Sin corrosión; CO_h/CO_d anormalmente altos indican problema aquí. Reparación solo en fábrica (Alemania) | L70: No | M70: Bloqueante | N70: Si CO_h/CO_d permanecen anormalmente altos tras revisar la Cadena 4 sin hallar causa: posible corrosión o daño del fotodiodo/preamplificador — reparación solo en fábrica. | O70: 4.4.1 | P70: Se observan valores CO_h/CO_d anormalmente altos con el filtro cero puesto, o corrosión visible en el fotodiodo/preamplificador. | Q70: Sí | R70: 1206152 (preamplificador completo) / AMB-C30808EH (fotodiodo) | S70: Correo EDM180C fault (dic-2021) | T70: Pendiente | V70: =IF($G70<>"Numérico","",IF($U70="","Sin dato",IF(AND(OR(NOT(ISNUMBER($J70)),$U70>=$J70),OR(NOT(ISNUMBER($K70)),$U70<=$K70)),"Dentro de rango","Fuera de rango")))
A71: 5.1.1 | B71: 5. Electrónica y control | C71: 5.1 Tarjetas | D71: Tarjeta digital del espectrómetro | E71: Operatividad de la tarjeta digital | F71: Con el equipo encendido, verificar en el software de diagnóstico que la tarjeta digital del espectrómetro permita la operación normal del equipo. | G71: OK / No OK | I71: Debe permitir la operación del equipo | L71: Sí | M71: Bloqueante | N71: Código SER-MAN “Black line on the display”: pantalla defectuosa o tarjeta digital defectuosa. También es el primer paso de diagnóstico retirado en la Cadena 3 (error de flujo). | O71: 3.4.1 | P71: La tarjeta digital del espectrómetro no permite la operación normal del equipo. | Q71: Sí | R71: X187486 | S71: MT_18A19035_260727 | T71: Pendiente | V71: =IF($G71<>"Numérico","",IF($U71="","Sin dato",IF(AND(OR(NOT(ISNUMBER($J71)),$U71>=$J71),OR(NOT(ISNUMBER($K71)),$U71<=$K71)),"Dentro de rango","Fuera de rango")))
A72: 5.1.2 | B72: 5. Electrónica y control | C72: 5.1 Tarjetas | D72: Tarjeta análoga | E72: Estado y operatividad de la tarjeta análoga | F72: Inspección visual de la tarjeta análoga (componentes, soldaduras) y verificación funcional indirecta a través de la estabilidad de las lecturas del equipo. | G72: OK / No OK | I72: Operativa | L72: Sí | M72: Cobrable | N72: Causa documentada de error de flujo/corriente de bomba alta: sustancia o residuo conductivo en la tarjeta análoga. Retirar la tarjeta digital (5.1.1) y el sensor de presión diferencial, inspeccionar y limpiar con limpiador de tarjetas. Ver Cadena 3. | O72: 5.1.1 · 3.4.1 | P72: La tarjeta análoga presenta daño visible o se asocia a inestabilidad en las lecturas del equipo. | Q72: Sí | R72: 1205391 (incl. sensores de presión) / 1205395 (sin sensores) | S72: MT_18A19035_260727 | T72: Pendiente | V72: =IF($G72<>"Numérico","",IF($U72="","Sin dato",IF(AND(OR(NOT(ISNUMBER($J72)),$U72>=$J72),OR(NOT(ISNUMBER($K72)),$U72<=$K72)),"Dentro de rango","Fuera de rango")))
A73: 5.1.3 | B73: 5. Electrónica y control | C73: 5.1 Tarjetas | D73: Aislante de apantallamiento | E73: Presencia del aislante entre la tarjeta digital y la análoga | F73: Abrir el gabinete electrónico e inspeccionar visualmente que el aislante entre la tarjeta digital y la análoga esté presente. | G73: Presente / Ausente | I73: Debe estar presente (su ausencia genera ruido electrónico) | L73: Sí | M73: Cobrable | N73: Reemplazar o reparar el componente indicado en Repuesto/parte asociada; incluir en la cotización al cliente. | P73: Falta el aislante de apantallamiento entre la tarjeta digital y la análoga. | Q73: Sí | S73: MT_18A19035_260727 | T73: Pendiente | V73: =IF($G73<>"Numérico","",IF($U73="","Sin dato",IF(AND(OR(NOT(ISNUMBER($J73)),$U73>=$J73),OR(NOT(ISNUMBER($K73)),$U73<=$K73)),"Dentro de rango","Fuera de rango")))
A74: 5.1.4 | B74: 5. Electrónica y control | C74: 5.1 Tarjetas | D74: Tarjeta driver del láser (Laser Driver Board) | E74: Estado y operatividad de la tarjeta que controla el diodo láser | F74: Inspección visual de la tarjeta driver del láser y verificación funcional a través de las lecturas de corriente/potencia del láser en el software de diagnóstico. | G74: OK / No OK | I74: Operativa | L74: Sí | M74: Bloqueante | N74: Vinculada al código “NEW CALIBRATION” (láser apagado/dañado) — revisar la tarjeta driver antes de asumir que la unidad láser completa está dañada. Ver Cadena 11. | O74: 4.3.1 | P74: La tarjeta driver del láser no opera correctamente. | Q74: Sí | R74: X187LDRVR / X187LDRVR-R — Zoho no vende la tarjeta driver por separado, solo la unidad láser completa | S74: Service Training NEW v0.8 | T74: Pendiente | V74: =IF($G74<>"Numérico","",IF($U74="","Sin dato",IF(AND(OR(NOT(ISNUMBER($J74)),$U74>=$J74),OR(NOT(ISNUMBER($K74)),$U74<=$K74)),"Dentro de rango","Fuera de rango")))
A75: 5.1.5 | B75: 5. Electrónica y control | C75: 5.1 Tarjetas | D75: Tarjeta del circuito LED | E75: Estado y operatividad de la tarjeta del circuito LED del equipo | F75: Inspección visual de la tarjeta del circuito LED y verificación funcional de los indicadores LED del equipo. | G75: OK / No OK | I75: Operativa | L75: No | M75: Alerta | N75: Registrar el hallazgo en Observación y dar seguimiento; no requiere acción inmediata. | P75: La tarjeta del circuito LED o los indicadores del equipo no funcionan correctamente. | Q75: No | R75: 1205267 | S75: Service Training NEW v0.8 | T75: Pendiente | V75: =IF($G75<>"Numérico","",IF($U75="","Sin dato",IF(AND(OR(NOT(ISNUMBER($J75)),$U75>=$J75),OR(NOT(ISNUMBER($K75)),$U75<=$K75)),"Dentro de rango","Fuera de rango")))
A76: 5.2.1 | B76: 5. Electrónica y control | C76: 5.2 Ajustes y ganancias | D76: Ganancia canal F | E76: Desviación de la ganancia del canal F respecto al espectrómetro de referencia | F76: En el software Diagnosis GRIMM, leer la desviación de ganancia del canal F respecto al espectrómetro de referencia durante la verificación con dolomita. | G76: Numérico | H76: % | I76: Entre -2 % y +5 % | J76: -2 | K76: 5 | L76: Sí | M76: Bloqueante | N76: Si la ganancia queda fuera de criterio, el Service Training documenta el ciclo completo de recalibración: pre-comparación → servicio/reparación → calibración (preamplificador, láser, flujo, umbrales) → prueba de 48 h → verificación final. Ver Cadena 13. | O76: 5.2.2 · 5.2.3 · 4.3.3 | P76: La desviación de la ganancia del canal F respecto al espectrómetro de referencia está fuera de rango. | Q76: Sí | S76: MT_18A24064_260609 | T76: Pendiente | V76: =IF($G76<>"Numérico","",IF($U76="","Sin dato",IF(AND(OR(NOT(ISNUMBER($J76)),$U76>=$J76),OR(NOT(ISNUMBER($K76)),$U76<=$K76)),"Dentro de rango","Fuera de rango"))) -> Sin dato
A77: 5.2.2 | B77: 5. Electrónica y control | C77: 5.2 Ajustes y ganancias | D77: Ganancia canal G | E77: Desviación de la ganancia del canal G respecto al espectrómetro de referencia | F77: En el software Diagnosis GRIMM, leer la desviación de ganancia del canal G respecto al espectrómetro de referencia durante la verificación con dolomita. | G77: Numérico | H77: % | I77: Entre -2 % y +5 % | J77: -2 | K77: 5 | L77: Sí | M77: Bloqueante | N77: Mismo ciclo de recalibración documentado que 5.2.1 (Cadena 13). | O77: 5.2.1 · 5.2.3 | P77: La desviación de la ganancia del canal G respecto al espectrómetro de referencia está fuera de rango. | Q77: Sí | S77: MT_18A24064_260609 | T77: Pendiente | V77: =IF($G77<>"Numérico","",IF($U77="","Sin dato",IF(AND(OR(NOT(ISNUMBER($J77)),$U77>=$J77),OR(NOT(ISNUMBER($K77)),$U77<=$K77)),"Dentro de rango","Fuera de rango"))) -> Sin dato
A78: 5.2.3 | B78: 5. Electrónica y control | C78: 5.2 Ajustes y ganancias | D78: Ajuste digital de ganancias (canales 0 a J) | E78: Desviación tras el ajuste digital de ganancias de los canales 0 a J, en Dolomita | F78: Ejecutar el procedimiento de ajuste digital de ganancias por canal (0 a J) del software Diagnosis GRIMM durante la verificación con dolomita, y registrar la desviación resultante. | G78: Numérico | H78: % | I78: ±2% (recomendado calibrar 1-2% hacia el lado negativo para compensar la verificación con aire ambiente) | J78: -2 | K78: 2 | L78: No | M78: Bloqueante | N78: Mismo ciclo de recalibración documentado que 5.2.1 (Cadena 13). | O78: 5.2.1 · 5.2.2 | P78: La desviación tras el ajuste digital de ganancias (canales 0 a J) supera el criterio de referencia. | Q78: Sí | S78: Correo EDM180C Calibration desviación (nov-2021) | T78: Pendiente | V78: =IF($G78<>"Numérico","",IF($U78="","Sin dato",IF(AND(OR(NOT(ISNUMBER($J78)),$U78>=$J78),OR(NOT(ISNUMBER($K78)),$U78<=$K78)),"Dentro de rango","Fuera de rango"))) -> Sin dato
A79: 5.3.1 | B79: 5. Electrónica y control | C79: 5.3 Alimentación y memoria | D79: Batería 3V tarjeta PCMCIA | E79: Estado / tensión de la batería CR2025 | F79: Medir con multímetro la tensión de la batería CR2025 de la tarjeta PCMCIA, o leer el valor reportado por el software si está disponible. | G79: Numérico | H79: V | I79: Tensión mínima 2,8 V | J79: 2.8 | K79: 3.3 | L79: Sí | M79: Cobrable | N79: Código SER-MAN “PLEASE REPLACE MEMORYCARD-BATT.”: respaldar los datos de la tarjeta antes de reemplazar la batería. Ver Cadena 10. | O79: 5.3.2 | P79: La tensión de la batería de la tarjeta PCMCIA está por debajo del mínimo requerido. | Q79: No | R79: CR2025 | S79: MT_18A20087_260512 | T79: Pendiente | V79: =IF($G79<>"Numérico","",IF($U79="","Sin dato",IF(AND(OR(NOT(ISNUMBER($J79)),$U79>=$J79),OR(NOT(ISNUMBER($K79)),$U79<=$K79)),"Dentro de rango","Fuera de rango"))) -> Sin dato
A80: 5.3.2 | B80: 5. Electrónica y control | C80: 5.3 Alimentación y memoria | D80: Tarjeta PCMCIA / almacenamiento | E80: Lectura y escritura de datos en la tarjeta de memoria | F80: Realizar una prueba de lectura y escritura de datos en la tarjeta de memoria PCMCIA desde el software del equipo. | G80: OK / No OK | I80: Debe leer y escribir | L80: Sí | M80: Bloqueante | N80: Códigos SER-MAN relacionados: “CARD ERROR” (insertada/retirada en operación o protección de escritura activa), “WRONG SerialNo.” / “WRONG VERSION” (datos de otro equipo/firmware — leer y respaldar antes de formatear), “PLEASE CHECK MEMORYCARD” (protegida contra escritura). Ver Cadena 10. | O80: 5.3.1 | P80: La tarjeta de memoria PCMCIA no permite lectura o escritura de datos. | Q80: No | R80: DS2430A (EEPROM 256-bit — posible chip de memoria/serial; no se halló SKU de la tarjeta PCMCIA completa en esta categoría) | S80: MT_18A20087_260512 | T80: Pendiente | V80: =IF($G80<>"Numérico","",IF($U80="","Sin dato",IF(AND(OR(NOT(ISNUMBER($J80)),$U80>=$J80),OR(NOT(ISNUMBER($K80)),$U80<=$K80)),"Dentro de rango","Fuera de rango")))
A81: 5.3.3 | B81: 5. Electrónica y control | C81: 5.3 Alimentación y memoria | D81: Cableado y conectores internos | E81: Estado de cableado, conectores y bornes internos | F81: Inspección visual del cableado, conectores y bornes internos, verificando ausencia de daño o corrosión. | G81: OK / No OK | I81: Sin daño ni corrosión | L81: Sí | M81: Cobrable | N81: Incluye el cableado hasta el switch de fin de carrera del lift, punto documentado de revisión si el lift falla (Cadena 8). | O81: 8.1.5 | P81: El cableado, los conectores o los bornes internos presentan daño o corrosión. | Q81: Sí | R81: 1205268 (cable set EDM180) / 1205050 (cable tarjeta análoga) / 1203585 (pasacables 4mm) — hay más conectores específicos en el catálogo Zoho (Han, D-Sub, etc.) | S81: Derivado | T81: Pendiente | V81: =IF($G81<>"Numérico","",IF($U81="","Sin dato",IF(AND(OR(NOT(ISNUMBER($J81)),$U81>=$J81),OR(NOT(ISNUMBER($K81)),$U81<=$K81)),"Dentro de rango","Fuera de rango")))
A82: 5.4.1 | B82: 5. Electrónica y control | C82: 5.4 Software de diagnóstico | D82: Lectura en Diagnosis GRIMM | E82: Los valores del software oficial indican operación correcta | F82: Abrir el software oficial Diagnosis GRIMM y revisar que los valores generales de operación estén dentro de rango. | G82: OK / No OK | I82: Valores dentro de rango | L82: Sí | M82: Alerta | N82: Registrar el hallazgo en Observación y dar seguimiento; no requiere acción inmediata. | P82: Uno o más valores del software Diagnosis GRIMM están fuera de rango. | Q82: Sí | S82: MT_18A18033_260108 | T82: Pendiente | V82: =IF($G82<>"Numérico","",IF($U82="","Sin dato",IF(AND(OR(NOT(ISNUMBER($J82)),$U82>=$J82),OR(NOT(ISNUMBER($K82)),$U82<=$K82)),"Dentro de rango","Fuera de rango")))
A83: 5.4.2 | B83: 5. Electrónica y control | C83: 5.4 Software de diagnóstico | D83: Captura del diagnóstico | E83: Se adjunta captura de pantalla del software de diagnóstico | F83: Tomar una captura de pantalla del software de diagnóstico y adjuntarla al informe de servicio. | G83: Sí/No | I83: Debe adjuntarse | L83: Sí | M83: Alerta | N83: Registrar el hallazgo en Observación y dar seguimiento; no requiere acción inmediata. | P83: No se adjuntó la captura de pantalla del software de diagnóstico al informe. | Q83: Sí | S83: MT_18A21062_260227 | T83: Pendiente | V83: =IF($G83<>"Numérico","",IF($U83="","Sin dato",IF(AND(OR(NOT(ISNUMBER($J83)),$U83>=$J83),OR(NOT(ISNUMBER($K83)),$U83<=$K83)),"Dentro de rango","Fuera de rango")))
A84: 5.5.1 | B84: 5. Electrónica y control | C84: 5.5 Reloj interno y trazabilidad | D84: Reloj interno (RTC) | E84: Persistencia de fecha y hora tras apagar el equipo; verificar en Hyperterminal esperando unos minutos | F84: Apagar el equipo, esperar unos minutos, encenderlo y verificar en Hyperterminal (u otra terminal serial) que la fecha y hora se mantuvieron correctas. | G84: OK / No OK | I84: Fecha/hora estable y correcta | L84: No | M84: Cobrable | N84: Orden de reemplazo documentado por GRIMM: 1) chip temporizador PCF8583 (primero, según experiencia de Ambientalia), 2) capacitor ajustable (causa más común según GRIMM), 3) cristal oscilador (última opción). Calibrar el trimmer del reloj con precisión tras cualquier reemplazo. Ver Cadena 5. | O84: 5.5.2 | P84: La fecha y hora del equipo no se mantienen correctas tras apagarlo y encenderlo. | Q84: No | R84: PCF8583P (SKU en Zoho; el correo de soporte cita «PCF8583F» — mismo circuito RTC, confirmar variante) / C-002RX 32.7680K-A:PBFREE (cristal oscilador) / 4030149 (capacitor variable) — el correo de soporte señala estos tres como causas posibles del reloj inestable | S84: Correo Date and hour problem SN 18A18103 | T84: Pendiente | V84: =IF($G84<>"Numérico","",IF($U84="","Sin dato",IF(AND(OR(NOT(ISNUMBER($J84)),$U84>=$J84),OR(NOT(ISNUMBER($K84)),$U84<=$K84)),"Dentro de rango","Fuera de rango")))
A85: 5.5.2 | B85: 5. Electrónica y control | C85: 5.5 Reloj interno y trazabilidad | D85: Batería del reloj interno | E85: Estado de la pila de litio del reloj interno (distinta de la batería de la tarjeta de memoria) | F85: Medir con multímetro la tensión de la pila de litio del reloj interno (SL-389), distinta de la batería de la tarjeta de memoria. | G85: OK / No OK | H85: V | I85: 3,6 V nominal (SL-389, 1AH) | J85: 3.2 | K85: 3.8 | L85: No | M85: Cobrable | N85: Reemplazar o reparar el componente indicado en Repuesto/parte asociada; incluir en la cotización al cliente. | P85: La tensión de la pila del reloj interno está fuera del rango de referencia. | Q85: No | R85: 1200168 (Lithium-Battery 3,6V 1,0Ah en Zoho; SL-389 es el part number de fábrica citado en SER-MAN) | S85: SER-MAN DUST MONITOR 180 | T85: Pendiente | V85: =IF($G85<>"Numérico","",IF($U85="","Sin dato",IF(AND(OR(NOT(ISNUMBER($J85)),$U85>=$J85),OR(NOT(ISNUMBER($K85)),$U85<=$K85)),"Dentro de rango","Fuera de rango")))
A86: 6.1.1 | B86: 6. Filtros y consumibles | C86: 6.1 Filtros | D86: Filtro de disposición 9933-05-BQ | E86: Colmatación y estado del filtro de disposición | F86: Inspección visual del filtro de disposición 9933-05-BQ, evaluando el nivel de colmatación por coloración/opacidad. | G86: OK / No OK | I86: Sin colmatación | L86: Sí | M86: Cobrable | N86: Ligado al mismo código “CHECK DUSTFILTER AND AIR PASSAGE” que el filtro principal (6.1.3). | O86: 6.1.3 | P86: El filtro de disposición está colmatado. | Q86: Sí | R86: J04993305BQ | S86: MT_18A20087_260512 | T86: Pendiente | V86: =IF($G86<>"Numérico","",IF($U86="","Sin dato",IF(AND(OR(NOT(ISNUMBER($J86)),$U86>=$J86),OR(NOT(ISNUMBER($K86)),$U86<=$K86)),"Dentro de rango","Fuera de rango")))
A87: 6.1.2 | B87: 6. Filtros y consumibles | C87: 6.1 Filtros | D87: Fecha del último cambio de filtro | E87: Registro de la fecha del último reemplazo | F87: Consultar el registro de mantenimiento o la etiqueta del filtro para determinar la fecha del último reemplazo. | G87: Fecha | I87: Según periodicidad del plan de mantenimiento | L87: No | M87: Alerta | N87: Registrar el hallazgo en Observación y dar seguimiento; no requiere acción inmediata. | P87: El registro del último cambio de filtro no está disponible o no corresponde a la periodicidad del plan de mantenimiento. | Q87: No | R87: J04993305BQ | S87: Derivado | T87: Pendiente | V87: =IF($G87<>"Numérico","",IF($U87="","Sin dato",IF(AND(OR(NOT(ISNUMBER($J87)),$U87>=$J87),OR(NOT(ISNUMBER($K87)),$U87<=$K87)),"Dentro de rango","Fuera de rango")))
A88: 6.1.3 | B88: 6. Filtros y consumibles | C88: 6.1 Filtros | D88: Filtro principal de polvo (main dust filter) | E88: Colmatación del filtro principal, distinto del filtro de disposición | F88: Inspección visual del filtro principal de polvo (distinto del filtro de disposición) y consulta del contador de carga acumulada en el software, comparándolo contra los umbrales de 20.000/40.000/60.000 µg. | G88: OK / No OK | I88: Cambiar según carga acumulada: ~20.000 µg/120 días (filtro), ~40.000 µg/240 días (+ chequeo ventilador), ~60.000 µg/360 días (mantenimiento anual completo) | L88: No | M88: Cobrable | N88: Código SER-MAN “CHECK DUSTFILTER AND AIR PASSAGE”: baja presión tras el filtro fino demasiado alta — cambiar el filtro; si persiste tras el cambio, contactar al fabricante/representante. Ver Cadena 12. | O88: 6.1.1 | P88: El filtro principal de polvo alcanzó o superó el umbral de carga acumulada y requiere cambio. | Q88: No | S88: Service Training.pdf | T88: Pendiente | V88: =IF($G88<>"Numérico","",IF($U88="","Sin dato",IF(AND(OR(NOT(ISNUMBER($J88)),$U88>=$J88),OR(NOT(ISNUMBER($K88)),$U88<=$K88)),"Dentro de rango","Fuera de rango")))
A89: 6.1.4 | B89: 6. Filtros y consumibles | C89: 6.1 Filtros | D89: Filtro CQ de autodiagnóstico (CQ-Filter Selftest) | E89: Estado del filtro CQ dedicado al ciclo de self-test | F89: Inspección visual del filtro CQ dedicado al ciclo de self-test, evaluando su nivel de colmatación. | G89: OK / No OK | I89: Sin colmatación | L89: No | M89: Cobrable | N89: Reemplazar o reparar el componente indicado en Repuesto/parte asociada; incluir en la cotización al cliente. | P89: El filtro CQ dedicado al ciclo de self-test está colmatado. | Q89: No | R89: J04993305CQ | S89: Service Training NEW v0.8 | T89: Pendiente | V89: =IF($G89<>"Numérico","",IF($U89="","Sin dato",IF(AND(OR(NOT(ISNUMBER($J89)),$U89>=$J89),OR(NOT(ISNUMBER($K89)),$U89<=$K89)),"Dentro de rango","Fuera de rango")))
A90: 6.1.5 | B90: 6. Filtros y consumibles | C90: 6.1 Filtros | D90: Filtro CQ de vacío (CQ-Filter Vacuum) | E90: Estado del filtro CQ dedicado a la etapa de vacío | F90: Inspección visual del filtro CQ dedicado a la etapa de vacío, evaluando su nivel de colmatación. | G90: OK / No OK | I90: Sin colmatación | L90: No | M90: Cobrable | N90: Reemplazar o reparar el componente indicado en Repuesto/parte asociada; incluir en la cotización al cliente. | P90: El filtro CQ dedicado a la etapa de vacío está colmatado. | Q90: No | R90: J04993305CQ (Zoho parece stockear un único CQ-Filter para ambas funciones selftest/vacío) | S90: Service Training NEW v0.8 | T90: Pendiente | V90: =IF($G90<>"Numérico","",IF($U90="","Sin dato",IF(AND(OR(NOT(ISNUMBER($J90)),$U90>=$J90),OR(NOT(ISNUMBER($K90)),$U90<=$K90)),"Dentro de rango","Fuera de rango")))
A91: 6.1.6 | B91: 6. Filtros y consumibles | C91: 6.1 Filtros | D91: Reinicio del contador de filtro (umbral 60.000 µg) | E91: Verificar si el contador de carga del filtro alcanzó el umbral de 60.000 µg/360 días y, de ser así, reiniciarlo tras completar el mantenimiento anual | F91: Consultar en el software el contador de carga del filtro; si alcanzó el umbral de 60.000 µg/360 días y ya se completó el mantenimiento anual, reiniciar el contador desde el menú correspondiente. | G91: Sí/No | I91: Reiniciar solo si se alcanzó el umbral y se completó el mantenimiento | L91: No | M91: Alerta | N91: Registrar el hallazgo en Observación y dar seguimiento; no requiere acción inmediata. | P91: El contador de carga del filtro alcanzó el umbral de reemplazo y no ha sido reiniciado tras el mantenimiento anual. | Q91: No | S91: Service Training NEW v0.8 / Service Training.pdf | T91: Pendiente | V91: =IF($G91<>"Numérico","",IF($U91="","Sin dato",IF(AND(OR(NOT(ISNUMBER($J91)),$U91>=$J91),OR(NOT(ISNUMBER($K91)),$U91<=$K91)),"Dentro de rango","Fuera de rango")))
A92: 6.2.1 | B92: 6. Filtros y consumibles | C92: 6.2 Juntas y sellos | D92: O-Ring 4x1 mm entrada de muestreo | E92: Estado de la junta tórica de la entrada de muestreo | F92: Desmontar la entrada de muestreo e inspeccionar visualmente la junta tórica en busca de desgaste. | G92: OK / No OK | I92: Sin desgaste | L92: Sí | M92: Cobrable | N92: Reemplazar o reparar el componente indicado en Repuesto/parte asociada; incluir en la cotización al cliente. | P92: El O-Ring de la entrada de muestreo presenta desgaste. | Q92: Sí | R92: C0004x1 | S92: MT_18A18033_260108 | T92: Pendiente | V92: =IF($G92<>"Numérico","",IF($U92="","Sin dato",IF(AND(OR(NOT(ISNUMBER($J92)),$U92>=$J92),OR(NOT(ISNUMBER($K92)),$U92<=$K92)),"Dentro de rango","Fuera de rango")))
A93: 6.2.2 | B93: 6. Filtros y consumibles | C93: 6.2 Juntas y sellos | D93: O-Ring 44x3 mm | E93: Estado de la junta tórica 44x3 mm | F93: Inspección visual de la junta tórica 44x3 mm en su punto de montaje. | G93: OK / No OK | I93: Sin desgaste | L93: No | M93: Cobrable | N93: Reemplazar o reparar el componente indicado en Repuesto/parte asociada; incluir en la cotización al cliente. | P93: El O-Ring de 44x3 mm presenta desgaste. | Q93: No | R93: C00044X3S70 | S93: MT_18A20087_260512 | T93: Pendiente | V93: =IF($G93<>"Numérico","",IF($U93="","Sin dato",IF(AND(OR(NOT(ISNUMBER($J93)),$U93>=$J93),OR(NOT(ISNUMBER($K93)),$U93<=$K93)),"Dentro de rango","Fuera de rango")))
A94: 6.2.3 | B94: 6. Filtros y consumibles | C94: 6.2 Juntas y sellos | D94: Set de tornillería | E94: Estado y completitud de la tornillería de servicio | F94: Verificar visualmente que el set de tornillería de servicio esté completo y sin piezas deformadas. | G94: OK / No OK | I94: Completa y sin deformación | L94: No | M94: Cobrable | N94: Reemplazar o reparar el componente indicado en Repuesto/parte asociada; incluir en la cotización al cliente. | P94: El set de tornillería de servicio está incompleto o presenta piezas deformadas. | Q94: No | R94: 4037489 / M00M3X3D913A2 / 4040565 (kit de piezas pequeñas y juntas, incluye fusible) / 4025003 (kit de repuestos EDM180/365 115V) | S94: MT_18A20087_260512 | T94: Pendiente | V94: =IF($G94<>"Numérico","",IF($U94="","Sin dato",IF(AND(OR(NOT(ISNUMBER($J94)),$U94>=$J94),OR(NOT(ISNUMBER($K94)),$U94<=$K94)),"Dentro de rango","Fuera de rango")))
A95: 7.1.1 | B95: 7. Sensores auxiliares | C95: 7.1 Sensor ambiental | D95: Sensor de T y HR ambiente | E95: Presencia del sensor de humedad y temperatura ambiente | F95: Inspección visual/física para confirmar la presencia del sensor de temperatura y humedad ambiente conectado al equipo. | G95: Presente / Ausente | I95: Debe estar presente para poder verificar los parámetros | L95: Sí | M95: Cobrable | N95: Código SER-MAN “NO SENSOR! PLEASE CHECK”: sensor de T/HR no conectado o defectuoso — la medición se detiene. Verificar conexión y, si es necesario, reemplazar (1200095/1200093). | P95: El sensor de temperatura y humedad ambiente no está presente o no se detecta conectado al equipo. | Q95: No | R95: 1200095 (con cable 3,5 m) / 1200093 (sin cable) | S95: MT_18A19035_260727 | T95: Pendiente | V95: =IF($G95<>"Numérico","",IF($U95="","Sin dato",IF(AND(OR(NOT(ISNUMBER($J95)),$U95>=$J95),OR(NOT(ISNUMBER($K95)),$U95<=$K95)),"Dentro de rango","Fuera de rango")))
A96: 7.1.2 | B96: 7. Sensores auxiliares | C96: 7.1 Sensor ambiental | D96: Lectura de temperatura ambiente | E96: Valor de temperatura ambiente reportado por el equipo | F96: Comparar la lectura de temperatura ambiente reportada por el equipo contra un termómetro/patrón de referencia. | G96: Numérico | H96: °C | I96: Coherente con patrón de referencia | J96: PENDIENTE DE VALIDAR | K96: PENDIENTE DE VALIDAR | L96: Sí | M96: Cobrable | N96: Reemplazar o reparar el componente indicado en Repuesto/parte asociada; incluir en la cotización al cliente. | P96: La lectura de temperatura ambiente reportada por el equipo no coincide con el patrón de referencia. | Q96: No | R96: 1200095 / 1200093 | S96: MT_18A19035_260727 | T96: Pendiente | V96: =IF($G96<>"Numérico","",IF($U96="","Sin dato",IF(AND(OR(NOT(ISNUMBER($J96)),$U96>=$J96),OR(NOT(ISNUMBER($K96)),$U96<=$K96)),"Dentro de rango","Fuera de rango"))) -> Sin dato
A97: 7.1.3 | B97: 7. Sensores auxiliares | C97: 7.1 Sensor ambiental | D97: Lectura de humedad relativa | E97: Valor de humedad relativa reportado por el equipo | F97: Comparar la lectura de humedad relativa reportada por el equipo contra un higrómetro/patrón de referencia. | G97: Numérico | H97: %HR | I97: Coherente con patrón de referencia | J97: 0 | K97: 100 | L97: Sí | M97: Cobrable | N97: Reemplazar o reparar el componente indicado en Repuesto/parte asociada; incluir en la cotización al cliente. | P97: La lectura de humedad relativa reportada por el equipo no coincide con el patrón de referencia. | Q97: No | R97: 1200095 / 1200093 | S97: MT_18A19035_260727 | T97: Pendiente | V97: =IF($G97<>"Numérico","",IF($U97="","Sin dato",IF(AND(OR(NOT(ISNUMBER($J97)),$U97>=$J97),OR(NOT(ISNUMBER($K97)),$U97<=$K97)),"Dentro de rango","Fuera de rango"))) -> Sin dato
A98: 7.1.4 | B98: 7. Sensores auxiliares | C98: 7.1 Sensor ambiental | D98: Sensor de presión atmosférica (barométrica) | E98: Lectura de presión atmosférica del equipo contrastada contra un valor de referencia local | F98: Comparar la lectura de presión atmosférica del equipo contra un valor de referencia local (p. ej. estación cercana o barómetro patrón), considerando la altitud del sitio. | G98: Numérico | H98: hPa | I98: Depende de la altitud de instalación (no hay un rango único válido para todos los sitios); en Bogotá el valor de referencia ronda 740-750 hPa. Un sensor saturado (salida cercana a 10 V) indica falla y debe reemplazarse/recalibrarse | J98: PENDIENTE DE VALIDAR | K98: PENDIENTE DE VALIDAR | L98: No | M98: Cobrable | N98: Antes de asumir el sensor dañado: verificar los valores P-Line (voltajes); si son coherentes, el sensor funciona y el problema son los factores de calibración (factor/offset) perdidos — frecuente tras reemplazar la tarjeta digital. Reconfigurar por Terminal (“$”, “4”, ENTER, factor, offset, ENTER). Ver Cadena 6. | O98: 5.1.1 · 3.4.1 | P98: La lectura de presión atmosférica del equipo no coincide con el valor de referencia local; puede indicar sensor saturado o pérdida de los factores de calibración. | Q98: No | R98: H6DP015AZ8H (sensor de presión absoluta) | S98: Correo Sensor Presión EDM180 18A12048 / Correo GRIMM Flow Error 18A12047 | T98: Pendiente | V98: =IF($G98<>"Numérico","",IF($U98="","Sin dato",IF(AND(OR(NOT(ISNUMBER($J98)),$U98>=$J98),OR(NOT(ISNUMBER($K98)),$U98<=$K98)),"Dentro de rango","Fuera de rango"))) -> Sin dato
A99: 7.2.1 | B99: 7. Sensores auxiliares | C99: 7.2 Sensores internos | D99: Temperatura interna del equipo | E99: Temperatura interna reportada en el software de diagnóstico | F99: Consultar en el software de diagnóstico la temperatura interna reportada por el equipo. | G99: Numérico | H99: °C | I99: Dentro del rango del fabricante | J99: PENDIENTE DE VALIDAR | K99: PENDIENTE DE VALIDAR | L99: No | M99: Alerta | N99: Registrar el hallazgo en Observación y dar seguimiento; no requiere acción inmediata. | P99: La temperatura interna reportada por el equipo está fuera del rango del fabricante. | Q99: No | R99: NTC-01 (termistor — posible sensor de temperatura interna, a confirmar) | S99: Derivado | T99: Pendiente | V99: =IF($G99<>"Numérico","",IF($U99="","Sin dato",IF(AND(OR(NOT(ISNUMBER($J99)),$U99>=$J99),OR(NOT(ISNUMBER($K99)),$U99<=$K99)),"Dentro de rango","Fuera de rango"))) -> Sin dato
A100: 7.2.2 | B100: 7. Sensores auxiliares | C100: 7.2 Sensores internos | D100: Sensor de flujo | E100: Coherencia de la lectura del sensor de flujo | F100: Comparar la lectura del sensor de flujo interno contra una medición externa con flujómetro de referencia. | G100: OK / No OK | I100: Coherente con la medición externa | L100: Sí | M100: Alerta | N100: Registrar el hallazgo en Observación y dar seguimiento; no requiere acción inmediata. | P100: La lectura del sensor de flujo interno no coincide con la medición externa de referencia. | Q100: No | S100: Derivado | T100: Pendiente | V100: =IF($G100<>"Numérico","",IF($U100="","Sin dato",IF(AND(OR(NOT(ISNUMBER($J100)),$U100>=$J100),OR(NOT(ISNUMBER($K100)),$U100<=$K100)),"Dentro de rango","Fuera de rango")))
A101: 8.1.1 | B101: 8. Gabinete, montaje e instalación | C101: 8.1 Gabinete | D101: Estado externo de la carcasa | E101: Golpes, corrosión y pintura de la carcasa | F101: Inspección visual de la carcasa en busca de golpes, corrosión o deterioro de la pintura. | G101: OK / No OK | I101: Sin daño estructural | L101: Sí | M101: Alerta | N101: Registrar el hallazgo en Observación y dar seguimiento; no requiere acción inmediata. | P101: La carcasa del equipo presenta golpes, corrosión o deterioro de pintura. | Q101: Sí | S101: MT_18A18033_260108 | T101: Pendiente | V101: =IF($G101<>"Numérico","",IF($U101="","Sin dato",IF(AND(OR(NOT(ISNUMBER($J101)),$U101>=$J101),OR(NOT(ISNUMBER($K101)),$U101<=$K101)),"Dentro de rango","Fuera de rango")))
A102: 8.1.2 | B102: 8. Gabinete, montaje e instalación | C102: 8.1 Gabinete | D102: Sellado y hermeticidad | E102: Hermeticidad del gabinete frente al ingreso de humedad | F102: Inspección visual de los puntos de sellado del gabinete, verificando que no permitan el ingreso de humedad. | G102: OK / No OK | I102: Hermético | L102: Sí | M102: Cobrable | N102: Reemplazar o reparar el componente indicado en Repuesto/parte asociada; incluir en la cotización al cliente. | P102: El gabinete no es hermético frente al ingreso de humedad. | Q102: Sí | S102: MT_18A18033_260108 | T102: Pendiente | V102: =IF($G102<>"Numérico","",IF($U102="","Sin dato",IF(AND(OR(NOT(ISNUMBER($J102)),$U102>=$J102),OR(NOT(ISNUMBER($K102)),$U102<=$K102)),"Dentro de rango","Fuera de rango")))
...

Sheet Resumen
A1: RESUMEN DE CONFORMIDAD POR NIVEL MACRO
A2: Calculado automáticamente sobre la hoja Inspección.
A4: Nivel macro (N1) | B4: Ítems | C4: Conforme | D4: No conforme | E4: Requiere reemplazo | F4: No aplica | G4: Pendiente | H4: % conformidad | I4: Fuera de rango
A5: 1. Verificación funcional inicial | B5: =COUNTIF(Inspección!$B$9:$B$111,$A5) -> 10 | C5: =COUNTIFS(Inspección!$B$9:$B$111,$A5,Inspección!$T$9:$T$111,"Conforme") -> 0 | D5: =COUNTIFS(Inspección!$B$9:$B$111,$A5,Inspección!$T$9:$T$111,"No conforme") -> 0 | E5: =COUNTIFS(Inspección!$B$9:$B$111,$A5,Inspección!$T$9:$T$111,"Requiere reemplazo") -> 0 | F5: =COUNTIFS(Inspección!$B$9:$B$111,$A5,Inspección!$T$9:$T$111,"No aplica") -> 0 | G5: =COUNTIFS(Inspección!$B$9:$B$111,$A5,Inspección!$T$9:$T$111,"Pendiente") -> 10 | H5: =IFERROR($C5/($B5-$F5-$G5),"") | I5: =COUNTIFS(Inspección!$B$9:$B$111,$A5,Inspección!$V$9:$V$111,"Fuera de rango") -> 0
A6: 2. Línea de muestreo y cabezal | B6: =COUNTIF(Inspección!$B$9:$B$111,$A6) -> 20 | C6: =COUNTIFS(Inspección!$B$9:$B$111,$A6,Inspección!$T$9:$T$111,"Conforme") -> 0 | D6: =COUNTIFS(Inspección!$B$9:$B$111,$A6,Inspección!$T$9:$T$111,"No conforme") -> 0 | E6: =COUNTIFS(Inspección!$B$9:$B$111,$A6,Inspección!$T$9:$T$111,"Requiere reemplazo") -> 0 | F6: =COUNTIFS(Inspección!$B$9:$B$111,$A6,Inspección!$T$9:$T$111,"No aplica") -> 0 | G6: =COUNTIFS(Inspección!$B$9:$B$111,$A6,Inspección!$T$9:$T$111,"Pendiente") -> 20 | H6: =IFERROR($C6/($B6-$F6-$G6),"") | I6: =COUNTIFS(Inspección!$B$9:$B$111,$A6,Inspección!$V$9:$V$111,"Fuera de rango") -> 0
A7: 3. Sistema neumático y etapa de secado | B7: =COUNTIF(Inspección!$B$9:$B$111,$A7) -> 18 | C7: =COUNTIFS(Inspección!$B$9:$B$111,$A7,Inspección!$T$9:$T$111,"Conforme") -> 0 | D7: =COUNTIFS(Inspección!$B$9:$B$111,$A7,Inspección!$T$9:$T$111,"No conforme") -> 0 | E7: =COUNTIFS(Inspección!$B$9:$B$111,$A7,Inspección!$T$9:$T$111,"Requiere reemplazo") -> 1 | F7: =COUNTIFS(Inspección!$B$9:$B$111,$A7,Inspección!$T$9:$T$111,"No aplica") -> 0 | G7: =COUNTIFS(Inspección!$B$9:$B$111,$A7,Inspección!$T$9:$T$111,"Pendiente") -> 17 | H7: =IFERROR($C7/($B7-$F7-$G7),"") -> 0 | I7: =COUNTIFS(Inspección!$B$9:$B$111,$A7,Inspección!$V$9:$V$111,"Fuera de rango") -> 1
A8: 4. Espectrómetro: cámara de medida y óptica | B8: =COUNTIF(Inspección!$B$9:$B$111,$A8) -> 14 | C8: =COUNTIFS(Inspección!$B$9:$B$111,$A8,Inspección!$T$9:$T$111,"Conforme") -> 0 | D8: =COUNTIFS(Inspección!$B$9:$B$111,$A8,Inspección!$T$9:$T$111,"No conforme") -> 0 | E8: =COUNTIFS(Inspección!$B$9:$B$111,$A8,Inspección!$T$9:$T$111,"Requiere reemplazo") -> 0 | F8: =COUNTIFS(Inspección!$B$9:$B$111,$A8,Inspección!$T$9:$T$111,"No aplica") -> 0 | G8: =COUNTIFS(Inspección!$B$9:$B$111,$A8,Inspección!$T$9:$T$111,"Pendiente") -> 14 | H8: =IFERROR($C8/($B8-$F8-$G8),"") | I8: =COUNTIFS(Inspección!$B$9:$B$111,$A8,Inspección!$V$9:$V$111,"Fuera de rango") -> 0
A9: 5. Electrónica y control | B9: =COUNTIF(Inspección!$B$9:$B$111,$A9) -> 15 | C9: =COUNTIFS(Inspección!$B$9:$B$111,$A9,Inspección!$T$9:$T$111,"Conforme") -> 0 | D9: =COUNTIFS(Inspección!$B$9:$B$111,$A9,Inspección!$T$9:$T$111,"No conforme") -> 0 | E9: =COUNTIFS(Inspección!$B$9:$B$111,$A9,Inspección!$T$9:$T$111,"Requiere reemplazo") -> 0 | F9: =COUNTIFS(Inspección!$B$9:$B$111,$A9,Inspección!$T$9:$T$111,"No aplica") -> 0 | G9: =COUNTIFS(Inspección!$B$9:$B$111,$A9,Inspección!$T$9:$T$111,"Pendiente") -> 15 | H9: =IFERROR($C9/($B9-$F9-$G9),"") | I9: =COUNTIFS(Inspección!$B$9:$B$111,$A9,Inspección!$V$9:$V$111,"Fuera de rango") -> 0
A10: 6. Filtros y consumibles | B10: =COUNTIF(Inspección!$B$9:$B$111,$A10) -> 9 | C10: =COUNTIFS(Inspección!$B$9:$B$111,$A10,Inspección!$T$9:$T$111,"Conforme") -> 0 | D10: =COUNTIFS(Inspección!$B$9:$B$111,$A10,Inspección!$T$9:$T$111,"No conforme") -> 0 | E10: =COUNTIFS(Inspección!$B$9:$B$111,$A10,Inspección!$T$9:$T$111,"Requiere reemplazo") -> 0 | F10: =COUNTIFS(Inspección!$B$9:$B$111,$A10,Inspección!$T$9:$T$111,"No aplica") -> 0 | G10: =COUNTIFS(Inspección!$B$9:$B$111,$A10,Inspección!$T$9:$T$111,"Pendiente") -> 9 | H10: =IFERROR($C10/($B10-$F10-$G10),"") | I10: =COUNTIFS(Inspección!$B$9:$B$111,$A10,Inspección!$V$9:$V$111,"Fuera de rango") -> 0
A11: 7. Sensores auxiliares | B11: =COUNTIF(Inspección!$B$9:$B$111,$A11) -> 6 | C11: =COUNTIFS(Inspección!$B$9:$B$111,$A11,Inspección!$T$9:$T$111,"Conforme") -> 0 | D11: =COUNTIFS(Inspección!$B$9:$B$111,$A11,Inspección!$T$9:$T$111,"No conforme") -> 0 | E11: =COUNTIFS(Inspección!$B$9:$B$111,$A11,Inspección!$T$9:$T$111,"Requiere reemplazo") -> 0 | F11: =COUNTIFS(Inspección!$B$9:$B$111,$A11,Inspección!$T$9:$T$111,"No aplica") -> 0 | G11: =COUNTIFS(Inspección!$B$9:$B$111,$A11,Inspección!$T$9:$T$111,"Pendiente") -> 6 | H11: =IFERROR($C11/($B11-$F11-$G11),"") | I11: =COUNTIFS(Inspección!$B$9:$B$111,$A11,Inspección!$V$9:$V$111,"Fuera de rango") -> 0
A12: 8. Gabinete, montaje e instalación | B12: =COUNTIF(Inspección!$B$9:$B$111,$A12) -> 11 | C12: =COUNTIFS(Inspección!$B$9:$B$111,$A12,Inspección!$T$9:$T$111,"Conforme") -> 0 | D12: =COUNTIFS(Inspección!$B$9:$B$111,$A12,Inspección!$T$9:$T$111,"No conforme") -> 0 | E12: =COUNTIFS(Inspección!$B$9:$B$111,$A12,Inspección!$T$9:$T$111,"Requiere reemplazo") -> 0 | F12: =COUNTIFS(Inspección!$B$9:$B$111,$A12,Inspección!$T$9:$T$111,"No aplica") -> 0 | G12: =COUNTIFS(Inspección!$B$9:$B$111,$A12,Inspección!$T$9:$T$111,"Pendiente") -> 11 | H12: =IFERROR($C12/($B12-$F12-$G12),"") | I12: =COUNTIFS(Inspección!$B$9:$B$111,$A12,Inspección!$V$9:$V$111,"Fuera de rango") -> 0
A13: TOTAL | B13: =SUM(B5:B12) -> 103 | C13: =SUM(C5:C12) -> 0 | D13: =SUM(D5:D12) -> 0 | E13: =SUM(E5:E12) -> 1 | F13: =SUM(F5:F12) -> 0 | G13: =SUM(G5:G12) -> 102 | H13: =IFERROR($C13/($B13-$F13-$G13),"") -> 0 | I13: =SUM(I5:I12) -> 1
A15: % conformidad = Conforme / (Ítems − No aplica − Pendiente).
A16: Nota: con la hoja recién abierta todos los ítems están en «Pendiente», por lo que el % queda vacío hasta diligenciar.
A19: RESUMEN POR CRITERIO DE FALLA
A20: Alerta = se registra, no detiene el proceso · Cobrable = genera línea de cotización · Bloqueante = el equipo no se libera sin resolverlo.
A22: Criterio de falla | B22: Ítems en catálogo | C22: Detectados en esta visita
A23: Alerta | B23: =COUNTIF(Inspección!$M$9:$M$111,$A23) -> 19 | C23: =COUNTIFS(Inspección!$M$9:$M$111,$A23,Inspección!$T$9:$T$111,"No conforme")+COUNTIFS(Inspección!$M$9:$M$111,$A23,Inspección!$T$9:$T$111,"Requiere reemplazo") -> 0
A24: Cobrable | B24: =COUNTIF(Inspección!$M$9:$M$111,$A24) -> 57 | C24: =COUNTIFS(Inspección!$M$9:$M$111,$A24,Inspección!$T$9:$T$111,"No conforme")+COUNTIFS(Inspección!$M$9:$M$111,$A24,Inspección!$T$9:$T$111,"Requiere reemplazo") -> 0
A25: Bloqueante | B25: =COUNTIF(Inspección!$M$9:$M$111,$A25) -> 27 | C25: =COUNTIFS(Inspección!$M$9:$M$111,$A25,Inspección!$T$9:$T$111,"No conforme")+COUNTIFS(Inspección!$M$9:$M$111,$A25,Inspección!$T$9:$T$111,"Requiere reemplazo") -> 1
A26: TOTAL | B26: =SUM(B23:B25) -> 103 | C26: =SUM(C23:C25) -> 1
A28: «Detectados en esta visita» cuenta los ítems con Resultado = No conforme o Requiere reemplazo (columna T de Inspección) según su Criterio de falla.
A29: El Criterio de falla es un criterio propio de Ambientalia (ítem por ítem, según impacto en medición/seguridad/trazabilidad), no un dato publicado por GRIMM — valídelo con el equipo técnico.

Sheet Flujo No OK
A1: FLUJO DE DIAGNÓSTICO CUANDO UN ÍTEM SALE NO OK
A2: Cadenas de diagnóstico documentadas en el notebook «ST Grimm EDM180» (manual SER-MAN DUST MONITOR 180 cap. 2, Service Training / Service Training NEW, correos de soporte GRIMM). Cada cadena cita su fuente; úsela junto con las columnas N «Acción si sale No OK» y O «Ítem(s) relacionado(s)» de la hoja Inspección.
A3: No es un árbol de decisión formal de GRIMM (ninguna fuente lo tiene así estructurado) — es una reconstrucción de Ambientalia a partir de mensajes de error tabulados y protocolos de servicio encontrados en las fuentes, para que la tabla se pueda navegar como un flujo. Cubre ~40 de los 103 ítems: los que tienen una secuencia de diagnóstico documentada. El resto del catálogo usa una acción por defecto en la hoja Inspección, según su Criterio de falla.
A5: Cadena 1 — El equipo no completa el self-test / no inicia medición
A6: Fuente: SER-MAN DUST MONITOR 180 cap. 2.1 · Service Training NEW
A7: Paso / disparador | B7: Verificación o acción | C7: Ítem(s) del catálogo
A8: Código en pantalla “New Self Test”. | B8: Limpiar la entrada de aire de muestra y reintentar el self-test. | C8: 2.1.3
A9: El código persiste tras la limpieza. | B9: El equipo requiere mantenimiento por personal de servicio calificado (Bloqueante). | C9: 1.1.1
A10: Código “Fatal Error Please Check!” (self-test fallido varias veces). | B10: Contactar al fabricante/representante (GRIMM/DURAG); no insistir con más ciclos en sitio. | C10: 1.1.1
A11: Código “CARD ERROR! PLEASE CHECK”. | B11: Tarjeta insertada/retirada durante operación, o protección de escritura activa — ver Cadena 10. | C11: 5.3.2
A12: Código “NO SENSOR! PLEASE CHECK”. | B12: Sensor de T/HR no conectado o defectuoso; la medición se detiene. | C12: 7.1.1
A14: Cadena 2 — Alarma “Dryer” / vacío de la etapa de secado no OK
A15: Fuente: SER-MAN DUST MONITOR 180 cap. 2.1
A16: Paso / disparador | B16: Verificación o acción | C16: Ítem(s) del catálogo
A17: “Self Test not OK!” con el LED del dryer en rojo (solo durante self-test). | B17: Vacío de la unidad de secado no OK — revisar el manómetro tras la tapa del panel frontal. | C17: 3.2.1
A18: Código “VACUUM NOT OK! PLEASE CHECK”. | B18: La medición se detiene; revisar la presión de vacío y el estado del secador Nafion/drenaje. | C18: 3.2.2 · 2.4.1 · 2.4.2
A19: Código “VACUUM SWITCH! PLEASE CHECK” (presostato cerrado sin vacío suficiente). | B19: La medición se detiene; el manual indica contactar al fabricante/representante — no resoluble en sitio (Bloqueante). | C19: 3.3.3
A21: Cadena 3 — Error de flujo (“AIR FLOW NOT OK”, corriente de bomba alta)
A22: Fuente: Correo “GRIMM EDM 180 FLOW ERROR” S/N 18A12047
A23: Paso / disparador | B23: Verificación o acción | C23: Ítem(s) del catálogo
A24: Código “AIR FLOW NOT OK CHECK AIR INLET” o alarma “AIR PUMP CURRENT TOO HIGH” en self-test. | B24: El controlador de flujo no logra regular a 1,2 L/min. | C24: 3.4.1
A25: Paso 1. | B25: Verificar fugas en el circuito y medir el voltaje de la válvula proporcional P-Valve (referencia de campo: 11,47 V). | C25: 3.3.1 · 3.4.2
A26: Paso 2. | B26: Aislar el espectrómetro: intercambiarlo a otra carcasa o usar tubería externa, para saber si la falla es interna o externa.
A27: Paso 3 (si la falla queda dentro del espectrómetro). | B27: Retirar la tarjeta digital y el sensor de presión diferencial; inspeccionar la tarjeta análoga en busca de residuos conductivos y limpiarla con limpiador de tarjetas. | C27: 5.1.1 · 5.1.2
A28: Paso 4. | B28: En modo servicio (Terminal/HyperTerminal): enviar “ctrl-f”, ajustar al 100 % el flujo manual, girar el potenciómetro de flujo antihorario hasta clic, reajustar a 1,2 L/min en sentido horario.
A29: Si aparece “Error 200” (problema de vacío). | B29: Revisar el manómetro y el flujo de vacío en el pin de salida trasero (~2,1 L/min); considerar el kit de vacío/bomba. | C29: 3.2.1 · 3.1.1 · 3.1.2
A30: Si la presión atmosférica muestra un valor anómalo (p. ej. 4 hPa) tras lo anterior. | B30: Los factores de calibración (factor/offset) del sensor de presión absoluta pueden haberse perdido, sobre todo tras reemplazar la tarjeta digital; reconfigurar por Terminal. | C30: 7.1.4
A31: Si nada de lo anterior resuelve el error y se confirma daño del láser. | B31: Reemplazo de la unidad láser completa (ref. de campo: pieza 1205338 “Lasereinheit 187 komplett”). | C31: 4.3.1 · 4.3.2 · 4.3.5
A33: Cadena 4 — Prueba de filtro cero: los conteos no dan cero
A34: Fuente: Service Training · Service Training NEW
A35: Paso / disparador | B35: Verificación o acción | C35: Ítem(s) del catálogo
A36: Todos los conteos deben ser cero con el filtro cero instalado; si no lo son… | B36: Revisar también CO_h y CO_d. | C36: 4.4.3
A37: Causas documentadas. | B37: Sistema neumático no estanco, conexiones de tubo defectuosas, disturbios electrónicos, membrana defectuosa del controlador de aire de purga (RAC). | C37: 3.3.1 · 2.4.3 · 5.1.2 · 5.1.3 · 3.4.3
A38: Si CO_h/CO_d quedan anormalmente altos sin causa hallada. | B38: Posible corrosión o daño del fotodiodo/preamplificador — reparación solo en fábrica (Bloqueante). | C38: 4.4.3
A40: Cadena 5 — Reloj interno (RTC) inestable
A41: Fuente: Correo “Date and hour problem” S/N 18A18103
A42: Paso / disparador | B42: Verificación o acción | C42: Ítem(s) del catálogo
A43: Verificación. | B43: En HyperTerminal: leer la hora, esperar unos minutos, volver a leer — si no coincide, el reloj interno dejó de funcionar. | C43: 5.5.1
A44: 1er componente a reemplazar. | B44: Chip temporizador PCF8583 (en Zoho, SKU activo PCF8583P; el correo cita PCF8583F). | C44: 5.5.1
A45: Si la falla reaparece. | B45: El capacitor ajustable es, según GRIMM, la causa más común — reemplazarlo. | C45: 5.5.1
A46: Si aún persiste. | B46: El cristal oscilador es el tercer componente — última opción de descarte. | C46: 5.5.1 · 5.5.2
A47: Tras cualquier reemplazo. | B47: Calibrar el trimmer del reloj con precisión; de lo contrario mostrará una hora adelantada o atrasada.
A49: Cadena 6 — Sensor de presión atmosférica con lectura anómala
A50: Fuente: Correo “GRIMM EDM 180 FLOW ERROR” 18A12047 · Correo “Sensor Presión EDM180” 18A12048
A51: Paso / disparador | B51: Verificación o acción | C51: Ítem(s) del catálogo
A52: Valor fuera de rango (p. ej. 4 hPa en vez de ~740-750 hPa). | B52: No asumir de inmediato que el sensor físico está dañado. | C52: 7.1.4
A53: Verificar los valores P-Line (voltajes) del sensor. | B53: Si son coherentes con una presión razonable, el sensor funciona — el problema son los factores de calibración (factor/offset) perdidos, frecuente tras reemplazar la tarjeta digital. | C53: 5.1.1
A54: Reconfiguración. | B54: Por Terminal: “$”, “4” (canal 4 = presión), ENTER, ingresar factor y offset de fábrica, ENTER, verificar en LCD.
A55: Solo si el sensor no responde en absoluto. | B55: Reemplazar el sensor físico (H6DP015AZ8H). | C55: 7.1.4
A57: Cadena 7 — Controlador de aire de purga (RAC) fuera de rango
A58: Fuente: Service Training · Service Training NEW
A59: Paso / disparador | B59: Verificación o acción | C59: Ítem(s) del catálogo
A60: Procedimiento. | B60: Retirar el tubo central del RAC; conectar la entrada del flujómetro al RAC y la salida al tubo retirado; enviar “ctrl+f” por HyperTerminal para correr la bomba de muestra o iniciar el equipo. | C60: 3.4.3
A61: Criterio. | B61: El flujo de aire de purga debe quedar entre 0,3 y 0,5 L/min.
A62: Si no. | B62: Revisar el filtro asociado al RAC. | C62: 3.4.6
A64: Cadena 8 — Mecanismo de elevación (lift) no responde
A65: Fuente: Service Training · Service Training NEW
A66: Paso / disparador | B66: Verificación o acción | C66: Ítem(s) del catálogo
A67: Procedimiento. | B67: Instalar el equipo tal como lo usaría el cliente; dejar el lift arriba, verificar su flexibilidad mecánica; correr el equipo sin modo servicio. | C67: 8.1.5
A68: Si aparece error de lift, revisar en orden. | B68: Contacto entre el lift y el soporte del tubo de muestra (Sample Pipe Holder), la palanca del lift, el switch de fin de carrera al final de la palanca, y el cableado hasta la fuente de alimentación. | C68: 2.2.6 · 5.3.3
A70: Cadena 9 — Prueba de estanqueidad (fugas) fuera de criterio
A71: Fuente: SER-MAN DUST MONITOR 180 · Service Training
A72: Paso / disparador | B72: Verificación o acción | C72: Ítem(s) del catálogo
A73: Criterio. | B73: Tras 20 s de carga a 80 mmHg, el sistema es estanco si queda por encima de 60 mmHg. | C73: 3.3.1
A74: Si no. | B74: Buscar la fuga con ayuda del esquema neumático (flow schematics) del equipo.
A75: Puntos habituales de fuga. | B75: O-rings del holder, O-ring de la boquilla de entrada, mangueras de la línea neumática. | C75: 3.3.2 · 2.2.5 · 2.4.3
A77: Cadena 10 — Mensajes de la tarjeta de memoria
A78: Fuente: SER-MAN DUST MONITOR 180 cap. 2.1
A79: Paso / disparador | B79: Verificación o acción | C79: Ítem(s) del catálogo
A80: “NO MEMOCARD”. | B80: No hay tarjeta insertada; insertarla si se va a usar.
A81: “CARD ERROR! PLEASE CHECK”. | B81: Tarjeta insertada/retirada durante operación, o protección de escritura activa. | C81: 5.3.2
A82: “PLEASE REPLACE MEMORYCARD-BATT.”. | B82: Reemplazar la batería de la tarjeta; respaldar los datos antes. | C82: 5.3.1
A83: “WRONG SerialNo.” / “WRONG VERSION! Clear Memorycard”. | B83: La tarjeta trae datos de otro equipo o firmware; leer y respaldar los datos, luego formatear. | C83: 5.3.2
A84: “PLEASE CHECK MEMORYCARD”. | B84: Tarjeta protegida contra escritura. | C84: 5.3.2
A86: Cadena 11 — Óptica y láser: “NEW CALIBRATION” / línea negra en pantalla
A87: Fuente: SER-MAN DUST MONITOR 180 cap. 2.2
A88: Paso / disparador | B88: Verificación o acción | C88: Ítem(s) del catálogo
A89: “NEW CALIBRATION”, DC-Diff (láser encendido/apagado) demasiado bajo. | B89: Láser apagado o dañado; revisar la tarjeta driver del láser. | C89: 4.3.1 · 4.3.2 · 5.1.4
A90: “NEW CALIBRATION”, DC-Diff demasiado alto. | B90: Óptica del láser contaminada — limpiar. | C90: 4.2.2
A91: “Black line on the display”. | B91: Pantalla defectuosa o tarjeta digital defectuosa. | C91: 5.1.1
A92: Si no se resuelve con limpieza de óptica ni ajuste. | B92: Falla de láser documentada en el correo Flow Error: reemplazo de la unidad láser completa (ref. de campo: pieza 1205338). | C92: 4.3.5
A94: Cadena 12 — Filtro de polvo colmatado (“CHECK DUSTFILTER AND AIR PASSAGE”)
A95: Fuente: SER-MAN DUST MONITOR 180 cap. 2.2
A96: Paso / disparador | B96: Verificación o acción | C96: Ítem(s) del catálogo
A97: Código en pantalla. | B97: Baja presión tras el filtro fino demasiado alta. | C97: 6.1.3
A98: Acción. | B98: Cambiar el filtro de polvo fino. | C98: 6.1.1
A99: Si persiste tras el cambio. | B99: Contactar al fabricante/representante.
A101: Cadena 13 — Ganancias/dolomita/desviación de masa fuera de criterio: ciclo de recalibración
A102: Fuente: Service Training NEW
A103: Paso / disparador | B103: Verificación o acción | C103: Ítem(s) del catálogo
A104: Pre-comparación. | B104: Conteo contra un patrón de referencia en la torre de calibración. | C104: 1.3.3
A105: Servicio-reparación. | B105: Limpieza y reajuste de los componentes implicados.
A106: Calibración. | B106: Preamplificador, láser, flujo, umbrales (thresholds). | C106: 5.2.1 · 5.2.2 · 5.2.3 · 4.3.3
A107: Prueba de resistencia (endurance test). | B107: 48 horas contra un patrón en condiciones reales de exterior.
A108: Verificación final. | B108: De todos los componentes, con entrega de certificado.

Sheet Flujo No OK 2
A1: ENCADENAMIENTO CONDICIONAL — TABLA DE ENLACES ORIGEN → DESTINO
A2: Un renglón por enlace del árbol de diagnóstico (misma filosofía que la referencia del cliente para los Horiba APxA-370). La columna «Rama activa» se enciende sola cuando el ítem de origen queda marcado como hallazgo (No conforme / Requiere reemplazo) en la hoja Inspección de esta misma visita.
A3: Filtre por «Rama activa = SÍ — verificar destino» para ver únicamente las verificaciones que la visita de hoy realmente disparó. ID origen e ID destino son hipervínculos a la fila del ítem en la hoja Inspección. Es la versión en tabla plana, consultable y filtrable, de las 13 cadenas narradas en la hoja «Flujo No OK»; cubre los mismos ~40 ítems con secuencia documentada en el notebook — no añade cobertura nueva, la reorganiza para poder filtrarla por resultado de visita.
A5: Modelo | B5: ID origen | C5: Ítem que salió No OK | D5: Criterio de falla | E5: Causa probable | F5: Orden | G5: ID destino | H5: Verificación siguiente | I5: Acción si se confirma | J5: Resultado del origen | K5: Rama activa
A6: GRIMM EDM180 | B6: 1.1.1 | C6: Ciclo self-test | D6: Bloqueante | E6: Código de self-test no superado: entrada de aire de muestra obstruida, sensor no conectado, o falla que requiere servicio calificado. | F6: 1 | G6: 2.1.3 | H6: Limpieza interna del cabezal | I6: Revisar el código específico mostrado en pantalla (SER-MAN cap. 2.1). Si es “New Self Test”, limpiar la entrada de aire de muestra (2.1.3) y reintentar; si el código persiste, el equipo requiere servicio técnico calificado. Ver Cadena 1 en hoja Flujo No OK. | J6: =IFERROR(INDEX(Inspección!$T$9:$T$111,MATCH($B6,Inspección!$A$9:$A$111,0)),"") -> Pendiente | K6: =IF(OR($J6="No conforme",$J6="Requiere reemplazo"),"SÍ — verificar destino","")
A7: GRIMM EDM180 | B7: 1.1.1 | C7: Ciclo self-test | D7: Bloqueante | E7: Código de self-test no superado: entrada de aire de muestra obstruida, sensor no conectado, o falla que requiere servicio calificado. | F7: 2 | G7: 5.3.2 | H7: Tarjeta PCMCIA / almacenamiento | I7: Revisar el código específico mostrado en pantalla (SER-MAN cap. 2.1). Si es “New Self Test”, limpiar la entrada de aire de muestra (2.1.3) y reintentar; si el código persiste, el equipo requiere servicio técnico calificado. Ver Cadena 1 en hoja Flujo No OK. | J7: =IFERROR(INDEX(Inspección!$T$9:$T$111,MATCH($B7,Inspección!$A$9:$A$111,0)),"") -> Pendiente | K7: =IF(OR($J7="No conforme",$J7="Requiere reemplazo"),"SÍ — verificar destino","")
A8: GRIMM EDM180 | B8: 1.1.1 | C8: Ciclo self-test | D8: Bloqueante | E8: Código de self-test no superado: entrada de aire de muestra obstruida, sensor no conectado, o falla que requiere servicio calificado. | F8: 3 | G8: 7.1.1 | H8: Sensor de T y HR ambiente | I8: Revisar el código específico mostrado en pantalla (SER-MAN cap. 2.1). Si es “New Self Test”, limpiar la entrada de aire de muestra (2.1.3) y reintentar; si el código persiste, el equipo requiere servicio técnico calificado. Ver Cadena 1 en hoja Flujo No OK. | J8: =IFERROR(INDEX(Inspección!$T$9:$T$111,MATCH($B8,Inspección!$A$9:$A$111,0)),"") -> Pendiente | K8: =IF(OR($J8="No conforme",$J8="Requiere reemplazo"),"SÍ — verificar destino","")
A9: GRIMM EDM180 | B9: 1.1.2 | C9: Inicio de medición | D9: Bloqueante | E9: Comparte causa probable con el self-test (1.1.1): mismo código de arranque no resuelto. | F9: 1 | G9: 1.1.1 | H9: Ciclo self-test | I9: Si el equipo completa el self-test pero no pasa a medición, revisar los mismos códigos de la Cadena 1 (self-test) — causa probablemente común con 1.1.1. | J9: =IFERROR(INDEX(Inspección!$T$9:$T$111,MATCH($B9,Inspección!$A$9:$A$111,0)),"") -> Pendiente | K9: =IF(OR($J9="No conforme",$J9="Requiere reemplazo"),"SÍ — verificar destino","")
A10: GRIMM EDM180 | B10: 1.1.3 | C10: Alarmas activas | D10: Alerta | E10: Alarma «Dryer» activa: vacío o presión de la etapa de secado fuera de rango. | F10: 1 | G10: 3.2.1 | H10: Manómetro de vacío | I10: Si la alarma es “Dryer”: revisar el manómetro de vacío tras la tapa del panel frontal (3.2.1) y la presión de vacío (3.2.2). Ver Cadena 2 en hoja Flujo No OK. | J10: =IFERROR(INDEX(Inspección!$T$9:$T$111,MATCH($B10,Inspección!$A$9:$A$111,0)),"") -> Pendiente | K10: =IF(OR($J10="No conforme",$J10="Requiere reemplazo"),"SÍ — verificar destino","")
A11: GRIMM EDM180 | B11: 1.1.3 | C11: Alarmas activas | D11: Alerta | E11: Alarma «Dryer» activa: vacío o presión de la etapa de secado fuera de rango. | F11: 2 | G11: 3.2.2 | H11: Presión negativa de succión (vacío) | I11: Si la alarma es “Dryer”: revisar el manómetro de vacío tras la tapa del panel frontal (3.2.1) y la presión de vacío (3.2.2). Ver Cadena 2 en hoja Flujo No OK. | J11: =IFERROR(INDEX(Inspección!$T$9:$T$111,MATCH($B11,Inspección!$A$9:$A$111,0)),"") -> Pendiente | K11: =IF(OR($J11="No conforme",$J11="Requiere reemplazo"),"SÍ — verificar destino","")
A12: GRIMM EDM180 | B12: 1.1.3 | C12: Alarmas activas | D12: Alerta | E12: Alarma «Dryer» activa: vacío o presión de la etapa de secado fuera de rango. | F12: 3 | G12: 2.4.1 | H12: Estado del Nafion | I12: Si la alarma es “Dryer”: revisar el manómetro de vacío tras la tapa del panel frontal (3.2.1) y la presión de vacío (3.2.2). Ver Cadena 2 en hoja Flujo No OK. | J12: =IFERROR(INDEX(Inspección!$T$9:$T$111,MATCH($B12,Inspección!$A$9:$A$111,0)),"") -> Pendiente | K12: =IF(OR($J12="No conforme",$J12="Requiere reemplazo"),"SÍ — verificar destino","")
A13: GRIMM EDM180 | B13: 1.3.3 | C13: Desviación relativa de masa (verificación con aire ambiente) | D13: Bloqueante | E13: Desviación de masa fuera de ±5%/±2 µg/m³ tras calibrar en torre: mismo ciclo de recalibración completo. | F13: 1 | G13: 5.2.1 | H13: Ganancia canal F | I13: Si la desviación de masa queda fuera de criterio tras calibrar en torre, el Service Training documenta el ciclo completo: pre-comparación, calibración de preamplificador/láser/flujo/umbrales, prueba de 48 h, verificación final. Ver Cadena 13. | J13: =IFERROR(INDEX(Inspección!$T$9:$T$111,MATCH($B13,Inspección!$A$9:$A$111,0)),"") -> Pendiente | K13: =IF(OR($J13="No conforme",$J13="Requiere reemplazo"),"SÍ — verificar destino","")
A14: GRIMM EDM180 | B14: 1.3.3 | C14: Desviación relativa de masa (verificación con aire ambiente) | D14: Bloqueante | E14: Desviación de masa fuera de ±5%/±2 µg/m³ tras calibrar en torre: mismo ciclo de recalibración completo. | F14: 2 | G14: 4.3.3 | H14: Respuesta a verificación con dolomita | I14: Si la desviación de masa queda fuera de criterio tras calibrar en torre, el Service Training documenta el ciclo completo: pre-comparación, calibración de preamplificador/láser/flujo/umbrales, prueba de 48 h, verificación final. Ver Cadena 13. | J14: =IFERROR(INDEX(Inspección!$T$9:$T$111,MATCH($B14,Inspección!$A$9:$A$111,0)),"") -> Pendiente | K14: =IF(OR($J14="No conforme",$J14="Requiere reemplazo"),"SÍ — verificar destino","")
A15: GRIMM EDM180 | B15: 2.2.5 | C15: O-Ring de la boquilla de entrada | D15: Cobrable | E15: Desgaste del O-Ring de la boquilla de entrada: punto habitual de fuga en la prueba de estanqueidad. | F15: 1 | G15: 3.3.1 | H15: Prueba de fugas del circuito (test de presión) | I15: Punto habitual de fuga documentado para la prueba de estanqueidad (Cadena 9). | J15: =IFERROR(INDEX(Inspección!$T$9:$T$111,MATCH($B15,Inspección!$A$9:$A$111,0)),"") -> Pendiente | K15: =IF(OR($J15="No conforme",$J15="Requiere reemplazo"),"SÍ — verificar destino","")
A16: GRIMM EDM180 | B16: 2.2.6 | C16: Soporte del tubo (Sample Pipe Holder) y tornillo de fijación | D16: Cobrable | E16: Contacto lift-soporte del tubo o switch de fin de carrera con falla. | F16: 1 | G16: 8.1.5 | H16: Mecanismo de elevación (lift) del bastidor | I16: Punto de contacto documentado en el diagnóstico del mecanismo de lift (Cadena 8) si falla el switch de fin de carrera. | J16: =IFERROR(INDEX(Inspección!$T$9:$T$111,MATCH($B16,Inspección!$A$9:$A$111,0)),"") -> Pendiente | K16: =IF(OR($J16="No conforme",$J16="Requiere reemplazo"),"SÍ — verificar destino","")
A17: GRIMM EDM180 | B17: 2.4.1 | C17: Estado del Nafion | D17: Cobrable | E17: Secador Nafion deteriorado, asociado a la alarma Dryer y a vacío fuera de rango. | F17: 1 | G17: 2.4.2 | H17: Water drain | I17: Estado del Nafion ligado a la alarma Dryer y a “vacío no OK” (Cadena 2); revisar junto con el drenaje (2.4.2). | J17: =IFERROR(INDEX(Inspección!$T$9:$T$111,MATCH($B17,Inspección!$A$9:$A$111,0)),"") -> Pendiente | K17: =IF(OR($J17="No conforme",$J17="Requiere reemplazo"),"SÍ — verificar destino","")
... A89: GRIMM EDM180 | B89: 8.1.5 | C89: Mecanismo de elevación (lift) del bastidor | D89: Cobrable | E89: Alarma «Self Test LIFT NOT OK» al levantar el bastidor. | F89: 2 | G89: 5.3.3 | H89: Cableado y conectores internos | I89: Protocolo documentado: si aparece error de lift, revisar en orden — contacto lift-soporte del tubo (2.2.6), palanca del lift, switch de fin de carrera, cableado hasta la fuente de alimentación (5.3.3). Ver Cadena 8. | J89: =IFERROR(INDEX(Inspección!$T$9:$T$111,MATCH($B89,Inspección!$A$9:$A$111,0)),"") -> Pendiente | K89: =IF(OR($J89="No conforme",$J89="Requiere reemplazo"),"SÍ — verificar destino","")
A91: 84 enlaces entre 41 ítems de origen y sus ítems relacionados — mismo contenido que las columnas N/O de Inspección y que la hoja Flujo No OK, reorganizado en tabla plana filtrable.
A92: No es un árbol de decisión formal de GRIMM: es una reconstrucción de Ambientalia a partir de mensajes de error y protocolos de servicio documentados en el notebook «ST Grimm EDM180» — misma fuente y mismo alcance (~40 de 103 ítems) que la hoja Flujo No OK.
