Workbook

Sheet Instrucciones
A1: INSPECCIÓN FÍSICA DE EQUIPO — SERIE HORIBA AP-370
A2: APMA-370 (CO) · APSA-370 (SO2) · APOA-370 (O3) · APNA-370 (NOx)
A3: Ambientalia — Servicio Técnico · v1.0 · Estructura derivada del prototipo GRIMM EDM180 v1.2
A5: Qué contiene este libro
A6: Una hoja de inspección por modelo de analizador. Cada hoja es a la vez el catálogo maestro de la
A7: jerarquía (niveles macro N1, subniveles N2 e ítems N3) y la hoja de captura de una visita, con la
A8: misma estructura de columnas del prototipo GRIMM EDM180 v1.2: las columnas A a N definen el ítem
A9: y las columnas O a S (en amarillo) son lo que diligencia el técnico en cada visita.
A11: Hojas del libro
A12: APMA-370 (CO) Analizador de monóxido de carbono HORIBA APMA-370 · NDIR con modulación de flujo cruzado
A13: 10 niveles macro, 34 subniveles y 80 ítems.
A14: APSA-370 (SO2) Analizador de dióxido de azufre HORIBA APSA-370 · Fluorescencia ultravioleta (UVF)
... A88: modelo (clic derecho → Mover o copiar → Crear una copia) antes de diligenciar las columnas O a S.

Sheet APMA-370 (CO)
A1: FASE 1 — INSPECCIÓN FÍSICA DEL EQUIPO · APMA-370 (CO) (catálogo + captura)
A3: Cliente: | D3: Principio de medición: | E3: NDIR con modulación de flujo cruzado
A4: NIT: | D4: Fecha de inspección:
A5: Equipo / Modelo: | B5: Analizador de monóxido de carbono HORIBA APMA-370 | D5: Técnico responsable:
A6: Número de serie: | D6: N.º de informe (MT):
A8: ID | B8: Nivel macro (N1) | C8: Subnivel (N2) | D8: Ítem (N3) | E8: Qué se verifica | F8: Tipo de dato | G8: Unidad | H8: Criterio de aceptación | I8: Límite inferior | J8: Límite superior | K8: Obligatorio | L8: Evidencia fotográfica requerida | M8: Repuesto / parte asociada | N8: Fuente documental | O8: Resultado | P8: Valor medido | Q8: Verificación de rango | R8: Foto adjunta | S8: Observación
A9: 1.1.1 | B9: 1. Verificación funcional inicial | C9: 1.1 Encendido y LEDs frontales | D9: LED de encendido (Power LED) | E9: Color del LED indicador de encendido en el panel frontal | F9: OK / No OK | H9: Debe iluminarse en verde fijo (operación normal). Rojo indica alarma activa | K9: Sí | L9: Sí | N9: P-ST-018-MAN OPER APMA 370 V2 | O9: Pendiente | Q9: =IF($F9<>"Numérico","",IF($P9="","Sin dato",IF(AND(OR(NOT(ISNUMBER($I9)),$P9>=$I9),OR(NOT(ISNUMBER($J9)),$P9<=$J9)),"Dentro de rango","Fuera de rango")))
A10: 1.1.2 | B10: 1. Verificación funcional inicial | C10: 1.1 Encendido y LEDs frontales | D10: LED de alarma (Alarm LED) | E10: Estado de alarma activa verificado mediante el color del indicador frontal | F10: Sí/No | H10: El LED de alarma debe permanecer apagado. Si cambia a rojo indica fallo de hardware o de parámetro | K10: Sí | L10: No | N10: P-ST-018-MAN OPER APMA 370 V2 | O10: Pendiente | Q10: =IF($F10<>"Numérico","",IF($P10="","Sin dato",IF(AND(OR(NOT(ISNUMBER($I10)),$P10>=$I10),OR(NOT(ISNUMBER($J10)),$P10<=$J10)),"Dentro de rango","Fuera de rango")))
A11: 1.1.3 | B11: 1. Verificación funcional inicial | C11: 1.1 Encendido y LEDs frontales | D11: Inicialización del display (TFT LCD) | E11: Arranque correcto y despliegue del menú MEAS. sin bloqueos ni líneas muertas | F11: OK / No OK | H11: La pantalla LCD TFT debe encender de forma estable y permitir navegación táctil | K11: Sí | L11: Sí | M11: LCD Unit chassis and LCD 3200618696 | N11: AP-370 LCD replacement / MT_191TE0NC_APMA370_241226 | O11: Pendiente | Q11: =IF($F11<>"Numérico","",IF($P11="","Sin dato",IF(AND(OR(NOT(ISNUMBER($I11)),$P11>=$I11),OR(NOT(ISNUMBER($J11)),$P11<=$J11)),"Dentro de rango","Fuera de rango")))
A12: 1.2.1 | B12: 1. Verificación funcional inicial | C12: 1.2 Autodiagnóstico de software | D12: Versión de programa (firmware) | E12: Lectura de la versión de programa en la pantalla de información de software | F12: Texto | H12: Debe coincidir con la versión homologada de fábrica (estándar AP: P1000878001) | K12: Sí | L12: No | N12: 1 - LCD design change AP EN | O12: Pendiente | Q12: =IF($F12<>"Numérico","",IF($P12="","Sin dato",IF(AND(OR(NOT(ISNUMBER($I12)),$P12>=$I12),OR(NOT(ISNUMBER($J12)),$P12<=$J12)),"Dentro de rango","Fuera de rango")))
A13: 1.3.1 | B13: 1. Verificación funcional inicial | C13: 1.3 Estabilización térmica | D13: Tiempo de calentamiento inicial (warm-up) | E13: Tiempo transcurrido desde el encendido en frío hasta la estabilización | F13: Numérico | G13: horas | H13: Mínimo 3 h de calentamiento para estabilizar banco óptico y catalizador antes de medir. Límite superior PENDIENTE DE VALIDAR | I13: 3 | K13: Sí | L13: No | N13: GZ0000117746B SM E APXX-370 (Service Manual) | O13: Pendiente | Q13: =IF($F13<>"Numérico","",IF($P13="","Sin dato",IF(AND(OR(NOT(ISNUMBER($I13)),$P13>=$I13),OR(NOT(ISNUMBER($J13)),$P13<=$J13)),"Dentro de rango","Fuera de rango"))) -> Sin dato
A14: 2.1.1 | B14: 2. Identificación y trazabilidad | C14: 2.1 Placas e identificación física | D14: Placa de número de serie frontal | E14: Presencia y legibilidad del número de serie en el panel frontal inferior | F14: Texto | H14: Debe ser legible y coincidir con el registro y la hoja de vida de la estación | K14: Sí | L14: No | N14: MT_U7D80D0J_APMA370_260116 | O14: Pendiente | Q14: =IF($F14<>"Numérico","",IF($P14="","Sin dato",IF(AND(OR(NOT(ISNUMBER($I14)),$P14>=$I14),OR(NOT(ISNUMBER($J14)),$P14<=$J14)),"Dentro de rango","Fuera de rango")))
A15: 2.1.2 | B15: 2. Identificación y trazabilidad | C15: 2.1 Placas e identificación física | D15: Placa de número de serie posterior | E15: Presencia y legibilidad de la placa de datos metálica HORIBA en el panel trasero | F15: Texto | H15: Debe ser legible y coincidir con el serial frontal y la etiqueta de la cabina | K15: Sí | L15: No | N15: MT_U7D80D0J_APMA370_260116 | O15: Pendiente | Q15: =IF($F15<>"Numérico","",IF($P15="","Sin dato",IF(AND(OR(NOT(ISNUMBER($I15)),$P15>=$I15),OR(NOT(ISNUMBER($J15)),$P15<=$J15)),"Dentro de rango","Fuera de rango")))
A16: 2.2.1 | B16: 2. Identificación y trazabilidad | C16: 2.2 Identificación lógica | D16: ID del equipo (Machine ID) | E16: Configuración del código ID del analizador para identificación en red | F16: Numérico | H16: El ID configurado en el menú SYSTEM debe coincidir con el asignado por el sistema de adquisición | I16: 0 | J16: 255 | K16: Sí | L16: No | N16: P-ST-018-MAN OPER APMA 370 V2 | O16: Pendiente | Q16: =IF($F16<>"Numérico","",IF($P16="","Sin dato",IF(AND(OR(NOT(ISNUMBER($I16)),$P16>=$I16),OR(NOT(ISNUMBER($J16)),$P16<=$J16)),"Dentro de rango","Fuera de rango"))) -> Sin dato
A17: 2.3.1 | B17: 2. Identificación y trazabilidad | C17: 2.3 Etiquetas de seguridad | D17: Señalización de choque eléctrico | E17: Etiquetas de advertencia de alto voltaje en cubiertas de placas y transformadores | F17: Presente / Ausente | H17: Deben estar adheridas y legibles las advertencias Choque eléctrico 1, 2 y 3 | K17: Sí | L17: Sí | N17: P-ST-019-MAN MTTO APMA370 V2 | O17: Pendiente | Q17: =IF($F17<>"Numérico","",IF($P17="","Sin dato",IF(AND(OR(NOT(ISNUMBER($I17)),$P17>=$I17),OR(NOT(ISNUMBER($J17)),$P17<=$J17)),"Dentro de rango","Fuera de rango")))
A18: 2.3.2 | B18: 2. Identificación y trazabilidad | C18: 2.3 Etiquetas de seguridad | D18: Señalización de componentes calientes | E18: Etiquetas adhesivas amarillas de advertencia térmica en zonas de alta temperatura | F18: Presente / Ausente | H18: Deben estar adheridas las etiquetas de calor sobre la carcasa del catalizador y de la bomba | K18: Sí | L18: Sí | N18: P-ST-019-MAN MTTO APMA370 V2 | O18: Pendiente | Q18: =IF($F18<>"Numérico","",IF($P18="","Sin dato",IF(AND(OR(NOT(ISNUMBER($I18)),$P18>=$I18),OR(NOT(ISNUMBER($J18)),$P18<=$J18)),"Dentro de rango","Fuera de rango")))
A19: 3.1.1 | B19: 3. Estado de calibración | C19: 3.1 Coeficientes de calibración | D19: Coeficiente de calibración de cero | E19: Factor de corrección de cero almacenado tras el último ajuste manual o AIC | F19: Numérico | G19: counts | H19: Debe estar dentro del rango operativo; fuera de él parpadea la alarma ZERO | I19: -3500 | J19: 3500 | K19: Sí | L19: No | N19: P-ST-018-MAN OPER APMA 370 V2 | O19: Pendiente | Q19: =IF($F19<>"Numérico","",IF($P19="","Sin dato",IF(AND(OR(NOT(ISNUMBER($I19)),$P19>=$I19),OR(NOT(ISNUMBER($J19)),$P19<=$J19)),"Dentro de rango","Fuera de rango"))) -> Sin dato
A20: 3.1.2 | B20: 3. Estado de calibración | C20: 3.1 Coeficientes de calibración | D20: Coeficiente de calibración de span | E20: Ganancia del detector de CO calibrada con gas patrón y almacenada en memoria | F20: Numérico | H20: Debe estar dentro de los límites de amplificación admitidos; fuera de él parpadea la alarma SPAN | I20: 0.5 | J20: 2 | K20: Sí | L20: No | N20: P-ST-018-MAN OPER APMA 370 V2 | O20: Pendiente | Q20: =IF($F20<>"Numérico","",IF($P20="","Sin dato",IF(AND(OR(NOT(ISNUMBER($I20)),$P20>=$I20),OR(NOT(ISNUMBER($J20)),$P20<=$J20)),"Dentro de rango","Fuera de rango"))) -> Sin dato
A21: 3.2.1 | B21: 3. Estado de calibración | C21: 3.2 Suministro de gases patrón | D21: Presión de entrada de gas patrón | E21: Presión de entrega de gases de referencia (cero y span) en las entradas traseras | F21: Numérico | G21: kPa | H21: Deben entregarse ligeramente por encima de la presión atmosférica para generar overflow | I21: 0 | J21: 0.5 | K21: Sí | L21: No | N21: P-ST-018-MAN OPER APMA 370 V2 | O21: Pendiente | Q21: =IF($F21<>"Numérico","",IF($P21="","Sin dato",IF(AND(OR(NOT(ISNUMBER($I21)),$P21>=$I21),OR(NOT(ISNUMBER($J21)),$P21<=$J21)),"Dentro de rango","Fuera de rango"))) -> Sin dato
A22: 3.2.2 | B22: 3. Estado de calibración | C22: 3.2 Suministro de gases patrón | D22: Caudal de exceso de gas de calibración (OVER FLOW) | E22: Caudal excedente medido por el sensor de flujo opcional de calibración | F22: Numérico | G22: L/min | H22: Caudal mínimo 1,2 L/min para que el analizador absorba gas patrón sin aspirar aire ambiente. Límite superior PENDIENTE DE VALIDAR | I22: 1.2 | K22: Sí | L22: No | N22: P-ST-018-MAN OPER APMA 370 V2 | O22: Pendiente | Q22: =IF($F22<>"Numérico","",IF($P22="","Sin dato",IF(AND(OR(NOT(ISNUMBER($I22)),$P22>=$I22),OR(NOT(ISNUMBER($J22)),$P22<=$J22)),"Dentro de rango","Fuera de rango"))) -> Sin dato
A23: 3.3.1 | B23: 3. Estado de calibración | C23: 3.3 Secuencia de autocalibración (AIC) | D23: Tiempo de espera (WAIT) en AIC | E23: Tiempo configurado para purgar la celda y estabilizar lecturas tras conmutar la línea de gas | F23: Numérico | G23: minutos | H23: Tiempo mínimo de retardo tras conmutar la línea de gas; el fabricante recomienda 3 min o más | I23: 3 | J23: 999 | K23: Sí | L23: No | N23: P-ST-018-MAN OPER APMA 370 V2 | O23: Pendiente | Q23: =IF($F23<>"Numérico","",IF($P23="","Sin dato",IF(AND(OR(NOT(ISNUMBER($I23)),$P23>=$I23),OR(NOT(ISNUMBER($J23)),$P23<=$J23)),"Dentro de rango","Fuera de rango"))) -> Sin dato
A24: 3.3.2 | B24: 3. Estado de calibración | C24: 3.3 Secuencia de autocalibración (AIC) | D24: Tiempo de sostenimiento (HOLD) en AIC | E24: Tiempo de retención y chequeo de lecturas de salida al finalizar el AIC | F24: Numérico | G24: minutos | H24: Tiempo de validación posterior a la calibración física de las señales analógicas | I24: 0 | J24: 999 | K24: Sí | L24: No | N24: P-ST-018-MAN OPER APMA 370 V2 | O24: Pendiente | Q24: =IF($F24<>"Numérico","",IF($P24="","Sin dato",IF(AND(OR(NOT(ISNUMBER($I24)),$P24>=$I24),OR(NOT(ISNUMBER($J24)),$P24<=$J24)),"Dentro de rango","Fuera de rango"))) -> Sin dato
A25: 3.3.3 | B25: 3. Estado de calibración | C25: 3.3 Secuencia de autocalibración (AIC) | D25: Activación de calibración (CAL) en AIC | E25: Selección de la corrección física del factor cero/span durante el AIC | F25: Sí/No | H25: Define si se corrigen factores (YES) o solo se realiza lectura de verificación (NO) | K25: Sí | L25: No | N25: P-ST-018-MAN OPER APMA 370 V2 | O25: Pendiente | Q25: =IF($F25<>"Numérico","",IF($P25="","Sin dato",IF(AND(OR(NOT(ISNUMBER($I25)),$P25>=$I25),OR(NOT(ISNUMBER($J25)),$P25<=$J25)),"Dentro de rango","Fuera de rango")))
A26: 4.1.1 | B26: 4. Línea de muestreo y acondicionamiento | C26: 4.1 Conectores neumáticos traseros | D26: Férula de Sample Inlet (Sleeve) | E26: Presencia del casquillo de teflón de sellado interno en la entrada de muestra | F26: Presente / Ausente | H26: Debe estar montada la férula para asegurar acople hermético libre de aire falso | K26: Sí | L26: Sí | M26: Sleeve SO2001-6 (3030021777) | N26: MT_P4B4CK60_APMA370_220511 | O26: Pendiente | Q26: =IF($F26<>"Numérico","",IF($P26="","Sin dato",IF(AND(OR(NOT(ISNUMBER($I26)),$P26>=$I26),OR(NOT(ISNUMBER($J26)),$P26<=$J26)),"Dentro de rango","Fuera de rango")))
A27: 4.1.2 | B27: 4. Línea de muestreo y acondicionamiento | C27: 4.1 Conectores neumáticos traseros | D27: Tuerca de Sample Inlet (Cap Nut) | E27: Presencia de la tuerca plástica de rosca fina en la entrada de muestra | F27: Presente / Ausente | H27: Debe estar presente y roscada firmemente la tuerca PVDF para sellar la tubería | K27: Sí | L27: Sí | M27: Cap Nut S020020-6PVDF (3030021779) | N27: MT_P4B4CK60_APMA370_220511 | O27: Pendiente | Q27: =IF($F27<>"Numérico","",IF($P27="","Sin dato",IF(AND(OR(NOT(ISNUMBER($I27)),$P27>=$I27),OR(NOT(ISNUMBER($J27)),$P27<=$J27)),"Dentro de rango","Fuera de rango")))
A28: 4.1.3 | B28: 4. Línea de muestreo y acondicionamiento | C28: 4.1 Conectores neumáticos traseros | D28: Férula de Exhaust (Sleeve) | E28: Presencia del casquillo de teflón de sellado interno en la salida de escape | F28: Presente / Ausente | H28: Debe estar montada la férula para evitar fugas de gases de escape hacia la cabina | K28: Sí | L28: Sí | M28: Sleeve SO2001-6 (3030021777) | N28: MT_P4B4CK60_APMA370_220511 | O28: Pendiente | Q28: =IF($F28<>"Numérico","",IF($P28="","Sin dato",IF(AND(OR(NOT(ISNUMBER($I28)),$P28>=$I28),OR(NOT(ISNUMBER($J28)),$P28<=$J28)),"Dentro de rango","Fuera de rango")))
A29: 4.1.4 | B29: 4. Línea de muestreo y acondicionamiento | C29: 4.1 Conectores neumáticos traseros | D29: Tuerca de Exhaust (Cap Nut) | E29: Presencia de la tuerca plástica de rosca fina en la salida de escape | F29: Presente / Ausente | H29: Debe estar presente y roscada firmemente la tuerca PVDF para canalizar el escape | K29: Sí | L29: Sí | M29: Cap Nut S020020-6PVDF (3030021779) | N29: MT_P4B4CK60_APMA370_220511 | O29: Pendiente | Q29: =IF($F29<>"Numérico","",IF($P29="","Sin dato",IF(AND(OR(NOT(ISNUMBER($I29)),$P29>=$I29),OR(NOT(ISNUMBER($J29)),$P29<=$J29)),"Dentro de rango","Fuera de rango")))
A30: 4.1.5 | B30: 4. Línea de muestreo y acondicionamiento | C30: 4.1 Conectores neumáticos traseros | D30: Panel Mount Union (SO21521-6 PVDF) | E30: Estado físico e integridad del racor plástico de montaje de panel | F30: OK / No OK | H30: Racor libre de fisuras en su rosca o fatiga de material por sobreajuste | K30: Sí | L30: Sí | M30: Panel mount union SO21521-6 (3030021548) | N30: MT_191TE0NC_APMA370_241226 | O30: Pendiente | Q30: =IF($F30<>"Numérico","",IF($P30="","Sin dato",IF(AND(OR(NOT(ISNUMBER($I30)),$P30>=$I30),OR(NOT(ISNUMBER($J30)),$P30<=$J30)),"Dentro de rango","Fuera de rango")))
A31: 4.2.1 | B31: 4. Línea de muestreo y acondicionamiento | C31: 4.2 Portafiltros frontal | D31: Colmatación del filtro de partículas PA-10L | E31: Nivel de colmatación, hollín, polvo o humedad en el filtro frontal de teflón de 54 mm | F31: OK / No OK | H31: Filtro de teflón blanco uniforme, sin partículas ni manchas oscuras que estrangulen el caudal | K31: Sí | L31: Sí | M31: Filter Element PA-10L (3200043947 / 3200043947-1PC) | N31: MT_56X1BA8G_APMA370_260109 | O31: Pendiente | Q31: =IF($F31<>"Numérico","",IF($P31="","Sin dato",IF(AND(OR(NOT(ISNUMBER($I31)),$P31>=$I31),OR(NOT(ISNUMBER($J31)),$P31<=$J31)),"Dentro de rango","Fuera de rango")))
A32: 4.2.2 | B32: 4. Línea de muestreo y acondicionamiento | C32: 4.2 Portafiltros frontal | D32: Empaque del filtro frontal (PA-10L) | E32: Flexibilidad y ausencia de grietas en la junta elástica plana del portafiltros | F32: OK / No OK | H32: Empaque blando, sin aplastamientos ni deformaciones permanentes que provoquen fugas | K32: Sí | L32: Sí | M32: Empaque de filtro (3200044273) | N32: P-ST-019-MAN MTTO APMA370 V2 | O32: Pendiente | Q32: =IF($F32<>"Numérico","",IF($P32="","Sin dato",IF(AND(OR(NOT(ISNUMBER($I32)),$P32>=$I32),OR(NOT(ISNUMBER($J32)),$P32<=$J32)),"Dentro de rango","Fuera de rango")))
A33: 4.2.3 | B33: 4. Línea de muestreo y acondicionamiento | C33: 4.2 Portafiltros frontal | D33: Junta tórica del portafiltros (O-Ring) | E33: Resequedad, microfisuras o deformación de la junta tórica de la tapa del filtro | F33: OK / No OK | H33: Junta de vitón elástica y ligeramente lubricada para garantizar hermetismo de la tapa | K33: Sí | L33: Sí | M33: O-ring (3200043785) | N33: P-ST-019-MAN MTTO APMA370 V2 | O33: Pendiente | Q33: =IF($F33<>"Numérico","",IF($P33="","Sin dato",IF(AND(OR(NOT(ISNUMBER($I33)),$P33>=$I33),OR(NOT(ISNUMBER($J33)),$P33<=$J33)),"Dentro de rango","Fuera de rango")))
A34: 4.3.1 | B34: 4. Línea de muestreo y acondicionamiento | C34: 4.3 Acondicionamiento de la muestra | D34: Trampa de humedad (Mist Catcher BAA) | E34: Acumulación de agua condensada y saturación del depurador de humedad | F34: OK / No OK | H34: El depósito debe estar libre de condensados y el relleno sin saturación física | K34: Sí | L34: Sí | M34: MC-1 (3200043946) | N34: MT_V440EL8D_APMA370_260430 | O34: Pendiente | Q34: =IF($F34<>"Numérico","",IF($P34="","Sin dato",IF(AND(OR(NOT(ISNUMBER($I34)),$P34>=$I34),OR(NOT(ISNUMBER($J34)),$P34<=$J34)),"Dentro de rango","Fuera de rango")))
A35: 4.3.2 | B35: 4. Línea de muestreo y acondicionamiento | C35: 4.3 Acondicionamiento de la muestra | D35: Líneas de teflón internas | E35: Estrangulamientos, dobleces agudos o acumulación de suciedad en mangueras neumáticas | F35: OK / No OK | H35: Tuberías de teflón translúcidas, firmes en sus racores y sin dobleces que restrinjan el flujo | K35: Sí | L35: Sí | N35: MT_U403C0JJ_APMA370_21033001 | O35: Pendiente | Q35: =IF($F35<>"Numérico","",IF($P35="","Sin dato",IF(AND(OR(NOT(ISNUMBER($I35)),$P35>=$I35),OR(NOT(ISNUMBER($J35)),$P35<=$J35)),"Dentro de rango","Fuera de rango")))
A36: 5.1.1 | B36: 5. Sistema neumático | C36: 5.1 Caudal y presión de muestra | D36: Caudal volumétrico de muestra (SAMPLE) | E36: Caudal de gas de muestra a través de la celda de medida en ANALOG INPUT | F36: Numérico | G36: L/min | H36: Caudal nominal de muestreo; fuera de 1,0 a 2,0 L/min se activa la alarma FLOW 1 | I36: 1 | J36: 2 | K36: Sí | L36: No | N36: P-ST-018-MAN OPER APMA 370 V2 | O36: Pendiente | Q36: =IF($F36<>"Numérico","",IF($P36="","Sin dato",IF(AND(OR(NOT(ISNUMBER($I36)),$P36>=$I36),OR(NOT(ISNUMBER($J36)),$P36<=$J36)),"Dentro de rango","Fuera de rango"))) -> Sin dato
A37: 5.1.2 | B37: 5. Sistema neumático | C37: 5.1 Caudal y presión de muestra | D37: Presión de succión de la bomba (PUMP) | E37: Presión de succión generada por la bomba de muestreo en la celda óptica | F37: Numérico | G37: kPa | H37: Lectura en ANALOG INPUT; un valor mayor o igual a 65 kPa activa la alarma PRE1 | I37: 0 | J37: 65 | K37: Sí | L37: No | N37: P-ST-018-MAN OPER APMA 370 V2 | O37: Pendiente | Q37: =IF($F37<>"Numérico","",IF($P37="","Sin dato",IF(AND(OR(NOT(ISNUMBER($I37)),$P37>=$I37),OR(NOT(ISNUMBER($J37)),$P37<=$J37)),"Dentro de rango","Fuera de rango"))) -> Sin dato
A38: 5.2.1 | B38: 5. Sistema neumático | C38: 5.2 Bomba de muestreo | D38: Vibración y ruido mecánico de la bomba (P-1-B) | E38: Estabilidad del motor y rodamientos de la bomba de muestreo (verificación auditiva y táctil) | F38: OK / No OK | H38: Operación continua y estable, sin golpes metálicos ni oscilación mecánica excesiva | K38: Sí | L38: Sí | M38: Pump unit doble cabezal P-1-B (3200043946) | N38: P-ST-019-MAN MTTO APMA370 V2 | O38: Pendiente | Q38: =IF($F38<>"Numérico","",IF($P38="","Sin dato",IF(AND(OR(NOT(ISNUMBER($I38)),$P38>=$I38),OR(NOT(ISNUMBER($J38)),$P38<=$J38)),"Dentro de rango","Fuera de rango")))
A39: 5.2.2 | B39: 5. Sistema neumático | C39: 5.2 Bomba de muestreo | D39: Desgaste de diafragmas de la bomba (P-1-D) | E39: Resequedad, porosidad o fisuras de los dos diafragmas de EPDM de la bomba | F39: OK / No OK | H39: Diafragmas de EPDM elásticos y sin fisuras, para evitar caídas de vacío y de caudal | K39: Sí | L39: Sí | M39: Diaphragm Assy GS/GD EPDM (3011026485 / 3200044033 / 3200602390) | N39: MT_2V0CY0DC_APMA370_250930 | O39: Pendiente | Q39: =IF($F39<>"Numérico","",IF($P39="","Sin dato",IF(AND(OR(NOT(ISNUMBER($I39)),$P39>=$I39),OR(NOT(ISNUMBER($J39)),$P39<=$J39)),"Dentro de rango","Fuera de rango")))
A40: 5.2.3 | B40: 5. Sistema neumático | C40: 5.2 Bomba de muestreo | D40: Limpieza de cabezales y válvulas de la bomba | E40: Acumulación de depósitos, residuos o polvo negro en las válvulas planas de teflón | F40: OK / No OK | H40: Cámaras del cabezal y charnelas de válvula limpias para garantizar sellado hermético | K40: Sí | L40: Sí | N40: MT_U403C0JJ_APMA370_21033001 | O40: Pendiente | Q40: =IF($F40<>"Numérico","",IF($P40="","Sin dato",IF(AND(OR(NOT(ISNUMBER($I40)),$P40>=$I40),OR(NOT(ISNUMBER($J40)),$P40<=$J40)),"Dentro de rango","Fuera de rango")))
A41: 5.3.1 | B41: 5. Sistema neumático | C41: 5.3 Válvulas y estanqueidad | D41: Conmutación de la válvula de modulación (SV-2) | E41: Conmutación cíclica entre gas de muestra y aire de referencia | F41: OK / No OK | H41: Debe conmutar neumáticamente de forma cíclica a una frecuencia constante de 1 Hz | K41: Sí | L41: Sí | M41: Solenoid Valve sample/Ref.-gas SV-2 (3200043946) | N41: P-ST-019-MAN MTTO APMA370 V2 | O41: Pendiente | Q41: =IF($F41<>"Numérico","",IF($P41="","Sin dato",IF(AND(OR(NOT(ISNUMBER($I41)),$P41>=$I41),OR(NOT(ISNUMBER($J41)),$P41<=$J41)),"Dentro de rango","Fuera de rango")))
A42: 5.3.2 | B42: 5. Sistema neumático | C42: 5.3 Válvulas y estanqueidad | D42: Prueba de estanqueidad (Leak Test) | E42: Mantenimiento del vacío sellando el puerto de entrada para detectar fugas | F42: OK / No OK | H42: El circuito neumático debe mantener el vacío estable sin fluctuaciones tras aislar la succión | K42: Sí | L42: Sí | N42: GZ0000117746B SM E APXX-370 (Service Manual) | O42: Pendiente | Q42: =IF($F42<>"Numérico","",IF($P42="","Sin dato",IF(AND(OR(NOT(ISNUMBER($I42)),$P42>=$I42),OR(NOT(ISNUMBER($J42)),$P42<=$J42)),"Dentro de rango","Fuera de rango")))
A43: 6.1.1 | B43: 6. Banco de medición y óptica | C43: 6.1 Señales del banco NDIR (modulación de flujo cruzado) | D43: Tensión de señal principal (SIGNAL MAIN) | E43: Tensión analógica del canal de medición de CO en ANALOG INPUT | F43: Numérico | G43: mV | H43: Representa la energía infrarroja del detector para el monóxido de carbono | I43: 0 | J43: 3000 | K43: Sí | L43: No | N43: P-ST-018-MAN OPER APMA 370 V2 | O43: Pendiente | Q43: =IF($F43<>"Numérico","",IF($P43="","Sin dato",IF(AND(OR(NOT(ISNUMBER($I43)),$P43>=$I43),OR(NOT(ISNUMBER($J43)),$P43<=$J43)),"Dentro de rango","Fuera de rango"))) -> Sin dato
A44: 6.1.2 | B44: 6. Banco de medición y óptica | C44: 6.1 Señales del banco NDIR (modulación de flujo cruzado) | D44: Tensión de señal de compensación (SIGNAL COMP) | E44: Tensión analógica del canal de referencia para corregir interferentes | F44: Numérico | G44: mV | H44: Empleada por el firmware para corregir el efecto de otros componentes de la muestra | I44: 0 | J44: 3000 | K44: Sí | L44: No | N44: P-ST-018-MAN OPER APMA 370 V2 | O44: Pendiente | Q44: =IF($F44<>"Numérico","",IF($P44="","Sin dato",IF(AND(OR(NOT(ISNUMBER($I44)),$P44>=$I44),OR(NOT(ISNUMBER($J44)),$P44<=$J44)),"Dentro de rango","Fuera de rango"))) -> Sin dato
A45: 6.2.1 | B45: 6. Banco de medición y óptica | C45: 6.2 Fuente infrarroja y celda óptica | D45: Lámpara infrarroja (IR Lamp) | E45: Desgaste térmico, estabilidad del haz e integridad del filamento de la fuente IR | F45: OK / No OK | H45: Filamento activo de forma continua y ampolla libre de manchas severas (indican desgaste) | K45: Sí | L45: Sí | M45: Lámpara IR (AP-XEP-02) | N45: MT_2V0CY0DC_APMA370_250930 / Service Manual | O45: Pendiente | Q45: =IF($F45<>"Numérico","",IF($P45="","Sin dato",IF(AND(OR(NOT(ISNUMBER($I45)),$P45>=$I45),OR(NOT(ISNUMBER($J45)),$P45<=$J45)),"Dentro de rango","Fuera de rango")))
A46: 6.2.2 | B46: 6. Banco de medición y óptica | C46: 6.2 Fuente infrarroja y celda óptica | D46: Limpieza de ventanas ópticas y lentes de la celda | E46: Suciedad, hollín o humedad en las caras translúcidas del tubo de absorción óptica | F46: OK / No OK | H46: Ventanas limpias y translúcidas para garantizar el paso libre del haz infrarrojo | K46: Sí | L46: Sí | N46: MT_2V0CY0DC_APMA370_250930 | O46: Pendiente | Q46: =IF($F46<>"Numérico","",IF($P46="","Sin dato",IF(AND(OR(NOT(ISNUMBER($I46)),$P46>=$I46),OR(NOT(ISNUMBER($J46)),$P46<=$J46)),"Dentro de rango","Fuera de rango")))
A47: 6.3.1 | B47: 6. Banco de medición y óptica | C47: 6.3 Suspensión mecánica del banco óptico | D47: Resortes de amortiguación del banco óptico | E47: Presencia y tensión de los 3 resortes que suspenden la celda de medida | F47: OK / No OK | H47: Los 3 resortes deben estar enganchados y libres de estiramientos o deformaciones | K47: Sí | L47: Sí | M47: Spring L=64 K=0.59 (3012161550) | N47: MT_191TE0NC_APMA370_241226 / MT_U7D80D0J_APMA370_260116 | O47: Pendiente | Q47: =IF($F47<>"Numérico","",IF($P47="","Sin dato",IF(AND(OR(NOT(ISNUMBER($I47)),$P47>=$I47),OR(NOT(ISNUMBER($J47)),$P47<=$J47)),"Dentro de rango","Fuera de rango")))
A48: 6.3.2 | B48: 6. Banco de medición y óptica | C48: 6.3 Suspensión mecánica del banco óptico | D48: Topes amortiguadores (Stoppers) | E48: Estado físico y flexibilidad de los soportes elásticos que limitan la oscilación de la celda | F48: OK / No OK | H48: Stoppers de goma flexibles en su zócalo, para absorber la vibración inducida por la bomba | K48: Sí | L48: Sí | M48: Stopper Spring for AIA-1X0 (3012165197) | N48: MT_191TE0NC_APMA370_241226 / MT_U7D80D0J_APMA370_260116 | O48: Pendiente | Q48: =IF($F48<>"Numérico","",IF($P48="","Sin dato",IF(AND(OR(NOT(ISNUMBER($I48)),$P48>=$I48),OR(NOT(ISNUMBER($J48)),$P48<=$J48)),"Dentro de rango","Fuera de rango")))
A49: 6.3.3 | B49: 6. Banco de medición y óptica | C49: 6.3 Suspensión mecánica del banco óptico | D49: Tornillos de tope (Screw Stopper) | E49: Presencia e integridad de los tornillos M5x20 que limitan el desplazamiento elástico | F49: Presente / Ausente | H49: Deben estar presentes y roscados firmemente los tornillos M5x20 en los anclajes del chasis | K49: Sí | L49: Sí | M49: Screw Stopper M5X20 for Spring (3012155051) | N49: MT_U6RF8092_APMA-370_240311 / MT_U7D80D0J_APMA370_260116 | O49: Pendiente | Q49: =IF($F49<>"Numérico","",IF($P49="","Sin dato",IF(AND(OR(NOT(ISNUMBER($I49)),$P49>=$I49),OR(NOT(ISNUMBER($J49)),$P49<=$J49)),"Dentro de rango","Fuera de rango")))
A50: 6.3.4 | B50: 6. Banco de medición y óptica | C50: 6.3 Suspensión mecánica del banco óptico | D50: Tuercas hexagonales de fijación | E50: Ajuste y torque de las tuercas M5 en los tornillos de los zócalos amortiguadores | F50: OK / No OK | H50: Tuercas M5 ajustadas firmemente para evitar desprendimiento del bloque óptico | K50: Sí | L50: Sí | M50: Hexagon Nut M05 S-ZN3 ROHS (3011000121) | N50: MT_U6RF8092_APMA-370_240311 / MT_U7D80D0J_APMA370_260116 | O50: Pendiente | Q50: =IF($F50<>"Numérico","",IF($P50="","Sin dato",IF(AND(OR(NOT(ISNUMBER($I50)),$P50>=$I50),OR(NOT(ISNUMBER($J50)),$P50<=$J50)),"Dentro de rango","Fuera de rango")))
A51: 6.4.1 | B51: 6. Banco de medición y óptica | C51: 6.4 Purificación de la línea de referencia | D51: Eficiencia del relleno catalítico de CO (CAT-1) | E51: Estado y capacidad de conversión del óxido metálico del catalizador interno de CO | F51: OK / No OK | H51: El catalizador debe asegurar la oxidación del CO en la línea de referencia y evitar derivas del cero | K51: Sí | L51: Sí | M51: Catalyzer Filling CO CAT-1 (3200043946) | N51: P-ST-019-MAN MTTO APMA370 V2 | O51: Pendiente | Q51: =IF($F51<>"Numérico","",IF($P51="","Sin dato",IF(AND(OR(NOT(ISNUMBER($I51)),$P51>=$I51),OR(NOT(ISNUMBER($J51)),$P51<=$J51)),"Dentro de rango","Fuera de rango")))
A52: 6.4.2 | B52: 6. Banco de medición y óptica | C52: 6.4 Purificación de la línea de referencia | D52: Filtro coalescente interno (DFU9900-05-BK) | E52: Nivel de colmatación o presencia de aceite en el filtro de microfibra Balston de referencia | F52: OK / No OK | H52: Elemento de microfibra limpio, para proteger el catalizador de contaminantes finos | K52: Sí | L52: Sí | M52: Inline Filter Element DFU9900-05-BK | N52: P-ST-019-MAN MTTO APMA370 V2 | O52: Pendiente | Q52: =IF($F52<>"Numérico","",IF($P52="","Sin dato",IF(AND(OR(NOT(ISNUMBER($I52)),$P52>=$I52),OR(NOT(ISNUMBER($J52)),$P52<=$J52)),"Dentro de rango","Fuera de rango")))
A53: 7.1.1 | B53: 7. Electrónica y control | C53: 7.1 Tarjetas electrónicas | D53: Estado de la tarjeta principal CPU (AP-CPU-02) | E53: Limpieza, sujeción y ausencia de corrosión en integrados y zócalos de la placa CPU | F53: OK / No OK | H53: Tarjeta lógica limpia, libre de polvo conductivo o rastros de sobrecalentamiento | K53: Sí | L53: Sí | M53: PRINTED BOARD INST. AP-CPU-02 (3200629662) | N53: 1 - LCD design change AP EN / MT_85HHP0N0_APMA370_20022603 | O53: Pendiente | Q53: =IF($F53<>"Numérico","",IF($P53="","Sin dato",IF(AND(OR(NOT(ISNUMBER($I53)),$P53>=$I53),OR(NOT(ISNUMBER($J53)),$P53<=$J53)),"Dentro de rango","Fuera de rango")))
A54: 7.1.2 | B54: 7. Electrónica y control | C54: 7.1 Tarjetas electrónicas | D54: Configuración del DIP switch SW2 en AP-ADC-05 | E54: Configuración física del DIP switch SW2 de modelo en la tarjeta de conversión analógica | F54: OK / No OK | H54: Para el modelo: BIT0 y BIT1 en ON, BIT2 y BIT3 en OFF | K54: Sí | L54: Sí | M54: AP-ADC-05 | N54: GZ0000117746B SM E APXX-370 (Service Manual) | O54: Pendiente | Q54: =IF($F54<>"Numérico","",IF($P54="","Sin dato",IF(AND(OR(NOT(ISNUMBER($I54)),$P54>=$I54),OR(NOT(ISNUMBER($J54)),$P54<=$J54)),"Dentro de rango","Fuera de rango")))
A55: 7.1.3 | B55: 7. Electrónica y control | C55: 7.1 Tarjetas electrónicas | D55: Indicadores LED de la tarjeta ADC (+24V, +5V) | E55: Iluminación de los LED indicadores de fuentes secundarias en la tarjeta ADC-05 | F55: OK / No OK | H55: Los LED de +24 V y +5 V deben iluminarse en verde fijo | K55: Sí | L55: Sí | M55: PCB AP-ADC-05 | N55: GZ0000117746B SM E APXX-370 (Service Manual) | O55: Pendiente | Q55: =IF($F55<>"Numérico","",IF($P55="","Sin dato",IF(AND(OR(NOT(ISNUMBER($I55)),$P55>=$I55),OR(NOT(ISNUMBER($J55)),$P55<=$J55)),"Dentro de rango","Fuera de rango")))
A56: 7.1.4 | B56: 7. Electrónica y control | C56: 7.1 Tarjetas electrónicas | D56: Estado físico de la tarjeta de relés (AP-RPL-02A) | E56: Sobrecalentamientos o quemaduras en relés y transistores de control de la placa RPL | F56: OK / No OK | H56: Componentes sin daños por sobrecarga; soldaduras intactas sin marcas de cortocircuito | K56: Sí | L56: Sí | M56: PCB AP-RPL-02 / AP-RPL-02A (H102518000) | N56: MT_191TE0NC_APMA370_241226 / Service Manual | O56: Pendiente | Q56: =IF($F56<>"Numérico","",IF($P56="","Sin dato",IF(AND(OR(NOT(ISNUMBER($I56)),$P56>=$I56),OR(NOT(ISNUMBER($J56)),$P56<=$J56)),"Dentro de rango","Fuera de rango")))
A57: 7.1.5 | B57: 7. Electrónica y control | C57: 7.1 Tarjetas electrónicas | D57: LED de comunicación ST0 y ST1 en tarjeta RPL | E57: Frecuencia de parpadeo de los indicadores LED de diagnóstico de la tarjeta de relés | F57: OK / No OK | H57: ST1 debe parpadear (H8 activo) y ST0 titilar rápido (I2C activo); luz fija o apagada indica falla | K57: Sí | L57: Sí | M57: PCB AP-RPL-02 / AP-RPL-02A | N57: GZ0000117746B SM E APXX-370 (Service Manual) | O57: Pendiente | Q57: =IF($F57<>"Numérico","",IF($P57="","Sin dato",IF(AND(OR(NOT(ISNUMBER($I57)),$P57>=$I57),OR(NOT(ISNUMBER($J57)),$P57<=$J57)),"Dentro de rango","Fuera de rango")))
A58: 7.1.6 | B58: 7. Electrónica y control | C58: 7.1 Tarjetas electrónicas | D58: LED de tensión +5 V en tarjeta RPL | E58: LED indicador de alimentación interna de 5 V en la tarjeta de relés periféricos | F58: OK / No OK | H58: Debe permanecer encendido continuo en verde, indicando que el regulador lógico local opera | K58: Sí | L58: Sí | M58: PCB AP-RPL-02 / AP-RPL-02A | N58: GZ0000117746B SM E APXX-370 (Service Manual) | O58: Pendiente | Q58: =IF($F58<>"Numérico","",IF($P58="","Sin dato",IF(AND(OR(NOT(ISNUMBER($I58)),$P58>=$I58),OR(NOT(ISNUMBER($J58)),$P58<=$J58)),"Dentro de rango","Fuera de rango")))
A59: 7.1.7 | B59: 7. Electrónica y control | C59: 7.1 Tarjetas electrónicas | D59: Switch de selección de alarma general (SW1/SW2 en RPL) | E59: Ajuste de interruptores de asociación de alarma que definen el contacto general | F59: OK / No OK | H59: Posiciones de los microinterruptores en concordancia con el esquema de alarmas de la estación | K59: Sí | L59: Sí | M59: PCB AP-RPL-02 / AP-RPL-02A | N59: GZ0000117746B SM E APXX-370 (Service Manual) | O59: Pendiente | Q59: =IF($F59<>"Numérico","",IF($P59="","Sin dato",IF(AND(OR(NOT(ISNUMBER($I59)),$P59>=$I59),OR(NOT(ISNUMBER($J59)),$P59<=$J59)),"Dentro de rango","Fuera de rango")))
A60: 7.2.1 | B60: 7. Electrónica y control | C60: 7.2 Respaldo de reloj y memoria | D60: Batería de litio del reloj de tiempo real (BATT1 / CR2032) | E60: Voltaje DC de la pila de litio de respaldo de hora y secuencia de autocalibración | F60: Numérico | G60: V | H60: Un voltaje inferior a 2,5 V activa la alarma BATT | I60: 2.5 | J60: 3.3 | K60: Sí | L60: No | M60: Li battery CR2032 (3030052489) | N60: P-ST-019-MAN MTTO APMA370 V2 | O60: Pendiente | Q60: =IF($F60<>"Numérico","",IF($P60="","Sin dato",IF(AND(OR(NOT(ISNUMBER($I60)),$P60>=$I60),OR(NOT(ISNUMBER($J60)),$P60<=$J60)),"Dentro de rango","Fuera de rango"))) -> Sin dato
A61: 7.3.1 | B61: 7. Electrónica y control | C61: 7.3 Display y cableado interno | D61: Cintas flex de la pantalla táctil LCD (Tape Wire) | E61: Arrugas, microfisuras o sulfatación en las terminales de los dos buses flex planos | F61: OK / No OK | H61: Cables flexibles intactos y firmemente enchufados a la placa CPU, para evitar fallos del panel | K61: Sí | L61: Sí | M61: Tape Wire (3010040355) / Tape Wire for LCD (3200257448) | N61: AP-370 LCD replacement / MT_191TE0NC_APMA370_241226 | O61: Pendiente | Q61: =IF($F61<>"Numérico","",IF($P61="","Sin dato",IF(AND(OR(NOT(ISNUMBER($I61)),$P61>=$I61),OR(NOT(ISNUMBER($J61)),$P61<=$J61)),"Dentro de rango","Fuera de rango")))
A62: 7.3.2 | B62: 7. Electrónica y control | C62: 7.3 Display y cableado interno | D62: Respuesta táctil de la pantalla (Touch Panel) | E62: Sensibilidad del panel resistivo al presionar y seleccionar opciones del display | F62: OK / No OK | H62: Desplazamiento ágil y preciso entre menús, sin derivas táctiles ni zonas inoperantes | K62: Sí | L62: Sí | M62: Touch Panel TP-AP370 | N62: MT_1JS71VM3_APMA370_21061101 / MT_85HHP0N0_APMA370_220822 | O62: Pendiente | Q62: =IF($F62<>"Numérico","",IF($P62="","Sin dato",IF(AND(OR(NOT(ISNUMBER($I62)),$P62>=$I62),OR(NOT(ISNUMBER($J62)),$P62<=$J62)),"Dentro de rango","Fuera de rango")))
A63: 7.4.1 | B63: 7. Electrónica y control | C63: 7.4 Alimentación eléctrica | D63: Tensiones secundarias de la fuente de poder principal | E63: Estabilidad de voltajes e integridad física de condensadores en la fuente principal | F63: OK / No OK | H63: Condensadores sin abombamientos y voltajes secundarios libres de rizado eléctrico | K63: Sí | L63: Sí | M63: Power Supply Assy (3200637753) | N63: MT_191TE0NC_APMA370_241226 | O63: Pendiente | Q63: =IF($F63<>"Numérico","",IF($P63="","Sin dato",IF(AND(OR(NOT(ISNUMBER($I63)),$P63>=$I63),OR(NOT(ISNUMBER($J63)),$P63<=$J63)),"Dentro de rango","Fuera de rango")))
A64: 7.4.2 | B64: 7. Electrónica y control | C64: 7.4 Alimentación eléctrica | D64: Transformador de la bomba de muestreo | E64: Tensión AC de salida en el secundario del transformador de aislamiento de la bomba | F64: Numérico | G64: V | H64: Transformador de aislamiento de 42 VA; debe suministrar tensión estable a la bobina del motor | I64: 100 | J64: 120 | K64: Sí | L64: No | M64: Power Transformer APXX-360/370 PUMP 42VA (3200488656) | N64: MT_191TE0NC_APMA370_241226 | O64: Pendiente | Q64: =IF($F64<>"Numérico","",IF($P64="","Sin dato",IF(AND(OR(NOT(ISNUMBER($I64)),$P64>=$I64),OR(NOT(ISNUMBER($J64)),$P64<=$J64)),"Dentro de rango","Fuera de rango"))) -> Sin dato
A65: 7.5.1 | B65: 7. Electrónica y control | C65: 7.5 Comunicaciones | D65: Conector del cable serial RS-232C | E65: Soldaduras, continuidad y asignación de pines del conector trasero DB9 de datos | F65: OK / No OK | H65: Pines 2 y 3 cruzados, pin 5 a tierra y pines 7-8 puenteados para habilitar el enlace serial | K65: Sí | L65: Sí | N65: I.X.X.X-X Instructivo Descarga de Datos Horiba AP | O65: Pendiente | Q65: =IF($F65<>"Numérico","",IF($P65="","Sin dato",IF(AND(OR(NOT(ISNUMBER($I65)),$P65>=$I65),OR(NOT(ISNUMBER($J65)),$P65<=$J65)),"Dentro de rango","Fuera de rango")))
A66: 7.5.2 | B66: 7. Electrónica y control | C66: 7.5 Comunicaciones | D66: Tarjeta serial opcional (AP-SIO-04) | E66: Presencia e integración de la placa serial dedicada en el conector CN2 | F66: Presente / Ausente | H66: Tarjeta SIO acoplada firmemente en el conector CN2 de la CPU si se implementa descarga remota | K66: Sí | L66: Sí | M66: Tarjeta SIO AP-SIO-04 | N66: Procedimiento Integración Tarjeta RS232 | O66: Pendiente | Q66: =IF($F66<>"Numérico","",IF($P66="","Sin dato",IF(AND(OR(NOT(ISNUMBER($I66)),$P66>=$I66),OR(NOT(ISNUMBER($J66)),$P66<=$J66)),"Dentro de rango","Fuera de rango")))
A67: 8.1.1 | B67: 8. Filtros y consumibles | C67: 8.1 Horómetros de consumibles | D67: Horas acumuladas del filtro de partículas PA-10L | E67: Horas de uso acumuladas del filtro frontal en la pantalla HOUR METER | F67: Numérico | G67: horas | H67: Cambio preventivo recomendado cada 2 semanas de uso (336 h) | I67: 0 | J67: 336 | K67: Sí | L67: No | M67: Elemento PA-10L (3200043947) | N67: P-ST-019-MAN MTTO APMA370 V2 | O67: Pendiente | Q67: =IF($F67<>"Numérico","",IF($P67="","Sin dato",IF(AND(OR(NOT(ISNUMBER($I67)),$P67>=$I67),OR(NOT(ISNUMBER($J67)),$P67<=$J67)),"Dentro de rango","Fuera de rango"))) -> Sin dato
A68: 8.1.2 | B68: 8. Filtros y consumibles | C68: 8.1 Horómetros de consumibles | D68: Horas acumuladas de diafragmas de la bomba (P-1-D) | E68: Horas acumuladas de operación de los diafragmas en la pantalla HOUR METER | F68: Numérico | G68: horas | H68: Contador para planificar el reemplazo anual de las membranas elásticas de la bomba | I68: 0 | J68: 8760 | K68: Sí | L68: No | M68: Diafragma P-1-D (3200044033 / 3011026485) | N68: P-ST-019-MAN MTTO APMA370 V2 | O68: Pendiente | Q68: =IF($F68<>"Numérico","",IF($P68="","Sin dato",IF(AND(OR(NOT(ISNUMBER($I68)),$P68>=$I68),OR(NOT(ISNUMBER($J68)),$P68<=$J68)),"Dentro de rango","Fuera de rango"))) -> Sin dato
A69: 8.1.3 | B69: 8. Filtros y consumibles | C69: 8.1 Horómetros de consumibles | D69: Horas acumuladas del catalizador de CO (CAT-1) | E69: Horas de operación acumuladas del catalizador oxidante de CO en HOUR METER | F69: Numérico | G69: horas | H69: Contador para programar el reemplazo del relleno del catalizador cada 2 años | I69: 0 | J69: 17520 | K69: Sí | L69: No | M69: Relleno CAT-1 (3200043946) | N69: P-ST-019-MAN MTTO APMA370 V2 | O69: Pendiente | Q69: =IF($F69<>"Numérico","",IF($P69="","Sin dato",IF(AND(OR(NOT(ISNUMBER($I69)),$P69>=$I69),OR(NOT(ISNUMBER($J69)),$P69<=$J69)),"Dentro de rango","Fuera de rango"))) -> Sin dato
A70: 8.1.4 | B70: 8. Filtros y consumibles | C70: 8.1 Horómetros de consumibles | D70: Horas acumuladas de la trampa Mist Catcher (MC-1) | E70: Horas de uso acumuladas de la trampa secadora de humedad en HOUR METER | F70: Numérico | G70: horas | H70: Contador para planificar la sustitución anual de la trampa Mist Catcher MC-1 | I70: 0 | J70: 8760 | K70: Sí | L70: No | M70: Mist Catcher BAA MC-1 (3200043946) | N70: P-ST-019-MAN MTTO APMA370 V2 | O70: Pendiente | Q70: =IF($F70<>"Numérico","",IF($P70="","Sin dato",IF(AND(OR(NOT(ISNUMBER($I70)),$P70>=$I70),OR(NOT(ISNUMBER($J70)),$P70<=$J70)),"Dentro de rango","Fuera de rango"))) -> Sin dato
A71: 8.1.5 | B71: 8. Filtros y consumibles | C71: 8.1 Horómetros de consumibles | D71: Horas acumuladas de la bomba completa (P-1-B) | E71: Horas de funcionamiento de la unidad de bomba electromecánica completa en HOUR METER | F71: Numérico | G71: horas | H71: Contador para programar el reemplazo o reconstrucción del motor de bomba cada 2 años | I71: 0 | J71: 17520 | K71: Sí | L71: No | M71: Bomba P-1-B (3200043946) | N71: P-ST-019-MAN MTTO APMA370 V2 | O71: Pendiente | Q71: =IF($F71<>"Numérico","",IF($P71="","Sin dato",IF(AND(OR(NOT(ISNUMBER($I71)),$P71>=$I71),OR(NOT(ISNUMBER($J71)),$P71<=$J71)),"Dentro de rango","Fuera de rango"))) -> Sin dato
A72: 8.2.1 | B72: 8. Filtros y consumibles | C72: 8.2 Filtros de chasis | D72: Obstrucción de esponjas disipadoras (Filter Sponge) | E72: Acumulación de polvo e integridad física de los filtros de esponja superiores del chasis | F72: OK / No OK | H72: Esponjas de poliuretano limpias y permeables al aire, para mantener la refrigeración interna | K72: Sí | L72: Sí | M72: Filter Sponge (3012299939) | N72: MT_191TE0NC_APMA370_241226 / MT_U7D80D0J_APMA370_260116 | O72: Pendiente | Q72: =IF($F72<>"Numérico","",IF($P72="","Sin dato",IF(AND(OR(NOT(ISNUMBER($I72)),$P72>=$I72),OR(NOT(ISNUMBER($J72)),$P72<=$J72)),"Dentro de rango","Fuera de rango")))
A73: 9.1.1 | B73: 9. Sensores auxiliares | C73: 9.1 Temperatura | D73: Temperatura de la celda de medida (CELL) | E73: Temperatura del compartimiento calentado de la celda óptica en ANALOG INPUT | F73: Numérico | G73: °C | H73: Valor estándar: temperatura ambiente + 5 a 15 °C (rango típico 30 a 55 °C) | I73: 30 | J73: 55 | K73: Sí | L73: No | N73: P-ST-018-MAN OPER APMA 370 V2 | O73: Pendiente | Q73: =IF($F73<>"Numérico","",IF($P73="","Sin dato",IF(AND(OR(NOT(ISNUMBER($I73)),$P73>=$I73),OR(NOT(ISNUMBER($J73)),$P73<=$J73)),"Dentro de rango","Fuera de rango"))) -> Sin dato
A74: 9.1.2 | B74: 9. Sensores auxiliares | C74: 9.1 Temperatura | D74: Sensor de temperatura del catalizador de CO (CAT) | E74: Lazo térmico de temperatura del catalizador de CO para oxidación de la referencia | F74: OK / No OK | H74: Temperatura del horno catalítico estable; su descenso drástico dispara la alarma CAT | K74: Sí | L74: Sí | N74: P-ST-018-MAN OPER APMA 370 V2 | O74: Pendiente | Q74: =IF($F74<>"Numérico","",IF($P74="","Sin dato",IF(AND(OR(NOT(ISNUMBER($I74)),$P74>=$I74),OR(NOT(ISNUMBER($J74)),$P74<=$J74)),"Dentro de rango","Fuera de rango")))
A75: 9.2.1 | B75: 9. Sensores auxiliares | C75: 9.2 Presión | D75: Presión barométrica ambiental (AMBIENT) | E75: Presión barométrica registrada por el transductor piezoeléctrico en ANALOG INPUT | F75: Numérico | G75: kPa | H75: Presión ambiental del sitio; usada para corregir la densidad del gas según la altitud | I75: 50 | J75: 115 | K75: Sí | L75: No | N75: P-ST-018-MAN OPER APMA 370 V2 / Procedimiento Ajuste de Presión Ambiente | O75: Pendiente | Q75: =IF($F75<>"Numérico","",IF($P75="","Sin dato",IF(AND(OR(NOT(ISNUMBER($I75)),$P75>=$I75),OR(NOT(ISNUMBER($J75)),$P75<=$J75)),"Dentro de rango","Fuera de rango"))) -> Sin dato
A76: 9.2.2 | B76: 9. Sensores auxiliares | C76: 9.2 Presión | D76: Desviación de los sensores de presión | E76: Desvío entre las lecturas internas de presión y los barómetros de referencia | F76: Numérico | G76: % | H76: La desviación entre el patrón externo y el valor en pantalla debe ser menor al 2 % | I76: 0 | J76: 2 | K76: Sí | L76: No | N76: P-ST-018-MAN OPER APMA 370 V2 / Service Manual | O76: Pendiente | Q76: =IF($F76<>"Numérico","",IF($P76="","Sin dato",IF(AND(OR(NOT(ISNUMBER($I76)),$P76>=$I76),OR(NOT(ISNUMBER($J76)),$P76<=$J76)),"Dentro de rango","Fuera de rango"))) -> Sin dato
A77: 9.3.1 | B77: 9. Sensores auxiliares | C77: 9.3 Tensiones internas | D77: Tensión interna del riel DC 24 V | E77: Tensión del bus DC secundario de alimentación de periféricos en ANALOG INPUT | F77: Numérico | G77: V | H77: Debe estar dentro de la tolerancia de 24 V ± 0,5 V | I77: 23.5 | J77: 24.5 | K77: Sí | L77: No | N77: P-ST-018-MAN OPER APMA 370 V2 / Service Manual | O77: Pendiente | Q77: =IF($F77<>"Numérico","",IF($P77="","Sin dato",IF(AND(OR(NOT(ISNUMBER($I77)),$P77>=$I77),OR(NOT(ISNUMBER($J77)),$P77<=$J77)),"Dentro de rango","Fuera de rango"))) -> Sin dato
A78: 9.3.2 | B78: 9. Sensores auxiliares | C78: 9.3 Tensiones internas | D78: Tensión interna del riel DC 5 V | E78: Tensión de alimentación regulada del microcontrolador lógico en ANALOG INPUT | F78: Numérico | G78: V | H78: Debe estar dentro de la tolerancia de 5 V ± 0,5 V | I78: 4.5 | J78: 5.5 | K78: Sí | L78: No | N78: P-ST-018-MAN OPER APMA 370 V2 / Service Manual | O78: Pendiente | Q78: =IF($F78<>"Numérico","",IF($P78="","Sin dato",IF(AND(OR(NOT(ISNUMBER($I78)),$P78>=$I78),OR(NOT(ISNUMBER($J78)),$P78<=$J78)),"Dentro de rango","Fuera de rango"))) -> Sin dato
A79: 10.1.1 | B79: 10. Gabinete, montaje e instalación | C79: 10.1 Chasis y puerta frontal | D79: Ajuste y fijación de la puerta frontal | E79: Alineación e integridad física de la puerta del panel frontal del gabinete | F79: OK / No OK | H79: Puerta encajada firmemente, sin desniveles que impidan presionar adecuadamente la pantalla | K79: Sí | L79: Sí | N79: MT_56X1BA8G_APMA370_260109 / MT_2V0CY0DC_APMA370_20060501 | O79: Pendiente | Q79: =IF($F79<>"Numérico","",IF($P79="","Sin dato",IF(AND(OR(NOT(ISNUMBER($I79)),$P79>=$I79),OR(NOT(ISNUMBER($J79)),$P79<=$J79)),"Dentro de rango","Fuera de rango")))
A80: 10.1.2 | B80: 10. Gabinete, montaje e instalación | C80: 10.1 Chasis y puerta frontal | D80: Casquillos de bisagra de la puerta frontal | E80: Presencia de los casquillos en los puntos de pivote del panel frontal basculante | F80: Presente / Ausente | H80: Casquillos plásticos de nylon en buen estado, para alinear simétricamente la apertura | K80: Sí | L80: Sí | M80: Hinge Bush (3012304035) | N80: MT_P4B4CK60_APMA370_220511 | O80: Pendiente | Q80: =IF($F80<>"Numérico","",IF($P80="","Sin dato",IF(AND(OR(NOT(ISNUMBER($I80)),$P80>=$I80),OR(NOT(ISNUMBER($J80)),$P80<=$J80)),"Dentro de rango","Fuera de rango")))
A81: 10.1.3 | B81: 10. Gabinete, montaje e instalación | C81: 10.1 Chasis y puerta frontal | D81: Eje de bisagra de la puerta frontal | E81: Presencia de los pasadores cilíndricos metálicos de rotación de la bisagra | F81: Presente / Ausente | H81: Pasadores metálicos introducidos a tope, para articular con seguridad la compuerta | K81: Sí | L81: Sí | M81: Hinge Shaft (3012297312) | N81: MT_P4B4CK60_APMA370_220511 | O81: Pendiente | Q81: =IF($F81<>"Numérico","",IF($P81="","Sin dato",IF(AND(OR(NOT(ISNUMBER($I81)),$P81>=$I81),OR(NOT(ISNUMBER($J81)),$P81<=$J81)),"Dentro de rango","Fuera de rango")))
A82: 10.2.1 | B82: 10. Gabinete, montaje e instalación | C82: 10.2 Ventilación | D82: Extractor de calor (Cooling Fan) posterior | E82: Operación del ventilador posterior de extracción activa de aire caliente | F82: OK / No OK | H82: Ventilador girando de forma estable, sin polvo extremo ni ruidos de rodamientos desgastados | K82: Sí | L82: Sí | M82: Fan (3200043946) | N82: MT_191TE0NC_APMA370_241226 | O82: Pendiente | Q82: =IF($F82<>"Numérico","",IF($P82="","Sin dato",IF(AND(OR(NOT(ISNUMBER($I82)),$P82>=$I82),OR(NOT(ISNUMBER($J82)),$P82<=$J82)),"Dentro de rango","Fuera de rango")))
A83: 10.3.1 | B83: 10. Gabinete, montaje e instalación | C83: 10.3 Montaje en rack | D83: Rieles o bandeja de base en rack de 19 pulgadas | E83: Presencia de guías de soporte o bandeja base para montaje del analizador en gabinete | F83: OK / No OK | H83: Base metálica firme para sostener el analizador (16 kg) y evitar la flexión frontal | K83: Sí | L83: Sí | N83: P-ST-018-MAN OPER APMA 370 V2 | O83: Pendiente | Q83: =IF($F83<>"Numérico","",IF($P83="","Sin dato",IF(AND(OR(NOT(ISNUMBER($I83)),$P83>=$I83),OR(NOT(ISNUMBER($J83)),$P83<=$J83)),"Dentro de rango","Fuera de rango")))
A84: 10.3.2 | B84: 10. Gabinete, montaje e instalación | C84: 10.3 Montaje en rack | D84: Holgura con el fondo del rack | E84: Separación libre entre el chasis posterior y la cubierta o puerta del rack | F84: Numérico | G84: mm | H84: Mínimo 150 mm en la parte trasera para mangueras neumáticas y ventilación. Límite superior PENDIENTE DE VALIDAR | I84: 150 | K84: Sí | L84: No | N84: P-ST-018-MAN OPER APMA 370 V2 | O84: Pendiente | Q84: =IF($F84<>"Numérico","",IF($P84="","Sin dato",IF(AND(OR(NOT(ISNUMBER($I84)),$P84>=$I84),OR(NOT(ISNUMBER($J84)),$P84<=$J84)),"Dentro de rango","Fuera de rango"))) -> Sin dato
A85: 10.4.1 | B85: 10. Gabinete, montaje e instalación | C85: 10.4 Condiciones ambientales del sitio | D85: Temperatura ambiental de operación de la sala | E85: Temperatura controlada del shelter para asegurar condiciones termoestables | F85: Numérico | G85: °C | H85: Rango de operación del analizador para mantener estabilidad óptica y química | I85: 5 | J85: 40 | K85: Sí | L85: No | N85: P-ST-018-MAN OPER APMA 370 V2 | O85: Pendiente | Q85: =IF($F85<>"Numérico","",IF($P85="","Sin dato",IF(AND(OR(NOT(ISNUMBER($I85)),$P85>=$I85),OR(NOT(ISNUMBER($J85)),$P85<=$J85)),"Dentro de rango","Fuera de rango"))) -> Sin dato
A86: 10.4.2 | B86: 10. Gabinete, montaje e instalación | C86: 10.4 Condiciones ambientales del sitio | D86: Humedad relativa con temperatura menor a 31 °C | E86: Límite higrométrico del aire ambiente en el shelter para temperaturas menores a 31 °C | F86: Numérico | G86: %HR | H86: Humedad relativa máxima 80 % para evitar condensaciones ópticas internas | I86: 0 | J86: 80 | K86: Sí | L86: No | N86: P-ST-018-MAN OPER APMA 370 V2 | O86: Pendiente | Q86: =IF($F86<>"Numérico","",IF($P86="","Sin dato",IF(AND(OR(NOT(ISNUMBER($I86)),$P86>=$I86),OR(NOT(ISNUMBER($J86)),$P86<=$J86)),"Dentro de rango","Fuera de rango"))) -> Sin dato
A87: 10.4.3 | B87: 10. Gabinete, montaje e instalación | C87: 10.4 Condiciones ambientales del sitio | D87: Humedad relativa con temperatura entre 31 y 40 °C | E87: Límite higrométrico descendente conforme aumenta la temperatura entre 31 y 40 °C | F87: Numérico | G87: %HR | H87: Humedad máxima controlada linealmente entre 80 % (31 °C) y 50 % (40 °C) | I87: 0 | J87: 50 | K87: Sí | L87: No | N87: P-ST-018-MAN OPER APMA 370 V2 | O87: Pendiente | Q87: =IF($F87<>"Numérico","",IF($P87="","Sin dato",IF(AND(OR(NOT(ISNUMBER($I87)),$P87>=$I87),OR(NOT(ISNUMBER($J87)),$P87<=$J87)),"Dentro de rango","Fuera de rango"))) -> Sin dato
A88: 10.5.1 | B88: 10. Gabinete, montaje e instalación | C88: 10.5 Suministro eléctrico | D88: Variación de tensión nominal AC | E88: Variación de tensión de la red eléctrica AC en la toma de corriente del analizador | F88: Numérico | G88: V | H88: Rango tolerado por la fuente interna para operación óptima (nominal 220 V AC) | I88: 198 | J88: 264 | K88: Sí | L88: No | N88: P-ST-018-MAN OPER APMA 370 V2 | O88: Pendiente | Q88: =IF($F88<>"Numérico","",IF($P88="","Sin dato",IF(AND(OR(NOT(ISNUMBER($I88)),$P88>=$I88),OR(NOT(ISNUMBER($J88)),$P88<=$J88)),"Dentro de rango","Fuera de rango"))) -> Sin dato

Sheet APSA-370 (SO2)
A1: FASE 1 — INSPECCIÓN FÍSICA DEL EQUIPO · APSA-370 (SO2) (catálogo + captura)
A3: Cliente: | D3: Principio de medición: | E3: Fluorescencia ultravioleta (UVF)
A4: NIT: | D4: Fecha de inspección:
A5: Equipo / Modelo: | B5: Analizador de dióxido de azufre HORIBA APSA-370 | D5: Técnico responsable:
A6: Número de serie: | D6: N.º de informe (MT):
A8: ID | B8: Nivel macro (N1) | C8: Subnivel (N2) | D8: Ítem (N3) | E8: Qué se verifica | F8: Tipo de dato | G8: Unidad | H8: Criterio de aceptación | I8: Límite inferior | J8: Límite superior | K8: Obligatorio | L8: Evidencia fotográfica requerida | M8: Repuesto / parte asociada | N8: Fuente documental | O8: Resultado | P8: Valor medido | Q8: Verificación de rango | R8: Foto adjunta | S8: Observación
A9: 1.1.1 | B9: 1. Verificación funcional inicial | C9: 1.1 Encendido y LEDs frontales | D9: LED de encendido del panel frontal | E9: Estado de iluminación del LED de encendido con el analizador energizado | F9: OK / No OK | H9: Debe iluminarse en verde en operación normal; cambia a rojo si existe alarma activa | K9: Sí | L9: Sí | N9: P-ST-030-MAN OPER APSA 370 V2 | O9: Pendiente | Q9: =IF($F9<>"Numérico","",IF($P9="","Sin dato",IF(AND(OR(NOT(ISNUMBER($I9)),$P9>=$I9),OR(NOT(ISNUMBER($J9)),$P9<=$J9)),"Dentro de rango","Fuera de rango")))
A10: 1.2.1 | B10: 1. Verificación funcional inicial | C10: 1.2 Autodiagnóstico de software | D10: Inicialización de parámetros en SRAM | E10: Carga de datos lógicos y ausencia de errores de inicialización al arrancar la CPU | F10: OK / No OK | H10: Arranque limpio sin errores de memoria y con la pantalla MEAS cargada automáticamente | K10: Sí | L10: Sí | N10: P-ST-030-MAN OPER APSA 370 V2 | O10: Pendiente | Q10: =IF($F10<>"Numérico","",IF($P10="","Sin dato",IF(AND(OR(NOT(ISNUMBER($I10)),$P10>=$I10),OR(NOT(ISNUMBER($J10)),$P10<=$J10)),"Dentro de rango","Fuera de rango")))
A11: 1.2.2 | B11: 1. Verificación funcional inicial | C11: 1.2 Autodiagnóstico de software | D11: Indicador de alarmas activas en pantalla | E11: Presencia del botón ALARM en la esquina inferior derecha de la pantalla principal | F11: Sí/No | H11: El botón de alarma no debe estar visible en la pantalla MEAS en condiciones normales | K11: Sí | L11: No | N11: P-ST-030-MAN OPER APSA 370 V2 | O11: Pendiente | Q11: =IF($F11<>"Numérico","",IF($P11="","Sin dato",IF(AND(OR(NOT(ISNUMBER($I11)),$P11>=$I11),OR(NOT(ISNUMBER($J11)),$P11<=$J11)),"Dentro de rango","Fuera de rango")))
A12: 1.2.3 | B12: 1. Verificación funcional inicial | C12: 1.2 Autodiagnóstico de software | D12: Identificación del programa en menú | E12: Versión y número de programa en la pantalla de información del sistema | F12: Texto | H12: Debe mostrar el código de programa estándar de fábrica (AP: P1000878001 / EN: P1000877001) | K12: Sí | L12: No | N12: 1 - LCD design change AP EN | O12: Pendiente | Q12: =IF($F12<>"Numérico","",IF($P12="","Sin dato",IF(AND(OR(NOT(ISNUMBER($I12)),$P12>=$I12),OR(NOT(ISNUMBER($J12)),$P12<=$J12)),"Dentro de rango","Fuera de rango")))
A13: 1.3.1 | B13: 1. Verificación funcional inicial | C13: 1.3 Estabilización térmica | D13: Tiempo de calentamiento y estabilización | E13: Tiempo transcurrido desde el encendido hasta la calibración o la medición en campo | F13: Numérico | G13: horas | H13: Mínimo 3 h de estabilización; se recomienda 24 a 48 h para mediciones de campo estables | I13: 3 | J13: 48 | K13: Sí | L13: No | N13: P-ST-030-MAN OPER APSA 370 V2 | O13: Pendiente | Q13: =IF($F13<>"Numérico","",IF($P13="","Sin dato",IF(AND(OR(NOT(ISNUMBER($I13)),$P13>=$I13),OR(NOT(ISNUMBER($J13)),$P13<=$J13)),"Dentro de rango","Fuera de rango"))) -> Sin dato
A14: 1.3.2 | B14: 1. Verificación funcional inicial | C14: 1.3 Estabilización térmica | D14: Ajuste del minuto de reset de integración | E14: Minuto del reloj en el que se ejecuta el reset de integración (RESET TIME) | F14: Numérico | G14: minutos | H14: Debe estar ajustado a 00 o 30 min según los requerimientos del sistema de adquisición | I14: 0 | J14: 30 | K14: Sí | L14: No | N14: P-ST-030-MAN OPER APSA 370 V2 | O14: Pendiente | Q14: =IF($F14<>"Numérico","",IF($P14="","Sin dato",IF(AND(OR(NOT(ISNUMBER($I14)),$P14>=$I14),OR(NOT(ISNUMBER($J14)),$P14<=$J14)),"Dentro de rango","Fuera de rango"))) -> Sin dato
A15: 2.1.1 | B15: 2. Identificación y trazabilidad | C15: 2.1 Placas e identificación física | D15: Número de serie del analizador | E15: Legibilidad e integridad del serial del fabricante en la placa posterior metálica | F15: Texto | H15: Debe ser legible y registrarse en la hoja de campo | K15: Sí | L15: No | N15: MT_829WE09R_APSA370_221102 | O15: Pendiente | Q15: =IF($F15<>"Numérico","",IF($P15="","Sin dato",IF(AND(OR(NOT(ISNUMBER($I15)),$P15>=$I15),OR(NOT(ISNUMBER($J15)),$P15<=$J15)),"Dentro de rango","Fuera de rango")))
A16: 2.1.2 | B16: 2. Identificación y trazabilidad | C16: 2.1 Placas e identificación física | D16: Número HGS del analizador | E16: Identificación del número HGS del analizador y del sistema para trazabilidad de repuestos | F16: Texto | H16: El número HGS debe estar identificado en la placa del equipo o en la documentación de fábrica | K16: Sí | L16: No | N16: 1 - LCD design change AP EN | O16: Pendiente | Q16: =IF($F16<>"Numérico","",IF($P16="","Sin dato",IF(AND(OR(NOT(ISNUMBER($I16)),$P16>=$I16),OR(NOT(ISNUMBER($J16)),$P16<=$J16)),"Dentro de rango","Fuera de rango")))
A17: 2.2.1 | B17: 2. Identificación y trazabilidad | C17: 2.2 Etiquetas de seguridad | D17: Etiqueta de advertencia de alto voltaje (lámpara) | E17: Presencia y legibilidad de la etiqueta de peligro de choque eléctrico cerca de la lámpara | F17: Presente / Ausente | H17: La etiqueta Choque Eléctrico 1 debe estar adherida y legible cerca del bloque óptico | K17: Sí | L17: Sí | N17: P-ST-029-MAN MTTO APSA370 V2 | O17: Pendiente | Q17: =IF($F17<>"Numérico","",IF($P17="","Sin dato",IF(AND(OR(NOT(ISNUMBER($I17)),$P17>=$I17),OR(NOT(ISNUMBER($J17)),$P17<=$J17)),"Dentro de rango","Fuera de rango")))
A18: 2.2.2 | B18: 2. Identificación y trazabilidad | C18: 2.2 Etiquetas de seguridad | D18: Etiqueta de advertencia de alta temperatura | E18: Etiqueta de peligro de quemadura térmica en componentes que acumulan calor | F18: Presente / Ausente | H18: La etiqueta de componente caliente debe estar visible en la bomba y en el HC Cutter | K18: Sí | L18: Sí | N18: P-ST-029-MAN MTTO APSA370 V2 | O18: Pendiente | Q18: =IF($F18<>"Numérico","",IF($P18="","Sin dato",IF(AND(OR(NOT(ISNUMBER($I18)),$P18>=$I18),OR(NOT(ISNUMBER($J18)),$P18<=$J18)),"Dentro de rango","Fuera de rango")))
A19: 3.1.1 | B19: 3. Estado de calibración | C19: 3.1 Coeficientes de calibración | D19: Coeficiente de calibración de cero (ZERO ADJUST) | E19: Coeficiente almacenado en el menú de calibración para el ajuste de cero | F19: Numérico | G19: counts | H19: Debe encontrarse dentro de los límites de tolerancia lógicos definidos por firmware | I19: -3500 | J19: 3500 | K19: Sí | L19: No | N19: P-ST-030-MAN OPER APSA 370 V2 | O19: Pendiente | Q19: =IF($F19<>"Numérico","",IF($P19="","Sin dato",IF(AND(OR(NOT(ISNUMBER($I19)),$P19>=$I19),OR(NOT(ISNUMBER($J19)),$P19<=$J19)),"Dentro de rango","Fuera de rango"))) -> Sin dato
A20: 3.1.2 | B20: 3. Estado de calibración | C20: 3.1 Coeficientes de calibración | D20: Coeficiente de calibración de span (SPAN ADJUST) | E20: Coeficiente de ganancia de pendiente almacenado tras la calibración de span | F20: Numérico | H20: Dentro de la tolerancia de ganancia de software; en campo se ubica típicamente entre 0,9 y 1,3 | I20: 0.5 | J20: 2 | K20: Sí | L20: No | N20: P-ST-030-MAN OPER APSA 370 V2 | O20: Pendiente | Q20: =IF($F20<>"Numérico","",IF($P20="","Sin dato",IF(AND(OR(NOT(ISNUMBER($I20)),$P20>=$I20),OR(NOT(ISNUMBER($J20)),$P20<=$J20)),"Dentro de rango","Fuera de rango"))) -> Sin dato
A21: 3.1.3 | B21: 3. Estado de calibración | C21: 3.1 Coeficientes de calibración | D21: Concentración de gas de span configurada (SPAN CONC) | E21: Ajuste de la concentración de gas patrón en la pantalla de edición de span | F21: Numérico | G21: ppm | H21: Debe configurarse el valor nominal exacto del cilindro de gas patrón de SO2 a utilizar | I21: 1e-05 | J21: 99999 | K21: Sí | L21: No | N21: P-ST-030-MAN OPER APSA 370 V2 | O21: Pendiente | Q21: =IF($F21<>"Numérico","",IF($P21="","Sin dato",IF(AND(OR(NOT(ISNUMBER($I21)),$P21>=$I21),OR(NOT(ISNUMBER($J21)),$P21<=$J21)),"Dentro de rango","Fuera de rango"))) -> Sin dato
A22: 3.2.1 | B22: 3. Estado de calibración | C22: 3.2 Suministro de gases patrón | D22: Presión del gas en el puerto posterior de calibración | E22: Estabilidad de la presión de suministro en la entrada de gas de calibración | F22: Numérico | G22: Pa | H22: La presión del gas de calibración debe mantenerse regulada para asegurar estabilidad neumática | I22: -500 | J22: 500 | K22: Sí | L22: No | N22: P-ST-030-MAN OPER APSA 370 V2 | O22: Pendiente | Q22: =IF($F22<>"Numérico","",IF($P22="","Sin dato",IF(AND(OR(NOT(ISNUMBER($I22)),$P22>=$I22),OR(NOT(ISNUMBER($J22)),$P22<=$J22)),"Dentro de rango","Fuera de rango"))) -> Sin dato
A23: 3.3.1 | B23: 3. Estado de calibración | C23: 3.3 Secuencia de autocalibración (AIC) | D23: Tiempo de espera para estabilización en AIC (WAIT) | E23: Tiempo de estabilización tras la conmutación de líneas de gas en calibración automática | F23: Numérico | G23: minutos | H23: Ajuste de tiempo para garantizar purga y estabilización completa de las lecturas | I23: 20 | J23: 999 | K23: Sí | L23: No | N23: P-ST-030-MAN OPER APSA 370 V2 | O23: Pendiente | Q23: =IF($F23<>"Numérico","",IF($P23="","Sin dato",IF(AND(OR(NOT(ISNUMBER($I23)),$P23>=$I23),OR(NOT(ISNUMBER($J23)),$P23<=$J23)),"Dentro de rango","Fuera de rango"))) -> Sin dato
A24: 3.3.2 | B24: 3. Estado de calibración | C24: 3.3 Secuencia de autocalibración (AIC) | D24: Tiempo de retención en AIC (HOLD) | E24: Tiempo de validación para registrar y verificar lecturas tras volver a MEAS | F24: Numérico | G24: minutos | H24: Tiempo configurado para la verificación posterior a la calibración | I24: 0 | J24: 999 | K24: Sí | L24: No | N24: P-ST-030-MAN OPER APSA 370 V2 | O24: Pendiente | Q24: =IF($F24<>"Numérico","",IF($P24="","Sin dato",IF(AND(OR(NOT(ISNUMBER($I24)),$P24>=$I24),OR(NOT(ISNUMBER($J24)),$P24<=$J24)),"Dentro de rango","Fuera de rango"))) -> Sin dato
A25: 3.3.3 | B25: 3. Estado de calibración | C25: 3.3 Secuencia de autocalibración (AIC) | D25: Habilitación de calibración en AIC (CAL YES/NO) | E25: Especificación de si se permite actualizar los coeficientes tras el AIC | F25: Sí/No | H25: YES actualiza automáticamente los coeficientes; NO solo calcula las derivas sin alterarlos | K25: Sí | L25: No | N25: P-ST-030-MAN OPER APSA 370 V2 | O25: Pendiente | Q25: =IF($F25<>"Numérico","",IF($P25="","Sin dato",IF(AND(OR(NOT(ISNUMBER($I25)),$P25>=$I25),OR(NOT(ISNUMBER($J25)),$P25<=$J25)),"Dentro de rango","Fuera de rango")))
A26: 3.4.1 | B26: 3. Estado de calibración | C26: 3.4 Deriva de cero (Zero Drift) | D26: Deriva diaria de cero en rangos bajos (rango menor o igual a 0,2 ppm) | E26: Deriva diaria de cero máxima permitida en rangos menores o iguales a 0,2 ppm | F26: Numérico | G26: ppb/día | H26: Desviación máxima diaria de la lectura del cero en rangos bajos | I26: -1 | J26: 1 | K26: Sí | L26: No | N26: P-ST-030-MAN OPER APSA 370 V2 | O26: Pendiente | Q26: =IF($F26<>"Numérico","",IF($P26="","Sin dato",IF(AND(OR(NOT(ISNUMBER($I26)),$P26>=$I26),OR(NOT(ISNUMBER($J26)),$P26<=$J26)),"Dentro de rango","Fuera de rango"))) -> Sin dato
A27: 3.4.2 | B27: 3. Estado de calibración | C27: 3.4 Deriva de cero (Zero Drift) | D27: Deriva semanal de cero en rangos bajos (rango menor o igual a 0,2 ppm) | E27: Deriva semanal de cero máxima permitida en rangos menores o iguales a 0,2 ppm | F27: Numérico | G27: ppb/semana | H27: Desviación máxima semanal de la lectura del cero en rangos bajos | I27: -1 | J27: 1 | K27: Sí | L27: No | N27: P-ST-030-MAN OPER APSA 370 V2 | O27: Pendiente | Q27: =IF($F27<>"Numérico","",IF($P27="","Sin dato",IF(AND(OR(NOT(ISNUMBER($I27)),$P27>=$I27),OR(NOT(ISNUMBER($J27)),$P27<=$J27)),"Dentro de rango","Fuera de rango"))) -> Sin dato
A28: 3.4.3 | B28: 3. Estado de calibración | C28: 3.4 Deriva de cero (Zero Drift) | D28: Deriva diaria de cero en rangos altos (rango mayor a 0,2 ppm) | E28: Deriva diaria de cero máxima permitida en rangos superiores a 0,2 ppm | F28: Numérico | G28: % F.S. | H28: Desviación máxima diaria del cero respecto al fondo de escala, en rangos altos | I28: -1 | J28: 1 | K28: Sí | L28: No | N28: P-ST-030-MAN OPER APSA 370 V2 | O28: Pendiente | Q28: =IF($F28<>"Numérico","",IF($P28="","Sin dato",IF(AND(OR(NOT(ISNUMBER($I28)),$P28>=$I28),OR(NOT(ISNUMBER($J28)),$P28<=$J28)),"Dentro de rango","Fuera de rango"))) -> Sin dato
A29: 3.4.4 | B29: 3. Estado de calibración | C29: 3.4 Deriva de cero (Zero Drift) | D29: Deriva semanal de cero en rangos altos (rango mayor a 0,2 ppm) | E29: Deriva semanal de cero máxima permitida en rangos superiores a 0,2 ppm | F29: Numérico | G29: % F.S. | H29: Desviación máxima semanal del cero respecto al fondo de escala, en rangos altos | I29: -2 | J29: 2 | K29: Sí | L29: No | N29: P-ST-030-MAN OPER APSA 370 V2 | O29: Pendiente | Q29: =IF($F29<>"Numérico","",IF($P29="","Sin dato",IF(AND(OR(NOT(ISNUMBER($I29)),$P29>=$I29),OR(NOT(ISNUMBER($J29)),$P29<=$J29)),"Dentro de rango","Fuera de rango"))) -> Sin dato
A30: 3.5.1 | B30: 3. Estado de calibración | C30: 3.5 Deriva de span (Span Drift) | D30: Deriva diaria de span (todos los rangos) | E30: Deriva diaria de span máxima permitida con variación térmica dentro de 5 °C | F30: Numérico | G30: % F.S. | H30: Desviación diaria máxima tolerada de la lectura de span | I30: -1 | J30: 1 | K30: Sí | L30: No | N30: P-ST-030-MAN OPER APSA 370 V2 | O30: Pendiente | Q30: =IF($F30<>"Numérico","",IF($P30="","Sin dato",IF(AND(OR(NOT(ISNUMBER($I30)),$P30>=$I30),OR(NOT(ISNUMBER($J30)),$P30<=$J30)),"Dentro de rango","Fuera de rango"))) -> Sin dato
A31: 3.5.2 | B31: 3. Estado de calibración | C31: 3.5 Deriva de span (Span Drift) | D31: Deriva semanal de span (todos los rangos) | E31: Deriva semanal de span máxima permitida con variación térmica dentro de 5 °C | F31: Numérico | G31: % F.S. | H31: Desviación semanal máxima tolerada de la lectura de span | I31: -2 | J31: 2 | K31: Sí | L31: No | N31: P-ST-030-MAN OPER APSA 370 V2 | O31: Pendiente | Q31: =IF($F31<>"Numérico","",IF($P31="","Sin dato",IF(AND(OR(NOT(ISNUMBER($I31)),$P31>=$I31),OR(NOT(ISNUMBER($J31)),$P31<=$J31)),"Dentro de rango","Fuera de rango"))) -> Sin dato
A32: 3.6.1 | B32: 3. Estado de calibración | C32: 3.6 Linealidad | D32: Criterio de linealidad de calibración (diferencia de mejor ajuste) | E32: Desviación máxima de cada punto de una calibración multipunto respecto a la recta de regresión | F32: Numérico | G32: % F.S. | H32: Diferencia máxima respecto a la línea de mejor ajuste, conforme a la normativa de calibración | I32: -2 | J32: 2 | K32: Sí | L32: No | N32: P-ST-030-MAN OPER APSA 370 V2 | O32: Pendiente | Q32: =IF($F32<>"Numérico","",IF($P32="","Sin dato",IF(AND(OR(NOT(ISNUMBER($I32)),$P32>=$I32),OR(NOT(ISNUMBER($J32)),$P32<=$J32)),"Dentro de rango","Fuera de rango"))) -> Sin dato
A33: 4.1.1 | B33: 4. Línea de muestreo y acondicionamiento | C33: 4.1 Portafiltros frontal | D33: Estado del elemento filtrante PA-10L | E33: Grado de saturación y oscurecimiento del filtro de teflón de 54 mm del panel frontal | F33: OK / No OK | H33: Debe verse limpio, sin hollín ni decoloración marrón; reemplazar cada 2 semanas | K33: Sí | L33: Sí | M33: Filter Element PA-10L (3200043947 / 3200043947-1PC) | N33: P-ST-029-MAN MTTO APSA370 V2 | O33: Pendiente | Q33: =IF($F33<>"Numérico","",IF($P33="","Sin dato",IF(AND(OR(NOT(ISNUMBER($I33)),$P33>=$I33),OR(NOT(ISNUMBER($J33)),$P33<=$J33)),"Dentro de rango","Fuera de rango")))
A34: 4.1.2 | B34: 4. Línea de muestreo y acondicionamiento | C34: 4.1 Portafiltros frontal | D34: Junta tórica del portafiltros (O-Ring) | E34: Elasticidad y sellado del O-ring de la tapa del portafiltros frontal | F34: OK / No OK | H34: Sin resequedad, fisuras ni deformación por aplastamiento; reemplazar cada 1 año | K34: Sí | L34: Sí | M34: O-Ring (3014059499) | N34: P-ST-029-MAN MTTO APSA370 V2 | O34: Pendiente | Q34: =IF($F34<>"Numérico","",IF($P34="","Sin dato",IF(AND(OR(NOT(ISNUMBER($I34)),$P34>=$I34),OR(NOT(ISNUMBER($J34)),$P34<=$J34)),"Dentro de rango","Fuera de rango")))
A35: 4.1.3 | B35: 4. Línea de muestreo y acondicionamiento | C35: 4.1 Portafiltros frontal | D35: Humedad en el portafiltros | E35: Presencia de condensación de agua líquida en la caja del portafiltros frontal | F35: Sí/No | H35: Debe estar completamente seco; la presencia de agua indica falla en trampas de condensado previas | K35: Sí | L35: No | N35: MT_B8RUT7HE_APSA370_20111702 | O35: Pendiente | Q35: =IF($F35<>"Numérico","",IF($P35="","Sin dato",IF(AND(OR(NOT(ISNUMBER($I35)),$P35>=$I35),OR(NOT(ISNUMBER($J35)),$P35<=$J35)),"Dentro de rango","Fuera de rango")))
A36: 4.2.1 | B36: 4. Línea de muestreo y acondicionamiento | C36: 4.2 Sonda y líneas de muestreo | D36: Integridad de la línea de teflón | E36: Estrangulamientos, fisuras o fugas físicas en la tubería de muestreo | F36: OK / No OK | H36: Tubería de teflón de 6 mm OD libre de dobleces agudos y bien ajustada | K36: Sí | L36: Sí | N36: P-ST-030-MAN OPER APSA 370 V2 | O36: Pendiente | Q36: =IF($F36<>"Numérico","",IF($P36="","Sin dato",IF(AND(OR(NOT(ISNUMBER($I36)),$P36>=$I36),OR(NOT(ISNUMBER($J36)),$P36<=$J36)),"Dentro de rango","Fuera de rango")))
A37: 4.2.2 | B37: 4. Línea de muestreo y acondicionamiento | C37: 4.2 Sonda y líneas de muestreo | D37: Protección térmica de las líneas | E37: Aislamiento de las tuberías de muestra frente a corrientes de aire frío directo | F37: OK / No OK | H37: No deben estar expuestas a corrientes de aire frío (p. ej. aire acondicionado) para evitar condensados | K37: Sí | L37: Sí | N37: P-ST-030-MAN OPER APSA 370 V2 | O37: Pendiente | Q37: =IF($F37<>"Numérico","",IF($P37="","Sin dato",IF(AND(OR(NOT(ISNUMBER($I37)),$P37>=$I37),OR(NOT(ISNUMBER($J37)),$P37<=$J37)),"Dentro de rango","Fuera de rango")))
A38: 4.3.1 | B38: 4. Línea de muestreo y acondicionamiento | C38: 4.3 Conexiones neumáticas traseras | D38: Férulas (Sleeve) en puertos de entrada y salida | E38: Presencia y estado del casquillo de soporte en las uniones de teflón posteriores | F38: Presente / Ausente | H38: Los casquillos de 6 mm deben estar presentes en las uniones traseras para garantizar el sellado | K38: Sí | L38: Sí | M38: Sleeve SO2001-6 (3030021777) | N38: MT_829WE09R_APSA370_221102 | O38: Pendiente | Q38: =IF($F38<>"Numérico","",IF($P38="","Sin dato",IF(AND(OR(NOT(ISNUMBER($I38)),$P38>=$I38),OR(NOT(ISNUMBER($J38)),$P38<=$J38)),"Dentro de rango","Fuera de rango")))
A39: 4.3.2 | B39: 4. Línea de muestreo y acondicionamiento | C39: 4.3 Conexiones neumáticas traseras | D39: Tuercas de compresión PVDF (Cap Nut) en puertos traseros | E39: Presencia y torque de las tuercas plásticas para tuberías de teflón de 6 mm | F39: Presente / Ausente | H39: Deben estar completas y debidamente ajustadas para evitar fugas neumáticas | K39: Sí | L39: Sí | M39: Cap Nut S020020-6PVDF (3030021779) | N39: MT_829WE09R_APSA370_221102 | O39: Pendiente | Q39: =IF($F39<>"Numérico","",IF($P39="","Sin dato",IF(AND(OR(NOT(ISNUMBER($I39)),$P39>=$I39),OR(NOT(ISNUMBER($J39)),$P39<=$J39)),"Dentro de rango","Fuera de rango")))
A40: 5.1.1 | B40: 5. Sistema neumático | C40: 5.1 Bomba y caudal de muestra | D40: Caudal de gas de muestra (SAMPLE) | E40: Flujo del gas de muestra a través de la celda óptica medido por el analizador | F40: Numérico | G40: L/min | H40: El flujo debe mantenerse estable dentro de los límites de diseño neumático | I40: 0.6 | J40: 1 | K40: Sí | L40: No | M40: Unidad de bomba (3014059491) | N40: P-ST-030-MAN OPER APSA 370 V2 | O40: Pendiente | Q40: =IF($F40<>"Numérico","",IF($P40="","Sin dato",IF(AND(OR(NOT(ISNUMBER($I40)),$P40>=$I40),OR(NOT(ISNUMBER($J40)),$P40<=$J40)),"Dentro de rango","Fuera de rango"))) -> Sin dato
A41: 5.1.2 | B41: 5. Sistema neumático | C41: 5.1 Bomba y caudal de muestra | D41: Presión de succión de la bomba (PUMP) | E41: Vacío de arrastre absoluto generado en la succión interna del analizador | F41: Numérico | G41: kPa | H41: Debe mantenerse por debajo del umbral de alarma; la alarma PRE1 se activa a 65 kPa o más | J41: 65 | K41: Sí | L41: No | M41: Diafragma EPDM (3011026485) | N41: P-ST-030-MAN OPER APSA 370 V2 | O41: Pendiente | Q41: =IF($F41<>"Numérico","",IF($P41="","Sin dato",IF(AND(OR(NOT(ISNUMBER($I41)),$P41>=$I41),OR(NOT(ISNUMBER($J41)),$P41<=$J41)),"Dentro de rango","Fuera de rango"))) -> Sin dato
A42: 5.1.3 | B42: 5. Sistema neumático | C42: 5.1 Bomba y caudal de muestra | D42: Integridad del diafragma de la bomba | E42: Estado de las membranas de diafragma de doble cabezal de la bomba | F42: OK / No OK | H42: Sin fisuras, grietas ni roturas; el desgaste causa baja de vacío, ruidos y disminución de flujo | K42: Sí | L42: Sí | M42: Diaphragm Assy (3011026485 / 3200602390) | N42: MT_829WE09R_APSA370_21041205 | O42: Pendiente | Q42: =IF($F42<>"Numérico","",IF($P42="","Sin dato",IF(AND(OR(NOT(ISNUMBER($I42)),$P42>=$I42),OR(NOT(ISNUMBER($J42)),$P42<=$J42)),"Dentro de rango","Fuera de rango")))
A43: 5.1.4 | B43: 5. Sistema neumático | C43: 5.1 Bomba y caudal de muestra | D43: Válvulas del cabezal de la bomba | E43: Estado físico y sello elástico de las juntas de flapper del cabezal | F43: OK / No OK | H43: Las válvulas elastoméricas deben estar limpias de partículas y sin deformaciones | K43: Sí | L43: Sí | M43: Kit de diafragma y válvulas (3011026485) | N43: P-ST-029-MAN MTTO APSA370 V2 | O43: Pendiente | Q43: =IF($F43<>"Numérico","",IF($P43="","Sin dato",IF(AND(OR(NOT(ISNUMBER($I43)),$P43>=$I43),OR(NOT(ISNUMBER($J43)),$P43<=$J43)),"Dentro de rango","Fuera de rango")))
A44: 5.1.5 | B44: 5. Sistema neumático | C44: 5.1 Bomba y caudal de muestra | D44: Sellado de las juntas de conexión de la bomba | E44: Uso de cinta selladora en las juntas roscadas de unión neumática a la bomba | F44: OK / No OK | H44: Las juntas roscadas deben sellarse con cinta de teflón para evitar fugas | K44: Sí | L44: Sí | N44: P-ST-029-MAN MTTO APSA370 V2 | O44: Pendiente | Q44: =IF($F44<>"Numérico","",IF($P44="","Sin dato",IF(AND(OR(NOT(ISNUMBER($I44)),$P44>=$I44),OR(NOT(ISNUMBER($J44)),$P44<=$J44)),"Dentro de rango","Fuera de rango")))
A45: 5.2.1 | B45: 5. Sistema neumático | C45: 5.2 Aire de purga del HC Cutter | D45: Caudal de purga del HC Cutter | E45: Flujo de aire de purga por la línea del eliminador de hidrocarburos | F45: Numérico | G45: L/min | H45: Flujo de aire limpio necesario para la correcta remoción de hidrocarburos interferentes | I45: 2 | J45: 3 | K45: Sí | L45: No | M45: Unidad HC Cutter (3014059458) | N45: GZ0000117746B SM E APXX-370 (Service Manual) | O45: Pendiente | Q45: =IF($F45<>"Numérico","",IF($P45="","Sin dato",IF(AND(OR(NOT(ISNUMBER($I45)),$P45>=$I45),OR(NOT(ISNUMBER($J45)),$P45<=$J45)),"Dentro de rango","Fuera de rango"))) -> Sin dato
A46: 5.3.1 | B46: 5. Sistema neumático | C46: 5.3 Válvulas solenoides | D46: Operación de la solenoide de cero (SV3) | E46: Conmutación física del solenoide al activar el modo ZERO | F46: OK / No OK | H46: Debe conmutar sin fugas internas y dirigir el flujo de gas cero hacia la celda | K46: Sí | L46: Sí | N46: GZ0000117746B SM E APXX-370 (Service Manual) | O46: Pendiente | Q46: =IF($F46<>"Numérico","",IF($P46="","Sin dato",IF(AND(OR(NOT(ISNUMBER($I46)),$P46>=$I46),OR(NOT(ISNUMBER($J46)),$P46<=$J46)),"Dentro de rango","Fuera de rango")))
A47: 5.3.2 | B47: 5. Sistema neumático | C47: 5.3 Válvulas solenoides | D47: Operación de la solenoide de span (SV7) | E47: Conmutación física del solenoide al activar el modo SPAN | F47: OK / No OK | H47: Debe activarse herméticamente para direccionar el gas patrón hacia la celda | K47: Sí | L47: Sí | N47: GZ0000117746B SM E APXX-370 (Service Manual) | O47: Pendiente | Q47: =IF($F47<>"Numérico","",IF($P47="","Sin dato",IF(AND(OR(NOT(ISNUMBER($I47)),$P47>=$I47),OR(NOT(ISNUMBER($J47)),$P47<=$J47)),"Dentro de rango","Fuera de rango")))
A48: 5.3.3 | B48: 5. Sistema neumático | C48: 5.3 Válvulas solenoides | D48: Operación de la solenoide de selección MEAS-CAL (SV8) | E48: Cambio entre la línea de muestreo de campo y la línea de calibración posterior | F48: OK / No OK | H48: Debe operar de forma instantánea al conmutar de MEAS a calibración (ZERO o SPAN) | K48: Sí | L48: Sí | N48: GZ0000117746B SM E APXX-370 (Service Manual) | O48: Pendiente | Q48: =IF($F48<>"Numérico","",IF($P48="","Sin dato",IF(AND(OR(NOT(ISNUMBER($I48)),$P48>=$I48),OR(NOT(ISNUMBER($J48)),$P48<=$J48)),"Dentro de rango","Fuera de rango")))
A49: 5.4.1 | B49: 5. Sistema neumático | C49: 5.4 Escape | D49: Caudal de gases de escape (Exhaust Flow) | E49: Flujo del gas de salida liberado por el puerto posterior EXHAUST | F49: Numérico | G49: L/min | H49: Flujo de escape en operación normal; debe mantenerse por debajo de 0,8 L/min | J49: 0.8 | K49: Sí | L49: No | N49: P-ST-030-MAN OPER APSA 370 V2 | O49: Pendiente | Q49: =IF($F49<>"Numérico","",IF($P49="","Sin dato",IF(AND(OR(NOT(ISNUMBER($I49)),$P49>=$I49),OR(NOT(ISNUMBER($J49)),$P49<=$J49)),"Dentro de rango","Fuera de rango"))) -> Sin dato
A50: 5.4.2 | B50: 5. Sistema neumático | C50: 5.4 Escape | D50: Presión de descarga del gas de escape | E50: Estabilidad de presión en la línea posterior de descarga del gas medido | F50: Numérico | G50: Pa | H50: La línea de descarga debe estar libre de contrapresión, dentro del rango seguro | I50: -490 | J50: 490 | K50: Sí | L50: No | N50: P-ST-030-MAN OPER APSA 370 V2 | O50: Pendiente | Q50: =IF($F50<>"Numérico","",IF($P50="","Sin dato",IF(AND(OR(NOT(ISNUMBER($I50)),$P50>=$I50),OR(NOT(ISNUMBER($J50)),$P50<=$J50)),"Dentro de rango","Fuera de rango"))) -> Sin dato
A51: 6.1.1 | B51: 6. Banco de medición y óptica | C51: 6.1 Lámpara de excitación UV | D51: Voltaje de intensidad de la lámpara de xenón (LAMP) | E51: Lectura del voltaje de la lámpara en el menú de entradas analógicas | F51: Numérico | G51: mV | H51: Lámpara nueva entre 500 y 1100 mV; por debajo de 200 mV se activa alarma y debe reemplazarse | I51: 200 | J51: 1100 | K51: Sí | L51: No | M51: Lámpara L4646 (3030020915 / 3030020915-TCA) | N51: P-ST-030-MAN OPER APSA 370 V2 | O51: Pendiente | Q51: =IF($F51<>"Numérico","",IF($P51="","Sin dato",IF(AND(OR(NOT(ISNUMBER($I51)),$P51>=$I51),OR(NOT(ISNUMBER($J51)),$P51<=$J51)),"Dentro de rango","Fuera de rango"))) -> Sin dato
A52: 6.1.2 | B52: 6. Banco de medición y óptica | C52: 6.1 Lámpara de excitación UV | D52: Contacto del socket y terminales de la lámpara | E52: Corrosión u oxidación en el socket de la lámpara de alta tensión (1000 V) | F52: OK / No OK | H52: Pines y contactos limpios y sin hollín, para evitar arcos eléctricos de alta tensión | K52: Sí | L52: Sí | M52: Lámpara L4646 (3030020915) | N52: MT_829WE09R_APSA370_241031 | O52: Pendiente | Q52: =IF($F52<>"Numérico","",IF($P52="","Sin dato",IF(AND(OR(NOT(ISNUMBER($I52)),$P52>=$I52),OR(NOT(ISNUMBER($J52)),$P52<=$J52)),"Dentro de rango","Fuera de rango")))
A53: 6.1.3 | B53: 6. Banco de medición y óptica | C53: 6.1 Lámpara de excitación UV | D53: Ajuste de la tensión de alimentación de la lámpara | E53: Medición y calibración del voltaje de la lámpara en cátodo y ánodo de D16 en la tarjeta de potencia | F53: Numérico | G53: V | H53: Ajuste para lámpara nueva mediante el potenciómetro VR2 (HV.C) con SW1 en EXT | I53: 945 | J53: 955 | K53: Sí | L53: No | N53: Ajuste_lampara_APSA | O53: Pendiente | Q53: =IF($F53<>"Numérico","",IF($P53="","Sin dato",IF(AND(OR(NOT(ISNUMBER($I53)),$P53>=$I53),OR(NOT(ISNUMBER($J53)),$P53<=$J53)),"Dentro de rango","Fuera de rango"))) -> Sin dato
A54: 6.1.4 | B54: 6. Banco de medición y óptica | C54: 6.1 Lámpara de excitación UV | D54: Desgaste de electrodos de la lámpara de xenón | E54: Envejecimiento y desgaste de los electrodos emisores de la lámpara L4646 | F54: OK / No OK | H54: Los electrodos internos no deben verse excesivamente quemados ni presentar depósitos negros | K54: Sí | L54: Sí | M54: Lámpara L4646 (3030020915) | N54: P-ST-029-MAN MTTO APSA370 V2 | O54: Pendiente | Q54: =IF($F54<>"Numérico","",IF($P54="","Sin dato",IF(AND(OR(NOT(ISNUMBER($I54)),$P54>=$I54),OR(NOT(ISNUMBER($J54)),$P54<=$J54)),"Dentro de rango","Fuera de rango")))
A55: 6.2.1 | B55: 6. Banco de medición y óptica | C55: 6.2 Bloque óptico y detección | D55: Integridad del espejo del detector y su holder | E55: Estado del espejo cóncavo detector y su fijación en el holder del bloque óptico | F55: OK / No OK | H55: El espejo no debe estar suelto ni desalineado; debe estar adherido al holder | K55: Sí | L55: Sí | M55: Miller adhesion unit (3014038766) | N55: MT_829WE09R_APSA370_221102 | O55: Pendiente | Q55: =IF($F55<>"Numérico","",IF($P55="","Sin dato",IF(AND(OR(NOT(ISNUMBER($I55)),$P55>=$I55),OR(NOT(ISNUMBER($J55)),$P55<=$J55)),"Dentro de rango","Fuera de rango")))
A56: 6.2.2 | B56: 6. Banco de medición y óptica | C56: 6.2 Bloque óptico y detección | D56: Filtro óptico de color HA-50 (lente de emisión) | E56: Presencia e integridad del filtro óptico de vidrio de color en el tubo de enfoque del PMT | F56: OK / No OK | H56: El filtro HOYA HA-50 de 21,5 mm debe estar limpio, sin manchas, ralladuras graves ni desportilladuras | K56: Sí | L56: Sí | M56: Color Filter Glass 21.5 HA-50 (3012305464) | N56: MT_B45H0D2F_APSA370_251028 | O56: Pendiente | Q56: =IF($F56<>"Numérico","",IF($P56="","Sin dato",IF(AND(OR(NOT(ISNUMBER($I56)),$P56>=$I56),OR(NOT(ISNUMBER($J56)),$P56<=$J56)),"Dentro de rango","Fuera de rango")))
A57: 6.2.3 | B57: 6. Banco de medición y óptica | C57: 6.2 Bloque óptico y detección | D57: Filtro óptico UV U-330 (lente de excitación) | E57: Presencia e integridad del filtro óptico UV de banda de excitación (215 nm) | F57: OK / No OK | H57: El filtro HOYA U-330 de 24 mm debe estar limpio y en excelente estado óptico | K57: Sí | L57: Sí | M57: Color Glass Filter U-330 D=24 (3014062371) | N57: MT_B45H0D2F_APSA370_251028 | O57: Pendiente | Q57: =IF($F57<>"Numérico","",IF($P57="","Sin dato",IF(AND(OR(NOT(ISNUMBER($I57)),$P57>=$I57),OR(NOT(ISNUMBER($J57)),$P57<=$J57)),"Dentro de rango","Fuera de rango")))
A58: 6.2.4 | B58: 6. Banco de medición y óptica | C58: 6.2 Bloque óptico y detección | D58: Estado de los lentes de la cámara de medición | E58: Opacidad, condensación o manchas en el compartimento de los lentes del PMT | F58: OK / No OK | H58: Los dos lentes bajo el fotomultiplicador deben estar transparentes y limpios | K58: Sí | L58: Sí | M58: 2 lentes de PMT | N58: Repuestos APSA-370 Nivel de Lámpara Bajo | O58: Pendiente | Q58: =IF($F58<>"Numérico","",IF($P58="","Sin dato",IF(AND(OR(NOT(ISNUMBER($I58)),$P58>=$I58),OR(NOT(ISNUMBER($J58)),$P58<=$J58)),"Dentro de rango","Fuera de rango")))
A59: 6.2.5 | B59: 6. Banco de medición y óptica | C59: 6.2 Bloque óptico y detección | D59: Acumulación de polvo en la cámara de reacción | E59: Grado de polución o polvo en el compartimento óptico del detector de fluorescencia | F59: OK / No OK | H59: El interior de la celda de fluorescencia debe estar libre de polvo, para evitar luz parásita y ruido | K59: Sí | L59: Sí | N59: MT_4P027475_APSA370_240124 | O59: Pendiente | Q59: =IF($F59<>"Numérico","",IF($P59="","Sin dato",IF(AND(OR(NOT(ISNUMBER($I59)),$P59>=$I59),OR(NOT(ISNUMBER($J59)),$P59<=$J59)),"Dentro de rango","Fuera de rango")))
A60: 6.2.6 | B60: 6. Banco de medición y óptica | C60: 6.2 Bloque óptico y detección | D60: Tubo fotomultiplicador (PMT) | E60: Respuesta y ganancia de amplificación del fotodetector principal | F60: OK / No OK | H60: El PMT debe reaccionar de forma estable a la fluorescencia del SO2, sin deriva térmica anormal | K60: Sí | L60: Sí | M60: Detector (GZ9100236244) | N60: MT_829WE09R_APSA370_21041205 | O60: Pendiente | Q60: =IF($F60<>"Numérico","",IF($P60="","Sin dato",IF(AND(OR(NOT(ISNUMBER($I60)),$P60>=$I60),OR(NOT(ISNUMBER($J60)),$P60<=$J60)),"Dentro de rango","Fuera de rango")))
A61: 6.2.7 | B61: 6. Banco de medición y óptica | C61: 6.2 Bloque óptico y detección | D61: Fotodiodo de monitoreo de la lámpara UV | E61: Sello hermético y señal del fotodiodo S12698-01 de monitoreo de la lámpara | F61: OK / No OK | H61: Debe operar de forma continua, registrando la emisión UV para corregir derivas de lámpara | K61: Sí | L61: Sí | M61: Photo Diode S12698-01 (3200546511) | N61: Procedimiento Cambio Foto Diodo Horiba APSA-370 | O61: Pendiente | Q61: =IF($F61<>"Numérico","",IF($P61="","Sin dato",IF(AND(OR(NOT(ISNUMBER($I61)),$P61>=$I61),OR(NOT(ISNUMBER($J61)),$P61<=$J61)),"Dentro de rango","Fuera de rango")))
A62: 6.3.1 | B62: 6. Banco de medición y óptica | C62: 6.3 Eliminación de interferentes | D62: Estado del eliminador de hidrocarburos (HC Cutter) | E62: Integridad del eliminador catalítico de hidrocarburos que previene falsas lecturas de SO2 | F62: OK / No OK | H62: El HC Cutter (CUT-1) debe mantener temperatura y eficiencia de remoción de aromáticos (m-xileno) | K62: Sí | L62: Sí | M62: HC Cutter (3014059458) | N62: P-ST-029-MAN MTTO APSA370 V2 | O62: Pendiente | Q62: =IF($F62<>"Numérico","",IF($P62="","Sin dato",IF(AND(OR(NOT(ISNUMBER($I62)),$P62>=$I62),OR(NOT(ISNUMBER($J62)),$P62<=$J62)),"Dentro de rango","Fuera de rango")))
A63: 6.3.2 | B63: 6. Banco de medición y óptica | C63: 6.3 Eliminación de interferentes | D63: Filtro depurador scrubber de entrada (ESU-050A) | E63: Desgaste y coloración del carbón del cartucho scrubber de entrada SCR-1 | F63: OK / No OK | H63: Debe estar libre de apelmazamiento o fugas, asegurando aire libre de SO2 para la línea de referencia | K63: Sí | L63: Sí | M63: Scrubber ESU-050A (3014059487) | N63: P-ST-029-MAN MTTO APSA370 V2 | O63: Pendiente | Q63: =IF($F63<>"Numérico","",IF($P63="","Sin dato",IF(AND(OR(NOT(ISNUMBER($I63)),$P63>=$I63),OR(NOT(ISNUMBER($J63)),$P63<=$J63)),"Dentro de rango","Fuera de rango")))
A64: 7.1.1 | B64: 7. Electrónica y control | C64: 7.1 Tarjetas electrónicas | D64: Tarjeta amplificadora AP-PRE-13 | E64: Acoplamiento físico e integridad de soldaduras de la placa preamplificadora de la señal del PMT | F64: OK / No OK | H64: Libre de sobrecalentamientos u oxidación de componentes; debe procesar adecuadamente la señal | K64: Sí | L64: Sí | M64: AP-PRE-13 (3014038440 / H1017887001B) | N64: Repuestos APSA-370 Nivel de Lámpara Bajo | O64: Pendiente | Q64: =IF($F64<>"Numérico","",IF($P64="","Sin dato",IF(AND(OR(NOT(ISNUMBER($I64)),$P64>=$I64),OR(NOT(ISNUMBER($J64)),$P64<=$J64)),"Dentro de rango","Fuera de rango")))
A65: 7.1.2 | B65: 7. Electrónica y control | C65: 7.1 Tarjetas electrónicas | D65: Tarjeta controladora de bomba AP-PMP-01 | E65: Estado eléctrico de la tarjeta controladora de potencia de motores y bombas | F65: OK / No OK | H65: Debe estar conectada firmemente y alimentar los actuadores y bombas de forma continua | K65: Sí | L65: Sí | M65: AP-PMP-01 (3014038441 / H1018866001A) | N65: Repuestos APSA-370 Nivel de Lámpara Bajo | O65: Pendiente | Q65: =IF($F65<>"Numérico","",IF($P65="","Sin dato",IF(AND(OR(NOT(ISNUMBER($I65)),$P65>=$I65),OR(NOT(ISNUMBER($J65)),$P65<=$J65)),"Dentro de rango","Fuera de rango")))
A66: 7.1.3 | B66: 7. Electrónica y control | C66: 7.1 Tarjetas electrónicas | D66: LED ST0 en tarjeta de relés AP-RPL-02A | E66: Indicación del LED verde ST0 de comunicación por bus I2C local | F66: OK / No OK | H66: Debe parpadear continuamente, indicando comunicación I2C activa con la tarjeta CPU | K66: Sí | L66: Sí | N66: GZ0000117746B SM E APXX-370 (Service Manual) | O66: Pendiente | Q66: =IF($F66<>"Numérico","",IF($P66="","Sin dato",IF(AND(OR(NOT(ISNUMBER($I66)),$P66>=$I66),OR(NOT(ISNUMBER($J66)),$P66<=$J66)),"Dentro de rango","Fuera de rango")))
A67: 7.1.4 | B67: 7. Electrónica y control | C67: 7.1 Tarjetas electrónicas | D67: LED ST1 en tarjeta de relés AP-RPL-02A | E67: Indicación del LED verde ST1 de operación (heartbeat) del microprocesador local H8 | F67: OK / No OK | H67: Debe parpadear constantemente; encendido o apagado fijo indica bloqueo lógico de la tarjeta | K67: Sí | L67: Sí | N67: GZ0000117746B SM E APXX-370 (Service Manual) | O67: Pendiente | Q67: =IF($F67<>"Numérico","",IF($P67="","Sin dato",IF(AND(OR(NOT(ISNUMBER($I67)),$P67>=$I67),OR(NOT(ISNUMBER($J67)),$P67<=$J67)),"Dentro de rango","Fuera de rango")))
A68: 7.1.5 | B68: 7. Electrónica y control | C68: 7.1 Tarjetas electrónicas | D68: LED de tensión +24 V en tarjeta ADC (AP-ADC-05) | E68: Estado del LED de alimentación de +24 V CC en la placa conversora analógica-digital | F68: OK / No OK | H68: Debe estar encendido de forma fija al estar suministrada la línea de 24 V CC | K68: Sí | L68: Sí | N68: GZ0000117746B SM E APXX-370 (Service Manual) | O68: Pendiente | Q68: =IF($F68<>"Numérico","",IF($P68="","Sin dato",IF(AND(OR(NOT(ISNUMBER($I68)),$P68>=$I68),OR(NOT(ISNUMBER($J68)),$P68<=$J68)),"Dentro de rango","Fuera de rango")))
A69: 7.1.6 | B69: 7. Electrónica y control | C69: 7.1 Tarjetas electrónicas | D69: LED de tensión +5 V en tarjeta ADC (AP-ADC-05) | E69: Estado del LED de alimentación lógica de +5 V CC en la placa de conversión | F69: OK / No OK | H69: Debe permanecer encendido de forma fija si los circuitos lógicos de la placa ADC están alimentados | K69: Sí | L69: Sí | N69: GZ0000117746B SM E APXX-370 (Service Manual) | O69: Pendiente | Q69: =IF($F69<>"Numérico","",IF($P69="","Sin dato",IF(AND(OR(NOT(ISNUMBER($I69)),$P69>=$I69),OR(NOT(ISNUMBER($J69)),$P69<=$J69)),"Dentro de rango","Fuera de rango")))
A70: 7.1.7 | B70: 7. Electrónica y control | C70: 7.1 Tarjetas electrónicas | D70: LED de tensión +3,3 V en tarjeta CPU | E70: Estado del LED indicador de alimentación interna de 3,3 V CC en la tarjeta principal | F70: OK / No OK | H70: El LED verde de 3,3 V debe estar encendido de forma fija | K70: Sí | L70: Sí | N70: GZ0000117746B SM E APXX-370 (Service Manual) | O70: Pendiente | Q70: =IF($F70<>"Numérico","",IF($P70="","Sin dato",IF(AND(OR(NOT(ISNUMBER($I70)),$P70>=$I70),OR(NOT(ISNUMBER($J70)),$P70<=$J70)),"Dentro de rango","Fuera de rango")))
A71: 7.1.8 | B71: 7. Electrónica y control | C71: 7.1 Tarjetas electrónicas | D71: LED de tensión +5 V en tarjeta CPU | E71: Estado del LED indicador de alimentación interna de 5 V CC en la tarjeta principal | F71: OK / No OK | H71: El LED verde de 5 V debe estar encendido de forma fija, indicando presencia de tensión digital | K71: Sí | L71: Sí | N71: GZ0000117746B SM E APXX-370 (Service Manual) | O71: Pendiente | Q71: =IF($F71<>"Numérico","",IF($P71="","Sin dato",IF(AND(OR(NOT(ISNUMBER($I71)),$P71>=$I71),OR(NOT(ISNUMBER($J71)),$P71<=$J71)),"Dentro de rango","Fuera de rango")))
A72: 7.1.9 | B72: 7. Electrónica y control | C72: 7.1 Tarjetas electrónicas | D72: LED de operación de la CPU (heartbeat) | E72: Parpadeo del LED de actividad de ejecución de tareas lógicas de la CPU | F72: OK / No OK | H72: Debe parpadear de forma continua; si se detiene indica congelamiento del firmware | K72: Sí | L72: Sí | N72: GZ0000117746B SM E APXX-370 (Service Manual) | O72: Pendiente | Q72: =IF($F72<>"Numérico","",IF($P72="","Sin dato",IF(AND(OR(NOT(ISNUMBER($I72)),$P72>=$I72),OR(NOT(ISNUMBER($J72)),$P72<=$J72)),"Dentro de rango","Fuera de rango")))
A73: 7.2.1 | B73: 7. Electrónica y control | C73: 7.2 Respaldo de reloj y memoria | D73: Voltaje de la batería de respaldo de SRAM y reloj | E73: Voltaje de la pila botón de litio CR2032 instalada en la tarjeta CPU | F73: Numérico | G73: V | H73: Debe mantener los parámetros de configuración y el calendario al apagar el equipo (vida aprox. 3 años) | I73: 2.5 | J73: 3.3 | K73: Sí | L73: No | M73: Batería CR2032 3 V | N73: P-ST-030-MAN OPER APSA 370 V2 | O73: Pendiente | Q73: =IF($F73<>"Numérico","",IF($P73="","Sin dato",IF(AND(OR(NOT(ISNUMBER($I73)),$P73>=$I73),OR(NOT(ISNUMBER($J73)),$P73<=$J73)),"Dentro de rango","Fuera de rango"))) -> Sin dato
A74: 7.3.1 | B74: 7. Electrónica y control | C74: 7.3 Configuración de hardware | D74: DIP switch SW2 de AP-ADC-05 (modelo) | E74: Posición de los microinterruptores BIT0 a BIT3 que identifican el modelo APSA-370 | F74: OK / No OK | H74: Para APSA-370 estándar: BIT3=OFF, BIT2=ON, BIT1=OFF, BIT0=OFF (código 0100) | K74: Sí | L74: Sí | N74: GZ0000117746B SM E APXX-370 (Service Manual) | O74: Pendiente | Q74: =IF($F74<>"Numérico","",IF($P74="","Sin dato",IF(AND(OR(NOT(ISNUMBER($I74)),$P74>=$I74),OR(NOT(ISNUMBER($J74)),$P74<=$J74)),"Dentro de rango","Fuera de rango")))
A75: 7.3.2 | B75: 7. Electrónica y control | C75: 7.3 Configuración de hardware | D75: DIP switch SW2 de AP-ADC-05 (especificación internacional) | E75: Posición del microinterruptor BIT4 para mercados fuera de Japón | F75: OK / No OK | H75: El BIT4 debe estar en ON para configurar la especificación internacional (Overseas spec) | K75: Sí | L75: Sí | N75: GZ0000117746B SM E APXX-370 (Service Manual) | O75: Pendiente | Q75: =IF($F75<>"Numérico","",IF($P75="","Sin dato",IF(AND(OR(NOT(ISNUMBER($I75)),$P75>=$I75),OR(NOT(ISNUMBER($J75)),$P75<=$J75)),"Dentro de rango","Fuera de rango")))
A76: 7.3.3 | B76: 7. Electrónica y control | C76: 7.3 Configuración de hardware | D76: DIP switch SW5 en CPU para comunicaciones RS-232C | E76: Posición de los interruptores del bloque SW5 en la CPU para habilitar RS-232C con AP-SIO-04 | F76: OK / No OK | H76: Interruptores 1 a 5 de SW5 en ON, e interruptores 6, 7 y 8 en OFF | K76: Sí | L76: Sí | N76: Procedimiento Integración Tarjeta RS232 | O76: Pendiente | Q76: =IF($F76<>"Numérico","",IF($P76="","Sin dato",IF(AND(OR(NOT(ISNUMBER($I76)),$P76>=$I76),OR(NOT(ISNUMBER($J76)),$P76<=$J76)),"Dentro de rango","Fuera de rango")))
A77: 7.3.4 | B77: 7. Electrónica y control | C77: 7.3 Configuración de hardware | D77: Interruptor SW1 en la tarjeta CPU | E77: Posición del switch principal de inicialización u operación en la CPU | F77: OK / No OK | H77: Debe estar en NORM para operación normal; INIT solo se usa para reset de CPU | K77: Sí | L77: Sí | N77: Procedimiento Integración Tarjeta RS232 | O77: Pendiente | Q77: =IF($F77<>"Numérico","",IF($P77="","Sin dato",IF(AND(OR(NOT(ISNUMBER($I77)),$P77>=$I77),OR(NOT(ISNUMBER($J77)),$P77<=$J77)),"Dentro de rango","Fuera de rango")))
A78: 7.4.1 | B78: 7. Electrónica y control | C78: 7.4 Interfaz de usuario | D78: Respuesta táctil de la pantalla LCD (Touch Panel) | E78: Precisión y respuesta al tacto del recubrimiento resistivo del panel táctil frontal | F78: OK / No OK | H78: La navegación táctil debe ser fluida, sin descalibraciones al presionar los botones lógicos | K78: Sí | L78: Sí | M78: Touch Panel TP3214S1F0 / AST-057 (3010040585) | N78: MT_RW2P5JMH_APSA370_240805 | O78: Pendiente | Q78: =IF($F78<>"Numérico","",IF($P78="","Sin dato",IF(AND(OR(NOT(ISNUMBER($I78)),$P78>=$I78),OR(NOT(ISNUMBER($J78)),$P78<=$J78)),"Dentro de rango","Fuera de rango")))
A79: 7.5.1 | B79: 7. Electrónica y control | C79: 7.5 Salidas analógicas | D79: Ajuste de cero analógico (DA ADJUST / ZERO) | E79: Voltaje en la salida analógica CH-1 configurada al 0 % de su escala | F79: Numérico | G79: V | H79: Ajuste por software para corregir desviaciones del cero eléctrico de la salida de 0 a 1 V | I79: 0 | J79: 0.1 | K79: Sí | L79: No | N79: P-ST-030-MAN OPER APSA 370 V2 | O79: Pendiente | Q79: =IF($F79<>"Numérico","",IF($P79="","Sin dato",IF(AND(OR(NOT(ISNUMBER($I79)),$P79>=$I79),OR(NOT(ISNUMBER($J79)),$P79<=$J79)),"Dentro de rango","Fuera de rango"))) -> Sin dato
A80: 7.5.2 | B80: 7. Electrónica y control | C80: 7.5 Salidas analógicas | D80: Ajuste de span analógico (DA ADJUST / SPAN) | E80: Voltaje en la salida analógica CH-1 configurada al 100 % de su escala | F80: Numérico | G80: V | H80: Tensión medida en las terminales traseras al forzar la salida al 100 % del fondo de escala | I80: 0.99 | J80: 1.01 | K80: Sí | L80: No | N80: P-ST-030-MAN OPER APSA 370 V2 | O80: Pendiente | Q80: =IF($F80<>"Numérico","",IF($P80="","Sin dato",IF(AND(OR(NOT(ISNUMBER($I80)),$P80>=$I80),OR(NOT(ISNUMBER($J80)),$P80<=$J80)),"Dentro de rango","Fuera de rango"))) -> Sin dato
A81: 7.5.3 | B81: 7. Electrónica y control | C81: 7.5 Salidas analógicas | D81: Asignación de la salida analógica CH-1 | E81: Señal analógica de 0 a 1 V asignada por hardware para la concentración de SO2 | F81: OK / No OK | H81: Salida no aislada CH-1 configurada por defecto para transmitir el valor instantáneo de concentración | K81: Sí | L81: Sí | N81: P-ST-030-MAN OPER APSA 370 V2 | O81: Pendiente | Q81: =IF($F81<>"Numérico","",IF($P81="","Sin dato",IF(AND(OR(NOT(ISNUMBER($I81)),$P81>=$I81),OR(NOT(ISNUMBER($J81)),$P81<=$J81)),"Dentro de rango","Fuera de rango")))
A82: 7.6.1 | B82: 7. Electrónica y control | C82: 7.6 Comunicaciones | D82: Tarjeta posterior e interfaz serie RS-232C | E82: Integridad física del puerto serie DB-9 en la tarjeta de comunicaciones posterior AP-SIO-04 | F82: OK / No OK | H82: El puerto posterior debe permitir la conexión para el envío de tramas de datos | K82: Sí | L82: Sí | M82: Tarjeta AP-SIO-04 | N82: Procedimiento Integración Tarjeta RS232 | O82: Pendiente | Q82: =IF($F82<>"Numérico","",IF($P82="","Sin dato",IF(AND(OR(NOT(ISNUMBER($I82)),$P82>=$I82),OR(NOT(ISNUMBER($J82)),$P82<=$J82)),"Dentro de rango","Fuera de rango")))
A83: 7.6.2 | B83: 7. Electrónica y control | C83: 7.6 Comunicaciones | D83: Identificación de la tarjeta CompactFlash (CF card) | E83: Estado del LED de inserción y detección de la CF card en la tarjeta CPU | F83: OK / No OK | H83: Debe estar encendido al introducir y reconocer la tarjeta de almacenamiento de datos | K83: Sí | L83: Sí | N83: GZ0000117746B SM E APXX-370 (Service Manual) | O83: Pendiente | Q83: =IF($F83<>"Numérico","",IF($P83="","Sin dato",IF(AND(OR(NOT(ISNUMBER($I83)),$P83>=$I83),OR(NOT(ISNUMBER($J83)),$P83<=$J83)),"Dentro de rango","Fuera de rango")))
A84: 7.7.1 | B84: 7. Electrónica y control | C84: 7.7 Protección eléctrica | D84: Fusible de alimentación posterior de CA | E84: Integridad del filamento del fusible en el portafusible de entrada de CA trasero | F84: OK / No OK | G84: A | H84: Debe ser del tipo retardado (T) con la capacidad especificada en la placa posterior | K84: Sí | L84: Sí | M84: FUSE 6.3A (T) para AC115V | N84: Cables ports | O84: Pendiente | Q84: =IF($F84<>"Numérico","",IF($P84="","Sin dato",IF(AND(OR(NOT(ISNUMBER($I84)),$P84>=$I84),OR(NOT(ISNUMBER($J84)),$P84<=$J84)),"Dentro de rango","Fuera de rango")))
A85: 8.1.1 | B85: 8. Filtros y consumibles | C85: 8.1 Horómetros de consumibles | D85: Horas de uso del filtro de purga de aire F-2 | E85: Horas acumuladas en el horómetro para el filtro de aire de 0,3 micras (F-2) | F85: Numérico | G85: horas | H85: Reemplazo obligatorio cada 2 años (17 520 h) para prevenir obstrucciones en la purga del HC Cutter | J85: 17520 | K85: Sí | L85: No | M85: Filtro F-2 (3200082322 / 3200044257) | N85: P-ST-029-MAN MTTO APSA370 V2 | O85: Pendiente | Q85: =IF($F85<>"Numérico","",IF($P85="","Sin dato",IF(AND(OR(NOT(ISNUMBER($I85)),$P85>=$I85),OR(NOT(ISNUMBER($J85)),$P85<=$J85)),"Dentro de rango","Fuera de rango"))) -> Sin dato
A86: 8.1.2 | B86: 8. Filtros y consumibles | C86: 8.1 Horómetros de consumibles | D86: Horas de uso del depurador (Scrubber ESU-050A) | E86: Horas acumuladas de operación del cartucho depurador de entrada de aire (SCR-1) | F86: Numérico | G86: horas | H86: Reemplazo preventivo cada 2 años (17 520 h) para asegurar retención óptima de SO2 | J86: 17520 | K86: Sí | L86: No | M86: Scrubber ESU-050A (3014059487) | N86: P-ST-029-MAN MTTO APSA370 V2 | O86: Pendiente | Q86: =IF($F86<>"Numérico","",IF($P86="","Sin dato",IF(AND(OR(NOT(ISNUMBER($I86)),$P86>=$I86),OR(NOT(ISNUMBER($J86)),$P86<=$J86)),"Dentro de rango","Fuera de rango"))) -> Sin dato
A87: 8.1.3 | B87: 8. Filtros y consumibles | C87: 8.1 Horómetros de consumibles | D87: Horas de uso del separador de hidrocarburos (HC Cutter) | E87: Horas acumuladas del catalizador extractor de compuestos aromáticos (CUT-1) | F87: Numérico | G87: horas | H87: Sustitución cada 2 años (17 520 h) o cuando se degrade la eficiencia de corte | J87: 17520 | K87: Sí | L87: No | M87: HC Cutter (3014059458) | N87: P-ST-029-MAN MTTO APSA370 V2 | O87: Pendiente | Q87: =IF($F87<>"Numérico","",IF($P87="","Sin dato",IF(AND(OR(NOT(ISNUMBER($I87)),$P87>=$I87),OR(NOT(ISNUMBER($J87)),$P87<=$J87)),"Dentro de rango","Fuera de rango"))) -> Sin dato
A88: 8.1.4 | B88: 8. Filtros y consumibles | C88: 8.1 Horómetros de consumibles | D88: Horas de uso del diafragma de la bomba (P-1-D) | E88: Horas de funcionamiento de las membranas elásticas de succión de la bomba | F88: Numérico | G88: horas | H88: Reemplazo preventivo cada 2 años (17 520 h) para evitar caídas de vacío y de flujo | J88: 17520 | K88: Sí | L88: No | M88: Diaphragm Assy (3011026485) | N88: P-ST-029-MAN MTTO APSA370 V2 | O88: Pendiente | Q88: =IF($F88<>"Numérico","",IF($P88="","Sin dato",IF(AND(OR(NOT(ISNUMBER($I88)),$P88>=$I88),OR(NOT(ISNUMBER($J88)),$P88<=$J88)),"Dentro de rango","Fuera de rango"))) -> Sin dato
A89: 8.1.5 | B89: 8. Filtros y consumibles | C89: 8.1 Horómetros de consumibles | D89: Horas de uso de la lámpara de xenón (LAMP) | E89: Horas acumuladas de destello del tubo de xenón en el horómetro del analizador | F89: Numérico | G89: horas | H89: Reemplazar cuando el voltaje cae por debajo de 200 mV o la lámpara muestra inestabilidad. Límites PENDIENTE DE VALIDAR | K89: Sí | L89: No | M89: Lámpara L4646 (3030020915) | N89: P-ST-029-MAN MTTO APSA370 V2 | O89: Pendiente | Q89: =IF($F89<>"Numérico","",IF($P89="","Sin dato",IF(AND(OR(NOT(ISNUMBER($I89)),$P89>=$I89),OR(NOT(ISNUMBER($J89)),$P89<=$J89)),"Dentro de rango","Fuera de rango"))) -> Sin dato
A90: 9.1.1 | B90: 9. Sensores auxiliares | C90: 9.1 Temperatura | D90: Temperatura de la celda (CELL) | E90: Temperatura del compartimento de la celda de detección óptica medida por termistor | F90: Numérico | G90: °C | H90: Debe mantenerse estabilizada en el valor estándar: temperatura ambiente + 5 a 15 °C | I90: 26 | J90: 34 | K90: Sí | L90: No | N90: P-ST-030-MAN OPER APSA 370 V2 | O90: Pendiente | Q90: =IF($F90<>"Numérico","",IF($P90="","Sin dato",IF(AND(OR(NOT(ISNUMBER($I90)),$P90>=$I90),OR(NOT(ISNUMBER($J90)),$P90<=$J90)),"Dentro de rango","Fuera de rango"))) -> Sin dato
A91: 9.2.1 | B91: 9. Sensores auxiliares | C91: 9.2 Presión | D91: Sensor de presión atmosférica (AMBIENT) | E91: Lectura de la presión barométrica o ambiente que sensa el analizador | F91: Numérico | G91: kPa | H91: Debe registrar la presión atmosférica del sitio para corrección barométrica. Límites PENDIENTE DE VALIDAR | K91: Sí | L91: No | N91: P-ST-030-MAN OPER APSA 370 V2 | O91: Pendiente | Q91: =IF($F91<>"Numérico","",IF($P91="","Sin dato",IF(AND(OR(NOT(ISNUMBER($I91)),$P91>=$I91),OR(NOT(ISNUMBER($J91)),$P91<=$J91)),"Dentro de rango","Fuera de rango"))) -> Sin dato
A92: 9.2.2 | B92: 9. Sensores auxiliares | C92: 9.2 Presión | D92: Sensor de presión de la bomba (PUMP) | E92: Lectura analógica del sensor de presión de vacío en la línea de la bomba de succión | F92: Numérico | G92: kPa | H92: Presión absoluta de succión; la alarma PRE1 se activa si supera 65 kPa | J92: 65 | K92: Sí | L92: No | N92: P-ST-030-MAN OPER APSA 370 V2 | O92: Pendiente | Q92: =IF($F92<>"Numérico","",IF($P92="","Sin dato",IF(AND(OR(NOT(ISNUMBER($I92)),$P92>=$I92),OR(NOT(ISNUMBER($J92)),$P92<=$J92)),"Dentro de rango","Fuera de rango"))) -> Sin dato
A93: 9.3.1 | B93: 9. Sensores auxiliares | C93: 9.3 Caudal | D93: Sensor de caudal de muestra (SAMPLE) | E93: Lectura analógica interna del flujo volumétrico de gas de muestra | F93: Numérico | G93: L/min | H93: La lectura debe estar dentro de la tolerancia neumática del medidor de caudal (opcional) | I93: 0.6 | J93: 1 | K93: Sí | L93: No | N93: P-ST-030-MAN OPER APSA 370 V2 | O93: Pendiente | Q93: =IF($F93<>"Numérico","",IF($P93="","Sin dato",IF(AND(OR(NOT(ISNUMBER($I93)),$P93>=$I93),OR(NOT(ISNUMBER($J93)),$P93<=$J93)),"Dentro de rango","Fuera de rango"))) -> Sin dato
A94: 9.4.1 | B94: 9. Sensores auxiliares | C94: 9.4 Tensiones internas | D94: Tensión de suministro de CC de 24 V | E94: Lectura del estado de tensión de alimentación de 24 V CC en el menú | F94: Numérico | G94: V | H94: La tensión regulada de 24 V CC debe estar dentro de la tolerancia de ± 0,5 V | I94: 23.5 | J94: 24.5 | K94: Sí | L94: No | N94: P-ST-030-MAN OPER APSA 370 V2 | O94: Pendiente | Q94: =IF($F94<>"Numérico","",IF($P94="","Sin dato",IF(AND(OR(NOT(ISNUMBER($I94)),$P94>=$I94),OR(NOT(ISNUMBER($J94)),$P94<=$J94)),"Dentro de rango","Fuera de rango"))) -> Sin dato
A95: 9.4.2 | B95: 9. Sensores auxiliares | C95: 9.4 Tensiones internas | D95: Tensión de suministro de CC de 5 V | E95: Lectura de la tensión lógica de alimentación de 5 V CC en el menú | F95: Numérico | G95: V | H95: La tensión regulada interna de 5 V CC debe mantenerse dentro de la tolerancia de ± 0,5 V | I95: 4.5 | J95: 5.5 | K95: Sí | L95: No | N95: P-ST-030-MAN OPER APSA 370 V2 | O95: Pendiente | Q95: =IF($F95<>"Numérico","",IF($P95="","Sin dato",IF(AND(OR(NOT(ISNUMBER($I95)),$P95>=$I95),OR(NOT(ISNUMBER($J95)),$P95<=$J95)),"Dentro de rango","Fuera de rango"))) -> Sin dato
A96: 10.1.1 | B96: 10. Gabinete, montaje e instalación | C96: 10.1 Entorno de operación | D96: Temperatura ambiente de la cabina | E96: Temperatura del aire ambiente interior de la cabina o estación de monitoreo | F96: Numérico | G96: °C | H96: Debe mantenerse estable dentro del rango, sin cambios bruscos de 5 °C o más | I96: 5 | J96: 40 | K96: Sí | L96: No | N96: P-ST-030-MAN OPER APSA 370 V2 | O96: Pendiente | Q96: =IF($F96<>"Numérico","",IF($P96="","Sin dato",IF(AND(OR(NOT(ISNUMBER($I96)),$P96>=$I96),OR(NOT(ISNUMBER($J96)),$P96<=$J96)),"Dentro de rango","Fuera de rango"))) -> Sin dato
A97: 10.1.2 | B97: 10. Gabinete, montaje e instalación | C97: 10.1 Entorno de operación | D97: Humedad relativa del sitio | E97: Porcentaje de humedad relativa en la estación de control del analizador | F97: Numérico | G97: % | H97: Debe mantenerse sin condensación, para proteger componentes internos y ópticos | J97: 85 | K97: Sí | L97: No | N97: P-ST-030-MAN OPER APSA 370 V2 | O97: Pendiente | Q97: =IF($F97<>"Numérico","",IF($P97="","Sin dato",IF(AND(OR(NOT(ISNUMBER($I97)),$P97>=$I97),OR(NOT(ISNUMBER($J97)),$P97<=$J97)),"Dentro de rango","Fuera de rango"))) -> Sin dato
A98: 10.1.3 | B98: 10. Gabinete, montaje e instalación | C98: 10.1 Entorno de operación | D98: Nivel de polvo de la cabina | E98: Concentración de material particulado ambiental en la sala de analizadores | F98: Numérico | G98: mg/m3 | H98: Debe controlarse por debajo de la especificación, para prevenir polución óptica rápida | J98: 0.1 | K98: Sí | L98: No | N98: P-ST-030-MAN OPER APSA 370 V2 | O98: Pendiente | Q98: =IF($F98<>"Numérico","",IF($P98="","Sin dato",IF(AND(OR(NOT(ISNUMBER($I98)),$P98>=$I98),OR(NOT(ISNUMBER($J98)),$P98<=$J98)),"Dentro de rango","Fuera de rango"))) -> Sin dato
A99: 10.2.1 | B99: 10. Gabinete, montaje e instalación | C99: 10.2 Montaje físico | D99: Nivelación horizontal del instrumento | E99: Verificación con nivel de burbuja de la posición del equipo en el rack | F99: OK / No OK | H99: La instalación física del analizador debe ser estrictamente horizontal | K99: Sí | L99: Sí | N99: P-ST-030-MAN OPER APSA 370 V2 | O99: Pendiente | Q99: =IF($F99<>"Numérico","",IF($P99="","Sin dato",IF(AND(OR(NOT(ISNUMBER($I99)),$P99>=$I99),OR(NOT(ISNUMBER($J99)),$P99<=$J99)),"Dentro de rango","Fuera de rango")))
A100: 10.2.2 | B100: 10. Gabinete, montaje e instalación | C100: 10.2 Montaje físico | D100: Espacio posterior para ventilación y servicio | E100: Distancia libre de obstáculos detrás del extractor posterior del analizador | F100: Numérico | G100: mm | H100: Mínimo 150 mm libres detrás de la unidad para flujo de aire y manipulación de cables. Límite superior PENDIENTE DE VALIDAR | I100: 150 | K100: Sí | L100: No | N100: P-ST-030-MAN OPER APSA 370 V2 | O100: Pendiente | Q100: =IF($F100<>"Numérico","",IF($P100="","Sin dato",IF(AND(OR(NOT(ISNUMBER($I100)),$P100>=$I100),OR(NOT(ISNUMBER($J100)),$P100<=$J100)),"Dentro de rango","Fuera de rango"))) -> Sin dato
A101: 10.2.3 | B101: 10. Gabinete, montaje e instalación | C101: 10.2 Montaje físico | D101: Bandeja de soporte en rack de 19 pulgadas | E101: Base metálica o rieles de soporte inferior en la cabina de instrumentación | F101: Sí/No | H101: Por el peso del instrumento (19 kg) es obligatorio colocar una base de soporte inferior | K101: Sí | L101: No | N101: P-ST-030-MAN OPER APSA 370 V2 | O101: Pendiente | Q101: =IF($F101<>"Numérico","",IF($P101="","Sin dato",IF(AND(OR(NOT(ISNUMBER($I101)),$P101>=$I101),OR(NOT(ISNUMBER($J101)),$P101<=$J101)),"Dentro de rango","Fuera de rango")))
A102: 10.3.1 | B102: 10. Gabinete, montaje e instalación | C102: 10.3 Chasis y puerta frontal | D102: Casquillos de bisagra de la puerta delantera | E102: Desgaste y holgura del casquillo plástico de la bisagra de la puerta frontal | F102: OK / No OK | H102: La puerta debe abrir y cerrar con alineamiento perfecto; sustituir casquillos desgastados | K102: Sí | L102: Sí | M102: Hinge Bush (3012304035) | N102: MT_RRWV1F42_APSA370_260427 | O102: Pendiente | Q102: =IF($F102<>"Numérico","",IF($P102="","Sin dato",IF(AND(OR(NOT(ISNUMBER($I102)),$P102>=$I102),OR(NOT(ISNUMBER($J102)),$P102<=$J102)),"Dentro de rango","Fuera de rango")))
...

Sheet APOA-370 (O3)
A1: FASE 1 — INSPECCIÓN FÍSICA DEL EQUIPO · APOA-370 (O3) (catálogo + captura)
A3: Cliente: | D3: Principio de medición: | E3: Absorción UV no dispersiva (NDUV)
A4: NIT: | D4: Fecha de inspección:
A5: Equipo / Modelo: | B5: Analizador de ozono HORIBA APOA-370 | D5: Técnico responsable:
A6: Número de serie: | D6: N.º de informe (MT):
A8: ID | B8: Nivel macro (N1) | C8: Subnivel (N2) | D8: Ítem (N3) | E8: Qué se verifica | F8: Tipo de dato | G8: Unidad | H8: Criterio de aceptación | I8: Límite inferior | J8: Límite superior | K8: Obligatorio | L8: Evidencia fotográfica requerida | M8: Repuesto / parte asociada | N8: Fuente documental | O8: Resultado | P8: Valor medido | Q8: Verificación de rango | R8: Foto adjunta | S8: Observación
A9: 1.1.1 | B9: 1. Verificación funcional inicial | C9: 1.1 Encendido y LEDs frontales | D9: LED de alimentación (panel frontal) | E9: Color del indicador de encendido tras activar el interruptor de alimentación | F9: OK / No OK | H9: Debe iluminarse en verde en operación normal y en rojo bajo condición de alarma | K9: Sí | L9: Sí | N9: P-ST-001-MAN OPER APOA 370 V2 | O9: Pendiente | Q9: =IF($F9<>"Numérico","",IF($P9="","Sin dato",IF(AND(OR(NOT(ISNUMBER($I9)),$P9>=$I9),OR(NOT(ISNUMBER($J9)),$P9<=$J9)),"Dentro de rango","Fuera de rango")))
A10: 1.1.2 | B10: 1. Verificación funcional inicial | C10: 1.1 Encendido y LEDs frontales | D10: Inicialización del visualizador táctil | E10: Que la pantalla de medición MEAS. se visualice automáticamente al encender | F10: Sí/No | H10: La pantalla MEAS. se despliega correctamente y el equipo inicia las mediciones | K10: Sí | L10: No | N10: P-ST-001-MAN OPER APOA 370 V2 | O10: Pendiente | Q10: =IF($F10<>"Numérico","",IF($P10="","Sin dato",IF(AND(OR(NOT(ISNUMBER($I10)),$P10>=$I10),OR(NOT(ISNUMBER($J10)),$P10<=$J10)),"Dentro de rango","Fuera de rango")))
A11: 1.1.3 | B11: 1. Verificación funcional inicial | C11: 1.1 Encendido y LEDs frontales | D11: Verificación de la pantalla de inicio | E11: Que la pantalla muestre el logotipo oficial HORIBA u OEM antes del modo MEAS. | F11: OK / No OK | H11: El logotipo oficial se despliega correctamente, sin distorsión ni corrupción gráfica | K11: Sí | L11: Sí | N11: GZ0000117746B SM E APXX-370 (Service Manual) | O11: Pendiente | Q11: =IF($F11<>"Numérico","",IF($P11="","Sin dato",IF(AND(OR(NOT(ISNUMBER($I11)),$P11>=$I11),OR(NOT(ISNUMBER($J11)),$P11<=$J11)),"Dentro de rango","Fuera de rango")))
A12: 1.2.1 | B12: 1. Verificación funcional inicial | C12: 1.2 Autodiagnóstico | D12: Iconos y botones de alarma en pantalla | E12: Presencia de iconos de alarma en la barra superior o del botón ALARM en la esquina inferior derecha | F12: Sí/No | H12: Ausencia completa de alarmas activas; el LED del panel frontal debe estar verde fijo | K12: Sí | L12: No | N12: P-ST-001-MAN OPER APOA 370 V2 | O12: Pendiente | Q12: =IF($F12<>"Numérico","",IF($P12="","Sin dato",IF(AND(OR(NOT(ISNUMBER($I12)),$P12>=$I12),OR(NOT(ISNUMBER($J12)),$P12<=$J12)),"Dentro de rango","Fuera de rango")))
A13: 1.2.2 | B13: 1. Verificación funcional inicial | C13: 1.2 Autodiagnóstico | D13: Verificación de intensidad inicial de la lámpara | E13: Que el autodiagnóstico no reporte error de intensidad de la lámpara UV al inicio | F13: OK / No OK | H13: El equipo no presenta error de intensidad LAMP durante la fase de inicialización | K13: Sí | L13: Sí | M13: UV Lamp (3014036635 / 9022009700) | N13: P-ST-001-MAN OPER APOA 370 V2 | O13: Pendiente | Q13: =IF($F13<>"Numérico","",IF($P13="","Sin dato",IF(AND(OR(NOT(ISNUMBER($I13)),$P13>=$I13),OR(NOT(ISNUMBER($J13)),$P13<=$J13)),"Dentro de rango","Fuera de rango")))
A14: 1.2.3 | B14: 1. Verificación funcional inicial | C14: 1.2 Autodiagnóstico | D14: Modulación de flujo cruzado a 1 Hz | E14: Sonido regular de conmutación de la electroválvula de flujo cruzado | F14: OK / No OK | H14: Sonido rítmico y constante de conmutación de la válvula a una frecuencia de 1 Hz | K14: Sí | L14: Sí | M14: Solenoid Valve SV-2 (3014034340 / 9022009300) | N14: P-ST-001-MAN OPER APOA 370 V2 | O14: Pendiente | Q14: =IF($F14<>"Numérico","",IF($P14="","Sin dato",IF(AND(OR(NOT(ISNUMBER($I14)),$P14>=$I14),OR(NOT(ISNUMBER($J14)),$P14<=$J14)),"Dentro de rango","Fuera de rango")))
A15: 1.3.1 | B15: 1. Verificación funcional inicial | C15: 1.3 Estabilización térmica | D15: Calentamiento inicial (warm-up) | E15: Tiempo de espera tras el encendido antes de calibrar o medir | F15: Numérico | G15: horas | H15: Mínimo 3 h para la estabilización térmica y óptica de celda, catalizador y lámpara. Límite superior PENDIENTE DE VALIDAR | I15: 3 | K15: Sí | L15: No | N15: P-ST-001-MAN OPER APOA 370 V2 | O15: Pendiente | Q15: =IF($F15<>"Numérico","",IF($P15="","Sin dato",IF(AND(OR(NOT(ISNUMBER($I15)),$P15>=$I15),OR(NOT(ISNUMBER($J15)),$P15<=$J15)),"Dentro de rango","Fuera de rango"))) -> Sin dato
A16: 2.1.1 | B16: 2. Identificación y trazabilidad | C16: 2.1 Placas e identificación física | D16: Número de serie del analizador | E16: Que el número de serie de la etiqueta trasera y del chasis coincida con la hoja de vida | F16: Texto | H16: Serial legible y coincidente con los registros del sistema de monitoreo | K16: Sí | L16: No | N16: MT_1T71YRV7_APOA370_220221 | O16: Pendiente | Q16: =IF($F16<>"Numérico","",IF($P16="","Sin dato",IF(AND(OR(NOT(ISNUMBER($I16)),$P16>=$I16),OR(NOT(ISNUMBER($J16)),$P16<=$J16)),"Dentro de rango","Fuera de rango")))
A17: 2.2.1 | B17: 2. Identificación y trazabilidad | C17: 2.2 Trazabilidad de software | D17: Versión del firmware (ROM) | E17: Versión del firmware cargado en la CPU, en el menú de sistema | F17: Texto | H17: La versión estándar debe mostrar P1000878001 más el número de parche | K17: Sí | L17: No | N17: GZ0000117746B SM E APXX-370 (Service Manual) | O17: Pendiente | Q17: =IF($F17<>"Numérico","",IF($P17="","Sin dato",IF(AND(OR(NOT(ISNUMBER($I17)),$P17>=$I17),OR(NOT(ISNUMBER($J17)),$P17<=$J17)),"Dentro de rango","Fuera de rango")))
A18: 2.2.2 | B18: 2. Identificación y trazabilidad | C18: 2.2 Trazabilidad de software | D18: Código HGS del sistema | E18: Confirmación del número HGS del analizador y del sistema mediante verificación HTS | F18: Texto | H18: HGS correcto y correspondiente al tipo de analizador instalado | K18: Sí | L18: No | N18: 1 - LCD design change AP EN | O18: Pendiente | Q18: =IF($F18<>"Numérico","",IF($P18="","Sin dato",IF(AND(OR(NOT(ISNUMBER($I18)),$P18>=$I18),OR(NOT(ISNUMBER($J18)),$P18<=$J18)),"Dentro de rango","Fuera de rango")))
A19: 2.3.1 | B19: 2. Identificación y trazabilidad | C19: 2.3 Etiquetas de seguridad | D19: Etiqueta de advertencia de alta temperatura | E19: Presencia y legibilidad de la etiqueta HOT COMPONENT en la carcasa de la bomba y del catalizador | F19: Presente / Ausente | H19: Etiqueta presente y visible, advirtiendo peligro de quemadura por superficies calientes | K19: Sí | L19: Sí | N19: APOA-370 Maintenance manual | O19: Pendiente | Q19: =IF($F19<>"Numérico","",IF($P19="","Sin dato",IF(AND(OR(NOT(ISNUMBER($I19)),$P19>=$I19),OR(NOT(ISNUMBER($J19)),$P19<=$J19)),"Dentro de rango","Fuera de rango")))
A20: 2.3.2 | B20: 2. Identificación y trazabilidad | C20: 2.3 Etiquetas de seguridad | D20: Etiqueta de advertencia de lámpara UV y mercurio | E20: Presencia y legibilidad de la etiqueta Contains Mercury cerca de la celda de medida | F20: Presente / Ausente | H20: Etiqueta de peligro de radiación UV y presencia de mercurio perfectamente legible | K20: Sí | L20: Sí | N20: P-ST-002-MAN MTTO APOA370 V2 | O20: Pendiente | Q20: =IF($F20<>"Numérico","",IF($P20="","Sin dato",IF(AND(OR(NOT(ISNUMBER($I20)),$P20>=$I20),OR(NOT(ISNUMBER($J20)),$P20<=$J20)),"Dentro de rango","Fuera de rango")))
A21: 2.4.1 | B21: 2. Identificación y trazabilidad | C21: 2.4 Identificación de puertos | D21: Marcación de conectores en el panel trasero | E21: Marcas serigrafiadas de SAMPLE INLET, CAL GAS INLET y EXHAUST | F21: OK / No OK | H21: Etiquetas e identificadores de puertos limpios, legibles y sin daños físicos | K21: Sí | L21: Sí | N21: P-ST-001-MAN OPER APOA 370 V2 | O21: Pendiente | Q21: =IF($F21<>"Numérico","",IF($P21="","Sin dato",IF(AND(OR(NOT(ISNUMBER($I21)),$P21>=$I21),OR(NOT(ISNUMBER($J21)),$P21<=$J21)),"Dentro de rango","Fuera de rango")))
A22: 3.1.1 | B22: 3. Estado de calibración | C22: 3.1 Coeficientes de calibración | D22: Coeficiente de calibración de cero (User Zero) | E22: Valor de corrimiento de cero almacenado en la pantalla CAL. | F22: Numérico | G22: counts | H22: El valor del ajuste de cero debe encontrarse dentro del rango permitido | I22: -3500 | J22: 3500 | K22: Sí | L22: No | N22: P-ST-001-MAN OPER APOA 370 V2 | O22: Pendiente | Q22: =IF($F22<>"Numérico","",IF($P22="","Sin dato",IF(AND(OR(NOT(ISNUMBER($I22)),$P22>=$I22),OR(NOT(ISNUMBER($J22)),$P22<=$J22)),"Dentro de rango","Fuera de rango"))) -> Sin dato
A23: 3.1.2 | B23: 3. Estado de calibración | C23: 3.1 Coeficientes de calibración | D23: Coeficiente de calibración de span (User Span) | E23: Factor de multiplicación de calibración de span en la pantalla CAL. | F23: Numérico | H23: El coeficiente de ganancia de span debe encontrarse dentro de los límites de aceptación | I23: 0.5 | J23: 2 | K23: Sí | L23: No | N23: P-ST-001-MAN OPER APOA 370 V2 | O23: Pendiente | Q23: =IF($F23<>"Numérico","",IF($P23="","Sin dato",IF(AND(OR(NOT(ISNUMBER($I23)),$P23>=$I23),OR(NOT(ISNUMBER($J23)),$P23<=$J23)),"Dentro de rango","Fuera de rango"))) -> Sin dato
A24: 3.2.1 | B24: 3. Estado de calibración | C24: 3.2 Límites de calibración de fábrica | D24: Coeficiente de cero de fábrica (Factory Zero) | E24: Coeficiente de cero de fábrica en la pantalla F.CAL de mantenimiento de servicio | F24: Numérico | G24: counts | H24: El coeficiente F.ZERO debe estar dentro del rango de conteo del ADC | I24: -32768 | J24: 32767 | K24: Sí | L24: No | N24: GZ0000117746B SM E APXX-370 (Service Manual) | O24: Pendiente | Q24: =IF($F24<>"Numérico","",IF($P24="","Sin dato",IF(AND(OR(NOT(ISNUMBER($I24)),$P24>=$I24),OR(NOT(ISNUMBER($J24)),$P24<=$J24)),"Dentro de rango","Fuera de rango"))) -> Sin dato
A25: 3.2.2 | B25: 3. Estado de calibración | C25: 3.2 Límites de calibración de fábrica | D25: Coeficiente de span de fábrica (Factory Span) | E25: Factor de multiplicación de fábrica en el menú de servicio | F25: Numérico | H25: El coeficiente F.SPAN estándar debe estar comprendido entre 0,7 y 1,3 | I25: 0.7 | J25: 1.3 | K25: Sí | L25: No | N25: GZ0000117746B SM E APXX-370 (Service Manual) | O25: Pendiente | Q25: =IF($F25<>"Numérico","",IF($P25="","Sin dato",IF(AND(OR(NOT(ISNUMBER($I25)),$P25>=$I25),OR(NOT(ISNUMBER($J25)),$P25<=$J25)),"Dentro de rango","Fuera de rango"))) -> Sin dato
A26: 3.3.1 | B26: 3. Estado de calibración | C26: 3.3 Suministro de gases patrón | D26: Presión de entrega de gas cero y de span | E26: Presión de introducción del gas cero o del gas patrón | F26: Numérico | G26: Pa | H26: La presión de suministro debe controlarse de forma estable respecto a la atmósfera | I26: -500 | J26: 500 | K26: Sí | L26: No | N26: P-ST-001-MAN OPER APOA 370 V2 | O26: Pendiente | Q26: =IF($F26<>"Numérico","",IF($P26="","Sin dato",IF(AND(OR(NOT(ISNUMBER($I26)),$P26>=$I26),OR(NOT(ISNUMBER($J26)),$P26<=$J26)),"Dentro de rango","Fuera de rango"))) -> Sin dato
A27: 3.3.2 | B27: 3. Estado de calibración | C27: 3.3 Suministro de gases patrón | D27: Lámpara del ozonizador interno (opcional) | E27: Si está equipado con generador de ozono interno, que la lámpara encienda al activar el span | F27: OK / No OK | H27: Lámpara del ozonizador interno operativa y estable, sin parpadeos anómalos. Repuesto PENDIENTE DE VALIDAR | K27: Sí | L27: Sí | N27: P-ST-001-MAN OPER APOA 370 V2 | O27: Pendiente | Q27: =IF($F27<>"Numérico","",IF($P27="","Sin dato",IF(AND(OR(NOT(ISNUMBER($I27)),$P27>=$I27),OR(NOT(ISNUMBER($J27)),$P27<=$J27)),"Dentro de rango","Fuera de rango")))
A28: 3.4.1 | B28: 3. Estado de calibración | C28: 3.4 Estabilidad de lectura | D28: Estabilidad de la lectura de cero | E28: Lectura de concentración con aire cero, para comprobar ruido y deriva | F28: Numérico | G28: ppb | H28: Lectura del analizador estabilizada cerca de cero | I28: -1 | J28: 1 | K28: Sí | L28: No | N28: P-ST-001-MAN OPER APOA 370 V2 | O28: Pendiente | Q28: =IF($F28<>"Numérico","",IF($P28="","Sin dato",IF(AND(OR(NOT(ISNUMBER($I28)),$P28>=$I28),OR(NOT(ISNUMBER($J28)),$P28<=$J28)),"Dentro de rango","Fuera de rango"))) -> Sin dato
A29: 4.1.1 | B29: 4. Línea de muestreo y acondicionamiento | C29: 4.1 Portafiltros frontal | D29: Filtro de partículas de teflón (PA-10L) | E29: Grado de suciedad, cambio de color o humedad del filtro de partículas | F29: OK / No OK | H29: El elemento filtrante debe estar limpio, de color blanco y completamente seco (cambio cada 2 semanas) | K29: Sí | L29: Sí | M29: Filter Element PA-10L (3200043947 / 9022003900) | N29: P-ST-002-MAN MTTO APOA370 V2 | O29: Pendiente | Q29: =IF($F29<>"Numérico","",IF($P29="","Sin dato",IF(AND(OR(NOT(ISNUMBER($I29)),$P29>=$I29),OR(NOT(ISNUMBER($J29)),$P29<=$J29)),"Dentro de rango","Fuera de rango")))
A30: 4.1.2 | B30: 4. Línea de muestreo y acondicionamiento | C30: 4.1 Portafiltros frontal | D30: Junta tórica del portafiltros (O-Ring G50) | E30: Estado físico, deformación o grietas de la junta tórica del vaso del portafiltros | F30: OK / No OK | H30: Junta elástica, sin aplastamientos ni resequedad, asegurando un sellado hermético | K30: Sí | L30: Sí | M30: O-Ring JISB2401 G50 (3014059499 / 9022005900) | N30: P-ST-002-MAN MTTO APOA370 V2 | O30: Pendiente | Q30: =IF($F30<>"Numérico","",IF($P30="","Sin dato",IF(AND(OR(NOT(ISNUMBER($I30)),$P30>=$I30),OR(NOT(ISNUMBER($J30)),$P30<=$J30)),"Dentro de rango","Fuera de rango")))
A31: 4.1.3 | B31: 4. Línea de muestreo y acondicionamiento | C31: 4.1 Portafiltros frontal | D31: Empaque de teflón del filtro | E31: Estado de la junta plana interna de asiento del filtro | F31: OK / No OK | H31: Empaque plano sin deformaciones, cortes ni residuos de suciedad. Repuesto PENDIENTE DE VALIDAR | K31: Sí | L31: Sí | N31: P-ST-002-MAN MTTO APOA370 V2 | O31: Pendiente | Q31: =IF($F31<>"Numérico","",IF($P31="","Sin dato",IF(AND(OR(NOT(ISNUMBER($I31)),$P31>=$I31),OR(NOT(ISNUMBER($J31)),$P31<=$J31)),"Dentro de rango","Fuera de rango")))
A32: 4.2.1 | B32: 4. Línea de muestreo y acondicionamiento | C32: 4.2 Humedad en la línea | D32: Humedad o condensación en el portafiltros | E32: Presencia de agua libre en las mangueras neumáticas y en el vaso del portafiltros | F32: OK / No OK | H32: Líneas neumáticas completamente secas y libres de goteo o acumulación de agua | K32: Sí | L32: Sí | N32: MT_H53MWBT2_APOA370_250428 | O32: Pendiente | Q32: =IF($F32<>"Numérico","",IF($P32="","Sin dato",IF(AND(OR(NOT(ISNUMBER($I32)),$P32>=$I32),OR(NOT(ISNUMBER($J32)),$P32<=$J32)),"Dentro de rango","Fuera de rango")))
A33: 4.3.1 | B33: 4. Línea de muestreo y acondicionamiento | C33: 4.3 Conexiones neumáticas | D33: Férula de teflón (Sleeve / SO2001-6) | E33: Presencia y estado de la férula de teflón de 6 mm en los acoples INLET y EXHAUST | F33: Presente / Ausente | H33: Férulas presentes en todas las uniones de mangueras de 6 mm, para evitar fugas | K33: Sí | L33: Sí | M33: Sleeve SO2001-6 (3030021777) | N33: MT_1T71YRV7_APOA370_220221 | O33: Pendiente | Q33: =IF($F33<>"Numérico","",IF($P33="","Sin dato",IF(AND(OR(NOT(ISNUMBER($I33)),$P33>=$I33),OR(NOT(ISNUMBER($J33)),$P33<=$J33)),"Dentro de rango","Fuera de rango")))
A34: 4.3.2 | B34: 4. Línea de muestreo y acondicionamiento | C34: 4.3 Conexiones neumáticas | D34: Tuerca de sellado PVDF (Cap Nut) | E34: Estado físico de la tuerca plástica de acople rápido PVDF en la entrada | F34: OK / No OK | H34: Tuerca sin fisuras, roscas barridas ni deformaciones que afecten el sellado | K34: Sí | L34: Sí | M34: Panel mount union SO21521-6 (3030021548) | N34: MT_4UFVB4RH_APOA370_221031 | O34: Pendiente | Q34: =IF($F34<>"Numérico","",IF($P34="","Sin dato",IF(AND(OR(NOT(ISNUMBER($I34)),$P34>=$I34),OR(NOT(ISNUMBER($J34)),$P34<=$J34)),"Dentro de rango","Fuera de rango")))
A35: 4.3.3 | B35: 4. Línea de muestreo y acondicionamiento | C35: 4.3 Conexiones neumáticas | D35: Racor de entrada frontal de muestra | E35: Estado del acople pasamuros frontal de entrada de muestra | F35: OK / No OK | H35: Racor completo, sin grietas, mellas ni fugas | K35: Sí | L35: Sí | M35: Panel mount union SO21521-6 (3030021548) | N35: MT_WKKT596N_APOA370_220225 | O35: Pendiente | Q35: =IF($F35<>"Numérico","",IF($P35="","Sin dato",IF(AND(OR(NOT(ISNUMBER($I35)),$P35>=$I35),OR(NOT(ISNUMBER($J35)),$P35<=$J35)),"Dentro de rango","Fuera de rango")))
A36: 4.4.1 | B36: 4. Línea de muestreo y acondicionamiento | C36: 4.4 Sonda y líneas externas | D36: Línea de teflón (PTFE) de entrada | E36: Tubo de teflón externo de muestreo, buscando dobleces o aplastamientos | F36: OK / No OK | H36: Tubo continuo de 6 mm OD / 4 mm ID libre de obstrucciones, torceduras o estrangulaciones | K36: Sí | L36: Sí | N36: P-ST-001-MAN OPER APOA 370 V2 | O36: Pendiente | Q36: =IF($F36<>"Numérico","",IF($P36="","Sin dato",IF(AND(OR(NOT(ISNUMBER($I36)),$P36>=$I36),OR(NOT(ISNUMBER($J36)),$P36<=$J36)),"Dentro de rango","Fuera de rango")))
A37: 5.1.1 | B37: 5. Sistema neumático | C37: 5.1 Bomba de muestreo | D37: Diafragma de la bomba (P-1-D) | E37: Estado del diafragma de la bomba de muestra desmontando el cabezal | F37: OK / No OK | H37: El diafragma de EPDM debe estar libre de fisuras, roturas o perforaciones | K37: Sí | L37: Sí | M37: Diaphragm Assy (3200044033 / 9022002900) | N37: P-ST-002-MAN MTTO APOA370 V2 | O37: Pendiente | Q37: =IF($F37<>"Numérico","",IF($P37="","Sin dato",IF(AND(OR(NOT(ISNUMBER($I37)),$P37>=$I37),OR(NOT(ISNUMBER($J37)),$P37<=$J37)),"Dentro de rango","Fuera de rango")))
A38: 5.1.2 | B38: 5. Sistema neumático | C38: 5.1 Bomba de muestreo | D38: Válvulas de flapper de la bomba | E38: Estado del par de válvulas planas de caucho dentro del cabezal de la bomba | F38: OK / No OK | H38: Válvulas limpias, planas, sin deformación ni rigidez excesiva | K38: Sí | L38: Sí | M38: Diaphragm Assy (3200044033 / 9022002900) | N38: P-ST-002-MAN MTTO APOA370 V2 | O38: Pendiente | Q38: =IF($F38<>"Numérico","",IF($P38="","Sin dato",IF(AND(OR(NOT(ISNUMBER($I38)),$P38>=$I38),OR(NOT(ISNUMBER($J38)),$P38<=$J38)),"Dentro de rango","Fuera de rango")))
A39: 5.1.3 | B39: 5. Sistema neumático | C39: 5.1 Bomba de muestreo | D39: Montaje y base amortiguadora de la bomba | E39: Que la bomba esté fija en sus soportes antivibratorios y no despegada de su base | F39: OK / No OK | H39: Soportes en buen estado y bomba fija al chasis, sin desacople por calor | K39: Sí | L39: Sí | N39: MT_3X0ND064_APOA370_241204 | O39: Pendiente | Q39: =IF($F39<>"Numérico","",IF($P39="","Sin dato",IF(AND(OR(NOT(ISNUMBER($I39)),$P39>=$I39),OR(NOT(ISNUMBER($J39)),$P39<=$J39)),"Dentro de rango","Fuera de rango")))
A40: 5.2.1 | B40: 5. Sistema neumático | C40: 5.2 Presión y vacío | D40: Presión absoluta de la bomba (PUMP) | E40: Presión de succión de la bomba en la pantalla ANALOG INPUT | F40: Numérico | G40: kPa | H40: Debe ser menor o igual a 65 kPa; la alarma PRE1 se activa a 65 kPa o más | J40: 65 | K40: Sí | L40: No | N40: P-ST-001-MAN OPER APOA 370 V2 | O40: Pendiente | Q40: =IF($F40<>"Numérico","",IF($P40="","Sin dato",IF(AND(OR(NOT(ISNUMBER($I40)),$P40>=$I40),OR(NOT(ISNUMBER($J40)),$P40<=$J40)),"Dentro de rango","Fuera de rango"))) -> Sin dato
A41: 5.3.1 | B41: 5. Sistema neumático | C41: 5.3 Caudal de muestra | D41: Caudal de muestra en display (SAMPLE) | E41: Valor del sensor de caudal de muestra (opcional) en la pantalla ANALOG INPUT | F41: Numérico | G41: L/min | H41: Valor estándar 0,5 a 0,9 L/min; la alarma FLO1 se activa fuera de 0,4 a 1,0 L/min | I41: 0.5 | J41: 0.9 | K41: Sí | L41: No | N41: P-ST-001-MAN OPER APOA 370 V2 | O41: Pendiente | Q41: =IF($F41<>"Numérico","",IF($P41="","Sin dato",IF(AND(OR(NOT(ISNUMBER($I41)),$P41>=$I41),OR(NOT(ISNUMBER($J41)),$P41<=$J41)),"Dentro de rango","Fuera de rango"))) -> Sin dato
A42: 5.3.2 | B42: 5. Sistema neumático | C42: 5.3 Caudal de muestra | D42: Caudal de toma medido externamente | E42: Caudal real de entrada de muestra con flujómetro patrón calibrado en el puerto INLET | F42: Numérico | G42: L/min | H42: Caudal nominal 0,7 L/min ± 0,05 L/min; fuera de rango se reemplaza el orificio de control de flujo | I42: 0.65 | J42: 0.75 | K42: Sí | L42: No | N42: GZ0000117746B SM E APXX-370 (Service Manual) | O42: Pendiente | Q42: =IF($F42<>"Numérico","",IF($P42="","Sin dato",IF(AND(OR(NOT(ISNUMBER($I42)),$P42>=$I42),OR(NOT(ISNUMBER($J42)),$P42<=$J42)),"Dentro de rango","Fuera de rango"))) -> Sin dato
A43: 5.3.3 | B43: 5. Sistema neumático | C43: 5.3 Caudal de muestra | D43: Unidad de orificio crítico (Critical Orifice) | E43: Que el orificio crítico interno de control de flujo esté libre de obstrucciones | F43: OK / No OK | H43: Orificio totalmente limpio y sin obstrucciones físicas. Repuesto PENDIENTE DE VALIDAR | K43: Sí | L43: Sí | N43: P-ST-002-MAN MTTO APOA370 V2 | O43: Pendiente | Q43: =IF($F43<>"Numérico","",IF($P43="","Sin dato",IF(AND(OR(NOT(ISNUMBER($I43)),$P43>=$I43),OR(NOT(ISNUMBER($J43)),$P43<=$J43)),"Dentro de rango","Fuera de rango")))
A44: 6.1.1 | B44: 6. Banco de medición y óptica | C44: 6.1 Absorción UV no dispersiva (NDUV) | D44: Intensidad de la lámpara UV (LAMP) | E44: Voltaje de la intensidad de la fuente de luz en la pantalla ANALOG INPUT | F44: Numérico | G44: mV | H44: Valor estándar 200 a 1200 mV; se activa alarma por debajo de 200 mV. Ajuste de fábrica: 800 a 1100 mV | I44: 200 | J44: 1200 | K44: Sí | L44: No | M44: UV Lamp (3014036635 / 9022009700) | N44: P-ST-001-MAN OPER APOA 370 V2 | O44: Pendiente | Q44: =IF($F44<>"Numérico","",IF($P44="","Sin dato",IF(AND(OR(NOT(ISNUMBER($I44)),$P44>=$I44),OR(NOT(ISNUMBER($J44)),$P44<=$J44)),"Dentro de rango","Fuera de rango"))) -> Sin dato
A45: 6.1.2 | B45: 6. Banco de medición y óptica | C45: 6.1 Absorción UV no dispersiva (NDUV) | D45: Temperatura de la celda (CELL) | E45: Valor de temperatura de la celda óptica en la pantalla ANALOG INPUT | F45: Numérico | G45: °C | H45: Valor estándar: temperatura ambiente + 5 a 15 °C. Los límites dependen de la temperatura del sitio | K45: Sí | L45: No | N45: P-ST-001-MAN OPER APOA 370 V2 | O45: Pendiente | Q45: =IF($F45<>"Numérico","",IF($P45="","Sin dato",IF(AND(OR(NOT(ISNUMBER($I45)),$P45>=$I45),OR(NOT(ISNUMBER($J45)),$P45<=$J45)),"Dentro de rango","Fuera de rango"))) -> Sin dato
A46: 6.1.3 | B46: 6. Banco de medición y óptica | C46: 6.1 Absorción UV no dispersiva (NDUV) | D46: Ruido de la señal analógica (SIGNAL) | E46: Valor y estabilidad del canal analógico SIGNAL en la primera página de ANALOG INPUT | F46: Numérico | G46: mV | H46: Señal de ozono estable cerca del nivel de referencia en ausencia de gas | I46: -10 | J46: 10 | K46: Sí | L46: No | N46: P-ST-002-MAN MTTO APOA370 V2 | O46: Pendiente | Q46: =IF($F46<>"Numérico","",IF($P46="","Sin dato",IF(AND(OR(NOT(ISNUMBER($I46)),$P46>=$I46),OR(NOT(ISNUMBER($J46)),$P46<=$J46)),"Dentro de rango","Fuera de rango"))) -> Sin dato
A47: 6.2.1 | B47: 6. Banco de medición y óptica | C47: 6.2 Celda de medida y óptica | D47: Ventanas de cuarzo de la celda | E47: Estado de las ventanas ópticas transparentes en los extremos de la celda de absorción | F47: OK / No OK | H47: Ventanas limpias, libres de polvo, películas de grasa o condensación de agua | K47: Sí | L47: Sí | N47: P-ST-002-MAN MTTO APOA370 V2 | O47: Pendiente | Q47: =IF($F47<>"Numérico","",IF($P47="","Sin dato",IF(AND(OR(NOT(ISNUMBER($I47)),$P47>=$I47),OR(NOT(ISNUMBER($J47)),$P47<=$J47)),"Dentro de rango","Fuera de rango")))
A48: 6.2.2 | B48: 6. Banco de medición y óptica | C48: 6.2 Celda de medida y óptica | D48: Sello de empaquetadura de la celda | E48: Estanqueidad y estado de los empaques de las uniones de la celda | F48: OK / No OK | H48: Sin evidencia de fugas en la celda de absorción; sellos continuos sin agrietamiento. Repuesto PENDIENTE DE VALIDAR | K48: Sí | L48: Sí | N48: P-ST-002-MAN MTTO APOA370 V2 | O48: Pendiente | Q48: =IF($F48<>"Numérico","",IF($P48="","Sin dato",IF(AND(OR(NOT(ISNUMBER($I48)),$P48>=$I48),OR(NOT(ISNUMBER($J48)),$P48<=$J48)),"Dentro de rango","Fuera de rango")))
A49: 6.2.3 | B49: 6. Banco de medición y óptica | C49: 6.2 Celda de medida y óptica | D49: Alineación de la lámpara UV | E49: Orientación de la lámpara para máxima intensidad, tras aflojar los tornillos de fijación | F49: OK / No OK | H49: Lámpara fijada con sus tornillos estriados en el punto de máxima señal en pantalla | K49: Sí | L49: Sí | N49: P-ST-002-MAN MTTO APOA370 V2 | O49: Pendiente | Q49: =IF($F49<>"Numérico","",IF($P49="","Sin dato",IF(AND(OR(NOT(ISNUMBER($I49)),$P49>=$I49),OR(NOT(ISNUMBER($J49)),$P49<=$J49)),"Dentro de rango","Fuera de rango")))
A50: 6.3.1 | B50: 6. Banco de medición y óptica | C50: 6.3 Canal de referencia (deozonizador) | D50: Unidad catalítica calentada (DO pipe) | E50: Que el deozonizador caliente y descomponga el O3 para el canal de referencia | F50: OK / No OK | H50: Destrucción completa de ozono en el gas de referencia y lecturas de referencia estables | K50: Sí | L50: Sí | M50: DO pipe (3014061445 / 9022006000) | N50: P-ST-002-MAN MTTO APOA370 V2 | O50: Pendiente | Q50: =IF($F50<>"Numérico","",IF($P50="","Sin dato",IF(AND(OR(NOT(ISNUMBER($I50)),$P50>=$I50),OR(NOT(ISNUMBER($J50)),$P50<=$J50)),"Dentro de rango","Fuera de rango")))
A51: 6.3.2 | B51: 6. Banco de medición y óptica | C51: 6.3 Canal de referencia (deozonizador) | D51: Conector del catalizador deozonizador | E51: Estado del enchufe de alimentación de CA del calentador del deozonizador | F51: OK / No OK | H51: Conector firmemente encajado, contactos sin corrosión ni sobrecalentamiento térmico | K51: Sí | L51: Sí | N51: P-ST-002-MAN MTTO APOA370 V2 | O51: Pendiente | Q51: =IF($F51<>"Numérico","",IF($P51="","Sin dato",IF(AND(OR(NOT(ISNUMBER($I51)),$P51>=$I51),OR(NOT(ISNUMBER($J51)),$P51<=$J51)),"Dentro de rango","Fuera de rango")))
A52: 6.4.1 | B52: 6. Banco de medición y óptica | C52: 6.4 Detección | D52: Fotodiodo detector de medición | E52: Estado de las conexiones soldadas del fotodiodo detector | F52: OK / No OK | H52: Conexiones firmes, sin sulfatación, falsos contactos ni desprendimiento por humedad | K52: Sí | L52: Sí | M52: Photo Diode (3030051996) | N52: MT_WKKT596N_APOA370_220225 | O52: Pendiente | Q52: =IF($F52<>"Numérico","",IF($P52="","Sin dato",IF(AND(OR(NOT(ISNUMBER($I52)),$P52>=$I52),OR(NOT(ISNUMBER($J52)),$P52<=$J52)),"Dentro de rango","Fuera de rango")))
A53: 6.4.2 | B53: 6. Banco de medición y óptica | C53: 6.4 Detección | D53: Tarjeta preamplificadora (AP-AMP-06) | E53: Estado de la PCB del preamplificador óptico montado junto al fotodiodo | F53: OK / No OK | H53: Placa limpia, libre de humedad, sulfatación o componentes recalentados | K53: Sí | L53: Sí | M53: Printed Board Unit (3200092494) | N53: MT_WKKT596N_APOA370_220225 | O53: Pendiente | Q53: =IF($F53<>"Numérico","",IF($P53="","Sin dato",IF(AND(OR(NOT(ISNUMBER($I53)),$P53>=$I53),OR(NOT(ISNUMBER($J53)),$P53<=$J53)),"Dentro de rango","Fuera de rango")))
A54: 6.5.1 | B54: 6. Banco de medición y óptica | C54: 6.5 Válvulas de modulación | D54: Unidad de solenoide de modulación (SV-2) | E54: Funcionamiento continuo de conmutación de la electroválvula de 3 vías (WTB-3K-NIF-3) | F54: OK / No OK | H54: Válvula solenoide que conmuta herméticamente y sin atascos de manera continua | K54: Sí | L54: Sí | M54: Solenoid Valve WTB-3K-NIF-3 (3014034340 / 9022009300) | N54: P-ST-002-MAN MTTO APOA370 V2 | O54: Pendiente | Q54: =IF($F54<>"Numérico","",IF($P54="","Sin dato",IF(AND(OR(NOT(ISNUMBER($I54)),$P54>=$I54),OR(NOT(ISNUMBER($J54)),$P54<=$J54)),"Dentro de rango","Fuera de rango")))
A55: 7.1.1 | B55: 7. Electrónica y control | C55: 7.1 Alimentación interna | D55: Riel de voltaje interno de 24 V (DC 24V) | E55: Voltaje de alimentación de 24 V en la segunda página de ANALOG INPUT | F55: Numérico | G55: V | H55: Debe mantenerse estable dentro de la tolerancia nominal de 24 V ± 0,5 V | I55: 23.5 | J55: 24.5 | K55: Sí | L55: No | N55: P-ST-001-MAN OPER APOA 370 V2 | O55: Pendiente | Q55: =IF($F55<>"Numérico","",IF($P55="","Sin dato",IF(AND(OR(NOT(ISNUMBER($I55)),$P55>=$I55),OR(NOT(ISNUMBER($J55)),$P55<=$J55)),"Dentro de rango","Fuera de rango"))) -> Sin dato
A56: 7.1.2 | B56: 7. Electrónica y control | C56: 7.1 Alimentación interna | D56: Riel de voltaje interno de 5 V (DC 5V) | E56: Voltaje de alimentación de 5 V en la segunda página de ANALOG INPUT | F56: Numérico | G56: V | H56: Debe mantenerse estable dentro de la tolerancia nominal de 5 V ± 0,5 V | I56: 4.5 | J56: 5.5 | K56: Sí | L56: No | N56: P-ST-001-MAN OPER APOA 370 V2 | O56: Pendiente | Q56: =IF($F56<>"Numérico","",IF($P56="","Sin dato",IF(AND(OR(NOT(ISNUMBER($I56)),$P56>=$I56),OR(NOT(ISNUMBER($J56)),$P56<=$J56)),"Dentro de rango","Fuera de rango"))) -> Sin dato
A57: 7.1.3 | B57: 7. Electrónica y control | C57: 7.1 Alimentación interna | D57: Riel de voltaje interno de 3,3 V | E57: Que el LED indicador de +3,3 V en la tarjeta AP-CPU-01 o AP-CPU-02 esté encendido | F57: OK / No OK | H57: LED indicador del riel de 3,3 V de la CPU encendido fijo, de color verde | K57: Sí | L57: Sí | N57: GZ0000117746B SM E APXX-370 (Service Manual) | O57: Pendiente | Q57: =IF($F57<>"Numérico","",IF($P57="","Sin dato",IF(AND(OR(NOT(ISNUMBER($I57)),$P57>=$I57),OR(NOT(ISNUMBER($J57)),$P57<=$J57)),"Dentro de rango","Fuera de rango")))
A58: 7.2.1 | B58: 7. Electrónica y control | C58: 7.2 Tarjetas electrónicas | D58: LED de estado en placa AP-ADC-05 | E58: LED de alimentación y diagnóstico de la tarjeta analógica principal | F58: OK / No OK | H58: LED +24 V y +5 V encendidos; LED de PIO conmutando en ciclo de operación normal | K58: Sí | L58: Sí | M58: AP-ADC-05 (V1018383001) | N58: GZ0000117746B SM E APXX-370 (Service Manual) | O58: Pendiente | Q58: =IF($F58<>"Numérico","",IF($P58="","Sin dato",IF(AND(OR(NOT(ISNUMBER($I58)),$P58>=$I58),OR(NOT(ISNUMBER($J58)),$P58<=$J58)),"Dentro de rango","Fuera de rango")))
A59: 7.2.2 | B59: 7. Electrónica y control | C59: 7.2 Tarjetas electrónicas | D59: LED de estado de CPU (AP-CPU-02) | E59: Que el LED de estado de operación de la CPU parpadee continuamente | F59: OK / No OK | H59: LED en destello rítmico constante, indicando que el procesador está corriendo | K59: Sí | L59: Sí | M59: AP-CPU-02 (V3096613) | N59: GZ0000117746B SM E APXX-370 (Service Manual) | O59: Pendiente | Q59: =IF($F59<>"Numérico","",IF($P59="","Sin dato",IF(AND(OR(NOT(ISNUMBER($I59)),$P59>=$I59),OR(NOT(ISNUMBER($J59)),$P59<=$J59)),"Dentro de rango","Fuera de rango")))
A60: 7.2.3 | B60: 7. Electrónica y control | C60: 7.2 Tarjetas electrónicas | D60: LED de comunicación en tarjeta AP-RPL-02A | E60: LED ST0 (I2C) y ST1 (H8) de la placa de relés, para evaluar comunicación interna | F60: OK / No OK | H60: ST1 parpadeando en ciclo normal y ST0 destellando, indicando comunicación activa con la CPU | K60: Sí | L60: Sí | M60: AP-RPL-02A (V1026172001) | N60: GZ0000117746B SM E APXX-370 (Service Manual) | O60: Pendiente | Q60: =IF($F60<>"Numérico","",IF($P60="","Sin dato",IF(AND(OR(NOT(ISNUMBER($I60)),$P60>=$I60),OR(NOT(ISNUMBER($J60)),$P60<=$J60)),"Dentro de rango","Fuera de rango")))
A61: 7.3.1 | B61: 7. Electrónica y control | C61: 7.3 Display | D61: Respuesta al toque del panel táctil | E61: Que los botones del visualizador táctil respondan con precisión a la presión física | F61: OK / No OK | H61: Entrada táctil calibrada; las capas de la pantalla sin separación, burbujas ni sulfatación | K61: Sí | L61: Sí | M61: LCD unit / Touch Panel (3014035613 / 9022009400) | N61: P-ST-002-MAN MTTO APOA370 V2 | O61: Pendiente | Q61: =IF($F61<>"Numérico","",IF($P61="","Sin dato",IF(AND(OR(NOT(ISNUMBER($I61)),$P61>=$I61),OR(NOT(ISNUMBER($J61)),$P61<=$J61)),"Dentro de rango","Fuera de rango")))
A62: 7.4.1 | B62: 7. Electrónica y control | C62: 7.4 Respaldo de reloj y memoria | D62: Batería de reloj en placa CPU (CR2032) | E62: Que la batería no presente corrosión y que la alarma BATT no esté activa | F62: OK / No OK | H62: Batería de litio libre de fugas de electrolito y con retención correcta de hora y fecha del RTC | K62: Sí | L62: Sí | M62: Battery CR2032 (3200043671 / 9022009800) | N62: P-ST-002-MAN MTTO APOA370 V2 | O62: Pendiente | Q62: =IF($F62<>"Numérico","",IF($P62="","Sin dato",IF(AND(OR(NOT(ISNUMBER($I62)),$P62>=$I62),OR(NOT(ISNUMBER($J62)),$P62<=$J62)),"Dentro de rango","Fuera de rango")))
A63: 7.5.1 | B63: 7. Electrónica y control | C63: 7.5 Comunicaciones y almacenamiento | D63: Inserción de la tarjeta CompactFlash (CF) | E63: Que la tarjeta CF esté instalada en su ranura y el LED indicador esté encendido | F63: Sí/No | H63: Tarjeta identificada sin alarmas de lectura o escritura (alarma CF ALM inactiva) | K63: Sí | L63: No | M63: CF card (H3068068001 / 3200381086) | N63: GZ0000117746B SM E APXX-370 (Service Manual) | O63: Pendiente | Q63: =IF($F63<>"Numérico","",IF($P63="","Sin dato",IF(AND(OR(NOT(ISNUMBER($I63)),$P63>=$I63),OR(NOT(ISNUMBER($J63)),$P63<=$J63)),"Dentro de rango","Fuera de rango")))
A64: 7.5.2 | B64: 7. Electrónica y control | C64: 7.5 Comunicaciones y almacenamiento | D64: Puerto RS-232C de mantenimiento frontal | E64: Comunicación conectando el software ApCpuConfig.exe mediante cable cruzado de 9 pines | F64: OK / No OK | H64: Enlace serial establecido a 19200 bps, con transmisión bidireccional estable | K64: Sí | L64: Sí | N64: ApCpuConfigManual | O64: Pendiente | Q64: =IF($F64<>"Numérico","",IF($P64="","Sin dato",IF(AND(OR(NOT(ISNUMBER($I64)),$P64>=$I64),OR(NOT(ISNUMBER($J64)),$P64<=$J64)),"Dentro de rango","Fuera de rango")))
A65: 7.5.3 | B65: 7. Electrónica y control | C65: 7.5 Comunicaciones y almacenamiento | D65: Puerto RJ-45 Ethernet trasero | E65: Estado físico del puerto de red y de los LED verde y amarillo con el enlace activo | F65: OK / No OK | H65: Conector RJ-45 limpio y firme; el LED de Link Status se mantiene iluminado fijo | K65: Sí | L65: Sí | N65: GZ0000117746B SM E APXX-370 (Service Manual) | O65: Pendiente | Q65: =IF($F65<>"Numérico","",IF($P65="","Sin dato",IF(AND(OR(NOT(ISNUMBER($I65)),$P65>=$I65),OR(NOT(ISNUMBER($J65)),$P65<=$J65)),"Dentro de rango","Fuera de rango")))
A66: 7.6.1 | B66: 7. Electrónica y control | C66: 7.6 Configuración de hardware | D66: DIP switch SW5 en placa AP-CPU-01/02 | E66: Configuración física del interruptor de 8 vías SW5 de la tarjeta CPU | F66: OK / No OK | H66: Interruptores en OFF para operación normal, tras el mantenimiento o la inicialización | K66: Sí | L66: Sí | N66: GZ0000117746B SM E APXX-370 (Service Manual) | O66: Pendiente | Q66: =IF($F66<>"Numérico","",IF($P66="","Sin dato",IF(AND(OR(NOT(ISNUMBER($I66)),$P66>=$I66),OR(NOT(ISNUMBER($J66)),$P66<=$J66)),"Dentro de rango","Fuera de rango")))
A67: 7.6.2 | B67: 7. Electrónica y control | C67: 7.6 Configuración de hardware | D67: DIP switch SW1 de inicialización de CPU | E67: Posición física del switch de modo de arranque de la CPU | F67: OK / No OK | H67: Debe estar en NORM para operación de campo; INIT solo para reset | K67: Sí | L67: Sí | N67: GZ0000117746B SM E APXX-370 (Service Manual) | O67: Pendiente | Q67: =IF($F67<>"Numérico","",IF($P67="","Sin dato",IF(AND(OR(NOT(ISNUMBER($I67)),$P67>=$I67),OR(NOT(ISNUMBER($J67)),$P67<=$J67)),"Dentro de rango","Fuera de rango")))
A68: 7.7.1 | B68: 7. Electrónica y control | C68: 7.7 Protección eléctrica | D68: Fusibles traseros de red de CA | E68: Filamento de los fusibles del receptáculo del AC Inlet | F68: OK / No OK | H68: Fusibles del amperaje correcto, continuos y sin rastros de cortocircuito o quemadura. Especificación PENDIENTE DE VALIDAR | K68: Sí | L68: Sí | N68: P-ST-001-MAN OPER APOA 370 V2 | O68: Pendiente | Q68: =IF($F68<>"Numérico","",IF($P68="","Sin dato",IF(AND(OR(NOT(ISNUMBER($I68)),$P68>=$I68),OR(NOT(ISNUMBER($J68)),$P68<=$J68)),"Dentro de rango","Fuera de rango")))
A69: 8.1.1 | B69: 8. Filtros y consumibles | C69: 8.1 Periodicidad de reemplazo | D69: Reemplazo del elemento filtrante PA-10L | E69: Tiempo transcurrido desde la última sustitución del filtro de teflón | F69: Fecha | H69: Frecuencia de cambio no mayor a dos semanas en condiciones estándar de muestreo | K69: Sí | L69: No | M69: Filter Element PA-10L (3200043947 / 9022003900) | N69: P-ST-002-MAN MTTO APOA370 V2 | O69: Pendiente | Q69: =IF($F69<>"Numérico","",IF($P69="","Sin dato",IF(AND(OR(NOT(ISNUMBER($I69)),$P69>=$I69),OR(NOT(ISNUMBER($J69)),$P69<=$J69)),"Dentro de rango","Fuera de rango")))
A70: 8.1.2 | B70: 8. Filtros y consumibles | C70: 8.1 Periodicidad de reemplazo | D70: Reemplazo de la junta tórica O-Ring G50 | E70: Intervalo transcurrido desde el cambio de la junta del portafiltros | F70: Fecha | H70: Sustitución recomendada anual, para prevenir fugas y mantener la estanqueidad neumática | K70: Sí | L70: No | M70: O-Ring JISB2401 G50 (3014059499 / 9022005900) | N70: P-ST-002-MAN MTTO APOA370 V2 | O70: Pendiente | Q70: =IF($F70<>"Numérico","",IF($P70="","Sin dato",IF(AND(OR(NOT(ISNUMBER($I70)),$P70>=$I70),OR(NOT(ISNUMBER($J70)),$P70<=$J70)),"Dentro de rango","Fuera de rango")))
A71: 8.1.3 | B71: 8. Filtros y consumibles | C71: 8.1 Periodicidad de reemplazo | D71: Vida útil de la batería de litio (CR2032) | E71: Tiempo transcurrido desde la instalación de la batería de respaldo de la CPU | F71: Fecha | H71: Reemplazo recomendado cada 3 años, para evitar pérdida de datos en ciclos de apagado | K71: Sí | L71: No | M71: Battery CR2032 (3200043671 / 9022009800) | N71: P-ST-002-MAN MTTO APOA370 V2 | O71: Pendiente | Q71: =IF($F71<>"Numérico","",IF($P71="","Sin dato",IF(AND(OR(NOT(ISNUMBER($I71)),$P71>=$I71),OR(NOT(ISNUMBER($J71)),$P71<=$J71)),"Dentro de rango","Fuera de rango")))
A72: 8.2.1 | B72: 8. Filtros y consumibles | C72: 8.2 Horómetros de consumibles | D72: Horómetro del diafragma de bomba (P-1-D) | E72: Horas acumuladas del diafragma de la bomba en la pantalla MAINTENANCE STATUS | F72: Numérico | G72: horas | H72: Reemplazo al cumplir el ciclo recomendado por el fabricante (2 años, 17 520 h) | J72: 17520 | K72: Sí | L72: No | M72: Diaphragm Assy (3200044033 / 9022002900) | N72: P-ST-002-MAN MTTO APOA370 V2 | O72: Pendiente | Q72: =IF($F72<>"Numérico","",IF($P72="","Sin dato",IF(AND(OR(NOT(ISNUMBER($I72)),$P72>=$I72),OR(NOT(ISNUMBER($J72)),$P72<=$J72)),"Dentro de rango","Fuera de rango"))) -> Sin dato
A73: 8.2.2 | B73: 8. Filtros y consumibles | C73: 8.2 Horómetros de consumibles | D73: Horómetro del catalizador deozonizador (DO-1) | E73: Horas acumuladas registradas para el catalizador deozonizador | F73: Numérico | G73: horas | H73: Reemplazo al cumplir las horas acumuladas recomendadas (2 años, 17 520 h) | J73: 17520 | K73: Sí | L73: No | M73: Catalyzer DO-5g / DO pipe (3014061445 / 9022006000) | N73: P-ST-002-MAN MTTO APOA370 V2 | O73: Pendiente | Q73: =IF($F73<>"Numérico","",IF($P73="","Sin dato",IF(AND(OR(NOT(ISNUMBER($I73)),$P73>=$I73),OR(NOT(ISNUMBER($J73)),$P73<=$J73)),"Dentro de rango","Fuera de rango"))) -> Sin dato
A74: 8.2.3 | B74: 8. Filtros y consumibles | C74: 8.2 Horómetros de consumibles | D74: Horómetro de la lámpara UV de medición (LAMP) | E74: Horas acumuladas de uso de la lámpara de emisión UV en la pantalla de estado | F74: Numérico | G74: horas | H74: Reemplazar oportunamente o cuando su voltaje decae por debajo de 200 mV | J74: 8760 | K74: Sí | L74: No | M74: UV Lamp (3014036635 / 9022009700) | N74: P-ST-002-MAN MTTO APOA370 V2 | O74: Pendiente | Q74: =IF($F74<>"Numérico","",IF($P74="","Sin dato",IF(AND(OR(NOT(ISNUMBER($I74)),$P74>=$I74),OR(NOT(ISNUMBER($J74)),$P74<=$J74)),"Dentro de rango","Fuera de rango"))) -> Sin dato
A75: 8.2.4 | B75: 8. Filtros y consumibles | C75: 8.2 Horómetros de consumibles | D75: Horómetro de la bomba completa (P-1-B) | E75: Horas acumuladas registradas para la unidad motora de la bomba | F75: Numérico | G75: horas | H75: La bomba de diafragma completa (GS-6EH) debe reemplazarse para prevenir fatiga mecánica | J75: 17520 | K75: Sí | L75: No | M75: Pump unit GS-6EH (3014059159 100V / 3014059160 230V) | N75: P-ST-002-MAN MTTO APOA370 V2 | O75: Pendiente | Q75: =IF($F75<>"Numérico","",IF($P75="","Sin dato",IF(AND(OR(NOT(ISNUMBER($I75)),$P75>=$I75),OR(NOT(ISNUMBER($J75)),$P75<=$J75)),"Dentro de rango","Fuera de rango"))) -> Sin dato
A76: 8.2.5 | B76: 8. Filtros y consumibles | C76: 8.2 Horómetros de consumibles | D76: Horómetro de la válvula solenoide (SV-2) | E76: Horas de conmutación acumuladas de la electroválvula solenoide | F76: Numérico | G76: horas | H76: La electroválvula de conmutación de 3 vías debe reemplazarse preventivamente | J76: 17520 | K76: Sí | L76: No | M76: Solenoid Valve WTB-3K-NIF-3 (3014034340 / 9022009300) | N76: P-ST-002-MAN MTTO APOA370 V2 | O76: Pendiente | Q76: =IF($F76<>"Numérico","",IF($P76="","Sin dato",IF(AND(OR(NOT(ISNUMBER($I76)),$P76>=$I76),OR(NOT(ISNUMBER($J76)),$P76<=$J76)),"Dentro de rango","Fuera de rango"))) -> Sin dato
A77: 9.1.1 | B77: 9. Sensores auxiliares | C77: 9.1 Presión | D77: Lectura de presión ambiente (AMBIENT) | E77: Presión atmosférica en ANALOG INPUT, comparada con un barómetro patrón | F77: Numérico | G77: kPa | H77: La diferencia entre la lectura interna y el barómetro patrón externo debe ser menor al 2 % | K77: Sí | L77: No | N77: GZ0000117746B SM E APXX-370 (Service Manual) | O77: Pendiente | Q77: =IF($F77<>"Numérico","",IF($P77="","Sin dato",IF(AND(OR(NOT(ISNUMBER($I77)),$P77>=$I77),OR(NOT(ISNUMBER($J77)),$P77<=$J77)),"Dentro de rango","Fuera de rango"))) -> Sin dato
A78: 9.1.2 | B78: 9. Sensores auxiliares | C78: 9.1 Presión | D78: Presión diferencial de celda | E78: Que el sensor de presión de la celda no registre derivas anómalas ni fallos (alarma PS_1) | F78: OK / No OK | H78: Transductor de presión operativo, sin error ni inestabilidad de lectura | K78: Sí | L78: Sí | N78: GZ0000117746B SM E APXX-370 (Service Manual) | O78: Pendiente | Q78: =IF($F78<>"Numérico","",IF($P78="","Sin dato",IF(AND(OR(NOT(ISNUMBER($I78)),$P78>=$I78),OR(NOT(ISNUMBER($J78)),$P78<=$J78)),"Dentro de rango","Fuera de rango")))
A79: 9.2.1 | B79: 9. Sensores auxiliares | C79: 9.2 Temperatura | D79: Termistor de temperatura de celda (TS_1) | E79: Que el sensor de temperatura de la celda registre valores estables y consistentes | F79: OK / No OK | H79: Termistor de la celda en correcto estado físico y entregando lectura lógica | K79: Sí | L79: Sí | N79: GZ0000117746B SM E APXX-370 (Service Manual) | O79: Pendiente | Q79: =IF($F79<>"Numérico","",IF($P79="","Sin dato",IF(AND(OR(NOT(ISNUMBER($I79)),$P79>=$I79),OR(NOT(ISNUMBER($J79)),$P79<=$J79)),"Dentro de rango","Fuera de rango")))
A80: 9.2.2 | B80: 9. Sensores auxiliares | C80: 9.2 Temperatura | D80: Termistor de temperatura del deozonizador | E80: Que el deozonizador estabilice su temperatura y no reporte alarmas de calentador | F80: OK / No OK | H80: Sensor del deozonizador en correcto estado y temperatura de control dentro de límites | K80: Sí | L80: Sí | N80: GZ0000117746B SM E APXX-370 (Service Manual) | O80: Pendiente | Q80: =IF($F80<>"Numérico","",IF($P80="","Sin dato",IF(AND(OR(NOT(ISNUMBER($I80)),$P80>=$I80),OR(NOT(ISNUMBER($J80)),$P80<=$J80)),"Dentro de rango","Fuera de rango")))
A81: 9.3.1 | B81: 9. Sensores auxiliares | C81: 9.3 Caudal | D81: Lectura del sensor de caudal de muestra (opcional) | E81: Lectura de caudal en la segunda pantalla de ANALOG INPUT | F81: Numérico | G81: L/min | H81: Caudal estable en rango nominal; alarma FLO1 si está fuera de 0,4 a 1,0 L/min | I81: 0.5 | J81: 0.9 | K81: Sí | L81: No | N81: GZ0000117746B SM E APXX-370 (Service Manual) | O81: Pendiente | Q81: =IF($F81<>"Numérico","",IF($P81="","Sin dato",IF(AND(OR(NOT(ISNUMBER($I81)),$P81>=$I81),OR(NOT(ISNUMBER($J81)),$P81<=$J81)),"Dentro de rango","Fuera de rango"))) -> Sin dato
A82: 9.4.1 | B82: 9. Sensores auxiliares | C82: 9.4 Cableado de sensores | D82: Integridad de cables planos de transductores | E82: Acople físico de los conectores de cinta de los sensores de presión a la placa ADC-05 | F82: OK / No OK | H82: Conectores planos perfectamente encajados, sin hilos sueltos ni daño en el aislamiento | K82: Sí | L82: Sí | N82: GZ0000117746B SM E APXX-370 (Service Manual) | O82: Pendiente | Q82: =IF($F82<>"Numérico","",IF($P82="","Sin dato",IF(AND(OR(NOT(ISNUMBER($I82)),$P82>=$I82),OR(NOT(ISNUMBER($J82)),$P82<=$J82)),"Dentro de rango","Fuera de rango")))
A83: 10.1.1 | B83: 10. Gabinete, montaje e instalación | C83: 10.1 Chasis y puerta frontal | D83: Puerta delantera y cierres | E83: Ajuste y alineación de la puerta frontal del analizador y firmeza del cierre | F83: OK / No OK | H83: La puerta delantera debe cerrar correctamente y su pestillo asegurar de manera firme | K83: Sí | L83: Sí | N83: MT_3X0ND064_APOA370_241204 | O83: Pendiente | Q83: =IF($F83<>"Numérico","",IF($P83="","Sin dato",IF(AND(OR(NOT(ISNUMBER($I83)),$P83>=$I83),OR(NOT(ISNUMBER($J83)),$P83<=$J83)),"Dentro de rango","Fuera de rango")))
A84: 10.1.2 | B84: 10. Gabinete, montaje e instalación | C84: 10.1 Chasis y puerta frontal | D84: Tornillos de fijación de la cubierta superior | E84: Presencia y apriete de los tornillos M3 de la tapa superior del chasis | F84: OK / No OK | H84: Los 8 tornillos de la cubierta superior deben estar presentes y ajustados firmemente | K84: Sí | L84: Sí | N84: P-ST-002-MAN MTTO APOA370 V2 | O84: Pendiente | Q84: =IF($F84<>"Numérico","",IF($P84="","Sin dato",IF(AND(OR(NOT(ISNUMBER($I84)),$P84>=$I84),OR(NOT(ISNUMBER($J84)),$P84<=$J84)),"Dentro de rango","Fuera de rango")))
A85: 10.2.1 | B85: 10. Gabinete, montaje e instalación | C85: 10.2 Montaje en rack | D85: Espacio libre vertical en rack de 19 pulgadas | E85: Espacio vertical disponible en el rack o panel cortado | F85: Numérico | G85: mm | H85: Requiere una altura mínima de 222 mm (5 unidades de rack). Límite superior PENDIENTE DE VALIDAR | I85: 222 | K85: Sí | L85: No | N85: P-ST-001-MAN OPER APOA 370 V2 | O85: Pendiente | Q85: =IF($F85<>"Numérico","",IF($P85="","Sin dato",IF(AND(OR(NOT(ISNUMBER($I85)),$P85>=$I85),OR(NOT(ISNUMBER($J85)),$P85<=$J85)),"Dentro de rango","Fuera de rango"))) -> Sin dato
A86: 10.2.2 | B86: 10. Gabinete, montaje e instalación | C86: 10.2 Montaje en rack | D86: Base de apoyo e instalación del chasis | E86: Presencia de platinas laterales de montaje y de una base de soporte en rack o escritorio | F86: Presente / Ausente | H86: Debe estar montado sobre base de apoyo o rieles adecuados para soportar sus 15 kg | K86: Sí | L86: Sí | N86: P-ST-001-MAN OPER APOA 370 V2 | O86: Pendiente | Q86: =IF($F86<>"Numérico","",IF($P86="","Sin dato",IF(AND(OR(NOT(ISNUMBER($I86)),$P86>=$I86),OR(NOT(ISNUMBER($J86)),$P86<=$J86)),"Dentro de rango","Fuera de rango")))
A87: 10.3.1 | B87: 10. Gabinete, montaje e instalación | C87: 10.3 Entorno de operación | D87: Temperatura ambiental del recinto (shelter) | E87: Temperatura ambiente dentro de la estación de monitoreo o cabina climática | F87: Numérico | G87: °C | H87: Debe mantenerse estable para evitar derivas por cambios bruscos superiores a 5 °C | I87: 5 | J87: 40 | K87: Sí | L87: No | N87: P-ST-001-MAN OPER APOA 370 V2 | O87: Pendiente | Q87: =IF($F87<>"Numérico","",IF($P87="","Sin dato",IF(AND(OR(NOT(ISNUMBER($I87)),$P87>=$I87),OR(NOT(ISNUMBER($J87)),$P87<=$J87)),"Dentro de rango","Fuera de rango"))) -> Sin dato
A88: 10.3.2 | B88: 10. Gabinete, montaje e instalación | C88: 10.3 Entorno de operación | D88: Humedad relativa en la cabina de monitoreo | E88: Humedad relativa dentro del shelter o recinto de alojamiento | F88: Numérico | G88: % | H88: Humedad baja para prevenir condensación en líneas y oxidación de la lámina táctil | J88: 80 | K88: Sí | L88: No | N88: MT_4UFVB4RH_APOA370_221031 | O88: Pendiente | Q88: =IF($F88<>"Numérico","",IF($P88="","Sin dato",IF(AND(OR(NOT(ISNUMBER($I88)),$P88>=$I88),OR(NOT(ISNUMBER($J88)),$P88<=$J88)),"Dentro de rango","Fuera de rango"))) -> Sin dato

Sheet APNA-370 (NOx)
A1: FASE 1 — INSPECCIÓN FÍSICA DEL EQUIPO · APNA-370 (NOx) (catálogo + captura)
A3: Cliente: | D3: Principio de medición: | E3: Quimiluminiscencia en fase reducida
A4: NIT: | D4: Fecha de inspección:
A5: Equipo / Modelo: | B5: Analizador de óxidos de nitrógeno HORIBA APNA-370 | D5: Técnico responsable:
A6: Número de serie: | D6: N.º de informe (MT):
A8: ID | B8: Nivel macro (N1) | C8: Subnivel (N2) | D8: Ítem (N3) | E8: Qué se verifica | F8: Tipo de dato | G8: Unidad | H8: Criterio de aceptación | I8: Límite inferior | J8: Límite superior | K8: Obligatorio | L8: Evidencia fotográfica requerida | M8: Repuesto / parte asociada | N8: Fuente documental | O8: Resultado | P8: Valor medido | Q8: Verificación de rango | R8: Foto adjunta | S8: Observación
A9: 1.1.1 | B9: 1. Verificación funcional inicial | C9: 1.1 Encendido y LEDs frontales | D9: Estado visual del LED frontal de encendido | E9: Color del LED en la esquina inferior izquierda del panel frontal | F9: OK / No OK | H9: Debe iluminarse en verde constante (operación normal); en rojo indica condición de alarma | K9: Sí | L9: Sí | N9: OP_APNA-370 (Manual de Operación) | O9: Pendiente | Q9: =IF($F9<>"Numérico","",IF($P9="","Sin dato",IF(AND(OR(NOT(ISNUMBER($I9)),$P9>=$I9),OR(NOT(ISNUMBER($J9)),$P9<=$J9)),"Dentro de rango","Fuera de rango")))
A10: 1.1.2 | B10: 1. Verificación funcional inicial | C10: 1.1 Encendido y LEDs frontales | D10: Operación del ozonizador interno | E10: Que la lámpara de ozono (UV) encienda y genere ozono en el sistema | F10: Sí/No | H10: La lámpara UV debe encender (descarga azul) y el LED de la tarjeta de potencia debe brillar | K10: Sí | L10: No | M10: UV Lamp ozonizador (3014038054) | N10: MT_926L0LFB_APNA370_241118 / MT_AE0FUTTH | O10: Pendiente | Q10: =IF($F10<>"Numérico","",IF($P10="","Sin dato",IF(AND(OR(NOT(ISNUMBER($I10)),$P10>=$I10),OR(NOT(ISNUMBER($J10)),$P10<=$J10)),"Dentro de rango","Fuera de rango")))
A11: 1.1.3 | B11: 1. Verificación funcional inicial | C11: 1.1 Encendido y LEDs frontales | D11: Estado y brillo del display LCD | E11: Encendido inicial de la pantalla, sin parpadeos, líneas muertas ni fallas de iluminación | F11: OK / No OK | H11: La pantalla LCD táctil debe encender normalmente y mostrar la interfaz gráfica MEAS | K11: Sí | L11: Sí | M11: LCD unit (3014035613) | N11: MT_UMJJYLV9_APNA370_220930 / OP_APNA-370 | O11: Pendiente | Q11: =IF($F11<>"Numérico","",IF($P11="","Sin dato",IF(AND(OR(NOT(ISNUMBER($I11)),$P11>=$I11),OR(NOT(ISNUMBER($J11)),$P11<=$J11)),"Dentro de rango","Fuera de rango")))
A12: 1.2.1 | B12: 1. Verificación funcional inicial | C12: 1.2 Autodiagnóstico | D12: Revisión de alarmas activas | E12: Presencia del icono ALARM en la esquina inferior derecha de la pantalla MEAS y revisión del histórico | F12: Presente / Ausente | H12: No deben existir alarmas activas después del periodo de estabilización inicial | K12: Sí | L12: Sí | N12: OP_APNA-370 (Manual de Operación) | O12: Pendiente | Q12: =IF($F12<>"Numérico","",IF($P12="","Sin dato",IF(AND(OR(NOT(ISNUMBER($I12)),$P12>=$I12),OR(NOT(ISNUMBER($J12)),$P12<=$J12)),"Dentro de rango","Fuera de rango")))
A13: 1.3.1 | B13: 1. Verificación funcional inicial | C13: 1.3 Estabilización térmica | D13: Tiempo de calentamiento posterior al encendido | E13: Tiempo transcurrido desde el encendido, para estabilización térmica del convertidor y del detector | F13: Numérico | G13: horas | H13: Mínimo 3 h antes de medir o calibrar; se recomienda 24 a 48 h | I13: 3 | J13: 48 | K13: Sí | L13: No | N13: GZ0000117746B SM E APXX-370 (Service Manual) | O13: Pendiente | Q13: =IF($F13<>"Numérico","",IF($P13="","Sin dato",IF(AND(OR(NOT(ISNUMBER($I13)),$P13>=$I13),OR(NOT(ISNUMBER($J13)),$P13<=$J13)),"Dentro de rango","Fuera de rango"))) -> Sin dato
A14: 2.1.1 | B14: 2. Identificación y trazabilidad | C14: 2.1 Placas e identificación física | D14: Número de serie y modelo del analizador | E14: Que la etiqueta posterior de fábrica con modelo y serial esté presente y legible | F14: Texto | H14: Debe coincidir exactamente con el número de serie registrado en las hojas de servicio | K14: Sí | L14: No | N14: MT_1XT65JR5_APNA370_240909 / Cables ports | O14: Pendiente | Q14: =IF($F14<>"Numérico","",IF($P14="","Sin dato",IF(AND(OR(NOT(ISNUMBER($I14)),$P14>=$I14),OR(NOT(ISNUMBER($J14)),$P14<=$J14)),"Dentro de rango","Fuera de rango")))
A15: 2.1.2 | B15: 2. Identificación y trazabilidad | C15: 2.1 Placas e identificación física | D15: Etiqueta de inventario o control del cliente | E15: Presencia de la etiqueta de control de inventario en la puerta frontal | F15: Presente / Ausente | H15: Etiqueta presente y legible, con el serial de control del cliente | K15: Sí | L15: Sí | N15: MT_US00XLH0_APNA370_251218 / MT_YM7PXU2K | O15: Pendiente | Q15: =IF($F15<>"Numérico","",IF($P15="","Sin dato",IF(AND(OR(NOT(ISNUMBER($I15)),$P15>=$I15),OR(NOT(ISNUMBER($J15)),$P15<=$J15)),"Dentro de rango","Fuera de rango")))
A16: 2.1.3 | B16: 2. Identificación y trazabilidad | C16: 2.1 Placas e identificación física | D16: Etiqueta de apertura de puerta (Open Label) | E16: Etiqueta que indica el sentido de apertura o las instrucciones en la puerta delantera | F16: Presente / Ausente | H16: La etiqueta adhesiva debe estar adherida en la puerta frontal y en buen estado | K16: Sí | L16: Sí | M16: Open label (3012296756) | N16: MT_JV765TV0_APNA370_220216 | O16: Pendiente | Q16: =IF($F16<>"Numérico","",IF($P16="","Sin dato",IF(AND(OR(NOT(ISNUMBER($I16)),$P16>=$I16),OR(NOT(ISNUMBER($J16)),$P16<=$J16)),"Dentro de rango","Fuera de rango")))
A17: 2.2.1 | B17: 2. Identificación y trazabilidad | C17: 2.2 Trazabilidad de software | D17: Número de programa HGS/HTS | E17: Número HGS/HTS del analizador, para validar si aplica programa estándar o especial | F17: Texto | H17: El número de programa estándar para APNA-370 (AP) debe ser P1000878001 | K17: Sí | L17: No | N17: 1 - LCD design change AP EN | O17: Pendiente | Q17: =IF($F17<>"Numérico","",IF($P17="","Sin dato",IF(AND(OR(NOT(ISNUMBER($I17)),$P17>=$I17),OR(NOT(ISNUMBER($J17)),$P17<=$J17)),"Dentro de rango","Fuera de rango")))
A18: 3.1.1 | B18: 3. Estado de calibración | C18: 3.1 Coeficientes de calibración | D18: Coeficiente de calibración de cero | E18: Coeficiente digital resultante de la calibración de cero, en la pantalla CAL. | F18: Numérico | G18: counts | H18: Debe encontrarse dentro de la tolerancia de desvío del fabricante para que la calibración sea exitosa | I18: -3500 | J18: 3500 | K18: Sí | L18: No | N18: OP_APNA-370 (Manual de Operación) | O18: Pendiente | Q18: =IF($F18<>"Numérico","",IF($P18="","Sin dato",IF(AND(OR(NOT(ISNUMBER($I18)),$P18>=$I18),OR(NOT(ISNUMBER($J18)),$P18<=$J18)),"Dentro de rango","Fuera de rango"))) -> Sin dato
A19: 3.1.2 | B19: 3. Estado de calibración | C19: 3.1 Coeficientes de calibración | D19: Coeficiente de cero de fábrica | E19: Límite de counts admitido para la calibración de cero en modo de fábrica | F19: Numérico | G19: counts | H19: El coeficiente de cero de fábrica debe estar dentro de la tolerancia máxima absoluta | I19: -7000 | J19: 7000 | K19: Sí | L19: No | N19: GZ0000117746B SM E APXX-370 (Service Manual) | O19: Pendiente | Q19: =IF($F19<>"Numérico","",IF($P19="","Sin dato",IF(AND(OR(NOT(ISNUMBER($I19)),$P19>=$I19),OR(NOT(ISNUMBER($J19)),$P19<=$J19)),"Dentro de rango","Fuera de rango"))) -> Sin dato
A20: 3.1.3 | B20: 3. Estado de calibración | C20: 3.1 Coeficientes de calibración | D20: Coeficiente de calibración de span | E20: Coeficiente digital resultante de la calibración de span, en la pantalla CAL. | F20: Numérico | H20: El factor de span resultante debe estar dentro del rango de ganancia del fabricante | I20: 0.5 | J20: 2 | K20: Sí | L20: No | N20: OP_APNA-370 (Manual de Operación) | O20: Pendiente | Q20: =IF($F20<>"Numérico","",IF($P20="","Sin dato",IF(AND(OR(NOT(ISNUMBER($I20)),$P20>=$I20),OR(NOT(ISNUMBER($J20)),$P20<=$J20)),"Dentro de rango","Fuera de rango"))) -> Sin dato
A21: 3.1.4 | B21: 3. Estado de calibración | C21: 3.1 Coeficientes de calibración | D21: Concentración de gas de span configurada | E21: Que el valor de concentración de span coincida con el cilindro certificado | F21: Numérico | G21: ppm | H21: Rango de configuración permitido por el software | I21: 1e-05 | J21: 99999 | K21: Sí | L21: No | N21: OP_APNA-370 (Manual de Operación) | O21: Pendiente | Q21: =IF($F21<>"Numérico","",IF($P21="","Sin dato",IF(AND(OR(NOT(ISNUMBER($I21)),$P21>=$I21),OR(NOT(ISNUMBER($J21)),$P21<=$J21)),"Dentro de rango","Fuera de rango"))) -> Sin dato
A22: 3.2.1 | B22: 3. Estado de calibración | C22: 3.2 Suministro de gases patrón | D22: Presión del gas patrón y del gas cero | E22: Presión de los gases suministrados al analizador, comprobada con manómetro externo | F22: Numérico | G22: kPa | H22: Debe controlarse ligeramente por encima de la presión atmosférica | I22: 0 | J22: 0.5 | K22: Sí | L22: No | N22: OP_APNA-370 (Manual de Operación) | O22: Pendiente | Q22: =IF($F22<>"Numérico","",IF($P22="","Sin dato",IF(AND(OR(NOT(ISNUMBER($I22)),$P22>=$I22),OR(NOT(ISNUMBER($J22)),$P22<=$J22)),"Dentro de rango","Fuera de rango"))) -> Sin dato
A23: 3.2.2 | B23: 3. Estado de calibración | C23: 3.2 Suministro de gases patrón | D23: Presión del gas de muestra | E23: Que la presión de entrada del gas de muestra en el puerto posterior se mantenga estable | F23: Numérico | G23: Pa | H23: La presión en el puerto trasero debe controlarse dentro del límite estable establecido | I23: -980 | J23: 980 | K23: Sí | L23: No | N23: OP_APNA-370 (Manual de Operación) | O23: Pendiente | Q23: =IF($F23<>"Numérico","",IF($P23="","Sin dato",IF(AND(OR(NOT(ISNUMBER($I23)),$P23>=$I23),OR(NOT(ISNUMBER($J23)),$P23<=$J23)),"Dentro de rango","Fuera de rango"))) -> Sin dato
A24: 3.2.3 | B24: 3. Estado de calibración | C24: 3.2 Suministro de gases patrón | D24: Presión del gas de escape | E24: Que la línea de descarga no presente contrapresión que afecte la cámara de reacción | F24: Numérico | G24: Pa | H24: La línea de escape debe liberarse a un lugar seguro, con contrapresión estable dentro del rango | I24: -980 | J24: 980 | K24: Sí | L24: No | N24: OP_APNA-370 (Manual de Operación) | O24: Pendiente | Q24: =IF($F24<>"Numérico","",IF($P24="","Sin dato",IF(AND(OR(NOT(ISNUMBER($I24)),$P24>=$I24),OR(NOT(ISNUMBER($J24)),$P24<=$J24)),"Dentro de rango","Fuera de rango"))) -> Sin dato
A25: 3.3.1 | B25: 3. Estado de calibración | C25: 3.3 Eficiencia del convertidor | D25: Rendimiento del convertidor de NO2 a NO | E25: Eficiencia de conversión de la celda catalítica, verificada por titulación en fase gas (GPT) | F25: Numérico | G25: % | H25: La eficiencia de conversión de NO2 a NO debe ser igual o superior al 96 % | I25: 96 | J25: 100 | K25: Sí | L25: No | M25: Catalyzer NO2-NO COM-1 (3014056464) | N25: MNT_APNA-370 (Manual de Mantenimiento) | O25: Pendiente | Q25: =IF($F25<>"Numérico","",IF($P25="","Sin dato",IF(AND(OR(NOT(ISNUMBER($I25)),$P25>=$I25),OR(NOT(ISNUMBER($J25)),$P25<=$J25)),"Dentro de rango","Fuera de rango"))) -> Sin dato
A26: 3.4.1 | B26: 3. Estado de calibración | C26: 3.4 Deriva y desempeño metrológico | D26: Deriva del cero diaria (Zero Drift) | E26: Desviación del punto cero transcurridas 24 h de operación continua | F26: Numérico | G26: % F.S. | H26: La deriva de cero en 24 h no debe superar el porcentaje de fondo de escala especificado | I26: -1 | J26: 1 | K26: Sí | L26: No | N26: OP_APNA-370 (Manual de Operación) | O26: Pendiente | Q26: =IF($F26<>"Numérico","",IF($P26="","Sin dato",IF(AND(OR(NOT(ISNUMBER($I26)),$P26>=$I26),OR(NOT(ISNUMBER($J26)),$P26<=$J26)),"Dentro de rango","Fuera de rango"))) -> Sin dato
A27: 3.4.2 | B27: 3. Estado de calibración | C27: 3.4 Deriva y desempeño metrológico | D27: Deriva del cero semanal (Zero Drift) | E27: Desviación del punto cero tras una semana de operación con variación de temperatura menor a 5 °C | F27: Numérico | G27: % F.S. | H27: La deriva de cero en una semana no debe superar el porcentaje de fondo de escala especificado | I27: -2 | J27: 2 | K27: Sí | L27: No | N27: OP_APNA-370 (Manual de Operación) | O27: Pendiente | Q27: =IF($F27<>"Numérico","",IF($P27="","Sin dato",IF(AND(OR(NOT(ISNUMBER($I27)),$P27>=$I27),OR(NOT(ISNUMBER($J27)),$P27<=$J27)),"Dentro de rango","Fuera de rango"))) -> Sin dato
A28: 3.4.3 | B28: 3. Estado de calibración | C28: 3.4 Deriva y desempeño metrológico | D28: Deriva del span diaria (Span Drift) | E28: Desviación del punto de span transcurridas 24 h de operación continua | F28: Numérico | G28: % F.S. | H28: La deriva de span en 24 h no debe superar el porcentaje de fondo de escala especificado | I28: -1 | J28: 1 | K28: Sí | L28: No | N28: OP_APNA-370 (Manual de Operación) | O28: Pendiente | Q28: =IF($F28<>"Numérico","",IF($P28="","Sin dato",IF(AND(OR(NOT(ISNUMBER($I28)),$P28>=$I28),OR(NOT(ISNUMBER($J28)),$P28<=$J28)),"Dentro de rango","Fuera de rango"))) -> Sin dato
A29: 3.4.4 | B29: 3. Estado de calibración | C29: 3.4 Deriva y desempeño metrológico | D29: Deriva del span semanal (Span Drift) | E29: Desviación del punto de span tras una semana con variación de temperatura menor a 5 °C | F29: Numérico | G29: % F.S. | H29: La deriva de span en una semana no debe superar el porcentaje de fondo de escala especificado | I29: -2 | J29: 2 | K29: Sí | L29: No | N29: OP_APNA-370 (Manual de Operación) | O29: Pendiente | Q29: =IF($F29<>"Numérico","",IF($P29="","Sin dato",IF(AND(OR(NOT(ISNUMBER($I29)),$P29>=$I29),OR(NOT(ISNUMBER($J29)),$P29<=$J29)),"Dentro de rango","Fuera de rango"))) -> Sin dato
A30: 3.4.5 | B30: 3. Estado de calibración | C30: 3.4 Deriva y desempeño metrológico | D30: Tiempo de respuesta T90 | E30: Tiempo para alcanzar el 90 % del valor final de concentración desde la entrada | F30: Numérico | G30: segundos | H30: El tiempo de respuesta T90 debe ser igual o menor a 120 s | I30: 0 | J30: 120 | K30: Sí | L30: No | N30: OP_APNA-370 (Manual de Operación) | O30: Pendiente | Q30: =IF($F30<>"Numérico","",IF($P30="","Sin dato",IF(AND(OR(NOT(ISNUMBER($I30)),$P30>=$I30),OR(NOT(ISNUMBER($J30)),$P30<=$J30)),"Dentro de rango","Fuera de rango"))) -> Sin dato
A31: 3.4.6 | B31: 3. Estado de calibración | C31: 3.4 Deriva y desempeño metrológico | D31: Repetitividad del equipo | E31: Repetitividad de lecturas bajo condiciones constantes de gas patrón | F31: Numérico | G31: % F.S. | H31: La repetitividad de las mediciones de NOx debe encontrarse dentro de la tolerancia | I31: -1 | J31: 1 | K31: Sí | L31: No | N31: OP_APNA-370 (Manual de Operación) | O31: Pendiente | Q31: =IF($F31<>"Numérico","",IF($P31="","Sin dato",IF(AND(OR(NOT(ISNUMBER($I31)),$P31>=$I31),OR(NOT(ISNUMBER($J31)),$P31<=$J31)),"Dentro de rango","Fuera de rango"))) -> Sin dato
A32: 3.4.7 | B32: 3. Estado de calibración | C32: 3.4 Deriva y desempeño metrológico | D32: Linealidad del analizador | E32: Desviación de la curva lineal en una calibración multipunto | F32: Numérico | G32: % F.S. | H32: La linealidad del equipo debe encontrarse dentro de la tolerancia máxima establecida | I32: -1 | J32: 1 | K32: Sí | L32: No | N32: OP_APNA-370 (Manual de Operación) | O32: Pendiente | Q32: =IF($F32<>"Numérico","",IF($P32="","Sin dato",IF(AND(OR(NOT(ISNUMBER($I32)),$P32>=$I32),OR(NOT(ISNUMBER($J32)),$P32<=$J32)),"Dentro de rango","Fuera de rango"))) -> Sin dato
A33: 4.1.1 | B33: 4. Línea de muestreo y acondicionamiento | C33: 4.1 Portafiltros frontal | D33: Elemento filtrante de muestra (PTFE) | E33: Color y estado del elemento filtrante PA-10L de 54 mm de diámetro | F33: OK / No OK | H33: Debe estar limpio y de color totalmente blanco; reemplazar cada 2 semanas si hay polución o humedad | K33: Sí | L33: Sí | M33: Filter Element PA-10L (3200043947) | N33: OP_APNA-370 / MT_9156R938 | O33: Pendiente | Q33: =IF($F33<>"Numérico","",IF($P33="","Sin dato",IF(AND(OR(NOT(ISNUMBER($I33)),$P33>=$I33),OR(NOT(ISNUMBER($J33)),$P33<=$J33)),"Dentro de rango","Fuera de rango")))
A34: 4.1.2 | B34: 4. Línea de muestreo y acondicionamiento | C34: 4.1 Portafiltros frontal | D34: Empaque del filtro de partículas frontal | E34: Empaque plano FKM del portafiltro frontal, para descartar grietas, deformaciones o fugas | F34: OK / No OK | H34: Empaque elástico y sin fisuras, que garantice hermeticidad de la línea; reemplazar cada 1 año | K34: Sí | L34: Sí | M34: Empaque de filtro (3200044273) | N34: MNT_APNA-370 (Manual de Mantenimiento) | O34: Pendiente | Q34: =IF($F34<>"Numérico","",IF($P34="","Sin dato",IF(AND(OR(NOT(ISNUMBER($I34)),$P34>=$I34),OR(NOT(ISNUMBER($J34)),$P34<=$J34)),"Dentro de rango","Fuera de rango")))
A35: 4.1.3 | B35: 4. Línea de muestreo y acondicionamiento | C35: 4.1 Portafiltros frontal | D35: Junta tórica del portafiltro (O-Ring G70) | E35: Estado del anillo de sellado JISB2401 G70 en el estuche del filtro | F35: OK / No OK | H35: Sin cortes ni pérdida de elasticidad, para evitar ingreso de aire ambiental; reemplazar cada 1 año | K35: Sí | L35: Sí | M35: O-Ring (3200043785) | N35: MNT_APNA-370 (Manual de Mantenimiento) | O35: Pendiente | Q35: =IF($F35<>"Numérico","",IF($P35="","Sin dato",IF(AND(OR(NOT(ISNUMBER($I35)),$P35>=$I35),OR(NOT(ISNUMBER($J35)),$P35<=$J35)),"Dentro de rango","Fuera de rango")))
A36: 4.2.1 | B36: 4. Línea de muestreo y acondicionamiento | C36: 4.2 Sonda y líneas de muestreo | D36: Tubería de teflón FEP externa | E36: Mangueras externas de entrada de muestra, calibración y escape | F36: OK / No OK | H36: Limpias, sin dobleces, estrangulaciones ni humedad acumulada; FEP de 6 mm OD / 4 mm ID | K36: Sí | L36: Sí | M36: Tubería FEP (AMB-CONTEF-001) | N36: OP_APNA-370 / MT_RFL6UD28 | O36: Pendiente | Q36: =IF($F36<>"Numérico","",IF($P36="","Sin dato",IF(AND(OR(NOT(ISNUMBER($I36)),$P36>=$I36),OR(NOT(ISNUMBER($J36)),$P36<=$J36)),"Dentro de rango","Fuera de rango")))
A37: 4.3.1 | B37: 4. Línea de muestreo y acondicionamiento | C37: 4.3 Acondicionamiento de la muestra | D37: Tanque de condensación neumático (Buffer Tank) | E37: Base del tanque de condensación interna, y si presenta fisuras o está pegada con adhesivos | F37: OK / No OK | H37: El tanque debe estar hermético y estable, sin fugas neumáticas | K37: Sí | L37: Sí | M37: Buffer tank (3012301739) | N37: MT_US00XLH0_APNA370_251218 / MT_RG4SR6AD | O37: Pendiente | Q37: =IF($F37<>"Numérico","",IF($P37="","Sin dato",IF(AND(OR(NOT(ISNUMBER($I37)),$P37>=$I37),OR(NOT(ISNUMBER($J37)),$P37<=$J37)),"Dentro de rango","Fuera de rango")))
A38: 4.3.2 | B38: 4. Línea de muestreo y acondicionamiento | C38: 4.3 Acondicionamiento de la muestra | D38: Unidad deshumidificadora de membrana (PPD-1) | E38: Que el tubo deshumidificador de membrana Nafion esté en buen estado, sin fugas ni obturaciones | F38: OK / No OK | H38: Debe garantizar el correcto secado del gas de muestra; reemplazar cuando sea necesario | K38: Sí | L38: Sí | M38: Dehumidifier unit PPD-1 (3200044461) | N38: MNT_APNA-370 / MT_N4CAMPC1_APNA-370_260313 | O38: Pendiente | Q38: =IF($F38<>"Numérico","",IF($P38="","Sin dato",IF(AND(OR(NOT(ISNUMBER($I38)),$P38>=$I38),OR(NOT(ISNUMBER($J38)),$P38<=$J38)),"Dentro de rango","Fuera de rango")))
A39: 5.1.1 | B39: 5. Sistema neumático | C39: 5.1 Bomba de muestreo | D39: Bomba de muestreo neumática de doble cabezal (GD-6EH) | E39: Funcionamiento mecánico de la bomba y ausencia de sobrecalentamiento del chasis | F39: OK / No OK | H39: Funcionamiento continuo y silencioso, sin ruidos metálicos ni exceso de temperatura; cambio cada 2 años | K39: Sí | L39: Sí | M39: Pump unit (3014059491) | N39: MNT_APNA-370 / MT_RFL6UD28 | O39: Pendiente | Q39: =IF($F39<>"Numérico","",IF($P39="","Sin dato",IF(AND(OR(NOT(ISNUMBER($I39)),$P39>=$I39),OR(NOT(ISNUMBER($J39)),$P39<=$J39)),"Dentro de rango","Fuera de rango")))
A40: 5.1.2 | B40: 5. Sistema neumático | C40: 5.1 Bomba de muestreo | D40: Ensamblaje del diafragma de la bomba (P-1-D) | E40: Fisuras o rupturas del diafragma de EPDM, retirando las tapas del cabezal | F40: Sí/No | H40: Diafragmas sin fisuras, perforaciones ni deformaciones mecánicas; reemplazar cada 1 a 2 años | K40: Sí | L40: No | M40: Diaphragm Assy (3200044033) | N40: MNT_APNA-370 / MT_A860VPB4_APNA370_20113004 | O40: Pendiente | Q40: =IF($F40<>"Numérico","",IF($P40="","Sin dato",IF(AND(OR(NOT(ISNUMBER($I40)),$P40>=$I40),OR(NOT(ISNUMBER($J40)),$P40<=$J40)),"Dentro de rango","Fuera de rango")))
A41: 5.1.3 | B41: 5. Sistema neumático | C41: 5.1 Bomba de muestreo | D41: Empaque tipo válvula (Flapper valve) | E41: Estado y desgaste del empaque elástico tipo válvula del cabezal de la bomba | F41: OK / No OK | H41: Limpiar, lubricar y de ser necesario rotar o cambiar el empaque, para corregir fluctuaciones de caudal | K41: Sí | L41: Sí | M41: Flapper valve (3012164657) | N41: MT_1TLF2RUY_APNA-370_230620 / MT_N4CAMPC1 | O41: Pendiente | Q41: =IF($F41<>"Numérico","",IF($P41="","Sin dato",IF(AND(OR(NOT(ISNUMBER($I41)),$P41>=$I41),OR(NOT(ISNUMBER($J41)),$P41<=$J41)),"Dentro de rango","Fuera de rango")))
A42: 5.2.1 | B42: 5. Sistema neumático | C42: 5.2 Caudal de muestra | D42: Valor medido del flujo de muestra (Sample Flow) | E42: Valor del flujo de muestra en MENU / MAINTENANCE / ANALOG INPUT | F42: Numérico | G42: L/min | H42: El caudal medido debe estar dentro del rango estándar de operación | I42: 0.8 | J42: 1.4 | K42: Sí | L42: No | N42: OP_APNA-370 / P_ST-008-MAN | O42: Pendiente | Q42: =IF($F42<>"Numérico","",IF($P42="","Sin dato",IF(AND(OR(NOT(ISNUMBER($I42)),$P42>=$I42),OR(NOT(ISNUMBER($J42)),$P42<=$J42)),"Dentro de rango","Fuera de rango"))) -> Sin dato
A43: 5.2.2 | B43: 5. Sistema neumático | C43: 5.2 Caudal de muestra | D43: Límites de alarma de flujo de muestra (FLO1) | E43: Rango configurado para el disparo de la alarma opcional FLO1 de flujo de muestra | F43: Numérico | G43: L/min | H43: El flujo de muestra no debe desviarse fuera del rango de alarma absoluto permitido | I43: 0.6 | J43: 1.5 | K43: Sí | L43: No | N43: GZ0000117746B SM E APXX-370 (Service Manual) | O43: Pendiente | Q43: =IF($F43<>"Numérico","",IF($P43="","Sin dato",IF(AND(OR(NOT(ISNUMBER($I43)),$P43>=$I43),OR(NOT(ISNUMBER($J43)),$P43<=$J43)),"Dentro de rango","Fuera de rango"))) -> Sin dato
A44: 5.2.3 | B44: 5. Sistema neumático | C44: 5.2 Caudal de muestra | D44: Caudal objetivo para ajuste manual con flujómetro | E44: Caudal físico en el puerto trasero, medido con flujómetro externo durante el mantenimiento | F44: Numérico | G44: mL/min | H44: El caudal de la línea de muestra y de la línea de NO se ajusta mediante el regulador R-2 | I44: 800 | J44: 900 | K44: Sí | L44: No | N44: GZ0000117746B SM E APXX-370 (Service Manual) | O44: Pendiente | Q44: =IF($F44<>"Numérico","",IF($P44="","Sin dato",IF(AND(OR(NOT(ISNUMBER($I44)),$P44>=$I44),OR(NOT(ISNUMBER($J44)),$P44<=$J44)),"Dentro de rango","Fuera de rango"))) -> Sin dato
A45: 5.3.1 | B45: 5. Sistema neumático | C45: 5.3 Restricción de flujo | D45: Orificios de restricción de flujo (Critical Orifice) | E45: Limpieza y ausencia de obstrucciones de polvo en los orificios críticos de teflón | F45: OK / No OK | H45: Los orificios capilares de flujo deben estar libres de obstrucciones y polución | K45: Sí | L45: Sí | M45: Orificio crítico (3014035610) | N45: MT_L2561A1S_APNA-370_230705_MTTO | O45: Pendiente | Q45: =IF($F45<>"Numérico","",IF($P45="","Sin dato",IF(AND(OR(NOT(ISNUMBER($I45)),$P45>=$I45),OR(NOT(ISNUMBER($J45)),$P45<=$J45)),"Dentro de rango","Fuera de rango")))
A46: 5.4.1 | B46: 5. Sistema neumático | C46: 5.4 Válvulas solenoides | D46: Estado mecánico de las electroválvulas (SV-2, SV-3, SV-11) | E46: Alternancia física y sello neumático de las 3 electroválvulas principales del detector | F46: OK / No OK | H46: Deben conmutar correctamente, sin atascos, con sello hermético y manteniendo la presión adecuada | K46: Sí | L46: Sí | M46: Solenoid valve (3014035610) | N46: MT_US00XLH0_APNA370_251218 / MT_REBXU06B | O46: Pendiente | Q46: =IF($F46<>"Numérico","",IF($P46="","Sin dato",IF(AND(OR(NOT(ISNUMBER($I46)),$P46>=$I46),OR(NOT(ISNUMBER($J46)),$P46<=$J46)),"Dentro de rango","Fuera de rango")))
A47: 5.5.1 | B47: 5. Sistema neumático | C47: 5.5 Reguladores de presión | D47: Regulador de presión R-1 | E47: Ajuste de la presión en el regulador R-1, retirando el tapón y conectando manómetro | F47: Numérico | G47: kPa | H47: La lectura en el punto de chequeo del regulador R-1 debe ser 80 kPa ± 4 kPa | I47: 76 | J47: 84 | K47: Sí | L47: No | M47: Regulador (3011017009) | N47: GZ0000117746B SM E APXX-370 (Service Manual) | O47: Pendiente | Q47: =IF($F47<>"Numérico","",IF($P47="","Sin dato",IF(AND(OR(NOT(ISNUMBER($I47)),$P47>=$I47),OR(NOT(ISNUMBER($J47)),$P47<=$J47)),"Dentro de rango","Fuera de rango"))) -> Sin dato
A48: 5.5.2 | B48: 5. Sistema neumático | C48: 5.5 Reguladores de presión | D48: Regulador de vacío R-2 (presión de la bomba) | E48: Lectura de presión de la bomba en la pantalla ANALOG INPUT 1/2 | F48: Numérico | G48: kPa | H48: La presión del regulador de vacío R-2 debe ajustarse al valor de diseño | I48: -23 | J48: -19 | K48: Sí | L48: No | M48: Regulador (3011017009) | N48: GZ0000117746B SM E APXX-370 (Service Manual) | O48: Pendiente | Q48: =IF($F48<>"Numérico","",IF($P48="","Sin dato",IF(AND(OR(NOT(ISNUMBER($I48)),$P48>=$I48),OR(NOT(ISNUMBER($J48)),$P48<=$J48)),"Dentro de rango","Fuera de rango"))) -> Sin dato
A49: 5.5.3 | B49: 5. Sistema neumático | C49: 5.5 Reguladores de presión | D49: Regulador diferencial R-3 | E49: Presión en el regulador diferencial R-3 | F49: Numérico | G49: kPa | H49: La lectura de presión del regulador diferencial R-3 debe ajustarse al valor de diseño | I49: -21 | J49: -19 | K49: Sí | L49: No | M49: Regulador (3011017009) | N49: GZ0000117746B SM E APXX-370 (Service Manual) | O49: Pendiente | Q49: =IF($F49<>"Numérico","",IF($P49="","Sin dato",IF(AND(OR(NOT(ISNUMBER($I49)),$P49>=$I49),OR(NOT(ISNUMBER($J49)),$P49<=$J49)),"Dentro de rango","Fuera de rango"))) -> Sin dato
A50: 5.5.4 | B50: 5. Sistema neumático | C50: 5.5 Reguladores de presión | D50: Presión absoluta del detector (límite de alarma PRE1) | E50: Presión absoluta interna de la celda o bomba mostrada en pantalla | F50: Numérico | G50: kPa | H50: Debe permanecer dentro del rango de 60 a 90 kPa; fuera de él se activa la alarma PRESS 1 | I50: 60 | J50: 90 | K50: Sí | L50: No | N50: GZ0000117746B SM E APXX-370 (Service Manual) | O50: Pendiente | Q50: =IF($F50<>"Numérico","",IF($P50="","Sin dato",IF(AND(OR(NOT(ISNUMBER($I50)),$P50>=$I50),OR(NOT(ISNUMBER($J50)),$P50<=$J50)),"Dentro de rango","Fuera de rango"))) -> Sin dato
A51: 6.1.1 | B51: 6. Banco de medición y óptica | C51: 6.1 Cámara de reacción (quimiluminiscencia) | D51: Hermeticidad del reactor | E51: Bloque del reactor, para descartar fugas, y estado de la junta elástica O-Ring W | F51: OK / No OK | H51: Bloque limpio, sin fisuras neumáticas y con el O-Ring W elástico y bien posicionado | K51: Sí | L51: Sí | M51: O-Ring W (3014059166) | N51: MT_H0004N72_APNA-370_241227 / MT_P7P8MW1M | O51: Pendiente | Q51: =IF($F51<>"Numérico","",IF($P51="","Sin dato",IF(AND(OR(NOT(ISNUMBER($I51)),$P51>=$I51),OR(NOT(ISNUMBER($J51)),$P51<=$J51)),"Dentro de rango","Fuera de rango")))
A52: 6.2.1 | B52: 6. Banco de medición y óptica | C52: 6.2 Convertidor de NO2 a NO | D52: Tubo catalizador de reducción (COM-1) | E52: Estado externo de la celda de reducción de NOx y de su resistencia calefactora | F52: OK / No OK | H52: Tubo catalizador libre de obstrucciones internas y con temperatura estable; cambio cada 1 a 4 años | K52: Sí | L52: Sí | M52: Catalyzer NO2-NO COM-1 (3014056464) | N52: MNT_APNA-370 (Manual de Mantenimiento) | O52: Pendiente | Q52: =IF($F52<>"Numérico","",IF($P52="","Sin dato",IF(AND(OR(NOT(ISNUMBER($I52)),$P52>=$I52),OR(NOT(ISNUMBER($J52)),$P52<=$J52)),"Dentro de rango","Fuera de rango")))
A53: 6.3.1 | B53: 6. Banco de medición y óptica | C53: 6.3 Generador de ozono interno | D53: Tarjeta de potencia del ozonizador (AP-UVP-03) | E53: Que la tarjeta osciladora encienda su LED de alta tensión para iluminar la lámpara UV | F53: Sí/No | H53: Tarjeta operativa sin quemaduras y LED indicador encendido durante la generación de ozono | K53: Sí | L53: No | M53: Printed Board Unit AP-UVP-03 (3200088405) | N53: MT_GMK01HJU_APNA370 / MT_A860VPB4 | O53: Pendiente | Q53: =IF($F53<>"Numérico","",IF($P53="","Sin dato",IF(AND(OR(NOT(ISNUMBER($I53)),$P53>=$I53),OR(NOT(ISNUMBER($J53)),$P53<=$J53)),"Dentro de rango","Fuera de rango")))
A54: 6.3.2 | B54: 6. Banco de medición y óptica | C54: 6.3 Generador de ozono interno | D54: Protector de PTFE de la lámpara UV (UV liner) | E54: Estado del protector de PTFE de la lámpara del ozonizador | F54: OK / No OK | H54: Funda de PTFE sin grietas ni deformidades por calor (263 x 145 x 0,8 mm); reemplazar cada 1 año | K54: Sí | L54: Sí | M54: UV Lamp with PTFE liner (3200044415) | N54: MNT_APNA-370 (Manual de Mantenimiento) | O54: Pendiente | Q54: =IF($F54<>"Numérico","",IF($P54="","Sin dato",IF(AND(OR(NOT(ISNUMBER($I54)),$P54>=$I54),OR(NOT(ISNUMBER($J54)),$P54<=$J54)),"Dentro de rango","Fuera de rango")))
A55: 6.4.1 | B55: 6. Banco de medición y óptica | C55: 6.4 Detección óptica | D55: Detector de luz de reacción | E55: Tipo y estado del sensor óptico del detector | F55: Texto | H55: El APNA-370 usa un fotodiodo de silicio de larga vida y no requiere fuente de alta tensión de PMT | K55: Sí | L55: No | M55: Detector (3014060117) | N55: APNA-370 Brochure / MT_A860VPB4_APNA370_20112702 | O55: Pendiente | Q55: =IF($F55<>"Numérico","",IF($P55="","Sin dato",IF(AND(OR(NOT(ISNUMBER($I55)),$P55>=$I55),OR(NOT(ISNUMBER($J55)),$P55<=$J55)),"Dentro de rango","Fuera de rango")))
A56: 6.4.2 | B56: 6. Banco de medición y óptica | C56: 6.4 Detección óptica | D56: Limpieza de filtros ópticos y ventana de celda | E56: Depósitos, humedad o manchas en el lente protector y el filtro óptico del detector | F56: OK / No OK | H56: El lente y los filtros ópticos deben estar limpios, transparentes y secos | K56: Sí | L56: Sí | M56: Filtro óptico (3014059379) | N56: MT_P7P8MW1M_APNA370_251028 / MT_1XT65JR5 | O56: Pendiente | Q56: =IF($F56<>"Numérico","",IF($P56="","Sin dato",IF(AND(OR(NOT(ISNUMBER($I56)),$P56>=$I56),OR(NOT(ISNUMBER($J56)),$P56<=$J56)),"Dentro de rango","Fuera de rango")))
A57: 6.5.1 | B57: 6. Banco de medición y óptica | C57: 6.5 Eliminación de ozono residual | D57: Catalizador de ozono de escape (DO-1 / Deozonizer) | E57: Estado del deozonizador de salida que elimina el ozono residual antes de la descarga | F57: OK / No OK | H57: Catalizador en buen estado, sin degradación que dañe prematuramente la bomba; cambio cada 1 a 2 años | K57: Sí | L57: Sí | M57: Catalyzer DO DO-1 (3200043513) | N57: MNT_APNA-370 (Manual de Mantenimiento) | O57: Pendiente | Q57: =IF($F57<>"Numérico","",IF($P57="","Sin dato",IF(AND(OR(NOT(ISNUMBER($I57)),$P57>=$I57),OR(NOT(ISNUMBER($J57)),$P57<=$J57)),"Dentro de rango","Fuera de rango")))
A58: 6.6.1 | B58: 6. Banco de medición y óptica | C58: 6.6 Secado del aire de ozonizador | D58: Contenedores de gel de sílice (Dryer D-1) | E58: Color de los granos de sílica gel en los dos cilindros de secado de aire | F58: OK / No OK | H58: Sustituir la sílica gel cada 1 a 2 años, o si presenta decoloración o saturación de humedad | K58: Sí | L58: Sí | M58: Silica gel for Dryer units D-1 (3200044017) | N58: MNT_APNA-370 / MT_1U67F10J | O58: Pendiente | Q58: =IF($F58<>"Numérico","",IF($P58="","Sin dato",IF(AND(OR(NOT(ISNUMBER($I58)),$P58>=$I58),OR(NOT(ISNUMBER($J58)),$P58<=$J58)),"Dentro de rango","Fuera de rango")))
A59: 6.6.2 | B59: 6. Banco de medición y óptica | C59: 6.6 Secado del aire de ozonizador | D59: Temperatura de reactivación del cilindro secador | E59: Que el cilindro secador inactivo caliente periódicamente para evaporar la humedad | F59: Numérico | G59: °C | H59: En la etapa de reactivación la sílica gel debe calentarse para liberar humedad tras 180 min | I59: 150 | J59: 170 | K59: Sí | L59: No | N59: OP_APNA-370 / P_ST-008-MAN | O59: Pendiente | Q59: =IF($F59<>"Numérico","",IF($P59="","Sin dato",IF(AND(OR(NOT(ISNUMBER($I59)),$P59>=$I59),OR(NOT(ISNUMBER($J59)),$P59<=$J59)),"Dentro de rango","Fuera de rango"))) -> Sin dato
A60: 7.1.1 | B60: 7. Electrónica y control | C60: 7.1 Tarjetas electrónicas | D60: Tarjeta CPU (AP-CPU-01 / AP-CPU-02) | E60: Que el LED de operación de la CPU destelle regularmente y no se observen daños térmicos | F60: OK / No OK | H60: El LED debe destellar en condiciones normales; tras reemplazar la CPU se inicializa con SW5 y SW1 | K60: Sí | L60: Sí | M60: AP-CPU-02 (3200629662) | N60: GZ0000117746B SM E APXX-370 (Service Manual) | O60: Pendiente | Q60: =IF($F60<>"Numérico","",IF($P60="","Sin dato",IF(AND(OR(NOT(ISNUMBER($I60)),$P60>=$I60),OR(NOT(ISNUMBER($J60)),$P60<=$J60)),"Dentro de rango","Fuera de rango")))
A61: 7.1.2 | B61: 7. Electrónica y control | C61: 7.1 Tarjetas electrónicas | D61: Tarjeta de conversión analógica-digital (AP-ADC-05) | E61: Posición de los DIP switches de configuración del modelo de analizador | F61: OK / No OK | H61: Para APNA-370: BIT0=ON, BIT1=OFF, BIT2=OFF, BIT3=OFF. Referencia PENDIENTE DE VALIDAR | K61: Sí | L61: Sí | N61: GZ0000117746B SM E APXX-370 (Service Manual) | O61: Pendiente | Q61: =IF($F61<>"Numérico","",IF($P61="","Sin dato",IF(AND(OR(NOT(ISNUMBER($I61)),$P61>=$I61),OR(NOT(ISNUMBER($J61)),$P61<=$J61)),"Dentro de rango","Fuera de rango")))
A62: 7.1.3 | B62: 7. Electrónica y control | C62: 7.1 Tarjetas electrónicas | D62: Tarjeta de relés y contactos (AP-RPL-02 / AP-RPL-02A) | E62: Estado de los terminales de cableado de entradas y salidas, y LED de comunicación I2C (ST0/ST1) | F62: OK / No OK | H62: LED ST1 de operación destellando normalmente y terminales libres de corrosión u holguras | K62: Sí | L62: Sí | N62: GZ0000117746B SM E APXX-370 (Service Manual) | O62: Pendiente | Q62: =IF($F62<>"Numérico","",IF($P62="","Sin dato",IF(AND(OR(NOT(ISNUMBER($I62)),$P62>=$I62),OR(NOT(ISNUMBER($J62)),$P62<=$J62)),"Dentro de rango","Fuera de rango")))
A63: 7.1.4 | B63: 7. Electrónica y control | C63: 7.1 Tarjetas electrónicas | D63: Tarjeta de comunicación serial RS-232C (AP-SIO-04) | E63: Integración física del puerto serial y su conexión con el cable CN2 en el puerto de la CPU | F63: OK / No OK | H63: Tarjeta fijada con los 4 tornillos M3x6 SUS y conectada con cable de 5 hilos | K63: Sí | L63: Sí | N63: Procedimiento Integración Tarjeta RS232 | O63: Pendiente | Q63: =IF($F63<>"Numérico","",IF($P63="","Sin dato",IF(AND(OR(NOT(ISNUMBER($I63)),$P63>=$I63),OR(NOT(ISNUMBER($J63)),$P63<=$J63)),"Dentro de rango","Fuera de rango")))
A64: 7.2.1 | B64: 7. Electrónica y control | C64: 7.2 Respaldo de reloj y memoria | D64: Pila de memoria y reloj RTC | E64: Voltaje de la batería de litio CR2032 y ausencia de la alarma BATT en pantalla | F64: Presente / Ausente | H64: Pila CR2032 instalada en el portapilas de la CPU; reemplazar cada 3 años | K64: Sí | L64: Sí | M64: Battery CR2032 (3200043671) | N64: MNT_APNA-370 / OP_APNA-370 | O64: Pendiente | Q64: =IF($F64<>"Numérico","",IF($P64="","Sin dato",IF(AND(OR(NOT(ISNUMBER($I64)),$P64>=$I64),OR(NOT(ISNUMBER($J64)),$P64<=$J64)),"Dentro de rango","Fuera de rango")))
A65: 7.3.1 | B65: 7. Electrónica y control | C65: 7.3 Display y cableado interno | D65: Cintas de datos planas (Tape Wire) | E65: Hilos cortados, grietas o malas conexiones en las cintas planas entre la CPU y la RPL | F65: OK / No OK | H65: Cable cinta en buen estado y firmemente asentado en sus conectores | K65: Sí | L65: Sí | M65: Tape Wire (3010040355) | N65: MT_H0004N72_APNA-370_241227 / MT_VMH2YJP3 | O65: Pendiente | Q65: =IF($F65<>"Numérico","",IF($P65="","Sin dato",IF(AND(OR(NOT(ISNUMBER($I65)),$P65>=$I65),OR(NOT(ISNUMBER($J65)),$P65<=$J65)),"Dentro de rango","Fuera de rango")))
A66: 7.3.2 | B66: 7. Electrónica y control | C66: 7.3 Display y cableado interno | D66: Panel digitalizador táctil (Touch Panel) | E66: Respuesta del teclado resistivo al presionar los menús de la interfaz gráfica | F66: OK / No OK | H66: Respuesta táctil precisa en todas las zonas; no utilizar bolígrafos ni puntas afiladas | K66: Sí | L66: Sí | M66: Touch Panel TP-AP370 | N66: MT_A860VPB4_APNA370_20111202 / OP_APNA-370 | O66: Pendiente | Q66: =IF($F66<>"Numérico","",IF($P66="","Sin dato",IF(AND(OR(NOT(ISNUMBER($I66)),$P66>=$I66),OR(NOT(ISNUMBER($J66)),$P66<=$J66)),"Dentro de rango","Fuera de rango")))
A67: 7.4.1 | B67: 7. Electrónica y control | C67: 7.4 Salidas analógicas | D67: Señales de concentración de salida (Mom/Avg) | E67: Voltaje en los canales CH-7, CH-8 o CH-9 de la parte trasera, medido con multímetro | F67: Numérico | G67: V | H67: Salida estándar no aislada de NO, NO2 o NOx de 0 a 1 V, proporcional al rango | I67: 0 | J67: 1 | K67: Sí | L67: No | N67: OP_APNA-370 (Manual de Operación) | O67: Pendiente | Q67: =IF($F67<>"Numérico","",IF($P67="","Sin dato",IF(AND(OR(NOT(ISNUMBER($I67)),$P67>=$I67),OR(NOT(ISNUMBER($J67)),$P67<=$J67)),"Dentro de rango","Fuera de rango"))) -> Sin dato
A68: 7.5.1 | B68: 7. Electrónica y control | C68: 7.5 Protección eléctrica | D68: Fusibles de entrada de red AC | E68: Continuidad de los fusibles integrados en el conector AC Inlet posterior | F68: OK / No OK | G68: A | H68: Fusible intacto; capacidad recomendada 6,3 A (T) para configuración de 115 V | K68: Sí | L68: Sí | N68: OP_APNA-370 / Cables ports | O68: Pendiente | Q68: =IF($F68<>"Numérico","",IF($P68="","Sin dato",IF(AND(OR(NOT(ISNUMBER($I68)),$P68>=$I68),OR(NOT(ISNUMBER($J68)),$P68<=$J68)),"Dentro de rango","Fuera de rango")))
A69: 8.1.1 | B69: 8. Filtros y consumibles | C69: 8.1 Consumibles del ozonizador | D69: Filtro de aire en línea del ozonizador | E69: Grado de saturación del filtro de aire de 0,3 micras en la línea de ozono | F69: OK / No OK | H69: Elemento filtrante seco y limpio de polvo; reemplazar cada 1 a 2 años | K69: Sí | L69: Sí | M69: Filtro de aire (3200044257) | N69: MNT_APNA-370 / MT_1U67F10J | O69: Pendiente | Q69: =IF($F69<>"Numérico","",IF($P69="","Sin dato",IF(AND(OR(NOT(ISNUMBER($I69)),$P69>=$I69),OR(NOT(ISNUMBER($J69)),$P69<=$J69)),"Dentro de rango","Fuera de rango")))
A70: 8.2.1 | B70: 8. Filtros y consumibles | C70: 8.2 Depuración de gases | D70: Depurador de gases de escape (Scrubber BAA-050) | E70: Color de las esferas de alúmina activada del depurador BAA-050 | F70: OK / No OK | H70: Reemplazar si presenta decoloración o saturación extrema; vida útil de 1 a 4 años | K70: Sí | L70: Sí | M70: Scrubber BAA-050 (3014061530) | N70: MNT_APNA-370 / MT_P7P8MW1M | O70: Pendiente | Q70: =IF($F70<>"Numérico","",IF($P70="","Sin dato",IF(AND(OR(NOT(ISNUMBER($I70)),$P70>=$I70),OR(NOT(ISNUMBER($J70)),$P70<=$J70)),"Dentro de rango","Fuera de rango")))
A71: 8.3.1 | B71: 8. Filtros y consumibles | C71: 8.3 Filtros de chasis | D71: Filtros de esponja de ventilación del chasis | E71: Acumulación de polvo en los filtros de esponja de la tapa exterior y del ventilador | F71: OK / No OK | H71: Esponjas limpias, lavadas o cambiadas periódicamente para garantizar el aire de enfriamiento; cada 1 año | K71: Sí | L71: Sí | M71: Filter Sponge (3012299939) | N71: MT_A860VPB4 / MT_T5DMLT1N_APNA370 | O71: Pendiente | Q71: =IF($F71<>"Numérico","",IF($P71="","Sin dato",IF(AND(OR(NOT(ISNUMBER($I71)),$P71>=$I71),OR(NOT(ISNUMBER($J71)),$P71<=$J71)),"Dentro de rango","Fuera de rango")))
A72: 9.1.1 | B72: 9. Sensores auxiliares | C72: 9.1 Temperatura | D72: Temperatura del detector (DETECTOR TEMP) | E72: Valor de temperatura del sensor óptico en MENU / MAINTENANCE / ANALOG INPUT | F72: Numérico | G72: °C | H72: La temperatura del detector debe mantenerse estable en torno al punto de diseño | I72: 38 | J72: 48 | K72: Sí | L72: No | N72: OP_APNA-370 / P_ST-008-MAN | O72: Pendiente | Q72: =IF($F72<>"Numérico","",IF($P72="","Sin dato",IF(AND(OR(NOT(ISNUMBER($I72)),$P72>=$I72),OR(NOT(ISNUMBER($J72)),$P72<=$J72)),"Dentro de rango","Fuera de rango"))) -> Sin dato
A73: 9.2.1 | B73: 9. Sensores auxiliares | C73: 9.2 Presión | D73: Presión interna del detector (PUMP PRESS) | E73: Presión del detector en el menú ANALOG INPUT | F73: Numérico | G73: kPa | H73: Rango de presión absoluta normal en operación | I73: 50 | J73: 54 | K73: Sí | L73: No | N73: MT_9156R938 / MT_KUS03MMP | O73: Pendiente | Q73: =IF($F73<>"Numérico","",IF($P73="","Sin dato",IF(AND(OR(NOT(ISNUMBER($I73)),$P73>=$I73),OR(NOT(ISNUMBER($J73)),$P73<=$J73)),"Dentro de rango","Fuera de rango"))) -> Sin dato
A74: 9.2.2 | B74: 9. Sensores auxiliares | C74: 9.2 Presión | D74: Presión ambiental (AMBIENT PRESS) | E74: Que el valor del sensor de presión atmosférica sea coherente con la altitud del sitio | F74: Numérico | G74: kPa | H74: Presión ambiental medida por el sensor PS_3 | I74: 70 | J74: 110 | K74: Sí | L74: No | N74: OP_APNA-370 / Procedimiento Ajuste de Presión Ambiente | O74: Pendiente | Q74: =IF($F74<>"Numérico","",IF($P74="","Sin dato",IF(AND(OR(NOT(ISNUMBER($I74)),$P74>=$I74),OR(NOT(ISNUMBER($J74)),$P74<=$J74)),"Dentro de rango","Fuera de rango"))) -> Sin dato
A75: 9.3.1 | B75: 9. Sensores auxiliares | C75: 9.3 Tensiones internas | D75: Canal de alimentación interna de 24 V DC | E75: Que la tensión de 24 V esté dentro de tolerancia, en la página 2 de ANALOG INPUT | F75: Numérico | G75: V | H75: Voltaje de suministro para bombas, solenoides y elementos calentadores (24 V ± 0,5 V) | I75: 23.5 | J75: 24.5 | K75: Sí | L75: No | N75: OP_APNA-370 / Service Manual | O75: Pendiente | Q75: =IF($F75<>"Numérico","",IF($P75="","Sin dato",IF(AND(OR(NOT(ISNUMBER($I75)),$P75>=$I75),OR(NOT(ISNUMBER($J75)),$P75<=$J75)),"Dentro de rango","Fuera de rango"))) -> Sin dato
A76: 9.3.2 | B76: 9. Sensores auxiliares | C76: 9.3 Tensiones internas | D76: Canal de alimentación interna de 5 V DC | E76: Que la tensión de 5 V esté dentro de tolerancia, en la página 2 de ANALOG INPUT | F76: Numérico | G76: V | H76: Voltaje de suministro para circuitos digitales y de control lógico (5 V ± 0,5 V) | I76: 4.5 | J76: 5.5 | K76: Sí | L76: No | N76: OP_APNA-370 / Service Manual | O76: Pendiente | Q76: =IF($F76<>"Numérico","",IF($P76="","Sin dato",IF(AND(OR(NOT(ISNUMBER($I76)),$P76>=$I76),OR(NOT(ISNUMBER($J76)),$P76<=$J76)),"Dentro de rango","Fuera de rango"))) -> Sin dato
A77: 10.1.1 | B77: 10. Gabinete, montaje e instalación | C77: 10.1 Gabinete y chasis | D77: Dimensiones físicas externas | E77: Que el espacio asignado en el rack cumpla con las medidas del chasis del analizador | F77: OK / No OK | H77: Gabinete estándar de 430 mm ancho x 221 mm alto x 550 mm profundidad (5U, 222 mm) | K77: Sí | L77: Sí | N77: OP_APNA-370 (Manual de Operación) | O77: Pendiente | Q77: =IF($F77<>"Numérico","",IF($P77="","Sin dato",IF(AND(OR(NOT(ISNUMBER($I77)),$P77>=$I77),OR(NOT(ISNUMBER($J77)),$P77<=$J77)),"Dentro de rango","Fuera de rango")))
A78: 10.1.2 | B78: 10. Gabinete, montaje e instalación | C78: 10.1 Gabinete y chasis | D78: Masa total del analizador | E78: Que la base de soporte o bandeja del rack tolere el peso neto del analizador | F78: Numérico | G78: kg | H78: Peso neto aproximado del equipo sin accesorios; requiere al menos 2 personas para su traslado | I78: 20 | J78: 22 | K78: Sí | L78: No | N78: OP_APNA-370 (Manual de Operación) | O78: Pendiente | Q78: =IF($F78<>"Numérico","",IF($P78="","Sin dato",IF(AND(OR(NOT(ISNUMBER($I78)),$P78>=$I78),OR(NOT(ISNUMBER($J78)),$P78<=$J78)),"Dentro de rango","Fuera de rango"))) -> Sin dato
A79: 10.1.3 | B79: 10. Gabinete, montaje e instalación | C79: 10.1 Gabinete y chasis | D79: Tornillos de fijación de la cubierta superior | E79: Que todos los tornillos M3 de la tapa metálica superior estén presentes y ajustados | F79: Sí/No | H79: Tapa asegurada firmemente con sus 8 tornillos M3, para evitar vibraciones e ingreso de polvo | K79: Sí | L79: No | M79: Tornillo M3 (3030049516) | N79: MT_T5DMLT1N_APNA370 / MT_N4CAMPC1_APNA-370_230705_MTTO | O79: Pendiente | Q79: =IF($F79<>"Numérico","",IF($P79="","Sin dato",IF(AND(OR(NOT(ISNUMBER($I79)),$P79>=$I79),OR(NOT(ISNUMBER($J79)),$P79<=$J79)),"Dentro de rango","Fuera de rango")))
A80: 10.1.4 | B80: 10. Gabinete, montaje e instalación | C80: 10.1 Gabinete y chasis | D80: Casquillos de bisagra de la puerta frontal | E80: Que la puerta delantera esté acoplada y gire suavemente | F80: OK / No OK | H80: Casquillos instalados, para evitar que la puerta delantera se descuelgue o se desacomode | K80: Sí | L80: Sí | M80: Hinge Bush (3012304035) | N80: MT_1TLF2RYU_APNA370_220511 / MT_A860VPB4 | O80: Pendiente | Q80: =IF($F80<>"Numérico","",IF($P80="","Sin dato",IF(AND(OR(NOT(ISNUMBER($I80)),$P80>=$I80),OR(NOT(ISNUMBER($J80)),$P80<=$J80)),"Dentro de rango","Fuera de rango")))
